Workbook

Sheet Sheet1
A1: Start Date | B1: End Date | C1: Profit | D1: Actual | E1: Total | F1: Cash | G1: Account Transfer | H1: Mul bhag
A2: 44866 | B2: 44895 | C2: =E2*0.3 -> 242775.6 | D2: =E2-C2 -> 566476.4 | E2: 809252 | F2: 441624 | G2: 367628 | H2: =C2/3 -> 80925.2 | J2: Avg business Before diwali | K2: =AVERAGE(E2:E12) -> 614454 | L2: =K2*10 -> 6144540 | N2: =L10*12/L2 -> 0.30856663
A3: 44896 | B3: 45261 | C3: =E3*0.3 -> 206920.5 | D3: =E3-C3 -> 482814.5 | E3: 689735 | F3: 331694 | G3: 358041 | H3: =C3/3 -> 68973.5 | J3: Avg business on diwali | K3: =SUM(E13:E14) -> 6840033.1
A4: 44928 | B4: 44957 | C4: =E4*0.3 -> 173440.5 | D4: =E4-C4 -> 404694.5 | E4: 578135 | F4: 300478 | G4: 277657 | H4: =C4/3 -> 57813.5
A5: 44958 | B5: 44985 | C5: =E5*0.3 -> 226772.7 | D5: =E5-C5 -> 529136.3 | E5: 755909 | F5: 382322 | G5: 373587 | H5: =C5/3 -> 75590.9 | J5: Fixed Cost | K5: Rent | L5: =105000 -> 105000
A6: 44986 | B6: 45016 | C6: =E6*0.3 -> 201082.8 | D6: =E6-C6 -> 469193.2 | E6: 670276 | F6: 288155 | G6: 382121 | H6: =C6/3 -> 67027.6 | K6: Avg Salary | L6: 36000
A7: 45017 | B7: 45046 | C7: =E7*0.3 -> 159962.4 | D7: =E7-C7 -> 373245.6 | E7: 533208 | F7: 314141 | G7: 219067 | H7: =C7/3 -> 53320.8 | K7: Light bill | L7: 10000
A8: 45047 | B8: 45077 | C8: =E8*0.3 -> 165549 | D8: =E8-C8 -> 386281 | E8: 551830 | F8: 266235 | G8: 285595 | H8: =C8/3 -> 55183 | K8: Breakage | L8: 7000
A9: 45078 | B9: 45107 | C9: =E9*0.3 -> 138583.5 | D9: =E9-C9 -> 323361.5 | E9: ='June 2023'!D30+'May 2023'!D49 -> 461945 | F9: ='June 2023'!E30+'May 2023'!E49 -> 190800 | G9: ='June 2023'!F30+'May 2023'!F49 -> 271145 | H9: =C9/3 -> 46194.5
A10: 45108 | B10: 45138 | C10: =E10*0.3 -> 106491 | D10: =E10-C10 -> 248479 | E10: ='July 2023'!D31+'July 2023'!D41 -> 354970 | F10: ='July 2023'!E31+'July 2023'!E41 -> 125790 | G10: ='July 2023'!F31+'July 2023'!F41 -> 229180 | H10: =C10/3 -> 35497 | L10: =SUM(L5:L9) -> 158000
A11: 45139 | B11: 45169 | C11: =E11*0.3 -> 185762.1 | D11: =E11-C11 -> 433444.9 | E11: 619207 | F11: 220841 | G11: 398366 | H11: =C11/3 -> 61920.7
A12: 45170 | B12: 45199 | C12: =E12*0.3 -> 220358.1 | D12: =E12-C12 -> 514168.9 | E12: 734527 | F12: 262189 | G12: 472338 | H12: =C12/3 -> 73452.7
A13: 45200 | B13: 45230 | C13: =E13*0.3 -> 1281118.2 | D13: =E13-C13 -> 2989275.9 | E13: 4270394.1 | F13: 2496280 | G13: 1326204.1 | H13: =C13/3 -> 427039.41
A14: 45231 | B14: 45256 | C14: =E14*0.3 -> 770891.7 | D14: =E14-C14 -> 1798747.3 | E14: 2569639 | F14: 1719140 | G14: 850499 | H14: =C14/3 -> 256963.9
A15: Total | C15: =SUM(C2:C14) -> 4079708.1 | D15: =SUM(D2:D14) -> 9519319 | E15: =SUM(E2:E14) -> 13599027 | F15: =SUM(F2:F14) -> 7339689 | G15: =SUM(G2:G14) -> 5811428.1 | H15: =SUM(H2:H14) -> 1359902.7
A18: Item(Packing) | B18: Actual Rate | C18: Sell Price | D18: Profit Per box | E18: Profit(%)
A19: T0(180) | B19: =(1.1*180)+52+6+20 -> 276 | C19: =180*2 -> 360 | D19: =C19-B19 -> 84 | E19: =D19/B19 -> 0.30434783
A20: T0(200) | B20: =(1.1*200)+52+6+20 -> 298 | C20: =200*2 -> 400 | D20: =C20-B20 -> 102 | E20: =D20/B20 -> 0.34228188
A21: T00(195) | B21: =(1.1*195)+52+6+20 -> 292.5 | C21: =195*2 -> 390 | D21: =C21-B21 -> 97.5 | E21: =D21/B21 -> 0.33333333
A22: T00(200) | B22: =(1.1*200)+52+6+20 -> 298 | C22: =200*2 -> 400 | D22: =C22-B22 -> 102 | E22: =D22/B22 -> 0.34228188
A23: T3(100) | B23: =(1.4*100)+52+6 -> 198 | C23: =100*3.5 -> 350 | D23: =C23-B23 -> 152 | E23: =D23/B23 -> 0.76767677
A24: Chai Kulhad big(100) | B24: =(2*100)+52+6 -> 258 | C24: =100*5 -> 500 | D24: =C24-B24 -> 242 | E24: =D24/B24 -> 0.9379845
A25: Chai Kulhad small(180) | B25: =(1.3*180)+52+6 -> 292 | C25: =180*2.4 -> 432 | D25: =C25-B25 -> 140 | E25: =D25/B25 -> 0.47945205
A26: T5(90) | B26: =(1.8*90)+52+6 -> 220 | C26: =90*5 -> 450 | D26: =C26-B26 -> 230 | E26: =D26/B26 -> 1.0454545
A27: T9(63) | B27: =(2.5*90)+52+6 -> 283 | C27: =63*7 -> 441 | D27: =C27-B27 -> 158 | E27: =D27/B27 -> 0.55830389
A28: Handi(500gms) | B28: =(12*18)+52+6 -> 274 | C28: =30*18 -> 540 | D28: =C28-B28 -> 266 | E28: =D28/B28 -> 0.97080292
A29: Handi(1000gms) | B29: =(17*12)+52+6 -> 262 | C29: =50*12 -> 600 | D29: =C29-B29 -> 338 | E29: =D29/B29 -> 1.2900763
A30: Handi(1500gms) | B30: =(10*27)+52+6 -> 328 | C30: =80*10 -> 800 | D30: =C30-B30 -> 472 | E30: =D30/B30 -> 1.4390244
A31: Lid | B31: =(30*5)+52+6 -> 208 | C31: =10*30 -> 300 | D31: =C31-B31 -> 92 | E31: =D31/B31 -> 0.44230769

Sheet January 2023
A1: Date | B1: Profit | C1: Actual | D1: Total | E1: Cash | F1: Account Transfer | G1: Expense | H1: Percentage | I1: Cash In Hand | K1: Date | L1: Profit | M1: Actual | N1: Total | O1: Cash | P1: Account Transfer | Q1: Expense
A2: 44928 | B2: =D2*0.3 -> 1242 | C2: =D2-B2 -> 2898 | D2: =E2+F2 -> 4140 | E2: 4060 | F2: 80 | G2: 100 | H2: =IFERROR(B2/C2,0) -> 0.42857143 | I2: =SUM($D$2:D2)-SUM($G$2:G2) -> 4040 | K2: Export | Q2: 0
A3: 44929 | B3: =D3*0.3 -> 12624 | C3: =D3-B3 -> 29456 | D3: =E3+F3 -> 42080 | E3: 33690 | F3: 8390 | G3: 1110 | H3: =IFERROR(B3/C3,0) -> 0.42857143 | I3: =SUM($D$2:D3)-SUM($G$2:G3) -> 45010 | K3: =A2 -> 44928 | L3: =N3*0.39 -> 1614.6 | M3: =N3-L3 -> 2525.4 | N3: =O3+P3 -> 4140 | O3: =VLOOKUP(K3,$A$1:$H$37,5,0) -> 4060 | P3: =VLOOKUP(K3,$A$1:$H$37,6,0) -> 80 | Q3: =VLOOKUP(K3,$A$1:$H$37,7,0) -> 100
A4: 44930 | B4: =D4*0.3 -> 11262 | C4: =D4-B4 -> 26278 | D4: =E4+F4 -> 37540 | E4: 10750 | F4: 26790 | G4: 100 | H4: =IFERROR(B4/C4,0) -> 0.42857143 | I4: =SUM($D$2:D4)-SUM($G$2:G4) -> 82450 | K4: =A3 -> 44929 | L4: =N4*0.39 -> 16411.2 | M4: =N4-L4 -> 25668.8 | N4: =O4+P4 -> 42080 | O4: =VLOOKUP(K4,$A$1:$H$37,5,0) -> 33690 | P4: =VLOOKUP(K4,$A$1:$H$37,6,0) -> 8390 | Q4: =VLOOKUP(K4,$A$1:$H$37,7,0) -> 1110
A5: 44931 | B5: =D5*0.3 -> 3051.3 | C5: =D5-B5 -> 7119.7 | D5: =E5+F5 -> 10171 | E5: 9421 | F5: 750 | G5: 3590 | H5: =IFERROR(B5/C5,0) -> 0.42857143 | I5: =SUM($D$2:D5)-SUM($G$2:G5) -> 89031 | K5: =A4 -> 44930 | L5: =N5*0.39 -> 14640.6 | M5: =N5-L5 -> 22899.4 | N5: =O5+P5 -> 37540 | O5: =VLOOKUP(K5,$A$1:$H$37,5,0) -> 10750 | P5: =VLOOKUP(K5,$A$1:$H$37,6,0) -> 26790 | Q5: =VLOOKUP(K5,$A$1:$H$37,7,0) -> 100
A6: 44932 | B6: =D6*0.3 -> 19530.3 | C6: =D6-B6 -> 45570.7 | D6: =E6+F6 -> 65101 | E6: 13750 | F6: 51351 | G6: 2730 | H6: =IFERROR(B6/C6,0) -> 0.42857143 | I6: =SUM($D$2:D6)-SUM($G$2:G6) -> 151402 | K6: =A5 -> 44931 | L6: =N6*0.39 -> 3966.69 | M6: =N6-L6 -> 6204.31 | N6: =O6+P6 -> 10171 | O6: =VLOOKUP(K6,$A$1:$H$37,5,0) -> 9421 | P6: =VLOOKUP(K6,$A$1:$H$37,6,0) -> 750 | Q6: =VLOOKUP(K6,$A$1:$H$37,7,0) -> 3590
A7: 44933 | B7: =D7*0.3 -> 2805 | C7: =D7-B7 -> 6545 | D7: =E7+F7 -> 9350 | E7: 4480 | F7: 4870 | G7: 170 | H7: =IFERROR(B7/C7,0) -> 0.42857143 | I7: =SUM($D$2:D7)-SUM($G$2:G7) -> 160582 | K7: =A6 -> 44932 | L7: =N7*0.39 -> 25389.39 | M7: =N7-L7 -> 39711.61 | N7: =O7+P7 -> 65101 | O7: =VLOOKUP(K7,$A$1:$H$37,5,0) -> 13750 | P7: =VLOOKUP(K7,$A$1:$H$37,6,0) -> 51351 | Q7: =VLOOKUP(K7,$A$1:$H$37,7,0) -> 2730
A8: 44934 | B8: =D8*0.3 -> 6366 | C8: =D8-B8 -> 14854 | D8: =E8+F8 -> 21220 | E8: 12070 | F8: 9150 | G8: 8700 | H8: =IFERROR(B8/C8,0) -> 0.42857143 | I8: =SUM($D$2:D8)-SUM($G$2:G8) -> 173102 | K8: =A7 -> 44933 | L8: =N8*0.39 -> 3646.5 | M8: =N8-L8 -> 5703.5 | N8: =O8+P8 -> 9350 | O8: =VLOOKUP(K8,$A$1:$H$37,5,0) -> 4480 | P8: =VLOOKUP(K8,$A$1:$H$37,6,0) -> 4870 | Q8: =VLOOKUP(K8,$A$1:$H$37,7,0) -> 170
A9: 44935 | B9: =D9*0.3 -> 3033 | C9: =D9-B9 -> 7077 | D9: =E9+F9 -> 10110 | E9: 6680 | F9: =2880+550 -> 3430 | G9: 400 | H9: =IFERROR(B9/C9,0) -> 0.42857143 | I9: =SUM($D$2:D9)-SUM($G$2:G9) -> 182812 | K9: =A8 -> 44934 | L9: =N9*0.39 -> 8275.8 | M9: =N9-L9 -> 12944.2 | N9: =O9+P9 -> 21220 | O9: =VLOOKUP(K9,$A$1:$H$37,5,0) -> 12070 | P9: =VLOOKUP(K9,$A$1:$H$37,6,0) -> 9150 | Q9: =VLOOKUP(K9,$A$1:$H$37,7,0) -> 8700
A10: 44936 | B10: =D10*0.3 -> 6240 | C10: =D10-B10 -> 14560 | D10: =E10+F10 -> 20800 | E10: 13260 | F10: 7540 | G10: 7100 | H10: =IFERROR(B10/C10,0) -> 0.42857143 | I10: =SUM($D$2:D10)-SUM($G$2:G10) -> 196512 | K10: Total | L10: =SUM(L3:L9) -> 73944.78 | M10: =SUM(M2:M9) -> 115657.22 | N10: =SUM(N2:N9) -> 189602 | O10: =SUM(O2:O9) -> 88221 | P10: =SUM(P2:P9) -> 101381 | Q10: =SUM(Q2:Q9) -> 16500
A11: 44937 | B11: =D11*0.3 -> 1782 | C11: =D11-B11 -> 4158 | D11: =E11+F11 -> 5940 | E11: 2710 | F11: 3230 | G11: 900 | H11: =IFERROR(B11/C11,0) -> 0.42857143 | I11: =SUM($D$2:D11)-SUM($G$2:G11) -> 201552 | K11: Mul Bhag | L11: =L10/3 -> 24648.26
A12: 44938 | B12: =D12*0.3 -> 10635.3 | C12: =D12-B12 -> 24815.7 | D12: =E12+F12 -> 35451 | E12: 30020 | F12: 5431 | G12: 4520 | H12: =IFERROR(B12/C12,0) -> 0.42857143 | I12: =SUM($D$2:D12)-SUM($G$2:G12) -> 232483
A13: 44939 | B13: =D13*0.3 -> 9395.4 | C13: =D13-B13 -> 21922.6 | D13: =E13+F13 -> 31318 | E13: 24638 | F13: 6680 | G13: 2310 | H13: =IFERROR(B13/C13,0) -> 0.42857143 | I13: =SUM($D$2:D13)-SUM($G$2:G13) -> 261491 | K13: Date | L13: Profit | M13: Actual | N13: Total | O13: Cash | P13: Account Transfer | Q13: Expense
A14: 44940 | B14: =D14*0.3 -> 4305 | C14: =D14-B14 -> 10045 | D14: =E14+F14 -> 14350 | E14: 6460 | F14: 7890 | G14: 560 | H14: =IFERROR(B14/C14,0) -> 0.42857143 | I14: =SUM($D$2:D14)-SUM($G$2:G14) -> 275281 | K14: =A9 -> 44935 | L14: =N14*0.39 -> 3942.9 | M14: =N14-L14 -> 6167.1 | N14: =O14+P14 -> 10110 | O14: =VLOOKUP(K14,$A$1:$H$37,5,0) -> 6680 | P14: =VLOOKUP(K14,$A$1:$H$37,6,0) -> 3430 | Q14: =VLOOKUP(K14,$A$1:$H$37,7,0) -> 400
A15: 44941 | B15: =D15*0.3 -> 1981.2 | C15: =D15-B15 -> 4622.8 | D15: =E15+F15 -> 6604 | E15: 4124 | F15: 2480 | G15: 100 | H15: =IFERROR(B15/C15,0) -> 0.42857143 | I15: =SUM($D$2:D15)-SUM($G$2:G15) -> 281785 | K15: =A10 -> 44936 | L15: =N15*0.39 -> 8112 | M15: =N15-L15 -> 12688 | N15: =O15+P15 -> 20800 | O15: =VLOOKUP(K15,$A$1:$H$37,5,0) -> 13260 | P15: =VLOOKUP(K15,$A$1:$H$37,6,0) -> 7540 | Q15: =VLOOKUP(K15,$A$1:$H$37,7,0) -> 7100
A16: 44942 | B16: =D16*0.3 -> 5217 | C16: =D16-B16 -> 12173 | D16: =E16+F16 -> 17390 | E16: 8240 | F16: 9150 | G16: 3100 | H16: =IFERROR(B16/C16,0) -> 0.42857143 | I16: =SUM($D$2:D16)-SUM($G$2:G16) -> 296075 | K16: =A11 -> 44937 | L16: =N16*0.39 -> 2316.6 | M16: =N16-L16 -> 3623.4 | N16: =O16+P16 -> 5940 | O16: =VLOOKUP(K16,$A$1:$H$37,5,0) -> 2710 | P16: =VLOOKUP(K16,$A$1:$H$37,6,0) -> 3230 | Q16: =VLOOKUP(K16,$A$1:$H$37,7,0) -> 900
A17: 44943 | B17: =D17*0.3 -> 6028.5 | C17: =D17-B17 -> 14066.5 | D17: =E17+F17 -> 20095 | E17: 7350 | F17: 12745 | G17: 160 | H17: =IFERROR(B17/C17,0) -> 0.42857143 | I17: =SUM($D$2:D17)-SUM($G$2:G17) -> 316010 | K17: =A12 -> 44938 | L17: =N17*0.39 -> 13825.89 | M17: =N17-L17 -> 21625.11 | N17: =O17+P17 -> 35451 | O17: =VLOOKUP(K17,$A$1:$H$37,5,0) -> 30020 | P17: =VLOOKUP(K17,$A$1:$H$37,6,0) -> 5431 | Q17: =VLOOKUP(K17,$A$1:$H$37,7,0) -> 4520
A18: 44944 | B18: =D18*0.3 -> 1839 | C18: =D18-B18 -> 4291 | D18: =E18+F18 -> 6130 | E18: 600 | F18: 5530 | G18: 60 | H18: =IFERROR(B18/C18,0) -> 0.42857143 | I18: =SUM($D$2:D18)-SUM($G$2:G18) -> 322080 | K18: =A13 -> 44939 | L18: =N18*0.39 -> 12214.02 | M18: =N18-L18 -> 19103.98 | N18: =O18+P18 -> 31318 | O18: =VLOOKUP(K18,$A$1:$H$37,5,0) -> 24638 | P18: =VLOOKUP(K18,$A$1:$H$37,6,0) -> 6680 | Q18: =VLOOKUP(K18,$A$1:$H$37,7,0) -> 2310
A19: 44945 | B19: =D19*0.3 -> 2760 | C19: =D19-B19 -> 6440 | D19: =E19+F19 -> 9200 | E19: 6600 | F19: 2600 | G19: 100 | H19: =IFERROR(B19/C19,0) -> 0.42857143 | I19: =SUM($D$2:D19)-SUM($G$2:G19) -> 331180 | K19: =A14 -> 44940 | L19: =N19*0.39 -> 5596.5 | M19: =N19-L19 -> 8753.5 | N19: =O19+P19 -> 14350 | O19: =VLOOKUP(K19,$A$1:$H$37,5,0) -> 6460 | P19: =VLOOKUP(K19,$A$1:$H$37,6,0) -> 7890 | Q19: =VLOOKUP(K19,$A$1:$H$37,7,0) -> 560
A20: 44946 | B20: =D20*0.3 -> 9960 | C20: =D20-B20 -> 23240 | D20: =E20+F20 -> 33200 | E20: 11990 | F20: 21210 | G20: 6060 | H20: =IFERROR(B20/C20,0) -> 0.42857143 | I20: =SUM($D$2:D20)-SUM($G$2:G20) -> 358320 | K20: =A15 -> 44941 | L20: =N20*0.39 -> 2575.56 | M20: =N20-L20 -> 4028.44 | N20: =O20+P20 -> 6604 | O20: =VLOOKUP(K20,$A$1:$H$37,5,0) -> 4124 | P20: =VLOOKUP(K20,$A$1:$H$37,6,0) -> 2480 | Q20: =VLOOKUP(K20,$A$1:$H$37,7,0) -> 100
A21: 44947 | B21: =D21*0.3 -> 5310 | C21: =D21-B21 -> 12390 | D21: =E21+F21 -> 17700 | E21: 11200 | F21: 6500 | G21: 60 | H21: =IFERROR(B21/C21,0) -> 0.42857143 | I21: =SUM($D$2:D21)-SUM($G$2:G21) -> 375960 | K21: Total | L21: =SUM(L14:L20) -> 48583.47 | M21: =SUM(M14:M20) -> 75989.53 | N21: =SUM(N14:N20) -> 124573 | O21: =SUM(O14:O20) -> 87892 | P21: =SUM(P14:P20) -> 36681 | Q21: =SUM(Q14:Q20) -> 15890
A22: 44948 | B22: =D22*0.3 -> 1278 | C22: =D22-B22 -> 2982 | D22: =E22+F22 -> 4260 | E22: 4160 | F22: 100 | G22: 100 | H22: =IFERROR(B22/C22,0) -> 0.42857143 | I22: =SUM($D$2:D22)-SUM($G$2:G22) -> 380120 | K22: Mul Bhag | L22: =L21/3 -> 16194.49
A23: 44949 | B23: =D23*0.3 -> 2934 | C23: =D23-B23 -> 6846 | D23: =E23+F23 -> 9780 | E23: 5580 | F23: 4200 | G23: 140 | H23: =IFERROR(B23/C23,0) -> 0.42857143 | I23: =SUM($D$2:D23)-SUM($G$2:G23) -> 389760
A24: 44950 | B24: =D24*0.3 -> 2191.5 | C24: =D24-B24 -> 5113.5 | D24: =E24+F24 -> 7305 | E24: 4730 | F24: 2575 | G24: 260 | H24: =IFERROR(B24/C24,0) -> 0.42857143 | I24: =SUM($D$2:D24)-SUM($G$2:G24) -> 396805 | K24: Date | L24: Profit | M24: Actual | N24: Total | O24: Cash | P24: Account Transfer | Q24: Expense
A25: 44951 | B25: =D25*0.3 -> 4194 | C25: =D25-B25 -> 9786 | D25: =E25+F25 -> 13980 | E25: 10140 | F25: 3840 | G25: 260 | H25: =IFERROR(B25/C25,0) -> 0.42857143 | I25: =SUM($D$2:D25)-SUM($G$2:G25) -> 410525 | K25: =A16 -> 44942 | L25: =N25*0.39 -> 6782.1 | M25: =N25-L25 -> 10607.9 | N25: =O25+P25 -> 17390 | O25: =VLOOKUP(K25,$A$1:$H$37,5,0) -> 8240 | P25: =VLOOKUP(K25,$A$1:$H$37,6,0) -> 9150 | Q25: =VLOOKUP(K25,$A$1:$H$37,7,0) -> 3100
A26: 44952 | B26: =D26*0.3 -> 1204.5 | C26: =D26-B26 -> 2810.5 | D26: =E26+F26 -> 4015 | E26: 3585 | F26: 430 | G26: 435 | H26: =IFERROR(B26/C26,0) -> 0.42857143 | I26: =SUM($D$2:D26)-SUM($G$2:G26) -> 414105 | K26: =A17 -> 44943 | L26: =N26*0.39 -> 7837.05 | M26: =N26-L26 -> 12257.95 | N26: =O26+P26 -> 20095 | O26: =VLOOKUP(K26,$A$1:$H$37,5,0) -> 7350 | P26: =VLOOKUP(K26,$A$1:$H$37,6,0) -> 12745 | Q26: =VLOOKUP(K26,$A$1:$H$37,7,0) -> 160
A27: 44953 | B27: =D27*0.3 -> 8373 | C27: =D27-B27 -> 19537 | D27: =E27+F27 -> 27910 | E27: 10180 | F27: 17730 | G27: 1360 | H27: =IFERROR(B27/C27,0) -> 0.42857143 | I27: =SUM($D$2:D27)-SUM($G$2:G27) -> 440655 | K27: =A18 -> 44944 | L27: =N27*0.39 -> 2390.7 | M27: =N27-L27 -> 3739.3 | N27: =O27+P27 -> 6130 | O27: =VLOOKUP(K27,$A$1:$H$37,5,0) -> 600 | P27: =VLOOKUP(K27,$A$1:$H$37,6,0) -> 5530 | Q27: =VLOOKUP(K27,$A$1:$H$37,7,0) -> 60
A28: 44954 | B28: =D28*0.3 -> 10746 | C28: =D28-B28 -> 25074 | D28: =E28+F28 -> 35820 | E28: 18090 | F28: 17730 | G28: 1360 | H28: =IFERROR(B28/C28,0) -> 0.42857143 | I28: =SUM($D$2:D28)-SUM($G$2:G28) -> 475115 | K28: =A19 -> 44945 | L28: =N28*0.39 -> 3588 | M28: =N28-L28 -> 5612 | N28: =O28+P28 -> 9200 | O28: =VLOOKUP(K28,$A$1:$H$37,5,0) -> 6600 | P28: =VLOOKUP(K28,$A$1:$H$37,6,0) -> 2600 | Q28: =VLOOKUP(K28,$A$1:$H$37,7,0) -> 100
A29: 44955 | B29: =D29*0.3 -> 4564.5 | C29: =D29-B29 -> 10650.5 | D29: =E29+F29 -> 15215 | E29: 5735 | F29: 9480 | G29: 2000 | H29: =IFERROR(B29/C29,0) -> 0.42857143 | I29: =SUM($D$2:D29)-SUM($G$2:G29) -> 488330 | K29: =A20 -> 44946 | L29: =N29*0.39 -> 12948 | M29: =N29-L29 -> 20252 | N29: =O29+P29 -> 33200 | O29: =VLOOKUP(K29,$A$1:$H$37,5,0) -> 11990 | P29: =VLOOKUP(K29,$A$1:$H$37,6,0) -> 21210 | Q29: =VLOOKUP(K29,$A$1:$H$37,7,0) -> 6060
A30: 44956 | B30: =D30*0.3 -> 3597 | C30: =D30-B30 -> 8393 | D30: =E30+F30 -> 11990 | E30: 6735 | F30: 5255 | G30: 1165 | H30: =IFERROR(B30/C30,0) -> 0.42857143 | I30: =SUM($D$2:D30)-SUM($G$2:G30) -> 499155 | K30: =A21 -> 44947 | L30: =N30*0.39 -> 6903 | M30: =N30-L30 -> 10797 | N30: =O30+P30 -> 17700 | O30: =VLOOKUP(K30,$A$1:$H$37,5,0) -> 11200 | P30: =VLOOKUP(K30,$A$1:$H$37,6,0) -> 6500 | Q30: =VLOOKUP(K30,$A$1:$H$37,7,0) -> 60
A31: 44957 | B31: =D31*0.3 -> 10233 | C31: =D31-B31 -> 23877 | D31: =E31+F31 -> 34110 | E31: 13510 | F31: 20600 | G31: 100 | H31: =IFERROR(B31/C31,0) -> 0.42857143 | I31: =SUM($D$2:D31)-SUM($G$2:G31) -> 533165 | K31: =A22 -> 44948 | L31: =N31*0.39 -> 1661.4 | M31: =N31-L31 -> 2598.6 | N31: =O31+P31 -> 4260 | O31: =VLOOKUP(K31,$A$1:$H$37,5,0) -> 4160 | P31: =VLOOKUP(K31,$A$1:$H$37,6,0) -> 100 | Q31: =VLOOKUP(K31,$A$1:$H$37,7,0) -> 100
A32: 44958 | B32: =D32*0.3 -> 5409 | C32: =D32-B32 -> 12621 | D32: =E32+F32 -> 18030 | E32: 8610 | F32: 9420 | G32: 6110 | H32: =IFERROR(B32/C32,0) -> 0.42857143 | I32: =SUM($D$2:D32)-SUM($G$2:G32) -> 545085 | K32: Total | L32: =SUM(L25:L31) -> 42110.25 | M32: =SUM(M25:M31) -> 65864.75 | N32: =SUM(N25:N31) -> 107975 | O32: =SUM(O25:O31) -> 50140 | P32: =SUM(P25:P31) -> 57835 | Q32: =SUM(Q25:Q31) -> 9640
A33: 44959 | B33: =D33*0.3 -> 6147 | C33: =D33-B33 -> 14343 | D33: =E33+F33 -> 20490 | E33: 17450 | F33: 3040 | G33: 5250 | H33: =IFERROR(B33/C33,0) -> 0.42857143 | I33: =SUM($D$2:D33)-SUM($G$2:G33) -> 560325 | K33: Mul Bhag | L33: =L32/3 -> 14036.75
A34: 44960 | B34: =D34*0.3 -> 6354 | C34: =D34-B34 -> 14826 | D34: =E34+F34 -> 21180 | E34: 11880 | F34: 9300 | G34: 200 | H34: =IFERROR(B34/C34,0) -> 0.42857143 | I34: =SUM($D$2:D34)-SUM($G$2:G34) -> 581305
A35: 44961 | B35: =D35*0.3 -> 7572 | C35: =D35-B35 -> 17668 | D35: =E35+F35 -> 25240 | E35: 17070 | F35: 8170 | G35: 5720 | H35: =IFERROR(B35/C35,0) -> 0.42857143 | I35: =SUM($D$2:D35)-SUM($G$2:G35) -> 600825 | K35: Date | L35: Profit | M35: Actual | N35: Total | O35: Cash | P35: Account Transfer | Q35: Expense
A36: 44962 | B36: =D36*0.3 -> 3457.5 | C36: =D36-B36 -> 8067.5 | D36: =E36+F36 -> 11525 | E36: 6615 | F36: 4910 | G36: 450 | H36: =IFERROR(B36/C36,0) -> 0.42857143 | I36: =SUM($D$2:D36)-SUM($G$2:G36) -> 611900 | K36: =A23 -> 44949 | L36: =N36*0.39 -> 3814.2 | M36: =N36-L36 -> 5965.8 | N36: =O36+P36 -> 9780 | O36: =VLOOKUP(K36,$A$1:$H$37,5,0) -> 5580 | P36: =VLOOKUP(K36,$A$1:$H$37,6,0) -> 4200 | Q36: =VLOOKUP(K36,$A$1:$H$37,7,0) -> 140
A37: Total | B37: =SUM(B3:B31) -> 173440.5 | C37: =SUM(C3:C31) -> 404694.5 | D37: =SUM(D3:D31) -> 578135 | E37: =SUM(E3:E31) -> 300478 | F37: =SUM(F3:F31) -> 277657 | G37: =SUM(G3:G31) -> 49010 | H37: =SUM(H3:H31) -> 12.428571 | I37: =SUM(I3:I31) -> 8760853 | K37: =A24 -> 44950 | L37: =N37*0.39 -> 2848.95 | M37: =N37-L37 -> 4456.05 | N37: =O37+P37 -> 7305 | O37: =VLOOKUP(K37,$A$1:$H$37,5,0) -> 4730 | P37: =VLOOKUP(K37,$A$1:$H$37,6,0) -> 2575 | Q37: =VLOOKUP(K37,$A$1:$H$37,7,0) -> 260
B38: =B37/3 -> 57813.5 | E38: =D37*0.42 -> 242816.7 | K38: =A25 -> 44951 | L38: =N38*0.39 -> 5452.2 | M38: =N38-L38 -> 8527.8 | N38: =O38+P38 -> 13980 | O38: =VLOOKUP(K38,$A$1:$H$37,5,0) -> 10140 | P38: =VLOOKUP(K38,$A$1:$H$37,6,0) -> 3840 | Q38: =VLOOKUP(K38,$A$1:$H$37,7,0) -> 260
B39: =B38*100/D37 -> 10 | E39: =E38/3 -> 80938.9 | K39: =A26 -> 44952 | L39: =N39*0.39 -> 1565.85 | M39: =N39-L39 -> 2449.15 | N39: =O39+P39 -> 4015 | O39: =VLOOKUP(K39,$A$1:$H$37,5,0) -> 3585 | P39: =VLOOKUP(K39,$A$1:$H$37,6,0) -> 430 | Q39: =VLOOKUP(K39,$A$1:$H$37,7,0) -> 435
K40: =A27 -> 44953 | L40: =N40*0.39 -> 10884.9 | M40: =N40-L40 -> 17025.1 | N40: =O40+P40 -> 27910 | O40: =VLOOKUP(K40,$A$1:$H$37,5,0) -> 10180 | P40: =VLOOKUP(K40,$A$1:$H$37,6,0) -> 17730 | Q40: =VLOOKUP(K40,$A$1:$H$37,7,0) -> 1360
K41: =A28 -> 44954 | L41: =N41*0.39 -> 13969.8 | M41: =N41-L41 -> 21850.2 | N41: =O41+P41 -> 35820 | O41: =VLOOKUP(K41,$A$1:$H$37,5,0) -> 18090 | P41: =VLOOKUP(K41,$A$1:$H$37,6,0) -> 17730 | Q41: =VLOOKUP(K41,$A$1:$H$37,7,0) -> 1360
A42: Date | B42: Profit | C42: Actual | D42: Total | E42: Cash | F42: Account Transfer | G42: Expense | K42: =A29 -> 44955 | L42: =N42*0.39 -> 5933.85 | M42: =N42-L42 -> 9281.15 | N42: =O42+P42 -> 15215 | O42: =VLOOKUP(K42,$A$1:$H$37,5,0) -> 5735 | P42: =VLOOKUP(K42,$A$1:$H$37,6,0) -> 9480 | Q42: =VLOOKUP(K42,$A$1:$H$37,7,0) -> 2000
A43: 44921 | B43: 2862.6 | C43: 4477.4 | D43: 7340 | E43: 6940 | F43: 400 | G43: 6570 | K43: Total | L43: =SUM(L36:L42) -> 44469.75 | M43: =SUM(M36:M42) -> 69555.25 | N43: =SUM(N36:N42) -> 114025 | O43: =SUM(O36:O42) -> 58040 | P43: =SUM(P36:P42) -> 55985 | Q43: =SUM(Q36:Q42) -> 5815
A44: 44922 | B44: 5873.4 | C44: 9186.6 | D44: 15060 | E44: 14060 | F44: 1000 | G44: 350 | K44: Mul Bhag | L44: =L43/3 -> 14823.25
A45: 44923 | B45: 11009.7 | C45: 17220.3 | D45: 28230 | E45: 13560 | F45: 14670 | G45: 3305
A46: 44924 | B46: 7692.36 | C46: 12031.64 | D46: 19724 | E46: 14090 | F46: 5634 | G46: 1440 | K46: Date | L46: Profit | M46: Actual | N46: Total | O46: Cash | P46: Account Transfer | Q46: Expense
A47: 44925 | B47: 7179.9 | C47: 11230.1 | D47: 18410 | E47: 9390 | F47: 9020 | G47: 220 | K47: =A30 -> 44956 | L47: =N47*0.39 -> 4676.1 | M47: =N47-L47 -> 7313.9 | N47: =O47+P47 -> 11990 | O47: =VLOOKUP(K47,$A$1:$H$37,5,0) -> 6735 | P47: =VLOOKUP(K47,$A$1:$H$37,6,0) -> 5255 | Q47: =VLOOKUP(K47,$A$1:$H$37,7,0) -> 1165
A48: 44926 | B48: 5087.55 | C48: 7957.45 | D48: 13045 | E48: 10150 | F48: 2895 | G48: 1490 | K48: =A31 -> 44957 | L48: =N48*0.39 -> 13302.9 | M48: =N48-L48 -> 20807.1 | N48: =O48+P48 -> 34110 | O48: =VLOOKUP(K48,$A$1:$H$37,5,0) -> 13510 | P48: =VLOOKUP(K48,$A$1:$H$37,6,0) -> 20600 | Q48: =VLOOKUP(K48,$A$1:$H$37,7,0) -> 100
A49: 44927 | B49: 1735.5 | C49: 2714.5 | D49: 4450 | E49: 3870 | F49: 580 | G49: 400 | K49: =A32 -> 44958 | L49: =N49*0.39 -> 7031.7 | M49: =N49-L49 -> 10998.3 | N49: =O49+P49 -> 18030 | O49: =VLOOKUP(K49,$A$1:$H$37,5,0) -> 8610 | P49: =VLOOKUP(K49,$A$1:$H$37,6,0) -> 9420 | Q49: =VLOOKUP(K49,$A$1:$H$37,7,0) -> 6110
A50: Total | B50: 41441.01 | C50: 64817.99 | D50: 106259 | E50: =SUM(E43:E49) -> 72060 | F50: =SUM(F43:F49) -> 34199 | G50: =SUM(G43:G49) -> 13775 | K50: =A33 -> 44959 | L50: =N50*0.39 -> 7991.1 | M50: =N50-L50 -> 12498.9 | N50: =O50+P50 -> 20490 | O50: =VLOOKUP(K50,$A$1:$H$37,5,0) -> 17450 | P50: =VLOOKUP(K50,$A$1:$H$37,6,0) -> 3040 | Q50: =VLOOKUP(K50,$A$1:$H$37,7,0) -> 5250
A51: Mul Bhag | B51: 13813.67 | K51: =A34 -> 44960 | L51: =N51*0.39 -> 8260.2 | M51: =N51-L51 -> 12919.8 | N51: =O51+P51 -> 21180 | O51: =VLOOKUP(K51,$A$1:$H$37,5,0) -> 11880 | P51: =VLOOKUP(K51,$A$1:$H$37,6,0) -> 9300 | Q51: =VLOOKUP(K51,$A$1:$H$37,7,0) -> 200
K52: =A35 -> 44961 | L52: =N52*0.39 -> 9843.6 | M52: =N52-L52 -> 15396.4 | N52: =O52+P52 -> 25240 | O52: =VLOOKUP(K52,$A$1:$H$37,5,0) -> 17070 | P52: =VLOOKUP(K52,$A$1:$H$37,6,0) -> 8170 | Q52: =VLOOKUP(K52,$A$1:$H$37,7,0) -> 5720
A53: Date | B53: Profit | C53: Actual | D53: Total | E53: Cash | F53: Account Transfer | G53: Expense | H53: Mul Bhag | K53: =A36 -> 44962 | L53: =N53*0.39 -> 4494.75 | M53: =N53-L53 -> 7030.25 | N53: =O53+P53 -> 11525 | O53: =VLOOKUP(K53,$A$1:$H$37,5,0) -> 6615 | P53: =VLOOKUP(K53,$A$1:$H$37,6,0) -> 4910 | Q53: =VLOOKUP(K53,$A$1:$H$37,7,0) -> 450
A54: 26-01-2023 to 01-01-2023 | B54: 41441.01 | C54: 64817.99 | D54: 106259 | E54: 72060 | F54: 34199 | G54: 13775 | H54: =B54/3 -> 13813.67 | K54: Total | L54: =SUM(L47:L53) -> 55600.35 | M54: =SUM(M47:M53) -> 86964.65 | N54: =SUM(N47:N53) -> 142565 | O54: =SUM(O47:O53) -> 81870 | P54: =SUM(P47:P53) -> 60695 | Q54: =SUM(Q47:Q53) -> 18995
A55: 02-01-2023 to 08-01-2023 | B55: 73944.78 | C55: 115657.22 | D55: 189602 | E55: 88221 | F55: 101381 | G55: 16500 | H55: =B55/3 -> 24648.26 | K55: Mul Bhag | L55: =L54/3 -> 18533.45
A56: 09-01-2023 to15-01-2023 | B56: 48583.47 | C56: 75989.53 | D56: 124573 | E56: 87892 | F56: 36681 | G56: 15890 | H56: =B56/3 -> 16194.49
A57: 16-01-2023 to 22-01-2023 | B57: 42110.25 | C57: 65864.75 | D57: 107975 | E57: 50140 | F57: 57835 | G57: 9640 | H57: =B57/3 -> 14036.75
A58: 23-01-2023 to 29-01-2023 | B58: 44469.75 | C58: 69555.25 | D58: 114025 | E58: 58040 | F58: 55985 | G58: 5815 | H58: =B58/3 -> 14823.25 | K58: Date | L58: Profit | M58: Actual | N58: Total | O58: Cash | P58: Account Transfer | Q58: Expense
A59: 30-01-2023 to 05-02-2023 | B59: 55600.35 | C59: 86964.65 | D59: 142565 | E59: 81870 | F59: 60695 | G59: 18995 | H59: =B59/3 -> 18533.45 | K59: =A6 -> 44932 | L59: =SUM(B2:B31) -> 174682.5 | M59: =SUM(C2:C31) -> 407592.5 | N59: =SUM(D2:D31) -> 582275 | O59: =SUM(E2:E31) -> 304538 | P59: =SUM(F2:F31) -> 277737 | Q59: =SUM(G2:G31) -> 49110
C60: Total | H60: =SUM(H54:H59) -> 102049.87 | K60: Mul Bhag | L60: =L59/3 -> 58227.5

Sheet Febuary 2023
A1: Date | B1: Profit | C1: Actual | D1: Total | E1: Cash | F1: Account Transfer | G1: Expense | H1: Percentage | I1: Cash In Hand | K1: Date | L1: Profit | M1: Actual | N1: Total | O1: Cash | P1: Account Transfer | Q1: Expense
A2: 44956 | B2: =D2*0.3 -> 3597 | C2: =D2-B2 -> 8393 | D2: =E2+F2 -> 11990 | E2: 6735 | F2: 5255 | G2: 1165 | H2: =IFERROR(B2/C2,0) -> 0.42857143 | I2: =SUM($D$2:D2)-SUM($G$2:G2) -> 10825 | K2: Export | Q2: 0
A3: 44957 | B3: =D3*0.3 -> 10233 | C3: =D3-B3 -> 23877 | D3: =E3+F3 -> 34110 | E3: 13510 | F3: 20600 | G3: 100 | H3: =IFERROR(B3/C3,0) -> 0.42857143 | I3: =SUM($D$2:D3)-SUM($G$2:G3) -> 44835 | K3: =A2 -> 44956 | L3: =N3*0.39 -> 4676.1 | M3: =N3-L3 -> 7313.9 | N3: =O3+P3 -> 11990 | O3: =VLOOKUP(K3,$A$1:$H$37,5,0) -> 6735 | P3: =VLOOKUP(K3,$A$1:$H$37,6,0) -> 5255 | Q3: =VLOOKUP(K3,$A$1:$H$37,7,0) -> 1165
A4: 44958 | B4: =D4*0.3 -> 5409 | C4: =D4-B4 -> 12621 | D4: =E4+F4 -> 18030 | E4: 8610 | F4: 9420 | G4: 6110 | H4: =IFERROR(B4/C4,0) -> 0.42857143 | I4: =SUM($D$2:D4)-SUM($G$2:G4) -> 56755 | K4: =A3 -> 44957 | L4: =N4*0.39 -> 13302.9 | M4: =N4-L4 -> 20807.1 | N4: =O4+P4 -> 34110 | O4: =VLOOKUP(K4,$A$1:$H$37,5,0) -> 13510 | P4: =VLOOKUP(K4,$A$1:$H$37,6,0) -> 20600 | Q4: =VLOOKUP(K4,$A$1:$H$37,7,0) -> 100
A5: 44959 | B5: =D5*0.3 -> 6147 | C5: =D5-B5 -> 14343 | D5: =E5+F5 -> 20490 | E5: 17450 | F5: 3040 | G5: 5250 | H5: =IFERROR(B5/C5,0) -> 0.42857143 | I5: =SUM($D$2:D5)-SUM($G$2:G5) -> 71995 | K5: =A4 -> 44958 | L5: =N5*0.39 -> 7031.7 | M5: =N5-L5 -> 10998.3 | N5: =O5+P5 -> 18030 | O5: =VLOOKUP(K5,$A$1:$H$37,5,0) -> 8610 | P5: =VLOOKUP(K5,$A$1:$H$37,6,0) -> 9420 | Q5: =VLOOKUP(K5,$A$1:$H$37,7,0) -> 6110
A6: 44960 | B6: =D6*0.3 -> 6354 | C6: =D6-B6 -> 14826 | D6: =E6+F6 -> 21180 | E6: 11880 | F6: 9300 | G6: 200 | H6: =IFERROR(B6/C6,0) -> 0.42857143 | I6: =SUM($D$2:D6)-SUM($G$2:G6) -> 92975 | K6: =A5 -> 44959 | L6: =N6*0.39 -> 7991.1 | M6: =N6-L6 -> 12498.9 | N6: =O6+P6 -> 20490 | O6: =VLOOKUP(K6,$A$1:$H$37,5,0) -> 17450 | P6: =VLOOKUP(K6,$A$1:$H$37,6,0) -> 3040 | Q6: =VLOOKUP(K6,$A$1:$H$37,7,0) -> 5250
A7: 44961 | B7: =D7*0.3 -> 7572 | C7: =D7-B7 -> 17668 | D7: =E7+F7 -> 25240 | E7: 17070 | F7: 8170 | G7: 5720 | H7: =IFERROR(B7/C7,0) -> 0.42857143 | I7: =SUM($D$2:D7)-SUM($G$2:G7) -> 112495 | K7: =A6 -> 44960 | L7: =N7*0.39 -> 8260.2 | M7: =N7-L7 -> 12919.8 | N7: =O7+P7 -> 21180 | O7: =VLOOKUP(K7,$A$1:$H$37,5,0) -> 11880 | P7: =VLOOKUP(K7,$A$1:$H$37,6,0) -> 9300 | Q7: =VLOOKUP(K7,$A$1:$H$37,7,0) -> 200
A8: 44962 | B8: =D8*0.3 -> 3457.5 | C8: =D8-B8 -> 8067.5 | D8: =E8+F8 -> 11525 | E8: 6615 | F8: 4910 | G8: 450 | H8: =IFERROR(B8/C8,0) -> 0.42857143 | I8: =SUM($D$2:D8)-SUM($G$2:G8) -> 123570 | K8: =A7 -> 44961 | L8: =N8*0.39 -> 9843.6 | M8: =N8-L8 -> 15396.4 | N8: =O8+P8 -> 25240 | O8: =VLOOKUP(K8,$A$1:$H$37,5,0) -> 17070 | P8: =VLOOKUP(K8,$A$1:$H$37,6,0) -> 8170 | Q8: =VLOOKUP(K8,$A$1:$H$37,7,0) -> 5720
A9: 44963 | B9: =D9*0.3 -> 3883.5 | C9: =D9-B9 -> 9061.5 | D9: =E9+F9 -> 12945 | E9: 3825 | F9: 9120 | G9: 1100 | H9: =IFERROR(B9/C9,0) -> 0.42857143 | I9: =SUM($D$2:D9)-SUM($G$2:G9) -> 135415 | K9: =A8 -> 44962 | L9: =N9*0.39 -> 4494.75 | M9: =N9-L9 -> 7030.25 | N9: =O9+P9 -> 11525 | O9: =VLOOKUP(K9,$A$1:$H$37,5,0) -> 6615 | P9: =VLOOKUP(K9,$A$1:$H$37,6,0) -> 4910 | Q9: =VLOOKUP(K9,$A$1:$H$37,7,0) -> 450
A10: 44964 | B10: =D10*0.3 -> 10995.6 | C10: =D10-B10 -> 25656.4 | D10: =E10+F10 -> 36652 | E10: 26892 | F10: 9760 | G10: 1020 | H10: =IFERROR(B10/C10,0) -> 0.42857143 | I10: =SUM($D$2:D10)-SUM($G$2:G10) -> 171047 | K10: Total | L10: =SUM(L3:L9) -> 55600.35 | M10: =SUM(M2:M9) -> 86964.65 | N10: =SUM(N2:N9) -> 142565 | O10: =SUM(O2:O9) -> 81870 | P10: =SUM(P2:P9) -> 60695 | Q10: =SUM(Q2:Q9) -> 18995
A11: 44965 | B11: =D11*0.3 -> 6683.7 | C11: =D11-B11 -> 15595.3 | D11: =E11+F11 -> 22279 | E11: 15235 | F11: 7044 | G11: 1920 | H11: =IFERROR(B11/C11,0) -> 0.42857143 | I11: =SUM($D$2:D11)-SUM($G$2:G11) -> 191406 | K11: Mul Bhag | L11: =L10/3 -> 18533.45
A12: 44966 | B12: =D12*0.3 -> 26995.5 | C12: =D12-B12 -> 62989.5 | D12: =E12+F12 -> 89985 | E12: 3750 | F12: 86235 | G12: 220 | H12: =IFERROR(B12/C12,0) -> 0.42857143 | I12: =SUM($D$2:D12)-SUM($G$2:G12) -> 281171
A13: 44967 | B13: =D13*0.3 -> 4899 | C13: =D13-B13 -> 11431 | D13: =E13+F13 -> 16330 | E13: 11890 | F13: 4440 | G13: 3890 | H13: =IFERROR(B13/C13,0) -> 0.42857143 | I13: =SUM($D$2:D13)-SUM($G$2:G13) -> 293611 | K13: Date | L13: Profit | M13: Actual | N13: Total | O13: Cash | P13: Account Transfer | Q13: Expense
A14: 44968 | B14: =D14*0.3 -> 17361 | C14: =D14-B14 -> 40509 | D14: =E14+F14 -> 57870 | E14: =33890+430 -> 34320 | F14: 23550 | G14: 2000 | H14: =IFERROR(B14/C14,0) -> 0.42857143 | I14: =SUM($D$2:D14)-SUM($G$2:G14) -> 349481 | K14: =A9 -> 44963 | L14: =N14*0.39 -> 5048.55 | M14: =N14-L14 -> 7896.45 | N14: =O14+P14 -> 12945 | O14: =VLOOKUP(K14,$A$1:$H$37,5,0) -> 3825 | P14: =VLOOKUP(K14,$A$1:$H$37,6,0) -> 9120 | Q14: =VLOOKUP(K14,$A$1:$H$37,7,0) -> 1100
A15: 44969 | B15: =D15*0.3 -> 12788.7 | C15: =D15-B15 -> 29840.3 | D15: =E15+F15 -> 42629 | E15: 9300 | F15: 33329 | G15: 220 | H15: =IFERROR(B15/C15,0) -> 0.42857143 | I15: =SUM($D$2:D15)-SUM($G$2:G15) -> 391890 | K15: =A10 -> 44964 | L15: =N15*0.39 -> 14294.28 | M15: =N15-L15 -> 22357.72 | N15: =O15+P15 -> 36652 | O15: =VLOOKUP(K15,$A$1:$H$37,5,0) -> 26892 | P15: =VLOOKUP(K15,$A$1:$H$37,6,0) -> 9760 | Q15: =VLOOKUP(K15,$A$1:$H$37,7,0) -> 1020
A16: 44970 | B16: =D16*0.3 -> 5730 | C16: =D16-B16 -> 13370 | D16: =E16+F16 -> 19100 | E16: 10300 | F16: 8800 | G16: 2700 | H16: =IFERROR(B16/C16,0) -> 0.42857143 | I16: =SUM($D$2:D16)-SUM($G$2:G16) -> 408290 | K16: =A11 -> 44965 | L16: =N16*0.39 -> 8688.81 | M16: =N16-L16 -> 13590.19 | N16: =O16+P16 -> 22279 | O16: =VLOOKUP(K16,$A$1:$H$37,5,0) -> 15235 | P16: =VLOOKUP(K16,$A$1:$H$37,6,0) -> 7044 | Q16: =VLOOKUP(K16,$A$1:$H$37,7,0) -> 1920
A17: 44971 | B17: =D17*0.3 -> 3387 | C17: =D17-B17 -> 7903 | D17: =E17+F17 -> 11290 | E17: 9870 | F17: 1420 | G17: 1130 | H17: =IFERROR(B17/C17,0) -> 0.42857143 | I17: =SUM($D$2:D17)-SUM($G$2:G17) -> 418450 | K17: =A12 -> 44966 | L17: =N17*0.39 -> 35094.15 | M17: =N17-L17 -> 54890.85 | N17: =O17+P17 -> 89985 | O17: =VLOOKUP(K17,$A$1:$H$37,5,0) -> 3750 | P17: =VLOOKUP(K17,$A$1:$H$37,6,0) -> 86235 | Q17: =VLOOKUP(K17,$A$1:$H$37,7,0) -> 220
A18: 44972 | B18: =D18*0.3 -> 2955 | C18: =D18-B18 -> 6895 | D18: =E18+F18 -> 9850 | E18: 7320 | F18: 2530 | G18: 17660 | H18: =IFERROR(B18/C18,0) -> 0.42857143 | I18: =SUM($D$2:D18)-SUM($G$2:G18) -> 410640 | K18: =A13 -> 44967 | L18: =N18*0.39 -> 6368.7 | M18: =N18-L18 -> 9961.3 | N18: =O18+P18 -> 16330 | O18: =VLOOKUP(K18,$A$1:$H$37,5,0) -> 11890 | P18: =VLOOKUP(K18,$A$1:$H$37,6,0) -> 4440 | Q18: =VLOOKUP(K18,$A$1:$H$37,7,0) -> 3890
A19: 44973 | B19: =D19*0.3 -> 3078 | C19: =D19-B19 -> 7182 | D19: =E19+F19 -> 10260 | E19: 1100 | F19: 9160 | G19: 0 | H19: =IFERROR(B19/C19,0) -> 0.42857143 | I19: =SUM($D$2:D19)-SUM($G$2:G19) -> 420900 | K19: =A14 -> 44968 | L19: =N19*0.39 -> 22569.3 | M19: =N19-L19 -> 35300.7 | N19: =O19+P19 -> 57870 | O19: =VLOOKUP(K19,$A$1:$H$37,5,0) -> 34320 | P19: =VLOOKUP(K19,$A$1:$H$37,6,0) -> 23550 | Q19: =VLOOKUP(K19,$A$1:$H$37,7,0) -> 2000
A20: 44974 | B20: =D20*0.3 -> 3985.5 | C20: =D20-B20 -> 9299.5 | D20: =E20+F20 -> 13285 | E20: 7220 | F20: 6065 | G20: 500 | H20: =IFERROR(B20/C20,0) -> 0.42857143 | I20: =SUM($D$2:D20)-SUM($G$2:G20) -> 433685 | K20: =A15 -> 44969 | L20: =N20*0.39 -> 16625.31 | M20: =N20-L20 -> 26003.69 | N20: =O20+P20 -> 42629 | O20: =VLOOKUP(K20,$A$1:$H$37,5,0) -> 9300 | P20: =VLOOKUP(K20,$A$1:$H$37,6,0) -> 33329 | Q20: =VLOOKUP(K20,$A$1:$H$37,7,0) -> 220
A21: 44975 | B21: =D21*0.3 -> 13852.5 | C21: =D21-B21 -> 32322.5 | D21: =E21+F21 -> 46175 | E21: 17640 | F21: 28535 | G21: 1200 | H21: =IFERROR(B21/C21,0) -> 0.42857143 | I21: =SUM($D$2:D21)-SUM($G$2:G21) -> 478660 | K21: Total | L21: =SUM(L14:L20) -> 108689.1 | M21: =SUM(M14:M20) -> 170000.9 | N21: =SUM(N14:N20) -> 278690 | O21: =SUM(O14:O20) -> 105212 | P21: =SUM(P14:P20) -> 173478 | Q21: =SUM(Q14:Q20) -> 10370
A22: 44976 | B22: =D22*0.3 -> 4338 | C22: =D22-B22 -> 10122 | D22: =E22+F22 -> 14460 | E22: 13490 | F22: 970 | G22: 2070 | H22: =IFERROR(B22/C22,0) -> 0.42857143 | I22: =SUM($D$2:D22)-SUM($G$2:G22) -> 491050 | K22: Mul Bhag | L22: =L21/3 -> 36229.7
A23: 44977 | B23: =D23*0.3 -> 1923 | C23: =D23-B23 -> 4487 | D23: =E23+F23 -> 6410 | E23: 5490 | F23: 920 | G23: 13200 | H23: =IFERROR(B23/C23,0) -> 0.42857143 | I23: =SUM($D$2:D23)-SUM($G$2:G23) -> 484260
A24: 44978 | B24: =D24*0.3 -> 4680 | C24: =D24-B24 -> 10920 | D24: =E24+F24 -> 15600 | E24: 10500 | F24: 5100 | G24: 830 | H24: =IFERROR(B24/C24,0) -> 0.42857143 | I24: =SUM($D$2:D24)-SUM($G$2:G24) -> 499030 | K24: Date | L24: Profit | M24: Actual | N24: Total | O24: Cash | P24: Account Transfer | Q24: Expense
A25: 44979 | B25: =D25*0.3 -> 17379 | C25: =D25-B25 -> 40551 | D25: =E25+F25 -> 57930 | E25: 9050 | F25: 48880 | G25: 1300 | H25: =IFERROR(B25/C25,0) -> 0.42857143 | I25: =SUM($D$2:D25)-SUM($G$2:G25) -> 555660 | K25: =A16 -> 44970 | L25: =N25*0.39 -> 7449 | M25: =N25-L25 -> 11651 | N25: =O25+P25 -> 19100 | O25: =VLOOKUP(K25,$A$1:$H$37,5,0) -> 10300 | P25: =VLOOKUP(K25,$A$1:$H$37,6,0) -> 8800 | Q25: =VLOOKUP(K25,$A$1:$H$37,7,0) -> 2700
A26: 44980 | B26: =D26*0.3 -> 18929.1 | C26: =D26-B26 -> 44167.9 | D26: =E26+F26 -> 63097 | E26: 45240 | F26: 17857 | G26: 770 | H26: =IFERROR(B26/C26,0) -> 0.42857143 | I26: =SUM($D$2:D26)-SUM($G$2:G26) -> 617987 | K26: =A17 -> 44971 | L26: =N26*0.39 -> 4403.1 | M26: =N26-L26 -> 6886.9 | N26: =O26+P26 -> 11290 | O26: =VLOOKUP(K26,$A$1:$H$37,5,0) -> 9870 | P26: =VLOOKUP(K26,$A$1:$H$37,6,0) -> 1420 | Q26: =VLOOKUP(K26,$A$1:$H$37,7,0) -> 1130
A27: 44981 | B27: =D27*0.3 -> 6217.5 | C27: =D27-B27 -> 14507.5 | D27: =E27+F27 -> 20725 | E27: 13860 | F27: 6865 | G27: 1100 | H27: =IFERROR(B27/C27,0) -> 0.42857143 | I27: =SUM($D$2:D27)-SUM($G$2:G27) -> 637612 | K27: =A18 -> 44972 | L27: =N27*0.39 -> 3841.5 | M27: =N27-L27 -> 6008.5 | N27: =O27+P27 -> 9850 | O27: =VLOOKUP(K27,$A$1:$H$37,5,0) -> 7320 | P27: =VLOOKUP(K27,$A$1:$H$37,6,0) -> 2530 | Q27: =VLOOKUP(K27,$A$1:$H$37,7,0) -> 17660
A28: 44982 | B28: =D28*0.3 -> 6785.1 | C28: =D28-B28 -> 15831.9 | D28: =E28+F28 -> 22617 | E28: 11205 | F28: 11412 | G28: 140 | H28: =IFERROR(B28/C28,0) -> 0.42857143 | I28: =SUM($D$2:D28)-SUM($G$2:G28) -> 660089 | K28: =A19 -> 44973 | L28: =N28*0.39 -> 4001.4 | M28: =N28-L28 -> 6258.6 | N28: =O28+P28 -> 10260 | O28: =VLOOKUP(K28,$A$1:$H$37,5,0) -> 1100 | P28: =VLOOKUP(K28,$A$1:$H$37,6,0) -> 9160 | Q28: =VLOOKUP(K28,$A$1:$H$37,7,0) -> 0
A29: 44983 | B29: =D29*0.3 -> 6699 | C29: =D29-B29 -> 15631 | D29: =E29+F29 -> 22330 | E29: =19270+360 -> 19630 | F29: 2700 | G29: 2200 | H29: =IFERROR(B29/C29,0) -> 0.42857143 | I29: =SUM($D$2:D29)-SUM($G$2:G29) -> 680219 | K29: =A20 -> 44974 | L29: =N29*0.39 -> 5181.15 | M29: =N29-L29 -> 8103.85 | N29: =O29+P29 -> 13285 | O29: =VLOOKUP(K29,$A$1:$H$37,5,0) -> 7220 | P29: =VLOOKUP(K29,$A$1:$H$37,6,0) -> 6065 | Q29: =VLOOKUP(K29,$A$1:$H$37,7,0) -> 500
A30: 44984 | B30: =D30*0.3 -> 5644.5 | C30: =D30-B30 -> 13170.5 | D30: =E30+F30 -> 18815 | E30: 11110 | F30: 7705 | G30: 100 | H30: =IFERROR(B30/C30,0) -> 0.42857143 | I30: =SUM($D$2:D30)-SUM($G$2:G30) -> 698934 | K30: =A21 -> 44975 | L30: =N30*0.39 -> 18008.25 | M30: =N30-L30 -> 28166.75 | N30: =O30+P30 -> 46175 | O30: =VLOOKUP(K30,$A$1:$H$37,5,0) -> 17640 | P30: =VLOOKUP(K30,$A$1:$H$37,6,0) -> 28535 | Q30: =VLOOKUP(K30,$A$1:$H$37,7,0) -> 1200
A31: 44985 | B31: =D31*0.3 -> 8643 | C31: =D31-B31 -> 20167 | D31: =E31+F31 -> 28810 | E31: 22460 | F31: 6350 | G31: 230 | H31: =IFERROR(B31/C31,0) -> 0.42857143 | I31: =SUM($D$2:D31)-SUM($G$2:G31) -> 727514 | K31: =A22 -> 44976 | L31: =N31*0.39 -> 5639.4 | M31: =N31-L31 -> 8820.6 | N31: =O31+P31 -> 14460 | O31: =VLOOKUP(K31,$A$1:$H$37,5,0) -> 13490 | P31: =VLOOKUP(K31,$A$1:$H$37,6,0) -> 970 | Q31: =VLOOKUP(K31,$A$1:$H$37,7,0) -> 2070
A32: 44986 | B32: =D32*0.3 -> 0 | C32: =D32-B32 -> 0 | D32: =E32+F32 -> 0 | H32: =IFERROR(B32/C32,0) -> 0 | I32: =SUM($D$2:D32)-SUM($G$2:G32) -> 727514 | K32: Total | L32: =SUM(L25:L31) -> 48523.8 | M32: =SUM(M25:M31) -> 75896.2 | N32: =SUM(N25:N31) -> 124420 | O32: =SUM(O25:O31) -> 66940 | P32: =SUM(P25:P31) -> 57480 | Q32: =SUM(Q25:Q31) -> 25260
A33: 44987 | B33: =D33*0.3 -> 0 | C33: =D33-B33 -> 0 | D33: =E33+F33 -> 0 | H33: =IFERROR(B33/C33,0) -> 0 | I33: =SUM($D$2:D33)-SUM($G$2:G33) -> 727514 | K33: Mul Bhag | L33: =L32/3 -> 16174.6
A34: 44988 | B34: =D34*0.3 -> 0 | C34: =D34-B34 -> 0 | D34: =E34+F34 -> 0 | H34: =IFERROR(B34/C34,0) -> 0 | I34: =SUM($D$2:D34)-SUM($G$2:G34) -> 727514
A35: 44989 | B35: =D35*0.3 -> 0 | C35: =D35-B35 -> 0 | D35: =E35+F35 -> 0 | H35: =IFERROR(B35/C35,0) -> 0 | I35: =SUM($D$2:D35)-SUM($G$2:G35) -> 727514 | K35: Date | L35: Profit | M35: Actual | N35: Total | O35: Cash | P35: Account Transfer | Q35: Expense
A36: 44990 | B36: =D36*0.3 -> 0 | C36: =D36-B36 -> 0 | D36: =E36+F36 -> 0 | H36: =IFERROR(B36/C36,0) -> 0 | I36: =SUM($D$2:D36)-SUM($G$2:G36) -> 727514 | K36: =A23 -> 44977 | L36: =N36*0.39 -> 2499.9 | M36: =N36-L36 -> 3910.1 | N36: =O36+P36 -> 6410 | O36: =VLOOKUP(K36,$A$1:$H$37,5,0) -> 5490 | P36: =VLOOKUP(K36,$A$1:$H$37,6,0) -> 920 | Q36: =VLOOKUP(K36,$A$1:$H$37,7,0) -> 13200
A37: Total | B37: =SUM(B4:B36) -> 226772.7 | C37: =SUM(C4:C36) -> 529136.3 | D37: =SUM(D4:D36) -> 755909 | E37: =SUM(E4:E36) -> 382322 | F37: =SUM(F4:F36) -> 373587 | G37: =SUM(G4:G36) -> 73230 | H37: =SUM(H4:H36) -> 12 | I37: =SUM(I4:I36) -> 14532361 | K37: =A24 -> 44978 | L37: =N37*0.39 -> 6084 | M37: =N37-L37 -> 9516 | N37: =O37+P37 -> 15600 | O37: =VLOOKUP(K37,$A$1:$H$37,5,0) -> 10500 | P37: =VLOOKUP(K37,$A$1:$H$37,6,0) -> 5100 | Q37: =VLOOKUP(K37,$A$1:$H$37,7,0) -> 830
B38: =B37/3 -> 75590.9 | E38: =D37*0.42 -> 317481.78 | K38: =A25 -> 44979 | L38: =N38*0.39 -> 22592.7 | M38: =N38-L38 -> 35337.3 | N38: =O38+P38 -> 57930 | O38: =VLOOKUP(K38,$A$1:$H$37,5,0) -> 9050 | P38: =VLOOKUP(K38,$A$1:$H$37,6,0) -> 48880 | Q38: =VLOOKUP(K38,$A$1:$H$37,7,0) -> 1300
B39: =B38*100/D37 -> 10 | E39: =E38/3 -> 105827.26 | K39: =A26 -> 44980 | L39: =N39*0.39 -> 24607.83 | M39: =N39-L39 -> 38489.17 | N39: =O39+P39 -> 63097 | O39: =VLOOKUP(K39,$A$1:$H$37,5,0) -> 45240 | P39: =VLOOKUP(K39,$A$1:$H$37,6,0) -> 17857 | Q39: =VLOOKUP(K39,$A$1:$H$37,7,0) -> 770
A40: Date | B40: Profit | C40: Actual | D40: Total | E40: Cash | F40: Account Transfer | G40: Expense | H40: Mul Bhag | K40: =A27 -> 44981 | L40: =N40*0.39 -> 8082.75 | M40: =N40-L40 -> 12642.25 | N40: =O40+P40 -> 20725 | O40: =VLOOKUP(K40,$A$1:$H$37,5,0) -> 13860 | P40: =VLOOKUP(K40,$A$1:$H$37,6,0) -> 6865 | Q40: =VLOOKUP(K40,$A$1:$H$37,7,0) -> 1100
A41: =CONCATENATE(TEXT(K3,"DD-MMM-YYY")," to ",TEXT(K9,"DD-MMM-YYYY")) -> 30-Jan-2023 to 05-Feb-2023 | B41: =L10 -> 55600.35 | C41: =M10 -> 86964.65 | D41: =N10 -> 142565 | E41: =O10 -> 81870 | F41: =P10 -> 60695 | G41: =Q10 -> 18995 | H41: =B41/3 -> 18533.45 | K41: =A28 -> 44982 | L41: =N41*0.39 -> 8820.63 | M41: =N41-L41 -> 13796.37 | N41: =O41+P41 -> 22617 | O41: =VLOOKUP(K41,$A$1:$H$37,5,0) -> 11205 | P41: =VLOOKUP(K41,$A$1:$H$37,6,0) -> 11412 | Q41: =VLOOKUP(K41,$A$1:$H$37,7,0) -> 140
A42: =CONCATENATE(TEXT(K14,"DD-MMM-YYY")," to ",TEXT(K20,"DD-MMM-YYYY")) -> 06-Feb-2023 to 12-Feb-2023 | B42: =L21 -> 108689.1 | C42: =M21 -> 170000.9 | D42: =N21 -> 278690 | E42: =O21 -> 105212 | F42: =P21 -> 173478 | G42: =Q21 -> 10370 | H42: =B42/3 -> 36229.7 | K42: =A29 -> 44983 | L42: =N42*0.39 -> 8708.7 | M42: =N42-L42 -> 13621.3 | N42: =O42+P42 -> 22330 | O42: =VLOOKUP(K42,$A$1:$H$37,5,0) -> 19630 | P42: =VLOOKUP(K42,$A$1:$H$37,6,0) -> 2700 | Q42: =VLOOKUP(K42,$A$1:$H$37,7,0) -> 2200
A43: =CONCATENATE(TEXT(K25,"DD-MMM-YYY")," to ",TEXT(K31,"DD-MMM-YYYY")) -> 13-Feb-2023 to 19-Feb-2023 | B43: =L32 -> 48523.8 | C43: =M32 -> 75896.2 | D43: =N32 -> 124420 | E43: =O32 -> 66940 | F43: =P32 -> 57480 | G43: =Q32 -> 25260 | H43: =B43/3 -> 16174.6 | K43: Total | L43: =SUM(L36:L42) -> 81396.51 | M43: =SUM(M36:M42) -> 127312.49 | N43: =SUM(N36:N42) -> 208709 | O43: =SUM(O36:O42) -> 114975 | P43: =SUM(P36:P42) -> 93734 | Q43: =SUM(Q36:Q42) -> 19540
A44: =CONCATENATE(TEXT(K36,"DD-MMM-YYY")," to ",TEXT(K42,"DD-MMM-YYYY")) -> 20-Feb-2023 to 26-Feb-2023 | B44: =L43 -> 81396.51 | C44: =M43 -> 127312.49 | D44: =N43 -> 208709 | E44: =O43 -> 114975 | F44: =P43 -> 93734 | G44: =Q43 -> 19540 | H44: =B44/3 -> 27132.17 | K44: Mul Bhag | L44: =L43/3 -> 27132.17
A45: =CONCATENATE(TEXT(K47,"DD-MMM-YYY")," to ",TEXT(K53,"DD-MMM-YYYY")) -> 27-Feb-2023 to 05-Mar-2023 | B45: =L54 -> 18573.75 | C45: =M54 -> 29051.25 | D45: =N54 -> 47625 | E45: =O54 -> 0 | F45: =P54 -> 0 | G45: =Q54 -> 0 | H45: =B45/3 -> 6191.25
A46: =CONCATENATE(TEXT(K59,"DD-MMM-YYY")," to ",TEXT(K58,"DD-MMM-YYYY")) -> 03-Feb-2023 to Date | B46: =SUM(B41:B45) -> 312783.51 | C46: =SUM(C41:C45) -> 489225.49 | D46: =SUM(D41:D45) -> 802009 | E46: =SUM(E41:E45) -> 368997 | F46: =SUM(F41:F45) -> 385387 | G46: =SUM(G41:G45) -> 74165 | H46: =SUM(H41:H45) -> 104261.17 | K46: Date | L46: Profit | M46: Actual | N46: Total | O46: Cash | P46: Account Transfer | Q46: Expense
C47: Total | K47: =A30 -> 44984 | L47: =N47*0.39 -> 7337.85 | M47: =N47-L47 -> 11477.15 | N47: =O47+P47 -> 18815 | O47: =VLOOKUP(K47,$A$1:$H$37,5,0) -> 11110 | P47: =VLOOKUP(K47,$A$1:$H$37,6,0) -> 7705 | Q47: =VLOOKUP(K47,$A$1:$H$37,7,0) -> 100
K48: =A31 -> 44985 | L48: =N48*0.39 -> 11235.9 | M48: =N48-L48 -> 17574.1 | N48: =O48+P48 -> 28810 | O48: =VLOOKUP(K48,$A$1:$H$37,5,0) -> 22460 | P48: =VLOOKUP(K48,$A$1:$H$37,6,0) -> 6350 | Q48: =VLOOKUP(K48,$A$1:$H$37,7,0) -> 230
K49: =A32 -> 44986 | L49: =N49*0.39 -> 0 | M49: =N49-L49 -> 0 | N49: =O49+P49 -> 0 | O49: =VLOOKUP(K49,$A$1:$H$37,5,0) -> 0 | P49: =VLOOKUP(K49,$A$1:$H$37,6,0) -> 0 | Q49: =VLOOKUP(K49,$A$1:$H$37,7,0) -> 0
K50: =A33 -> 44987 | L50: =N50*0.39 -> 0 | M50: =N50-L50 -> 0 | N50: =O50+P50 -> 0 | O50: =VLOOKUP(K50,$A$1:$H$37,5,0) -> 0 | P50: =VLOOKUP(K50,$A$1:$H$37,6,0) -> 0 | Q50: =VLOOKUP(K50,$A$1:$H$37,7,0) -> 0
K51: =A34 -> 44988 | L51: =N51*0.39 -> 0 | M51: =N51-L51 -> 0 | N51: =O51+P51 -> 0 | O51: =VLOOKUP(K51,$A$1:$H$37,5,0) -> 0 | P51: =VLOOKUP(K51,$A$1:$H$37,6,0) -> 0 | Q51: =VLOOKUP(K51,$A$1:$H$37,7,0) -> 0
K52: =A35 -> 44989 | L52: =N52*0.39 -> 0 | M52: =N52-L52 -> 0 | N52: =O52+P52 -> 0 | O52: =VLOOKUP(K52,$A$1:$H$37,5,0) -> 0 | P52: =VLOOKUP(K52,$A$1:$H$37,6,0) -> 0 | Q52: =VLOOKUP(K52,$A$1:$H$37,7,0) -> 0
K53: =A36 -> 44990 | L53: =N53*0.39 -> 0 | M53: =N53-L53 -> 0 | N53: =O53+P53 -> 0 | O53: =VLOOKUP(K53,$A$1:$H$37,5,0) -> 0 | P53: =VLOOKUP(K53,$A$1:$H$37,6,0) -> 0 | Q53: =VLOOKUP(K53,$A$1:$H$37,7,0) -> 0
K54: Total | L54: =SUM(L47:L53) -> 18573.75 | M54: =SUM(M47:M53) -> 29051.25 | N54: =SUM(N47:N53) -> 47625
K55: Mul Bhag | L55: =L54/3 -> 6191.25
K58: Date | L58: Profit | M58: Actual | N58: Total | O58: Cash | P58: Account Transfer | Q58: Expense
K59: =A6 -> 44960 | L59: =SUM(B4:B31) -> 226772.7 | M59: =SUM(C4:C31) -> 529136.3 | N59: =SUM(D4:D31) -> 755909 | O59: =SUM(E4:E31) -> 382322 | P59: =SUM(F4:F31) -> 373587 | Q59: =SUM(G4:G31) -> 73230
K60: Mul Bhag | L60: =L59/3 -> 75590.9

Sheet March 2023
A1: Date | B1: Profit | C1: Actual | D1: Total | E1: Cash | F1: Account Transfer | G1: Expense | H1: Percentage | I1: Cash In Hand | K1: Date | L1: Profit | M1: Actual | N1: Total | O1: Cash | P1: Account Transfer | Q1: Expense
A2: 44984 | B2: =D2*0.39 -> 7337.85 | C2: =D2-B2 -> 11477.15 | D2: =E2+F2 -> 18815 | E2: 11110 | F2: 7705 | G2: 100 | H2: =IFERROR(B2/C2,0) -> 0.63934426 | I2: =SUM($D$2:D2)-SUM($G$2:G2) -> 18715 | K2: Export | Q2: 0
A3: 44985 | B3: =D3*0.39 -> 11235.9 | C3: =D3-B3 -> 17574.1 | D3: 28810 | E3: 22460 | F3: 6350 | G3: 230 | H3: =IFERROR(B3/C3,0) -> 0.63934426 | I3: =SUM($D$2:D3)-SUM($G$2:G3) -> 47295 | K3: =A2 -> 44984 | L3: =N3*0.39 -> 7337.85 | M3: =N3-L3 -> 11477.15 | N3: =O3+P3 -> 18815 | O3: =VLOOKUP(K3,$A$1:$H$37,5,0) -> 11110 | P3: =VLOOKUP(K3,$A$1:$H$37,6,0) -> 7705 | Q3: =VLOOKUP(K3,$A$1:$H$37,7,0) -> 100
A4: 44986 | B4: =D4*0.39 -> 4849.65 | C4: =D4-B4 -> 7585.35 | D4: 12435 | E4: 8725 | F4: 3710 | G4: 5140 | H4: =IFERROR(B4/C4,0) -> 0.63934426 | I4: =SUM($D$2:D4)-SUM($G$2:G4) -> 54590 | K4: =A3 -> 44985 | L4: =N4*0.39 -> 11235.9 | M4: =N4-L4 -> 17574.1 | N4: =O4+P4 -> 28810 | O4: =VLOOKUP(K4,$A$1:$H$37,5,0) -> 22460 | P4: =VLOOKUP(K4,$A$1:$H$37,6,0) -> 6350 | Q4: =VLOOKUP(K4,$A$1:$H$37,7,0) -> 230
A5: 44987 | B5: =D5*0.39 -> 3798.6 | C5: =D5-B5 -> 5941.4 | D5: 9740 | E5: 6610 | F5: 3130 | G5: 300 | H5: =IFERROR(B5/C5,0) -> 0.63934426 | I5: =SUM($D$2:D5)-SUM($G$2:G5) -> 64030 | K5: =A4 -> 44986 | L5: =N5*0.39 -> 4849.65 | M5: =N5-L5 -> 7585.35 | N5: =O5+P5 -> 12435 | O5: =VLOOKUP(K5,$A$1:$H$37,5,0) -> 8725 | P5: =VLOOKUP(K5,$A$1:$H$37,6,0) -> 3710 | Q5: =VLOOKUP(K5,$A$1:$H$37,7,0) -> 5140
A6: 44988 | B6: =D6*0.39 -> 3572.4 | C6: =D6-B6 -> 5587.6 | D6: 9160 | E6: 5020 | F6: 4140 | G6: 19200 | H6: =IFERROR(B6/C6,0) -> 0.63934426 | I6: =SUM($D$2:D6)-SUM($G$2:G6) -> 53990 | K6: =A5 -> 44987 | L6: =N6*0.39 -> 3798.6 | M6: =N6-L6 -> 5941.4 | N6: =O6+P6 -> 9740 | O6: =VLOOKUP(K6,$A$1:$H$37,5,0) -> 6610 | P6: =VLOOKUP(K6,$A$1:$H$37,6,0) -> 3130 | Q6: =VLOOKUP(K6,$A$1:$H$37,7,0) -> 300
A7: 44989 | B7: =D7*0.39 -> 9151.35 | C7: =D7-B7 -> 14313.65 | D7: 23465 | E7: 12665 | F7: 10800 | G7: 15935 | H7: =IFERROR(B7/C7,0) -> 0.63934426 | I7: =SUM($D$2:D7)-SUM($G$2:G7) -> 61520 | K7: =A6 -> 44988 | L7: =N7*0.39 -> 3572.4 | M7: =N7-L7 -> 5587.6 | N7: =O7+P7 -> 9160 | O7: =VLOOKUP(K7,$A$1:$H$37,5,0) -> 5020 | P7: =VLOOKUP(K7,$A$1:$H$37,6,0) -> 4140 | Q7: =VLOOKUP(K7,$A$1:$H$37,7,0) -> 19200
A8: 44990 | B8: =D8*0.39 -> 18335.85 | C8: =D8-B8 -> 28679.15 | D8: 47015 | E8: 25600 | F8: 21415 | G8: 12600 | H8: =IFERROR(B8/C8,0) -> 0.63934426 | I8: =SUM($D$2:D8)-SUM($G$2:G8) -> 95935 | K8: =A7 -> 44989 | L8: =N8*0.39 -> 9151.35 | M8: =N8-L8 -> 14313.65 | N8: =O8+P8 -> 23465 | O8: =VLOOKUP(K8,$A$1:$H$37,5,0) -> 12665 | P8: =VLOOKUP(K8,$A$1:$H$37,6,0) -> 10800 | Q8: =VLOOKUP(K8,$A$1:$H$37,7,0) -> 15935
A9: 44991 | B9: =D9*0.39 -> 4688.58 | C9: =D9-B9 -> 7333.42 | D9: =E9+F9 -> 12022 | E9: 4760 | F9: 7262 | G9: 100 | H9: =IFERROR(B9/C9,0) -> 0.63934426 | I9: =SUM($D$2:D9)-SUM($G$2:G9) -> 107857 | K9: =A8 -> 44990 | L9: =N9*0.39 -> 18335.85 | M9: =N9-L9 -> 28679.15 | N9: =O9+P9 -> 47015 | O9: =VLOOKUP(K9,$A$1:$H$37,5,0) -> 25600 | P9: =VLOOKUP(K9,$A$1:$H$37,6,0) -> 21415 | Q9: =VLOOKUP(K9,$A$1:$H$37,7,0) -> 12600
A10: 44992 | B10: =D10*0.39 -> 0 | C10: =D10-B10 -> 0 | D10: =E10+F10 -> 0 | E10: 0 | H10: =IFERROR(B10/C10,0) -> 0 | I10: =SUM($D$2:D10)-SUM($G$2:G10) -> 107857 | K10: Total | L10: =SUM(L3:L9) -> 58281.6 | M10: =SUM(M2:M9) -> 91158.4 | N10: =SUM(N2:N9) -> 149440 | O10: =SUM(O2:O9) -> 92190 | P10: =SUM(P2:P9) -> 57250 | Q10: =SUM(Q2:Q9) -> 53505
A11: 44993 | B11: =D11*0.39 -> 21536.19 | C11: =D11-B11 -> 33684.81 | D11: =E11+F11 -> 55221 | E11: 7450 | F11: =47771 -> 47771 | G11: 200 | H11: =IFERROR(B11/C11,0) -> 0.63934426 | I11: =SUM($D$2:D11)-SUM($G$2:G11) -> 162878 | K11: Mul Bhag | L11: =L10/3 -> 19427.2
A12: 44994 | B12: =D12*0.39 -> 11230.05 | C12: =D12-B12 -> 17564.95 | D12: =E12+F12 -> 28795 | E12: 8450 | F12: 20345 | G12: 1880 | H12: =IFERROR(B12/C12,0) -> 0.63934426 | I12: =SUM($D$2:D12)-SUM($G$2:G12) -> 189793
A13: 44995 | B13: =D13*0.39 -> 1823.25 | C13: =D13-B13 -> 2851.75 | D13: =E13+F13 -> 4675 | E13: 3975 | F13: 700 | G13: 2200 | H13: =IFERROR(B13/C13,0) -> 0.63934426 | I13: =SUM($D$2:D13)-SUM($G$2:G13) -> 192268 | K13: Date | L13: Profit | M13: Actual | N13: Total | O13: Cash | P13: Account Transfer | Q13: Expense
A14: 44996 | B14: =D14*0.39 -> 7597.2 | C14: =D14-B14 -> 11882.8 | D14: =E14+F14 -> 19480 | E14: 8810 | F14: 10670 | G14: 3270 | H14: =IFERROR(B14/C14,0) -> 0.63934426 | I14: =SUM($D$2:D14)-SUM($G$2:G14) -> 208478 | K14: =A9 -> 44991 | L14: =N14*0.39 -> 4688.58 | M14: =N14-L14 -> 7333.42 | N14: =O14+P14 -> 12022 | O14: =VLOOKUP(K14,$A$1:$H$37,5,0) -> 4760 | P14: =VLOOKUP(K14,$A$1:$H$37,6,0) -> 7262 | Q14: =VLOOKUP(K14,$A$1:$H$37,7,0) -> 100
A15: 44997 | B15: =D15*0.39 -> 9180.6 | C15: =D15-B15 -> 14359.4 | D15: =E15+F15 -> 23540 | E15: 15765 | F15: 7775 | G15: 4200 | H15: =IFERROR(B15/C15,0) -> 0.63934426 | I15: =SUM($D$2:D15)-SUM($G$2:G15) -> 227818 | K15: =A10 -> 44992 | L15: =N15*0.39 -> 0 | M15: =N15-L15 -> 0 | N15: =O15+P15 -> 0 | O15: =VLOOKUP(K15,$A$1:$H$37,5,0) -> 0 | P15: =VLOOKUP(K15,$A$1:$H$37,6,0) -> 0 | Q15: =VLOOKUP(K15,$A$1:$H$37,7,0) -> 0
A16: 44998 | B16: =D16*0.39 -> 1620.45 | C16: =D16-B16 -> 2534.55 | D16: =E16+F16 -> 4155 | E16: 3175 | F16: 980 | G16: 230 | H16: =IFERROR(B16/C16,0) -> 0.63934426 | I16: =SUM($D$2:D16)-SUM($G$2:G16) -> 231743 | K16: =A11 -> 44993 | L16: =N16*0.3 -> 16566.3 | M16: =N16-L16 -> 38654.7 | N16: =O16+P16 -> 55221 | O16: =VLOOKUP(K16,$A$1:$H$37,5,0) -> 7450 | P16: =VLOOKUP(K16,$A$1:$H$37,6,0) -> 47771 | Q16: =VLOOKUP(K16,$A$1:$H$37,7,0) -> 200
A17: 44999 | B17: =D17*0.39 -> 2000.7 | C17: =D17-B17 -> 3129.3 | D17: =E17+F17 -> 5130 | E17: 3350 | F17: 1780 | G17: 150 | H17: =IFERROR(B17/C17,0) -> 0.63934426 | I17: =SUM($D$2:D17)-SUM($G$2:G17) -> 236723 | K17: =A12 -> 44994 | L17: =N17*0.3 -> 8638.5 | M17: =N17-L17 -> 20156.5 | N17: =O17+P17 -> 28795 | O17: =VLOOKUP(K17,$A$1:$H$37,5,0) -> 8450 | P17: =VLOOKUP(K17,$A$1:$H$37,6,0) -> 20345 | Q17: =VLOOKUP(K17,$A$1:$H$37,7,0) -> 1880
A18: 45000 | B18: =D18*0.39 -> 7597.2 | C18: =D18-B18 -> 11882.8 | D18: =E18+F18 -> 19480 | E18: 10570 | F18: 8910 | G18: 3620 | H18: =IFERROR(B18/C18,0) -> 0.63934426 | I18: =SUM($D$2:D18)-SUM($G$2:G18) -> 252583 | K18: =A13 -> 44995 | L18: =N18*0.39 -> 1823.25 | M18: =N18-L18 -> 2851.75 | N18: =O18+P18 -> 4675 | O18: =VLOOKUP(K18,$A$1:$H$37,5,0) -> 3975 | P18: =VLOOKUP(K18,$A$1:$H$37,6,0) -> 700 | Q18: =VLOOKUP(K18,$A$1:$H$37,7,0) -> 2200
A19: 45001 | B19: =D19*0.39 -> 15296.97 | C19: =D19-B19 -> 23926.03 | D19: =E19+F19 -> 39223 | E19: 7360 | F19: 31863 | G19: 1600 | H19: =IFERROR(B19/C19,0) -> 0.63934426 | I19: =SUM($D$2:D19)-SUM($G$2:G19) -> 290206 | K19: =A14 -> 44996 | L19: =N19*0.39 -> 7597.2 | M19: =N19-L19 -> 11882.8 | N19: =O19+P19 -> 19480 | O19: =VLOOKUP(K19,$A$1:$H$37,5,0) -> 8810 | P19: =VLOOKUP(K19,$A$1:$H$37,6,0) -> 10670 | Q19: =VLOOKUP(K19,$A$1:$H$37,7,0) -> 3270
A20: 45002 | B20: =D20*0.39 -> 4317.3 | C20: =D20-B20 -> 6752.7 | D20: =E20+F20 -> 11070 | E20: =5280+1800 -> 7080 | F20: =3240+750 -> 3990 | G20: 900 | H20: =IFERROR(B20/C20,0) -> 0.63934426 | I20: =SUM($D$2:D20)-SUM($G$2:G20) -> 300376 | K20: =A15 -> 44997 | L20: =N20*0.3 -> 7062 | M20: =N20-L20 -> 16478 | N20: =O20+P20 -> 23540 | O20: =VLOOKUP(K20,$A$1:$H$37,5,0) -> 15765 | P20: =VLOOKUP(K20,$A$1:$H$37,6,0) -> 7775 | Q20: =VLOOKUP(K20,$A$1:$H$37,7,0) -> 4200
A21: 45003 | B21: =D21*0.39 -> 7761 | C21: =D21-B21 -> 12139 | D21: =E21+F21 -> 19900 | E21: =5120+1080 -> 6200 | F21: 13700 | G21: 3600 | H21: =IFERROR(B21/C21,0) -> 0.63934426 | I21: =SUM($D$2:D21)-SUM($G$2:G21) -> 316676 | K21: Total | L21: =SUM(L14:L20) -> 46375.83 | M21: =SUM(M14:M20) -> 97357.17 | N21: =SUM(N14:N20) -> 143733 | O21: =SUM(O14:O20) -> 49210 | P21: =SUM(P14:P20) -> 94523 | Q21: =SUM(Q14:Q20) -> 11850
A22: 45004 | B22: =D22*0.39 -> 6576.57 | C22: =D22-B22 -> 10286.43 | D22: =E22+F22 -> 16863 | E22: =7285+4260 -> 11545 | F22: 5318 | G22: 600 | H22: =IFERROR(B22/C22,0) -> 0.63934426 | I22: =SUM($D$2:D22)-SUM($G$2:G22) -> 332939 | K22: Mul Bhag | L22: =L21/3 -> 15458.61
A23: 45005 | B23: =D23*0.39 -> 4722.9 | C23: =D23-B23 -> 7387.1 | D23: =E23+F23 -> 12110 | E23: 3980 | F23: 8130 | G23: 900 | H23: =IFERROR(B23/C23,0) -> 0.63934426 | I23: =SUM($D$2:D23)-SUM($G$2:G23) -> 344149
A24: 45006 | B24: =D24*0.39 -> 17961.45 | C24: =D24-B24 -> 28093.55 | D24: =E24+F24 -> 46055 | E24: 29915 | F24: 16140 | G24: 100 | H24: =IFERROR(B24/C24,0) -> 0.63934426 | I24: =SUM($D$2:D24)-SUM($G$2:G24) -> 390104 | K24: Date | L24: Profit | M24: Actual | N24: Total | O24: Cash | P24: Account Transfer | Q24: Expense
A25: 45007 | B25: =D25*0.39 -> 5619.9 | C25: =D25-B25 -> 8790.1 | D25: =E25+F25 -> 14410 | E25: 11070 | F25: 3340 | G25: 3130 | H25: =IFERROR(B25/C25,0) -> 0.63934426 | I25: =SUM($D$2:D25)-SUM($G$2:G25) -> 401384 | K25: =A16 -> 44998 | L25: =N25*0.39 -> 1620.45 | M25: =N25-L25 -> 2534.55 | N25: =O25+P25 -> 4155 | O25: =VLOOKUP(K25,$A$1:$H$37,5,0) -> 3175 | P25: =VLOOKUP(K25,$A$1:$H$37,6,0) -> 980 | Q25: =VLOOKUP(K25,$A$1:$H$37,7,0) -> 230
A26: 45008 | B26: =D26*0.39 -> 8819.46 | C26: =D26-B26 -> 13794.54 | D26: =E26+F26 -> 22614 | E26: 14390 | F26: 8224 | G26: 35100 | H26: =IFERROR(B26/C26,0) -> 0.63934426 | I26: =SUM($D$2:D26)-SUM($G$2:G26) -> 388898 | K26: =A17 -> 44999 | L26: =N26*0.39 -> 2000.7 | M26: =N26-L26 -> 3129.3 | N26: =O26+P26 -> 5130 | O26: =VLOOKUP(K26,$A$1:$H$37,5,0) -> 3350 | P26: =VLOOKUP(K26,$A$1:$H$37,6,0) -> 1780 | Q26: =VLOOKUP(K26,$A$1:$H$37,7,0) -> 150
A27: 45009 | B27: =D27*0.39 -> 20330.7 | C27: =D27-B27 -> 31799.3 | D27: =E27+F27 -> 52130 | E27: 8450 | F27: 43680 | G27: 3100 | H27: =IFERROR(B27/C27,0) -> 0.63934426 | I27: =SUM($D$2:D27)-SUM($G$2:G27) -> 437928 | K27: =A18 -> 45000 | L27: =N27*0.39 -> 7597.2 | M27: =N27-L27 -> 11882.8 | N27: =O27+P27 -> 19480 | O27: =VLOOKUP(K27,$A$1:$H$37,5,0) -> 10570 | P27: =VLOOKUP(K27,$A$1:$H$37,6,0) -> 8910 | Q27: =VLOOKUP(K27,$A$1:$H$37,7,0) -> 3620
A28: 45010 | B28: =D28*0.39 -> 6895.2 | C28: =D28-B28 -> 10784.8 | D28: =E28+F28 -> 17680 | E28: 3940 | F28: 13740 | G28: 2600 | H28: =IFERROR(B28/C28,0) -> 0.63934426 | I28: =SUM($D$2:D28)-SUM($G$2:G28) -> 453008 | K28: =A19 -> 45001 | L28: =N28*0.39 -> 15296.97 | M28: =N28-L28 -> 23926.03 | N28: =O28+P28 -> 39223 | O28: =VLOOKUP(K28,$A$1:$H$37,5,0) -> 7360 | P28: =VLOOKUP(K28,$A$1:$H$37,6,0) -> 31863 | Q28: =VLOOKUP(K28,$A$1:$H$37,7,0) -> 1600
A29: 45011 | B29: =D29*0.39 -> 8697 | C29: =D29-B29 -> 13603 | D29: =E29+F29 -> 22300 | E29: 16300 | F29: 6000 | G29: 6120 | H29: =IFERROR(B29/C29,0) -> 0.63934426 | I29: =SUM($D$2:D29)-SUM($G$2:G29) -> 469188 | K29: =A20 -> 45002 | L29: =N29*0.39 -> 4317.3 | M29: =N29-L29 -> 6752.7 | N29: =O29+P29 -> 11070 | O29: =VLOOKUP(K29,$A$1:$H$37,5,0) -> 7080 | P29: =VLOOKUP(K29,$A$1:$H$37,6,0) -> 3990 | Q29: =VLOOKUP(K29,$A$1:$H$37,7,0) -> 900
A30: 45012 | B30: =D30*0.39 -> 4048.2 | C30: =D30-B30 -> 6331.8 | D30: =E30+F30 -> 10380 | E30: 7630 | F30: 2750 | G30: 9840 | H30: =IFERROR(B30/C30,0) -> 0.63934426 | I30: =SUM($D$2:D30)-SUM($G$2:G30) -> 469728 | K30: =A21 -> 45003 | L30: =N30*0.39 -> 7761 | M30: =N30-L30 -> 12139 | N30: =O30+P30 -> 19900 | O30: =VLOOKUP(K30,$A$1:$H$37,5,0) -> 6200 | P30: =VLOOKUP(K30,$A$1:$H$37,6,0) -> 13700 | Q30: =VLOOKUP(K30,$A$1:$H$37,7,0) -> 3600
A31: 45013 | B31: =D31*0.39 -> 21983.52 | C31: =D31-B31 -> 34384.48 | D31: =E31+F31 -> 56368 | E31: 9120 | F31: 47248 | G31: =2280+1200 -> 3480 | H31: =IFERROR(B31/C31,0) -> 0.63934426 | I31: =SUM($D$2:D31)-SUM($G$2:G31) -> 522616 | K31: =A22 -> 45004 | L31: =N31*0.39 -> 6576.57 | M31: =N31-L31 -> 10286.43 | N31: =O31+P31 -> 16863 | O31: =VLOOKUP(K31,$A$1:$H$37,5,0) -> 11545 | P31: =VLOOKUP(K31,$A$1:$H$37,6,0) -> 5318 | Q31: =VLOOKUP(K31,$A$1:$H$37,7,0) -> 600
A32: 45014 | B32: =D32*0.39 -> 11294.01 | C32: =D32-B32 -> 17664.99 | D32: =E32+F32 -> 28959 | E32: =9130+670 -> 9800 | F32: 19159 | G32: 2500 | H32: =IFERROR(B32/C32,0) -> 0.63934426 | I32: =SUM($D$2:D32)-SUM($G$2:G32) -> 549075 | K32: Total | L32: =SUM(L25:L31) -> 45170.19 | M32: =SUM(M25:M31) -> 70650.81 | N32: =SUM(N25:N31) -> 115821 | O32: =SUM(O25:O31) -> 49280 | P32: =SUM(P25:P31) -> 66541 | Q32: =SUM(Q25:Q31) -> 10700
A33: 45015 | B33: =D33*0.39 -> 7012.59 | C33: =D33-B33 -> 10968.41 | D33: =E33+F33 -> 17981 | E33: 10730 | F33: 7251 | G33: 2500 | H33: =IFERROR(B33/C33,0) -> 0.63934426 | I33: =SUM($D$2:D33)-SUM($G$2:G33) -> 564556 | K33: Mul Bhag | L33: =L32/3 -> 15056.73
A34: 45016 | B34: =D34*0.39 -> 3088.8 | C34: =D34-B34 -> 4831.2 | D34: =E34+F34 -> 7920 | E34: 5720 | F34: 2200 | G34: 1000 | H34: =IFERROR(B34/C34,0) -> 0.63934426 | I34: =SUM($D$2:D34)-SUM($G$2:G34) -> 571476
A35: 45017 | B35: =D35*0.39 -> 8503.95 | C35: =D35-B35 -> 13301.05 | D35: =E35+F35 -> 21805 | E35: 14285 | F35: 7520 | G35: 200 | H35: =IFERROR(B35/C35,0) -> 0.63934426 | I35: =SUM($D$2:D35)-SUM($G$2:G35) -> 593081 | K35: Date | L35: Profit | M35: Actual | N35: Total | O35: Cash | P35: Account Transfer | Q35: Expense
A36: 45018 | B36: =D36*0.39 -> 13185.9 | C36: =D36-B36 -> 20624.1 | D36: =E36+F36 -> 33810 | E36: 23325 | F36: 10485 | G36: 6600 | H36: =IFERROR(B36/C36,0) -> 0.63934426 | I36: =SUM($D$2:D36)-SUM($G$2:G36) -> 620291 | K36: =A23 -> 45005 | L36: =N36*0.3 -> 3633 | M36: =N36-L36 -> 8477 | N36: =O36+P36 -> 12110 | O36: =VLOOKUP(K36,$A$1:$H$37,5,0) -> 3980 | P36: =VLOOKUP(K36,$A$1:$H$37,6,0) -> 8130 | Q36: =VLOOKUP(K36,$A$1:$H$37,7,0) -> 900
A37: Total | B37: =SUM(B4:B34) -> 261407.64 | C37: =SUM(C4:C34) -> 408868.36 | D37: =SUM(D4:D34) -> 670276 | E37: =SUM(E4:E34) -> 288155 | F37: =SUM(F4:F34) -> 382121 | G37: =SUM(G4:G34) -> 146095 | H37: =SUM(H4:H34) -> 19.180328 | I37: =SUM(I4:I34) -> 9050370 | K37: =A24 -> 45006 | L37: =N37*0.3 -> 13816.5 | M37: =N37-L37 -> 32238.5 | N37: =O37+P37 -> 46055 | O37: =VLOOKUP(K37,$A$1:$H$37,5,0) -> 29915 | P37: =VLOOKUP(K37,$A$1:$H$37,6,0) -> 16140 | Q37: =VLOOKUP(K37,$A$1:$H$37,7,0) -> 100
B38: =B37/3 -> 87135.88 | E38: =D37*0.42 -> 281515.92 | K38: =A25 -> 45007 | L38: =N38*0.3 -> 4323 | M38: =N38-L38 -> 10087 | N38: =O38+P38 -> 14410 | O38: =VLOOKUP(K38,$A$1:$H$37,5,0) -> 11070 | P38: =VLOOKUP(K38,$A$1:$H$37,6,0) -> 3340 | Q38: =VLOOKUP(K38,$A$1:$H$37,7,0) -> 3130
B39: =B38*100/D37 -> 13 | E39: =E38/3 -> 93838.64 | K39: =A26 -> 45008 | L39: =N39*0.3 -> 6784.2 | M39: =N39-L39 -> 15829.8 | N39: =O39+P39 -> 22614 | O39: =VLOOKUP(K39,$A$1:$H$37,5,0) -> 14390 | P39: =VLOOKUP(K39,$A$1:$H$37,6,0) -> 8224 | Q39: =VLOOKUP(K39,$A$1:$H$37,7,0) -> 35100
A40: Date | B40: Profit | C40: Actual | D40: Total | E40: Cash | F40: Account Transfer | G40: Expense | H40: Mul Bhag | K40: =A27 -> 45009 | L40: =N40*0.3 -> 15639 | M40: =N40-L40 -> 36491 | N40: =O40+P40 -> 52130 | O40: =VLOOKUP(K40,$A$1:$H$37,5,0) -> 8450 | P40: =VLOOKUP(K40,$A$1:$H$37,6,0) -> 43680 | Q40: =VLOOKUP(K40,$A$1:$H$37,7,0) -> 3100
A41: =CONCATENATE(TEXT(K3,"DD-MMM-YYY")," to ",TEXT(K9,"DD-MMM-YYYY")) -> 27-Feb-2023 to 05-Mar-2023 | B41: =L10 -> 58281.6 | C41: =M10 -> 91158.4 | D41: =N10 -> 149440 | E41: =O10 -> 92190 | F41: =P10 -> 57250 | G41: =Q10 -> 53505 | H41: =B41/3 -> 19427.2 | K41: =A28 -> 45010 | L41: =N41*0.3 -> 5304 | M41: =N41-L41 -> 12376 | N41: =O41+P41 -> 17680 | O41: =VLOOKUP(K41,$A$1:$H$37,5,0) -> 3940 | P41: =VLOOKUP(K41,$A$1:$H$37,6,0) -> 13740 | Q41: =VLOOKUP(K41,$A$1:$H$37,7,0) -> 2600
A42: =CONCATENATE(TEXT(K14,"DD-MMM-YYY")," to ",TEXT(K20,"DD-MMM-YYYY")) -> 06-Mar-2023 to 12-Mar-2023 | B42: =L21 -> 46375.83 | C42: =M21 -> 97357.17 | D42: =N21 -> 143733 | E42: =O21 -> 49210 | F42: =P21 -> 94523 | G42: =Q21 -> 11850 | H42: =B42/3 -> 15458.61 | K42: =A29 -> 45011 | L42: =N42*0.3 -> 6690 | M42: =N42-L42 -> 15610 | N42: =O42+P42 -> 22300 | O42: =VLOOKUP(K42,$A$1:$H$37,5,0) -> 16300 | P42: =VLOOKUP(K42,$A$1:$H$37,6,0) -> 6000 | Q42: =VLOOKUP(K42,$A$1:$H$37,7,0) -> 6120
A43: =CONCATENATE(TEXT(K25,"DD-MMM-YYY")," to ",TEXT(K31,"DD-MMM-YYYY")) -> 13-Mar-2023 to 19-Mar-2023 | B43: =L32 -> 45170.19 | C43: =M32 -> 70650.81 | D43: =N32 -> 115821 | E43: =O32 -> 49280 | F43: =P32 -> 66541 | G43: =Q32 -> 10700 | H43: =B43/3 -> 15056.73 | K43: Total | L43: =SUM(L36:L42) -> 56189.7 | M43: =SUM(M36:M42) -> 131109.3 | N43: =SUM(N36:N42) -> 187299 | O43: =SUM(O36:O42) -> 88045 | P43: =SUM(P36:P42) -> 99254 | Q43: =SUM(Q36:Q42) -> 51050
A44: =CONCATENATE(TEXT(K36,"DD-MMM-YYY")," to ",TEXT(K42,"DD-MMM-YYYY")) -> 20-Mar-2023 to 26-Mar-2023 | B44: =L43 -> 56189.7 | C44: =M43 -> 131109.3 | D44: =N43 -> 187299 | E44: =O43 -> 88045 | F44: =P43 -> 99254 | G44: =Q43 -> 51050 | H44: =B44/3 -> 18729.9 | K44: Mul Bhag | L44: =L43/3 -> 18729.9
A45: =CONCATENATE(TEXT(K47,"DD-MMM-YYY")," to ",TEXT(K53,"DD-MMM-YYYY")) -> 27-Mar-2023 to 02-Apr-2023 | B45: =L54 -> 53166.9 | C45: =M54 -> 124056.1 | D45: =N54 -> 177223 | E45: =O54 -> 80610 | F45: =P54 -> 96613 | G45: =Q54 -> 26120 | H45: =B45/3 -> 17722.3
A46: =CONCATENATE(TEXT(K59,"DD-MMM-YYY")," to ",TEXT(K58,"DD-MMM-YYYY")) -> 03-Mar-2023 to Date | B46: =SUM(B41:B45) -> 259184.22 | C46: =SUM(C41:C45) -> 514331.78 | D46: =SUM(D41:D45) -> 773516 | E46: =SUM(E41:E45) -> 359335 | F46: =SUM(F41:F45) -> 414181 | G46: =SUM(G41:G45) -> 153225 | H46: =SUM(H41:H45) -> 86394.74 | K46: Date | L46: Profit | M46: Actual | N46: Total | O46: Cash | P46: Account Transfer | Q46: Expense
C47: Total | K47: =A30 -> 45012 | L47: =N47*0.3 -> 3114 | M47: =N47-L47 -> 7266 | N47: =O47+P47 -> 10380 | O47: =VLOOKUP(K47,$A$1:$H$37,5,0) -> 7630 | P47: =VLOOKUP(K47,$A$1:$H$37,6,0) -> 2750 | Q47: =VLOOKUP(K47,$A$1:$H$37,7,0) -> 9840
K48: =A31 -> 45013 | L48: =N48*0.3 -> 16910.4 | M48: =N48-L48 -> 39457.6 | N48: =O48+P48 -> 56368 | O48: =VLOOKUP(K48,$A$1:$H$37,5,0) -> 9120 | P48: =VLOOKUP(K48,$A$1:$H$37,6,0) -> 47248 | Q48: =VLOOKUP(K48,$A$1:$H$37,7,0) -> 3480
K49: =A32 -> 45014 | L49: =N49*0.3 -> 8687.7 | M49: =N49-L49 -> 20271.3 | N49: =O49+P49 -> 28959 | O49: =VLOOKUP(K49,$A$1:$H$37,5,0) -> 9800 | P49: =VLOOKUP(K49,$A$1:$H$37,6,0) -> 19159 | Q49: =VLOOKUP(K49,$A$1:$H$37,7,0) -> 2500
K50: =A33 -> 45015 | L50: =N50*0.3 -> 5394.3 | M50: =N50-L50 -> 12586.7 | N50: =O50+P50 -> 17981 | O50: =VLOOKUP(K50,$A$1:$H$37,5,0) -> 10730 | P50: =VLOOKUP(K50,$A$1:$H$37,6,0) -> 7251 | Q50: =VLOOKUP(K50,$A$1:$H$37,7,0) -> 2500
K51: =A34 -> 45016 | L51: =N51*0.3 -> 2376 | M51: =N51-L51 -> 5544 | N51: =O51+P51 -> 7920 | O51: =VLOOKUP(K51,$A$1:$H$37,5,0) -> 5720 | P51: =VLOOKUP(K51,$A$1:$H$37,6,0) -> 2200 | Q51: =VLOOKUP(K51,$A$1:$H$37,7,0) -> 1000
K52: =A35 -> 45017 | L52: =N52*0.3 -> 6541.5 | M52: =N52-L52 -> 15263.5 | N52: =O52+P52 -> 21805 | O52: =VLOOKUP(K52,$A$1:$H$37,5,0) -> 14285 | P52: =VLOOKUP(K52,$A$1:$H$37,6,0) -> 7520 | Q52: =VLOOKUP(K52,$A$1:$H$37,7,0) -> 200
K53: =A36 -> 45018 | L53: =N53*0.3 -> 10143 | M53: =N53-L53 -> 23667 | N53: =O53+P53 -> 33810 | O53: =VLOOKUP(K53,$A$1:$H$37,5,0) -> 23325 | P53: =VLOOKUP(K53,$A$1:$H$37,6,0) -> 10485 | Q53: =VLOOKUP(K53,$A$1:$H$37,7,0) -> 6600
K54: Total | L54: =SUM(L47:L53) -> 53166.9 | M54: =SUM(M47:M53) -> 124056.1 | N54: =SUM(N47:N53) -> 177223 | O54: =SUM(O47:O53) -> 80610 | P54: =SUM(P47:P53) -> 96613 | Q54: =SUM(Q47:Q53) -> 26120
K55: Mul Bhag | L55: =L54/3 -> 17722.3
K58: Date | L58: Profit | M58: Actual | N58: Total | O58: Cash | P58: Account Transfer | Q58: Expense
K59: =A6 -> 44988 | L59: =SUM(B4:B34) -> 261407.64 | M59: =SUM(C4:C34) -> 408868.36 | N59: =SUM(D4:D34) -> 670276 | O59: =SUM(E4:E34) -> 288155 | P59: =SUM(F4:F34) -> 382121 | Q59: =SUM(G4:G34) -> 146095
K60: Mul Bhag | L60: =L59/3 -> 87135.88

Sheet April 2023
A1: Date | B1: Profit | C1: Actual | D1: Total | E1: Cash | F1: Account Transfer | G1: Expense | H1: Percentage | I1: Cash In Hand | J1: Glass | K1: Total | L1: Cash | M1: Account Transfer | O1: Date | P1: Profit | Q1: Actual | R1: Total | S1: Cash | T1: Account Transfer | U1: Expense
A2: 45012 | B2: =D2*0.39 -> 4048.2 | C2: =D2-B2 -> 6331.8 | D2: =E2+F2 -> 10380 | E2: 7630 | F2: 2750 | G2: 9840 | H2: =IFERROR(B2/C2,0) -> 0.63934426 | I2: =SUM($D$2:D2)-SUM($G$2:G2) -> 540 | K2: =L2+M2 -> 0 | O2: Export | U2: 0
A3: 45013 | B3: =D3*0.39 -> 21983.52 | C3: =D3-B3 -> 34384.48 | D3: =E3+F3 -> 56368 | E3: 9120 | F3: 47248 | G3: =2280+1200 -> 3480 | H3: =IFERROR(B3/C3,0) -> 0.63934426 | I3: =SUM($D$2:D3)-SUM($G$2:G3) -> 53428 | K3: =L3+M3 -> 0 | O3: =A2 -> 45012 | P3: =R3*0.3 -> 3114 | Q3: =R3-P3 -> 7266 | R3: =S3+T3 -> 10380 | S3: =VLOOKUP(O3,$A$1:$H$37,5,0) -> 7630 | T3: =VLOOKUP(O3,$A$1:$H$37,6,0) -> 2750 | U3: =VLOOKUP(O3,$A$1:$H$37,7,0) -> 9840
A4: 45014 | B4: =D4*0.39 -> 11294.01 | C4: =D4-B4 -> 17664.99 | D4: =E4+F4 -> 28959 | E4: =9130+670 -> 9800 | F4: 19159 | G4: 2500 | H4: =IFERROR(B4/C4,0) -> 0.63934426 | I4: =SUM($D$2:D4)-SUM($G$2:G4) -> 79887 | K4: =L4+M4 -> 0 | O4: =A3 -> 45013 | P4: =R4*0.3 -> 16910.4 | Q4: =R4-P4 -> 39457.6 | R4: =S4+T4 -> 56368 | S4: =VLOOKUP(O4,$A$1:$H$37,5,0) -> 9120 | T4: =VLOOKUP(O4,$A$1:$H$37,6,0) -> 47248 | U4: =VLOOKUP(O4,$A$1:$H$37,7,0) -> 3480
A5: 45015 | B5: =D5*0.39 -> 7012.59 | C5: =D5-B5 -> 10968.41 | D5: =E5+F5 -> 17981 | E5: 10730 | F5: 7251 | G5: 2500 | H5: =IFERROR(B5/C5,0) -> 0.63934426 | I5: =SUM($D$2:D5)-SUM($G$2:G5) -> 95368 | K5: =L5+M5 -> 0 | O5: =A4 -> 45014 | P5: =R5*0.3 -> 8687.7 | Q5: =R5-P5 -> 20271.3 | R5: =S5+T5 -> 28959 | S5: =VLOOKUP(O5,$A$1:$H$37,5,0) -> 9800 | T5: =VLOOKUP(O5,$A$1:$H$37,6,0) -> 19159 | U5: =VLOOKUP(O5,$A$1:$H$37,7,0) -> 2500
A6: 45016 | B6: =D6*0.39 -> 3088.8 | C6: =D6-B6 -> 4831.2 | D6: =E6+F6 -> 7920 | E6: 5720 | F6: 2200 | G6: 1000 | H6: =IFERROR(B6/C6,0) -> 0.63934426 | I6: =SUM($D$2:D6)-SUM($G$2:G6) -> 102288 | K6: =L6+M6 -> 0 | O6: =A5 -> 45015 | P6: =R6*0.3 -> 5394.3 | Q6: =R6-P6 -> 12586.7 | R6: =S6+T6 -> 17981 | S6: =VLOOKUP(O6,$A$1:$H$37,5,0) -> 10730 | T6: =VLOOKUP(O6,$A$1:$H$37,6,0) -> 7251 | U6: =VLOOKUP(O6,$A$1:$H$37,7,0) -> 2500
A7: 45017 | B7: =D7*0.39 -> 8503.95 | C7: =D7-B7 -> 13301.05 | D7: =E7+F7 -> 21805 | E7: 14285 | F7: 7520 | G7: 200 | H7: =IFERROR(B7/C7,0) -> 0.63934426 | I7: =SUM($D$2:D7)-SUM($G$2:G7) -> 123893 | J7: T0,T00 | K7: =L7+M7 -> 7800 | L7: 2160 | M7: 5640 | O7: =A6 -> 45016 | P7: =R7*0.3 -> 2376 | Q7: =R7-P7 -> 5544 | R7: =S7+T7 -> 7920 | S7: =VLOOKUP(O7,$A$1:$H$37,5,0) -> 5720 | T7: =VLOOKUP(O7,$A$1:$H$37,6,0) -> 2200 | U7: =VLOOKUP(O7,$A$1:$H$37,7,0) -> 1000
A8: 45018 | B8: =D8*0.39 -> 13185.9 | C8: =D8-B8 -> 20624.1 | D8: =E8+F8 -> 33810 | E8: 23325 | F8: 10485 | G8: 6600 | H8: =IFERROR(B8/C8,0) -> 0.63934426 | I8: =SUM($D$2:D8)-SUM($G$2:G8) -> 151103 | K8: =L8+M8 -> 8520 | L8: 8520 | O8: =A7 -> 45017 | P8: =R8*0.3 -> 6541.5 | Q8: =R8-P8 -> 15263.5 | R8: =S8+T8 -> 21805 | S8: =VLOOKUP(O8,$A$1:$H$37,5,0) -> 14285 | T8: =VLOOKUP(O8,$A$1:$H$37,6,0) -> 7520 | U8: =VLOOKUP(O8,$A$1:$H$37,7,0) -> 200
A9: 45019 | B9: =D9*0.39 -> 5091.84 | C9: =D9-B9 -> 7964.16 | D9: =E9+F9 -> 13056 | E9: 8572 | F9: 4484 | G9: 8400 | H9: =IFERROR(B9/C9,0) -> 0.63934426 | I9: =SUM($D$2:D9)-SUM($G$2:G9) -> 155759 | K9: =L9+M9 -> 1384 | L9: 1384 | O9: =A8 -> 45018 | P9: =R9*0.3 -> 10143 | Q9: =R9-P9 -> 23667 | R9: =S9+T9 -> 33810 | S9: =VLOOKUP(O9,$A$1:$H$37,5,0) -> 23325 | T9: =VLOOKUP(O9,$A$1:$H$37,6,0) -> 10485 | U9: =VLOOKUP(O9,$A$1:$H$37,7,0) -> 6600
A10: 45020 | B10: =D10*0.39 -> 7889.7 | C10: =D10-B10 -> 12340.3 | D10: =E10+F10 -> 20230 | E10: 9480 | F10: 10750 | G10: 2900 | H10: =IFERROR(B10/C10,0) -> 0.63934426 | I10: =SUM($D$2:D10)-SUM($G$2:G10) -> 173089 | K10: =L10+M10 -> 3830 | L10: 540 | M10: 3290 | O10: Total | P10: =SUM(P3:P9) -> 53166.9 | Q10: =SUM(Q2:Q9) -> 124056.1 | R10: =SUM(R2:R9) -> 177223 | S10: =SUM(S2:S9) -> 80610 | T10: =SUM(T2:T9) -> 96613 | U10: =SUM(U2:U9) -> 26120
A11: 45021 | B11: =D11*0.39 -> 12628.2 | C11: =D11-B11 -> 19751.8 | D11: =E11+F11 -> 32380 | E11: 17260 | F11: 15120 | G11: 9820 | H11: =IFERROR(B11/C11,0) -> 0.63934426 | I11: =SUM($D$2:D11)-SUM($G$2:G11) -> 195649 | K11: =L11+M11 -> 0 | O11: Mul Bhag | P11: =P10/3 -> 17722.3
A12: 45022 | B12: =D12*0.39 -> 1571.7 | C12: =D12-B12 -> 2458.3 | D12: =E12+F12 -> 4030 | E12: 2650 | F12: 1380 | G12: 200 | H12: =IFERROR(B12/C12,0) -> 0.63934426 | I12: =SUM($D$2:D12)-SUM($G$2:G12) -> 199479 | K12: =L12+M12 -> 0
A13: 45023 | B13: =D13*0.39 -> 5326.62 | C13: =D13-B13 -> 8331.38 | D13: =E13+F13 -> 13658 | E13: 9890 | F13: 3768 | G13: 660 | H13: =IFERROR(B13/C13,0) -> 0.63934426 | I13: =SUM($D$2:D13)-SUM($G$2:G13) -> 212477 | K13: =L13+M13 -> 0 | O13: Date | P13: Profit | Q13: Actual | R13: Total | S13: Cash | T13: Account Transfer | U13: Expense
A14: 45024 | B14: =D14*0.39 -> 5508.75 | C14: =D14-B14 -> 8616.25 | D14: =E14+F14 -> 14125 | E14: 8225 | F14: 5900 | G14: 3700 | H14: =IFERROR(B14/C14,0) -> 0.63934426 | I14: =SUM($D$2:D14)-SUM($G$2:G14) -> 222902 | K14: =L14+M14 -> 0 | O14: =A9 -> 45019 | P14: =R14*0.3 -> 3916.8 | Q14: =R14-P14 -> 9139.2 | R14: =S14+T14 -> 13056 | S14: =VLOOKUP(O14,$A$1:$H$37,5,0) -> 8572 | T14: =VLOOKUP(O14,$A$1:$H$37,6,0) -> 4484 | U14: =VLOOKUP(O14,$A$1:$H$37,7,0) -> 8400
A15: 45025 | B15: =D15*0.39 -> 6084 | C15: =D15-B15 -> 9516 | D15: =E15+F15 -> 15600 | E15: 13820 | F15: 1780 | G15: 100 | H15: =IFERROR(B15/C15,0) -> 0.63934426 | I15: =SUM($D$2:D15)-SUM($G$2:G15) -> 238402 | K15: =L15+M15 -> 0 | O15: =A10 -> 45020 | P15: =R15*0.3 -> 6069 | Q15: =R15-P15 -> 14161 | R15: =S15+T15 -> 20230 | S15: =VLOOKUP(O15,$A$1:$H$37,5,0) -> 9480 | T15: =VLOOKUP(O15,$A$1:$H$37,6,0) -> 10750 | U15: =VLOOKUP(O15,$A$1:$H$37,7,0) -> 2900
A16: 45026 | B16: =D16*0.39 -> 9059.7 | C16: =D16-B16 -> 14170.3 | D16: =E16+F16 -> 23230 | E16: 4280 | F16: 18950 | G16: 100 | H16: =IFERROR(B16/C16,0) -> 0.63934426 | I16: =SUM($D$2:D16)-SUM($G$2:G16) -> 261532 | K16: =L16+M16 -> 0 | O16: =A11 -> 45021 | P16: =R16*0.3 -> 9714 | Q16: =R16-P16 -> 22666 | R16: =S16+T16 -> 32380 | S16: =VLOOKUP(O16,$A$1:$H$37,5,0) -> 17260 | T16: =VLOOKUP(O16,$A$1:$H$37,6,0) -> 15120 | U16: =VLOOKUP(O16,$A$1:$H$37,7,0) -> 9820
A17: 45027 | B17: =D17*0.39 -> 6501.3 | C17: =D17-B17 -> 10168.7 | D17: =E17+F17 -> 16670 | E17: 6000 | F17: 10670 | G17: 27100 | H17: =IFERROR(B17/C17,0) -> 0.63934426 | I17: =SUM($D$2:D17)-SUM($G$2:G17) -> 251102 | K17: =L17+M17 -> 0 | O17: =A12 -> 45022 | P17: =R17*0.3 -> 1209 | Q17: =R17-P17 -> 2821 | R17: =S17+T17 -> 4030 | S17: =VLOOKUP(O17,$A$1:$H$37,5,0) -> 2650 | T17: =VLOOKUP(O17,$A$1:$H$37,6,0) -> 1380 | U17: =VLOOKUP(O17,$A$1:$H$37,7,0) -> 200
A18: 45028 | B18: =D18*0.39 -> 13263.9 | C18: =D18-B18 -> 20746.1 | D18: =E18+F18 -> 34010 | E18: 18710 | F18: 15300 | G18: 15700 | H18: =IFERROR(B18/C18,0) -> 0.63934426 | I18: =SUM($D$2:D18)-SUM($G$2:G18) -> 269412 | K18: =L18+M18 -> 0 | O18: =A13 -> 45023 | P18: =R18*0.3 -> 4097.4 | Q18: =R18-P18 -> 9560.6 | R18: =S18+T18 -> 13658 | S18: =VLOOKUP(O18,$A$1:$H$37,5,0) -> 9890 | T18: =VLOOKUP(O18,$A$1:$H$37,6,0) -> 3768 | U18: =VLOOKUP(O18,$A$1:$H$37,7,0) -> 660
A19: 45029 | B19: =D19*0.39 -> 4219.8 | C19: =D19-B19 -> 6600.2 | D19: =E19+F19 -> 10820 | E19: 9050 | F19: 1770 | G19: 3500 | H19: =IFERROR(B19/C19,0) -> 0.63934426 | I19: =SUM($D$2:D19)-SUM($G$2:G19) -> 276732 | K19: =L19+M19 -> 0 | O19: =A14 -> 45024 | P19: =R19*0.3 -> 4237.5 | Q19: =R19-P19 -> 9887.5 | R19: =S19+T19 -> 14125 | S19: =VLOOKUP(O19,$A$1:$H$37,5,0) -> 8225 | T19: =VLOOKUP(O19,$A$1:$H$37,6,0) -> 5900 | U19: =VLOOKUP(O19,$A$1:$H$37,7,0) -> 3700
A20: 45030 | B20: =D20*0.39 -> 6093.75 | C20: =D20-B20 -> 9531.25 | D20: =E20+F20 -> 15625 | E20: 11800 | F20: 3825 | G20: 1090 | H20: =IFERROR(B20/C20,0) -> 0.63934426 | I20: =SUM($D$2:D20)-SUM($G$2:G20) -> 291267 | K20: =L20+M20 -> 0 | O20: =A15 -> 45025 | P20: =R20*0.3 -> 4680 | Q20: =R20-P20 -> 10920 | R20: =S20+T20 -> 15600 | S20: =VLOOKUP(O20,$A$1:$H$37,5,0) -> 13820 | T20: =VLOOKUP(O20,$A$1:$H$37,6,0) -> 1780 | U20: =VLOOKUP(O20,$A$1:$H$37,7,0) -> 100
A21: 45031 | B21: =D21*0.39 -> 9941.1 | C21: =D21-B21 -> 15548.9 | D21: =E21+F21 -> 25490 | E21: 5820 | F21: 19670 | G21: 52600 | H21: =IFERROR(B21/C21,0) -> 0.63934426 | I21: =SUM($D$2:D21)-SUM($G$2:G21) -> 264157 | K21: =L21+M21 -> 0 | O21: Total | P21: =SUM(P14:P20) -> 33923.7 | Q21: =SUM(Q14:Q20) -> 79155.3 | R21: =SUM(R14:R20) -> 113079 | S21: =SUM(S14:S20) -> 69897 | T21: =SUM(T14:T20) -> 43182 | U21: =SUM(U14:U20) -> 25780
A22: 45032 | B22: =D22*0.39 -> 12316.2 | C22: =D22-B22 -> 19263.8 | D22: =E22+F22 -> 31580 | E22: 17875 | F22: 13705 | G22: 900 | H22: =IFERROR(B22/C22,0) -> 0.63934426 | I22: =SUM($D$2:D22)-SUM($G$2:G22) -> 294837 | K22: =L22+M22 -> 0 | O22: Mul Bhag | P22: =P21/3 -> 11307.9 | Q22: 12750 | R22: =Q22+P22 -> 24057.9
A23: 45033 | B23: =D23*0.39 -> 12000.3 | C23: =D23-B23 -> 18769.7 | D23: =E23+F23 -> 30770 | E23: 10390 | F23: 20380 | G23: 4000 | H23: =IFERROR(B23/C23,0) -> 0.63934426 | I23: =SUM($D$2:D23)-SUM($G$2:G23) -> 321607 | K23: =L23+M23 -> 0 | Q23: ser
A24: 45034 | B24: =D24*0.39 -> 6688.5 | C24: =D24-B24 -> 10461.5 | D24: =E24+F24 -> 17150 | E24: 9430 | F24: 7720 | G24: 2300 | H24: =IFERROR(B24/C24,0) -> 0.63934426 | I24: =SUM($D$2:D24)-SUM($G$2:G24) -> 336457 | K24: =L24+M24 -> 0 | O24: Date | P24: Profit | Q24: Actual | R24: Total | S24: Cash | T24: Account Transfer | U24: Expense
A25: 45035 | B25: =D25*0.39 -> 8225.1 | C25: =D25-B25 -> 12864.9 | D25: =E25+F25 -> 21090 | E25: 5190 | F25: 15900 | G25: 40 | H25: =IFERROR(B25/C25,0) -> 0.63934426 | I25: =SUM($D$2:D25)-SUM($G$2:G25) -> 357507 | K25: =L25+M25 -> 0 | O25: =A16 -> 45026 | P25: =R25*0.3 -> 6969 | Q25: =R25-P25 -> 16261 | R25: =S25+T25 -> 23230 | S25: =VLOOKUP(O25,$A$1:$H$37,5,0) -> 4280 | T25: =VLOOKUP(O25,$A$1:$H$37,6,0) -> 18950 | U25: =VLOOKUP(O25,$A$1:$H$37,7,0) -> 100
A26: 45036 | B26: =D26*0.39 -> 10830.3 | C26: =D26-B26 -> 16939.7 | D26: =E26+F26 -> 27770 | E26: =Table23453456879111215141617181920212223242526272834[[#This Row],[Expense]]+21540 -> 27550 | F26: 220 | G26: 6010 | H26: =IFERROR(B26/C26,0) -> 0.63934426 | I26: =SUM($D$2:D26)-SUM($G$2:G26) -> 379267 | K26: =L26+M26 -> 0 | O26: =A17 -> 45027 | P26: =R26*0.3 -> 5001 | Q26: =R26-P26 -> 11669 | R26: =S26+T26 -> 16670 | S26: =VLOOKUP(O26,$A$1:$H$37,5,0) -> 6000 | T26: =VLOOKUP(O26,$A$1:$H$37,6,0) -> 10670 | U26: =VLOOKUP(O26,$A$1:$H$37,7,0) -> 27100
A27: 45037 | B27: =D27*0.39 -> 1661.4 | C27: =D27-B27 -> 2598.6 | D27: =E27+F27 -> 4260 | E27: =Table23453456879111215141617181920212223242526272834[[#This Row],[Expense]]+3957 -> 4080 | F27: 180 | G27: 123 | H27: =IFERROR(B27/C27,0) -> 0.63934426 | I27: =SUM($D$2:D27)-SUM($G$2:G27) -> 383404 | K27: =L27+M27 -> 0 | O27: =A18 -> 45028 | P27: =R27*0.3 -> 10203 | Q27: =R27-P27 -> 23807 | R27: =S27+T27 -> 34010 | S27: =VLOOKUP(O27,$A$1:$H$37,5,0) -> 18710 | T27: =VLOOKUP(O27,$A$1:$H$37,6,0) -> 15300 | U27: =VLOOKUP(O27,$A$1:$H$37,7,0) -> 15700
A28: 45038 | B28: =D28*0.39 -> 4740.06 | C28: =D28-B28 -> 7413.94 | D28: =E28+F28 -> 12154 | E28: =Table23453456879111215141617181920212223242526272834[[#This Row],[Expense]]+5912 -> 6044 | F28: 6110 | G28: 132 | H28: =IFERROR(B28/C28,0) -> 0.63934426 | I28: =SUM($D$2:D28)-SUM($G$2:G28) -> 395426 | K28: =L28+M28 -> 0 | O28: =A19 -> 45029 | P28: =R28*0.3 -> 3246 | Q28: =R28-P28 -> 7574 | R28: =S28+T28 -> 10820 | S28: =VLOOKUP(O28,$A$1:$H$37,5,0) -> 9050 | T28: =VLOOKUP(O28,$A$1:$H$37,6,0) -> 1770 | U28: =VLOOKUP(O28,$A$1:$H$37,7,0) -> 3500
A29: 45039 | B29: =D29*0.39 -> 12082.2 | C29: =D29-B29 -> 18897.8 | D29: =E29+F29 -> 30980 | E29: =Table23453456879111215141617181920212223242526272834[[#This Row],[Expense]]+28350 -> 28420 | F29: 2560 | G29: 70 | H29: =IFERROR(B29/C29,0) -> 0.63934426 | I29: =SUM($D$2:D29)-SUM($G$2:G29) -> 426336 | K29: =L29+M29 -> 0 | O29: =A20 -> 45030 | P29: =R29*0.3 -> 4687.5 | Q29: =R29-P29 -> 10937.5 | R29: =S29+T29 -> 15625 | S29: =VLOOKUP(O29,$A$1:$H$37,5,0) -> 11800 | T29: =VLOOKUP(O29,$A$1:$H$37,6,0) -> 3825 | U29: =VLOOKUP(O29,$A$1:$H$37,7,0) -> 1090
A30: 45040 | B30: =D30*0.39 -> 1996.8 | C30: =D30-B30 -> 3123.2 | D30: =E30+F30 -> 5120 | E30: =4088+Table23453456879111215141617181920212223242526272834[[#This Row],[Expense]] -> 4290 | F30: 830 | G30: 202 | H30: =IFERROR(B30/C30,0) -> 0.63934426 | I30: =SUM($D$2:D30)-SUM($G$2:G30) -> 431254 | K30: =L30+M30 -> 0 | O30: =A21 -> 45031 | P30: =R30*0.3 -> 7647 | Q30: =R30-P30 -> 17843 | R30: =S30+T30 -> 25490 | S30: =VLOOKUP(O30,$A$1:$H$37,5,0) -> 5820 | T30: =VLOOKUP(O30,$A$1:$H$37,6,0) -> 19670 | U30: =VLOOKUP(O30,$A$1:$H$37,7,0) -> 52600
A31: 45041 | B31: =D31*0.39 -> 319.8 | C31: =D31-B31 -> 500.2 | D31: =E31+F31 -> 820 | E31: =750+Table23453456879111215141617181920212223242526272834[[#This Row],[Expense]] -> 820 | G31: 70 | H31: =IFERROR(B31/C31,0) -> 0.63934426 | I31: =SUM($D$2:D31)-SUM($G$2:G31) -> 432004 | K31: =L31+M31 -> 0 | O31: =A22 -> 45032 | P31: =R31*0.3 -> 9474 | Q31: =R31-P31 -> 22106 | R31: =S31+T31 -> 31580 | S31: =VLOOKUP(O31,$A$1:$H$37,5,0) -> 17875 | T31: =VLOOKUP(O31,$A$1:$H$37,6,0) -> 13705 | U31: =VLOOKUP(O31,$A$1:$H$37,7,0) -> 900
A32: 45042 | B32: =D32*0.39 -> 11943.75 | C32: =D32-B32 -> 18681.25 | D32: =E32+F32 -> 30625 | E32: =Table23453456879111215141617181920212223242526272834[[#This Row],[Expense]]+6039 -> 21105 | F32: 9520 | G32: 15066 | H32: =IFERROR(B32/C32,0) -> 0.63934426 | I32: =SUM($D$2:D32)-SUM($G$2:G32) -> 447563 | K32: =L32+M32 -> 0 | O32: Total | P32: =SUM(P25:P31) -> 47227.5 | Q32: =SUM(Q25:Q31) -> 110197.5 | R32: =SUM(R25:R31) -> 157425 | S32: =SUM(S25:S31) -> 73535 | T32: =SUM(T25:T31) -> 83890 | U32: =SUM(U25:U31) -> 100990
A33: 45043 | B33: =D33*0.39 -> 1540.5 | C33: =D33-B33 -> 2409.5 | D33: =E33+F33 -> 3950 | E33: =Table23453456879111215141617181920212223242526272834[[#This Row],[Expense]]+2670 -> 3190 | F33: 760 | G33: 520 | H33: =IFERROR(B33/C33,0) -> 0.63934426 | I33: =SUM($D$2:D33)-SUM($G$2:G33) -> 450993 | K33: =L33+M33 -> 0 | O33: Mul Bhag | P33: =P32/3 -> 15742.5
A34: 45044 | B34: =D34*0.39 -> 1914.9 | C34: =D34-B34 -> 2995.1 | D34: =E34+F34 -> 4910 | E34: =Table23453456879111215141617181920212223242526272834[[#This Row],[Expense]]+2380 -> 2460 | F34: 2450 | G34: 80 | H34: =IFERROR(B34/C34,0) -> 0.63934426 | I34: =SUM($D$2:D34)-SUM($G$2:G34) -> 455823 | K34: =L34+M34 -> 0
A35: 45045 | B35: =D35*0.39 -> 3256.5 | C35: =D35-B35 -> 5093.5 | D35: =E35+F35 -> 8350 | E35: =Table23453456879111215141617181920212223242526272834[[#This Row],[Expense]]+5000 -> 5050 | F35: 3300 | G35: 50 | H35: =IFERROR(B35/C35,0) -> 0.63934426 | I35: =SUM($D$2:D35)-SUM($G$2:G35) -> 464123 | K35: =L35+M35 -> 0 | O35: Date | P35: Profit | Q35: Actual | R35: Total | S35: Cash | T35: Account Transfer | U35: Expense
A36: 45046 | B36: =D36*0.39 -> 3564.6 | C36: =D36-B36 -> 5575.4 | D36: =E36+F36 -> 9140 | E36: =Table23453456879111215141617181920212223242526272834[[#This Row],[Expense]]+5000 -> 5080 | F36: 4060 | G36: 80 | H36: =IFERROR(B36/C36,0) -> 0.63934426 | I36: =SUM($D$2:D36)-SUM($G$2:G36) -> 473183 | K36: =L36+M36 -> 0 | O36: =A23 -> 45033 | P36: =R36*0.3 -> 9231 | Q36: =R36-P36 -> 21539 | R36: =S36+T36 -> 30770 | S36: =VLOOKUP(O36,$A$1:$H$37,5,0) -> 10390 | T36: =VLOOKUP(O36,$A$1:$H$37,6,0) -> 20380 | U36: =VLOOKUP(O36,$A$1:$H$37,7,0) -> 4000
A37: Total | B37: =SUM(B7:B36) -> 207951.12 | C37: =SUM(C7:C36) -> 325256.88 | D37: =SUM(D7:D36) -> 533208 | E37: =SUM(E7:E36) -> 314141 | F37: =SUM(F7:F36) -> 219067 | G37: =SUM(G7:G36) -> 162313 | H37: =SUM(H7:H36) -> 19.180328 | I37: =SUM(I7:I36) -> 9336739 | K37: =SUM(K3:K36) -> 21534 | L37: =SUM(L3:L36) -> 12604 | M37: =SUM(M3:M36) -> 8930 | O37: =A24 -> 45034 | P37: =R37*0.3 -> 5145 | Q37: =R37-P37 -> 12005 | R37: =S37+T37 -> 17150 | S37: =VLOOKUP(O37,$A$1:$H$37,5,0) -> 9430 | T37: =VLOOKUP(O37,$A$1:$H$37,6,0) -> 7720 | U37: =VLOOKUP(O37,$A$1:$H$37,7,0) -> 2300
B38: =B37/3 -> 69317.04 | E38: =D37*0.42 -> 223947.36 | L38: =K37*0.42 -> 9044.28 | O38: =A25 -> 45035 | P38: =R38*0.3 -> 6327 | Q38: =R38-P38 -> 14763 | R38: =S38+T38 -> 21090 | S38: =VLOOKUP(O38,$A$1:$H$37,5,0) -> 5190 | T38: =VLOOKUP(O38,$A$1:$H$37,6,0) -> 15900 | U38: =VLOOKUP(O38,$A$1:$H$37,7,0) -> 40
B39: =B38*100/D37 -> 13 | E39: =E38/3 -> 74649.12 | L39: =L38/3 -> 3014.76 | O39: =A26 -> 45036 | P39: =R39*0.3 -> 8331 | Q39: =R39-P39 -> 19439 | R39: =S39+T39 -> 27770 | S39: =VLOOKUP(O39,$A$1:$H$37,5,0) -> 27550 | T39: =VLOOKUP(O39,$A$1:$H$37,6,0) -> 220 | U39: =VLOOKUP(O39,$A$1:$H$37,7,0) -> 6010
A40: Date | B40: Profit | C40: Actual | D40: Total | E40: Cash | F40: Account Transfer | G40: Expense | H40: Mul Bhag | K40: Total | L40: Cash | M40: Account Transfer | O40: =A27 -> 45037 | P40: =R40*0.3 -> 1278 | Q40: =R40-P40 -> 2982 | R40: =S40+T40 -> 4260 | S40: =VLOOKUP(O40,$A$1:$H$37,5,0) -> 4080 | T40: =VLOOKUP(O40,$A$1:$H$37,6,0) -> 180 | U40: =VLOOKUP(O40,$A$1:$H$37,7,0) -> 123
A41: =CONCATENATE(TEXT(O3,"DD-MMM-YYY")," to ",TEXT(O9,"DD-MMM-YYYY")) -> 27-Mar-2023 to 02-Apr-2023 | B41: =P10 -> 53166.9 | C41: =Q10 -> 124056.1 | D41: =R10 -> 177223 | E41: =S10 -> 80610 | F41: =T10 -> 96613 | G41: =U10 -> 26120 | H41: =B41/3 -> 17722.3 | K41: =Y10 -> 0 | L41: =Z10 -> 0 | M41: =AA10 -> 0 | O41: =A28 -> 45038 | P41: =R41*0.3 -> 3646.2 | Q41: =R41-P41 -> 8507.8 | R41: =S41+T41 -> 12154 | S41: =VLOOKUP(O41,$A$1:$H$37,5,0) -> 6044 | T41: =VLOOKUP(O41,$A$1:$H$37,6,0) -> 6110 | U41: =VLOOKUP(O41,$A$1:$H$37,7,0) -> 132
A42: =CONCATENATE(TEXT(O14,"DD-MMM-YYY")," to ",TEXT(O20,"DD-MMM-YYYY")) -> 03-Apr-2023 to 09-Apr-2023 | B42: =P21 -> 33923.7 | C42: =Q21 -> 79155.3 | D42: =R21 -> 113079 | E42: =S21 -> 69897 | F42: =T21 -> 43182 | G42: =U21 -> 25780 | H42: =B42/3 -> 11307.9 | K42: =Y21 -> 0 | L42: =Z21 -> 0 | M42: =AA21 -> 0 | O42: =A29 -> 45039 | P42: =R42*0.3 -> 9294 | Q42: =R42-P42 -> 21686 | R42: =S42+T42 -> 30980 | S42: =VLOOKUP(O42,$A$1:$H$37,5,0) -> 28420 | T42: =VLOOKUP(O42,$A$1:$H$37,6,0) -> 2560 | U42: =VLOOKUP(O42,$A$1:$H$37,7,0) -> 70
A43: =CONCATENATE(TEXT(O25,"DD-MMM-YYY")," to ",TEXT(O31,"DD-MMM-YYYY")) -> 10-Apr-2023 to 16-Apr-2023 | B43: =P32 -> 47227.5 | C43: =Q32 -> 110197.5 | D43: =R32 -> 157425 | E43: =S32 -> 73535 | F43: =T32 -> 83890 | G43: =U32 -> 100990 | H43: =B43/3 -> 15742.5 | K43: =Y32 -> 0 | L43: =Z32 -> 0 | M43: =AA32 -> 0 | O43: Total | P43: =SUM(P36:P42) -> 43252.2 | Q43: =SUM(Q36:Q42) -> 100921.8 | R43: =SUM(R36:R42) -> 144174 | S43: =SUM(S36:S42) -> 91104 | T43: =SUM(T36:T42) -> 53070 | U43: =SUM(U36:U42) -> 12675
A44: =CONCATENATE(TEXT(O36,"DD-MMM-YYY")," to ",TEXT(O42,"DD-MMM-YYYY")) -> 17-Apr-2023 to 23-Apr-2023 | B44: =P43 -> 43252.2 | C44: =Q43 -> 100921.8 | D44: =R43 -> 144174 | E44: =S43 -> 91104 | F44: =T43 -> 53070 | G44: =U43 -> 12675 | H44: =B44/3 -> 14417.4 | K44: =Y43 -> 0 | L44: =Z43 -> 0 | M44: =AA43 -> 0 | O44: Mul Bhag | P44: =P43/3 -> 14417.4
A45: =CONCATENATE(TEXT(O47,"DD-MMM-YYY")," to ",TEXT(O53,"DD-MMM-YYYY")) -> 24-Apr-2023 to 30-Apr-2023 | B45: =P54 -> 18874.5 | C45: =Q54 -> 44040.5 | D45: =R54 -> 62915 | E45: =S54 -> 41995 | F45: =T54 -> 20920 | G45: =U54 -> 16068 | H45: =B45/3 -> 6291.5 | K45: =Y54 -> 0 | L45: =Z54 -> 0 | M45: =AA54 -> 0
A46: =CONCATENATE(TEXT(O59,"DD-MMM-YYY")," to ",TEXT(O58,"DD-MMM-YYYY")) -> 31-Mar-2023 to Date | B46: =SUM(B41:B45) -> 196444.8 | C46: =SUM(C41:C45) -> 458371.2 | D46: =SUM(D41:D45) -> 654816 | E46: =SUM(E41:E45) -> 357141 | F46: =SUM(F41:F45) -> 297675 | G46: =SUM(G41:G45) -> 181633 | H46: =SUM(H41:H45) -> 65481.6 | K46: =SUM(K41:K45) -> 0 | L46: =SUM(L41:L45) -> 0 | M46: =SUM(M41:M45) -> 0 | O46: Date | P46: Profit | Q46: Actual | R46: Total | S46: Cash | T46: Account Transfer | U46: Expense
C47: Total | O47: =A30 -> 45040 | P47: =R47*0.3 -> 1536 | Q47: =R47-P47 -> 3584 | R47: =S47+T47 -> 5120 | S47: =VLOOKUP(O47,$A$1:$H$37,5,0) -> 4290 | T47: =VLOOKUP(O47,$A$1:$H$37,6,0) -> 830 | U47: =VLOOKUP(O47,$A$1:$H$37,7,0) -> 202
O48: =A31 -> 45041 | P48: =R48*0.3 -> 246 | Q48: =R48-P48 -> 574 | R48: =S48+T48 -> 820 | S48: =VLOOKUP(O48,$A$1:$H$37,5,0) -> 820 | T48: =VLOOKUP(O48,$A$1:$H$37,6,0) -> 0 | U48: =VLOOKUP(O48,$A$1:$H$37,7,0) -> 70
O49: =A32 -> 45042 | P49: =R49*0.3 -> 9187.5 | Q49: =R49-P49 -> 21437.5 | R49: =S49+T49 -> 30625 | S49: =VLOOKUP(O49,$A$1:$H$37,5,0) -> 21105 | T49: =VLOOKUP(O49,$A$1:$H$37,6,0) -> 9520 | U49: =VLOOKUP(O49,$A$1:$H$37,7,0) -> 15066
O50: =A33 -> 45043 | P50: =R50*0.3 -> 1185 | Q50: =R50-P50 -> 2765 | R50: =S50+T50 -> 3950 | S50: =VLOOKUP(O50,$A$1:$H$37,5,0) -> 3190 | T50: =VLOOKUP(O50,$A$1:$H$37,6,0) -> 760 | U50: =VLOOKUP(O50,$A$1:$H$37,7,0) -> 520
O51: =A34 -> 45044 | P51: =R51*0.3 -> 1473 | Q51: =R51-P51 -> 3437 | R51: =S51+T51 -> 4910 | S51: =VLOOKUP(O51,$A$1:$H$37,5,0) -> 2460 | T51: =VLOOKUP(O51,$A$1:$H$37,6,0) -> 2450 | U51: =VLOOKUP(O51,$A$1:$H$37,7,0) -> 80
O52: =A35 -> 45045 | P52: =R52*0.3 -> 2505 | Q52: =R52-P52 -> 5845 | R52: =S52+T52 -> 8350 | S52: =VLOOKUP(O52,$A$1:$H$37,5,0) -> 5050 | T52: =VLOOKUP(O52,$A$1:$H$37,6,0) -> 3300 | U52: =VLOOKUP(O52,$A$1:$H$37,7,0) -> 50
O53: =A36 -> 45046 | P53: =R53*0.3 -> 2742 | Q53: =R53-P53 -> 6398 | R53: =S53+T53 -> 9140 | S53: =VLOOKUP(O53,$A$1:$H$37,5,0) -> 5080 | T53: =VLOOKUP(O53,$A$1:$H$37,6,0) -> 4060 | U53: =VLOOKUP(O53,$A$1:$H$37,7,0) -> 80
O54: Total | P54: =SUM(P47:P53) -> 18874.5 | Q54: =SUM(Q47:Q53) -> 44040.5 | R54: =SUM(R47:R53) -> 62915 | S54: =SUM(S47:S53) -> 41995 | T54: =SUM(T47:T53) -> 20920 | U54: =SUM(U47:U53) -> 16068
O55: Mul Bhag | P55: =P54/3 -> 6291.5
O58: Date | P58: Profit | Q58: Actual | R58: Total | S58: Cash | T58: Account Transfer | U58: Expense
O59: =A6 -> 45016 | P59: =SUM(B7:B36) -> 207951.12 | Q59: =SUM(C7:C36) -> 325256.88 | R59: =SUM(D7:D36) -> 533208 | S59: =SUM(E7:E36) -> 314141 | T59: =SUM(F7:F36) -> 219067 | U59: =SUM(G7:G36) -> 162313
O60: Mul Bhag | P60: =P59/3 -> 69317.04

Sheet May 2023
A1: Date | B1: Profit | C1: Actual | D1: Total | E1: Cash | F1: Account Transfer | G1: Expense | H1: Percentage | I1: Cash In Hand | J1: Glass | K1: Total | L1: Cash | M1: Account Transfer | O1: Date | P1: Profit | Q1: Actual | R1: Total | S1: Cash | T1: Account Transfer | U1: Expense
A2: 45047 | B2: =D2*0.39 -> 8541 | C2: =D2-B2 -> 13359 | D2: =E2+F2 -> 21900 | E2: 7930 | F2: 13970 | G2: 1150 | H2: =IFERROR(B2/C2,0) -> 0.63934426 | I2: =SUM($D$2:D2)-SUM($G$2:G2) -> 20750 | K2: =L2+M2 -> 0 | O2: Export | U2: 0
A3: 45048 | B3: =D3*0.39 -> 5483.4 | C3: =D3-B3 -> 8576.6 | D3: =E3+F3 -> 14060 | E3: =8070+5240 -> 13310 | F3: 750 | G3: 3940 | H3: =IFERROR(B3/C3,0) -> 0.63934426 | I3: =SUM($D$2:D3)-SUM($G$2:G3) -> 30870 | K3: =L3+M3 -> 0 | O3: =A2 -> 45047 | P3: =R3*0.3 -> 6570 | Q3: =R3-P3 -> 15330 | R3: =S3+T3 -> 21900 | S3: =VLOOKUP(O3,$A$1:$H$37,5,0) -> 7930 | T3: =VLOOKUP(O3,$A$1:$H$37,6,0) -> 13970 | U3: =VLOOKUP(O3,$A$1:$H$37,7,0) -> 1150
A4: 45049 | B4: =D4*0.39 -> 6171.75 | C4: =D4-B4 -> 9653.25 | D4: =E4+F4 -> 15825 | E4: 4650 | F4: 11175 | G4: =610+340 -> 950 | H4: =IFERROR(B4/C4,0) -> 0.63934426 | I4: =SUM($D$2:D4)-SUM($G$2:G4) -> 45745 | K4: =L4+M4 -> 0 | O4: =A3 -> 45048 | P4: =R4*0.3 -> 4218 | Q4: =R4-P4 -> 9842 | R4: =S4+T4 -> 14060 | S4: =VLOOKUP(O4,$A$1:$H$37,5,0) -> 13310 | T4: =VLOOKUP(O4,$A$1:$H$37,6,0) -> 750 | U4: =VLOOKUP(O4,$A$1:$H$37,7,0) -> 3940
A5: 45050 | B5: =D5*0.39 -> 6002.1 | C5: =D5-B5 -> 9387.9 | D5: =E5+F5 -> 15390 | E5: 9180 | F5: 6210 | G5: 3970 | H5: =IFERROR(B5/C5,0) -> 0.63934426 | I5: =SUM($D$2:D5)-SUM($G$2:G5) -> 57165 | K5: =L5+M5 -> 0 | O5: =A4 -> 45049 | P5: =R5*0.3 -> 4747.5 | Q5: =R5-P5 -> 11077.5 | R5: =S5+T5 -> 15825 | S5: =VLOOKUP(O5,$A$1:$H$37,5,0) -> 4650 | T5: =VLOOKUP(O5,$A$1:$H$37,6,0) -> 11175 | U5: =VLOOKUP(O5,$A$1:$H$37,7,0) -> 950
A6: 45051 | B6: =D6*0.39 -> 10629.45 | C6: =D6-B6 -> 16625.55 | D6: =E6+F6 -> 27255 | E6: 2325 | F6: 24930 | G6: 35 | H6: =IFERROR(B6/C6,0) -> 0.63934426 | I6: =SUM($D$2:D6)-SUM($G$2:G6) -> 84385 | K6: =L6+M6 -> 0 | O6: =A5 -> 45050 | P6: =R6*0.3 -> 4617 | Q6: =R6-P6 -> 10773 | R6: =S6+T6 -> 15390 | S6: =VLOOKUP(O6,$A$1:$H$37,5,0) -> 9180 | T6: =VLOOKUP(O6,$A$1:$H$37,6,0) -> 6210 | U6: =VLOOKUP(O6,$A$1:$H$37,7,0) -> 3970
A7: 45052 | B7: =D7*0.39 -> 6750.9 | C7: =D7-B7 -> 10559.1 | D7: =E7+F7 -> 17310 | E7: 9620 | F7: 7690 | G7: 290 | H7: =IFERROR(B7/C7,0) -> 0.63934426 | I7: =SUM($D$2:D7)-SUM($G$2:G7) -> 101405 | K7: =L7+M7 -> 0 | O7: =A6 -> 45051 | P7: =R7*0.3 -> 8176.5 | Q7: =R7-P7 -> 19078.5 | R7: =S7+T7 -> 27255 | S7: =VLOOKUP(O7,$A$1:$H$37,5,0) -> 2325 | T7: =VLOOKUP(O7,$A$1:$H$37,6,0) -> 24930 | U7: =VLOOKUP(O7,$A$1:$H$37,7,0) -> 35
A8: 45053 | B8: =D8*0.39 -> 5296.2 | C8: =D8-B8 -> 8283.8 | D8: =E8+F8 -> 13580 | E8: 3920 | F8: 9660 | G8: 1620 | H8: =IFERROR(B8/C8,0) -> 0.63934426 | I8: =SUM($D$2:D8)-SUM($G$2:G8) -> 113365 | K8: =L8+M8 -> 0 | O8: =A7 -> 45052 | P8: =R8*0.3 -> 5193 | Q8: =R8-P8 -> 12117 | R8: =S8+T8 -> 17310 | S8: =VLOOKUP(O8,$A$1:$H$37,5,0) -> 9620 | T8: =VLOOKUP(O8,$A$1:$H$37,6,0) -> 7690 | U8: =VLOOKUP(O8,$A$1:$H$37,7,0) -> 290
A9: 45054 | B9: =D9*0.39 -> 7374.9 | C9: =D9-B9 -> 11535.1 | D9: =E9+F9 -> 18910 | E9: 11960 | F9: 6950 | G9: 28700 | H9: =IFERROR(B9/C9,0) -> 0.63934426 | I9: =SUM($D$2:D9)-SUM($G$2:G9) -> 103575 | K9: =L9+M9 -> 0 | O9: =A8 -> 45053 | P9: =R9*0.3 -> 4074 | Q9: =R9-P9 -> 9506 | R9: =S9+T9 -> 13580 | S9: =VLOOKUP(O9,$A$1:$H$37,5,0) -> 3920 | T9: =VLOOKUP(O9,$A$1:$H$37,6,0) -> 9660 | U9: =VLOOKUP(O9,$A$1:$H$37,7,0) -> 1620
A10: 45055 | B10: =D10*0.39 -> 13353.6 | C10: =D10-B10 -> 20886.4 | D10: =E10+F10 -> 34240 | E10: 10200 | F10: 24040 | G10: 740 | H10: =IFERROR(B10/C10,0) -> 0.63934426 | I10: =SUM($D$2:D10)-SUM($G$2:G10) -> 137075 | K10: =L10+M10 -> 0 | O10: Total | P10: =SUM(P3:P9) -> 37596 | Q10: =SUM(Q2:Q9) -> 87724 | R10: =SUM(R2:R9) -> 125320 | S10: =SUM(S2:S9) -> 50935 | T10: =SUM(T2:T9) -> 74385 | U10: =SUM(U2:U9) -> 11955
A11: 45056 | B11: =D11*0.39 -> 9578.4 | C11: =D11-B11 -> 14981.6 | D11: =E11+F11 -> 24560 | E11: 11660 | F11: 12900 | G11: =680+8700 -> 9380 | H11: =IFERROR(B11/C11,0) -> 0.63934426 | I11: =SUM($D$2:D11)-SUM($G$2:G11) -> 152255 | K11: =L11+M11 -> 0 | O11: Mul Bhag | P11: =P10/3 -> 12532
A12: 45057 | B12: =D12*0.39 -> 5721.3 | C12: =D12-B12 -> 8948.7 | D12: =E12+F12 -> 14670 | E12: 5570 | F12: 9100 | G12: 190 | H12: =IFERROR(B12/C12,0) -> 0.63934426 | I12: =SUM($D$2:D12)-SUM($G$2:G12) -> 166735 | K12: =L12+M12 -> 0
A13: 45058 | B13: =D13*0.39 -> 3706.95 | C13: =D13-B13 -> 5798.05 | D13: =E13+F13 -> 9505 | E13: 5375 | F13: 4130 | G13: 4550 | H13: =IFERROR(B13/C13,0) -> 0.63934426 | I13: =SUM($D$2:D13)-SUM($G$2:G13) -> 171690 | K13: =L13+M13 -> 0 | O13: Date | P13: Profit | Q13: Actual | R13: Total | S13: Cash | T13: Account Transfer | U13: Expense
A14: 45059 | B14: =D14*0.39 -> 9147.45 | C14: =D14-B14 -> 14307.55 | D14: =E14+F14 -> 23455 | E14: 6915 | F14: 16540 | G14: 120 | H14: =IFERROR(B14/C14,0) -> 0.63934426 | I14: =SUM($D$2:D14)-SUM($G$2:G14) -> 195025 | K14: =L14+M14 -> 0 | O14: =A9 -> 45054 | P14: =R14*0.3 -> 5673 | Q14: =R14-P14 -> 13237 | R14: =S14+T14 -> 18910 | S14: =VLOOKUP(O14,$A$1:$H$37,5,0) -> 11960 | T14: =VLOOKUP(O14,$A$1:$H$37,6,0) -> 6950 | U14: =VLOOKUP(O14,$A$1:$H$37,7,0) -> 28700
A15: 45060 | B15: =D15*0.39 -> 5298.15 | C15: =D15-B15 -> 8286.85 | D15: =E15+F15 -> 13585 | E15: 9705 | F15: 3880 | G15: 80 | H15: =IFERROR(B15/C15,0) -> 0.63934426 | I15: =SUM($D$2:D15)-SUM($G$2:G15) -> 208530 | K15: =L15+M15 -> 0 | O15: =A10 -> 45055 | P15: =R15*0.3 -> 10272 | Q15: =R15-P15 -> 23968 | R15: =S15+T15 -> 34240 | S15: =VLOOKUP(O15,$A$1:$H$37,5,0) -> 10200 | T15: =VLOOKUP(O15,$A$1:$H$37,6,0) -> 24040 | U15: =VLOOKUP(O15,$A$1:$H$37,7,0) -> 740
A16: 45061 | B16: =D16*0.39 -> 5171.4 | C16: =D16-B16 -> 8088.6 | D16: =E16+F16 -> 13260 | E16: 10180 | F16: 3080 | G16: 140 | H16: =IFERROR(B16/C16,0) -> 0.63934426 | I16: =SUM($D$2:D16)-SUM($G$2:G16) -> 221650 | K16: =L16+M16 -> 17590 | L16: 10190 | M16: =3470+3930 -> 7400 | O16: =A11 -> 45056 | P16: =R16*0.3 -> 7368 | Q16: =R16-P16 -> 17192 | R16: =S16+T16 -> 24560 | S16: =VLOOKUP(O16,$A$1:$H$37,5,0) -> 11660 | T16: =VLOOKUP(O16,$A$1:$H$37,6,0) -> 12900 | U16: =VLOOKUP(O16,$A$1:$H$37,7,0) -> 9380
A17: 45062 | B17: =D17*0.39 -> 5212.35 | C17: =D17-B17 -> 8152.65 | D17: =E17+F17 -> 13365 | E17: 11435 | F17: 1930 | G17: 650 | H17: =IFERROR(B17/C17,0) -> 0.63934426 | I17: =SUM($D$2:D17)-SUM($G$2:G17) -> 234365 | K17: =L17+M17 -> 0 | O17: =A12 -> 45057 | P17: =R17*0.3 -> 4401 | Q17: =R17-P17 -> 10269 | R17: =S17+T17 -> 14670 | S17: =VLOOKUP(O17,$A$1:$H$37,5,0) -> 5570 | T17: =VLOOKUP(O17,$A$1:$H$37,6,0) -> 9100 | U17: =VLOOKUP(O17,$A$1:$H$37,7,0) -> 190
A18: 45063 | B18: =D18*0.39 -> 8724.3 | C18: =D18-B18 -> 13645.7 | D18: =E18+F18 -> 22370 | E18: 20900 | F18: 1470 | G18: 1600 | H18: =IFERROR(B18/C18,0) -> 0.63934426 | I18: =SUM($D$2:D18)-SUM($G$2:G18) -> 255135 | K18: =L18+M18 -> 0 | O18: =A13 -> 45058 | P18: =R18*0.3 -> 2851.5 | Q18: =R18-P18 -> 6653.5 | R18: =S18+T18 -> 9505 | S18: =VLOOKUP(O18,$A$1:$H$37,5,0) -> 5375 | T18: =VLOOKUP(O18,$A$1:$H$37,6,0) -> 4130 | U18: =VLOOKUP(O18,$A$1:$H$37,7,0) -> 4550
A19: 45064 | B19: =D19*0.39 -> 4291.95 | C19: =D19-B19 -> 6713.05 | D19: =E19+F19 -> 11005 | E19: 8335 | F19: 2670 | G19: 650 | H19: =IFERROR(B19/C19,0) -> 0.63934426 | I19: =SUM($D$2:D19)-SUM($G$2:G19) -> 265490 | K19: =L19+M19 -> 0 | O19: =A14 -> 45059 | P19: =R19*0.3 -> 7036.5 | Q19: =R19-P19 -> 16418.5 | R19: =S19+T19 -> 23455 | S19: =VLOOKUP(O19,$A$1:$H$37,5,0) -> 6915 | T19: =VLOOKUP(O19,$A$1:$H$37,6,0) -> 16540 | U19: =VLOOKUP(O19,$A$1:$H$37,7,0) -> 120
A20: 45065 | B20: =D20*0.39 -> 3125.85 | C20: =D20-B20 -> 4889.15 | D20: =E20+F20 -> 8015 | E20: =5400+380 -> 5780 | F20: 2235 | G20: 650 | H20: =IFERROR(B20/C20,0) -> 0.63934426 | I20: =SUM($D$2:D20)-SUM($G$2:G20) -> 272855 | K20: =L20+M20 -> 0 | O20: =A15 -> 45060 | P20: =R20*0.3 -> 4075.5 | Q20: =R20-P20 -> 9509.5 | R20: =S20+T20 -> 13585 | S20: =VLOOKUP(O20,$A$1:$H$37,5,0) -> 9705 | T20: =VLOOKUP(O20,$A$1:$H$37,6,0) -> 3880 | U20: =VLOOKUP(O20,$A$1:$H$37,7,0) -> 80
A21: 45066 | B21: =D21*0.39 -> 5731.05 | C21: =D21-B21 -> 8963.95 | D21: =E21+F21 -> 14695 | E21: 2525 | F21: 12170 | G21: 2530 | H21: =IFERROR(B21/C21,0) -> 0.63934426 | I21: =SUM($D$2:D21)-SUM($G$2:G21) -> 285020 | K21: =L21+M21 -> 0 | O21: Total | P21: =SUM(P14:P20) -> 41677.5 | Q21: =SUM(Q14:Q20) -> 97247.5 | R21: =SUM(R14:R20) -> 138925 | S21: =SUM(S14:S20) -> 61385 | T21: =SUM(T14:T20) -> 77540 | U21: =SUM(U14:U20) -> 43760
A22: 45067 | B22: =D22*0.39 -> 13921.05 | C22: =D22-B22 -> 21773.95 | D22: =E22+F22 -> 35695 | E22: 17225 | F22: 18470 | G22: 1180 | H22: =IFERROR(B22/C22,0) -> 0.63934426 | I22: =SUM($D$2:D22)-SUM($G$2:G22) -> 319535 | K22: =L22+M22 -> 0 | O22: Mul Bhag | P22: =P21/3 -> 13892.5 | Q22: 12750 | R22: =Q22+P22 -> 26642.5
A23: 45068 | B23: =D23*0.39 -> 10959 | C23: =D23-B23 -> 17141 | D23: =E23+F23 -> 28100 | E23: 5670 | F23: 22430 | G23: =19500+1400 -> 20900 | H23: =IFERROR(B23/C23,0) -> 0.63934426 | I23: =SUM($D$2:D23)-SUM($G$2:G23) -> 326735 | K23: =L23+M23 -> 0 | Q23: ser
A24: 45069 | B24: =D24*0.39 -> 10479.3 | C24: =D24-B24 -> 16390.7 | D24: =E24+F24 -> 26870 | E24: 13920 | F24: 12950 | G24: 550 | H24: =IFERROR(B24/C24,0) -> 0.63934426 | I24: =SUM($D$2:D24)-SUM($G$2:G24) -> 353055 | K24: =L24+M24 -> 0 | O24: Date | P24: Profit | Q24: Actual | R24: Total | S24: Cash | T24: Account Transfer | U24: Expense
A25: 45070 | B25: =D25*0.39 -> 5411.25 | C25: =D25-B25 -> 8463.75 | D25: =E25+F25 -> 13875 | E25: 9955 | F25: 3920 | G25: 530 | H25: =IFERROR(B25/C25,0) -> 0.63934426 | I25: =SUM($D$2:D25)-SUM($G$2:G25) -> 366400 | K25: =L25+M25 -> 0 | O25: =A16 -> 45061 | P25: =R25*0.3 -> 924 | Q25: =R25-P25 -> 2156 | R25: =S25+T25 -> 3080 | S25: 0 | T25: =VLOOKUP(O25,$A$1:$H$37,6,0) -> 3080 | U25: =VLOOKUP(O25,$A$1:$H$37,7,0) -> 140
A26: 45071 | B26: =D26*0.39 -> 9438 | C26: =D26-B26 -> 14762 | D26: =E26+F26 -> 24200 | E26: 8600 | F26: 15600 | G26: 3100 | H26: =IFERROR(B26/C26,0) -> 0.63934426 | I26: =SUM($D$2:D26)-SUM($G$2:G26) -> 387500 | K26: =L26+M26 -> 0 | O26: =A17 -> 45062 | P26: =R26*0.3 -> 4009.5 | Q26: =R26-P26 -> 9355.5 | R26: =S26+T26 -> 13365 | S26: =VLOOKUP(O26,$A$1:$H$37,5,0) -> 11435 | T26: =VLOOKUP(O26,$A$1:$H$37,6,0) -> 1930 | U26: =VLOOKUP(O26,$A$1:$H$37,7,0) -> 650
A27: 45072 | B27: =D27*0.39 -> 1969.5 | C27: =D27-B27 -> 3080.5 | D27: =E27+F27 -> 5050 | E27: 4500 | F27: 550 | G27: 8800 | H27: =IFERROR(B27/C27,0) -> 0.63934426 | I27: =SUM($D$2:D27)-SUM($G$2:G27) -> 383750 | K27: =L27+M27 -> 0 | O27: =A18 -> 45063 | P27: =R27*0.3 -> 6711 | Q27: =R27-P27 -> 15659 | R27: =S27+T27 -> 22370 | S27: =VLOOKUP(O27,$A$1:$H$37,5,0) -> 20900 | T27: =VLOOKUP(O27,$A$1:$H$37,6,0) -> 1470 | U27: =VLOOKUP(O27,$A$1:$H$37,7,0) -> 1600
A28: 45073 | B28: =D28*0.39 -> 4941.3 | C28: =D28-B28 -> 7728.7 | D28: =E28+F28 -> 12670 | E28: 7270 | F28: 5400 | G28: 140 | H28: =IFERROR(B28/C28,0) -> 0.63934426 | I28: =SUM($D$2:D28)-SUM($G$2:G28) -> 396280 | K28: =L28+M28 -> 0 | O28: =A19 -> 45064 | P28: =R28*0.3 -> 3301.5 | Q28: =R28-P28 -> 7703.5 | R28: =S28+T28 -> 11005 | S28: =VLOOKUP(O28,$A$1:$H$37,5,0) -> 8335 | T28: =VLOOKUP(O28,$A$1:$H$37,6,0) -> 2670 | U28: =VLOOKUP(O28,$A$1:$H$37,7,0) -> 650
A29: 45074 | B29: =D29*0.39 -> 2558.4 | C29: =D29-B29 -> 4001.6 | D29: =E29+F29 -> 6560 | E29: 5550 | F29: 1010 | G29: 100 | H29: =IFERROR(B29/C29,0) -> 0.63934426 | I29: =SUM($D$2:D29)-SUM($G$2:G29) -> 402740 | K29: =L29+M29 -> 0 | O29: =A20 -> 45065 | P29: =R29*0.3 -> 2404.5 | Q29: =R29-P29 -> 5610.5 | R29: =S29+T29 -> 8015 | S29: =VLOOKUP(O29,$A$1:$H$37,5,0) -> 5780 | T29: =VLOOKUP(O29,$A$1:$H$37,6,0) -> 2235 | U29: =VLOOKUP(O29,$A$1:$H$37,7,0) -> 650
A30: 45075 | B30: =D30*0.39 -> 5898.75 | C30: =D30-B30 -> 9226.25 | D30: =E30+F30 -> 15125 | E30: 4750 | F30: 10375 | G30: 18120 | H30: =IFERROR(B30/C30,0) -> 0.63934426 | I30: =SUM($D$2:D30)-SUM($G$2:G30) -> 399745 | K30: =L30+M30 -> 0 | O30: =A21 -> 45066 | P30: =R30*0.3 -> 4408.5 | Q30: =R30-P30 -> 10286.5 | R30: =S30+T30 -> 14695 | S30: =VLOOKUP(O30,$A$1:$H$37,5,0) -> 2525 | T30: =VLOOKUP(O30,$A$1:$H$37,6,0) -> 12170 | U30: =VLOOKUP(O30,$A$1:$H$37,7,0) -> 2530
A31: 45076 | B31: =D31*0.39 -> 8890.05 | C31: =D31-B31 -> 13904.95 | D31: =E31+F31 -> 22795 | E31: 12420 | F31: 10375 | G31: 18120 | H31: =IFERROR(B31/C31,0) -> 0.63934426 | I31: =SUM($D$2:D31)-SUM($G$2:G31) -> 404420 | K31: =L31+M31 -> 0 | O31: =A22 -> 45067 | P31: =R31*0.3 -> 10708.5 | Q31: =R31-P31 -> 24986.5 | R31: =S31+T31 -> 35695 | S31: =VLOOKUP(O31,$A$1:$H$37,5,0) -> 17225 | T31: =VLOOKUP(O31,$A$1:$H$37,6,0) -> 18470 | U31: =VLOOKUP(O31,$A$1:$H$37,7,0) -> 1180
A32: 45077 | B32: =D32*0.39 -> 5434.65 | C32: =D32-B32 -> 8500.35 | D32: =E32+F32 -> 13935 | E32: 4900 | F32: 9035 | G32: 17850 | H32: =IFERROR(B32/C32,0) -> 0.63934426 | I32: =SUM($D$2:D32)-SUM($G$2:G32) -> 400505 | K32: =L32+M32 -> 0 | O32: Total | P32: =SUM(P25:P31) -> 32467.5 | Q32: =SUM(Q25:Q31) -> 75757.5 | R32: =SUM(R25:R31) -> 108225 | S32: =SUM(S25:S31) -> 66200 | T32: =SUM(T25:T31) -> 42025 | U32: =SUM(U25:U31) -> 7400
A33: 45078 | B33: =D33*0.39 -> 11239.8 | C33: =D33-B33 -> 17580.2 | D33: =E33+F33 -> 28820 | E33: 6560 | F33: 22260 | G33: 1100 | H33: =IFERROR(B33/C33,0) -> 0.63934426 | I33: =SUM($D$2:D33)-SUM($G$2:G33) -> 428225 | K33: =L33+M33 -> 0 | O33: Mul Bhag | P33: =P32/3 -> 10822.5
A34: 45079 | B34: =D34*0.39 -> 4722.9 | C34: =D34-B34 -> 7387.1 | D34: =E34+F34 -> 12110 | E34: 5280 | F34: 6830 | G34: 1810 | H34: =IFERROR(B34/C34,0) -> 0.63934426 | I34: =SUM($D$2:D34)-SUM($G$2:G34) -> 438525 | K34: =L34+M34 -> 0
A35: 45080 | B35: =D35*0.39 -> 2835.3 | C35: =D35-B35 -> 4434.7 | D35: =E35+F35 -> 7270 | E35: =4250+550 -> 4800 | F35: 2470 | G35: 50 | H35: =IFERROR(B35/C35,0) -> 0.63934426 | I35: =SUM($D$2:D35)-SUM($G$2:G35) -> 445745 | K35: =L35+M35 -> 0 | O35: Date | P35: Profit | Q35: Actual | R35: Total | S35: Cash | T35: Account Transfer | U35: Expense
A36: 45081 | B36: =D36*0.39 -> 9987.9 | C36: =D36-B36 -> 15622.1 | D36: =E36+F36 -> 25610 | E36: 13790 | F36: 11820 | G36: 2950 | H36: =IFERROR(B36/C36,0) -> 0.63934426 | I36: =SUM($D$2:D36)-SUM($G$2:G36) -> 468405 | K36: =L36+M36 -> 0 | O36: =A23 -> 45068 | P36: =R36*0.3 -> 8430 | Q36: =R36-P36 -> 19670 | R36: =S36+T36 -> 28100 | S36: =VLOOKUP(O36,$A$1:$H$37,5,0) -> 5670 | T36: =VLOOKUP(O36,$A$1:$H$37,6,0) -> 22430 | U36: =VLOOKUP(O36,$A$1:$H$37,7,0) -> 20900
A37: Total | B37: =SUM(B2:B32) -> 215213.7 | C37: =SUM(C2:C32) -> 336616.3 | D37: =SUM(D2:D32) -> 551830 | E37: =SUM(E2:E32) -> 266235 | F37: =SUM(F2:F32) -> 285595 | G37: =SUM(G2:G32) -> 151325 | H37: =SUM(H2:H32) -> 19.819672 | I37: =SUM(I2:I32) -> 7263750 | K37: =SUM(K3:K36) -> 17590 | L37: =SUM(L3:L36) -> 10190 | M37: =SUM(M3:M36) -> 7400 | O37: =A24 -> 45069 | P37: =R37*0.3 -> 8061 | Q37: =R37-P37 -> 18809 | R37: =S37+T37 -> 26870 | S37: =VLOOKUP(O37,$A$1:$H$37,5,0) -> 13920 | T37: =VLOOKUP(O37,$A$1:$H$37,6,0) -> 12950 | U37: =VLOOKUP(O37,$A$1:$H$37,7,0) -> 550
B38: =B37/3 -> 71737.9 | E38: =D37*0.42 -> 231768.6 | L38: =K37*0.42 -> 7387.8 | O38: =A25 -> 45070 | P38: =R38*0.3 -> 4162.5 | Q38: =R38-P38 -> 9712.5 | R38: =S38+T38 -> 13875 | S38: =VLOOKUP(O38,$A$1:$H$37,5,0) -> 9955 | T38: =VLOOKUP(O38,$A$1:$H$37,6,0) -> 3920 | U38: =VLOOKUP(O38,$A$1:$H$37,7,0) -> 530
B39: =B38*100/D37 -> 13 | E39: =E38/3 -> 77256.2 | L39: =L38/3 -> 2462.6 | O39: =A26 -> 45071 | P39: =R39*0.3 -> 7260 | Q39: =R39-P39 -> 16940 | R39: =S39+T39 -> 24200 | S39: =VLOOKUP(O39,$A$1:$H$37,5,0) -> 8600 | T39: =VLOOKUP(O39,$A$1:$H$37,6,0) -> 15600 | U39: =VLOOKUP(O39,$A$1:$H$37,7,0) -> 3100
A40: Date | B40: Profit | C40: Actual | D40: Total | E40: Cash | F40: Account Transfer | G40: Expense | H40: Mul Bhag | K40: Total | L40: Cash | M40: Account Transfer | O40: =A27 -> 45072 | P40: =R40*0.3 -> 1515 | Q40: =R40-P40 -> 3535 | R40: =S40+T40 -> 5050 | S40: =VLOOKUP(O40,$A$1:$H$37,5,0) -> 4500 | T40: =VLOOKUP(O40,$A$1:$H$37,6,0) -> 550 | U40: =VLOOKUP(O40,$A$1:$H$37,7,0) -> 8800
A41: =CONCATENATE(TEXT(O3,"DD-MMM-YYY")," to ",TEXT(O9,"DD-MMM-YYYY")) -> 01-May-2023 to 07-May-2023 | B41: =P10 -> 37596 | C41: =Q10 -> 87724 | D41: =R10 -> 125320 | E41: =S10 -> 50935 | F41: =T10 -> 74385 | G41: =U10 -> 11955 | H41: =B41/3 -> 12532 | K41: =Y10 -> 0 | L41: =Z10 -> 0 | M41: =AA10 -> 0 | O41: =A28 -> 45073 | P41: =R41*0.3 -> 3801 | Q41: =R41-P41 -> 8869 | R41: =S41+T41 -> 12670 | S41: =VLOOKUP(O41,$A$1:$H$37,5,0) -> 7270 | T41: =VLOOKUP(O41,$A$1:$H$37,6,0) -> 5400 | U41: =VLOOKUP(O41,$A$1:$H$37,7,0) -> 140
A42: =CONCATENATE(TEXT(O14,"DD-MMM-YYY")," to ",TEXT(O20,"DD-MMM-YYYY")) -> 08-May-2023 to 14-May-2023 | B42: =P21 -> 41677.5 | C42: =Q21 -> 97247.5 | D42: =R21 -> 138925 | E42: =S21 -> 61385 | F42: =T21 -> 77540 | G42: =U21 -> 43760 | H42: =B42/3 -> 13892.5 | K42: =Y21 -> 0 | L42: =Z21 -> 0 | M42: =AA21 -> 0 | O42: =A29 -> 45074 | P42: =R42*0.3 -> 1968 | Q42: =R42-P42 -> 4592 | R42: =S42+T42 -> 6560 | S42: =VLOOKUP(O42,$A$1:$H$37,5,0) -> 5550 | T42: =VLOOKUP(O42,$A$1:$H$37,6,0) -> 1010 | U42: =VLOOKUP(O42,$A$1:$H$37,7,0) -> 100
A43: =CONCATENATE(TEXT(O25,"DD-MMM-YYY")," to ",TEXT(O31,"DD-MMM-YYYY")) -> 15-May-2023 to 21-May-2023 | B43: =P32 -> 32467.5 | C43: =Q32 -> 75757.5 | D43: =R32 -> 108225 | E43: =S32 -> 66200 | F43: =T32 -> 42025 | G43: =U32 -> 7400 | H43: =B43/3 -> 10822.5 | K43: =Y32 -> 0 | L43: =Z32 -> 0 | M43: =AA32 -> 0 | O43: Total | P43: =SUM(P36:P42) -> 35197.5 | Q43: =SUM(Q36:Q42) -> 82127.5 | R43: =SUM(R36:R42) -> 117325 | S43: =SUM(S36:S42) -> 55465 | T43: =SUM(T36:T42) -> 61860 | U43: =SUM(U36:U42) -> 34120
A44: =CONCATENATE(TEXT(O36,"DD-MMM-YYY")," to ",TEXT(O42,"DD-MMM-YYYY")) -> 22-May-2023 to 28-May-2023 | B44: =P43 -> 35197.5 | C44: =Q43 -> 82127.5 | D44: =R43 -> 117325 | E44: =S43 -> 55465 | F44: =T43 -> 61860 | G44: =U43 -> 34120 | H44: =B44/3 -> 11732.5 | K44: =Y43 -> 0 | L44: =Z43 -> 0 | M44: =AA43 -> 0 | O44: Mul Bhag | P44: =P43/3 -> 11732.5
A45: =CONCATENATE(TEXT(O47,"DD-MMM-YYY")," to ",TEXT(O53,"DD-MMM-YYYY")) -> 29-May-2023 to 04-Jun-2023 | B45: =P54 -> 37699.5 | C45: =Q54 -> 87965.5 | D45: =R54 -> 125665 | E45: =S54 -> 52500 | F45: =T54 -> 73165 | G45: =U54 -> 60000 | H45: =B45/3 -> 12566.5 | K45: =Y54 -> 0 | L45: =Z54 -> 0 | M45: =AA54 -> 0
A46: =CONCATENATE(TEXT(O59,"DD-MMM-YYY")," to ",TEXT(O58,"DD-MMM-YYYY")) -> 05-May-2023 to Date | B46: =SUM(B41:B45) -> 184638 | C46: =SUM(C41:C45) -> 430822 | D46: =SUM(D41:D45) -> 615460 | E46: =SUM(E41:E45) -> 286485 | F46: =SUM(F41:F45) -> 328975 | G46: =SUM(G41:G45) -> 157235 | H46: =SUM(H41:H45) -> 61546 | K46: =SUM(K41:K45) -> 0 | L46: =SUM(L41:L45) -> 0 | M46: =SUM(M41:M45) -> 0 | O46: Date | P46: Profit | Q46: Actual | R46: Total | S46: Cash | T46: Account Transfer | U46: Expense
B47: =B46/3 -> 61546 | C47: Total | O47: =A30 -> 45075 | P47: =R47*0.3 -> 4537.5 | Q47: =R47-P47 -> 10587.5 | R47: =S47+T47 -> 15125 | S47: =VLOOKUP(O47,$A$1:$H$37,5,0) -> 4750 | T47: =VLOOKUP(O47,$A$1:$H$37,6,0) -> 10375 | U47: =VLOOKUP(O47,$A$1:$H$37,7,0) -> 18120
O48: =A31 -> 45076 | P48: =R48*0.3 -> 6838.5 | Q48: =R48-P48 -> 15956.5 | R48: =S48+T48 -> 22795 | S48: =VLOOKUP(O48,$A$1:$H$37,5,0) -> 12420 | T48: =VLOOKUP(O48,$A$1:$H$37,6,0) -> 10375 | U48: =VLOOKUP(O48,$A$1:$H$37,7,0) -> 18120
B49: =SUM(B33:B36) -> 28785.9 | C49: =SUM(C33:C36) -> 45024.1 | D49: =SUM(D33:D36) -> 73810 | E49: =SUM(E33:E36) -> 30430 | F49: =SUM(F33:F36) -> 43380 | G49: =SUM(G33:G36) -> 5910 | H49: =SUM(H33:H36) -> 2.557377 | O49: =A32 -> 45077 | P49: =R49*0.3 -> 4180.5 | Q49: =R49-P49 -> 9754.5 | R49: =S49+T49 -> 13935 | S49: =VLOOKUP(O49,$A$1:$H$37,5,0) -> 4900 | T49: =VLOOKUP(O49,$A$1:$H$37,6,0) -> 9035 | U49: =VLOOKUP(O49,$A$1:$H$37,7,0) -> 17850
O50: =A33 -> 45078 | P50: =R50*0.3 -> 8646 | Q50: =R50-P50 -> 20174 | R50: =S50+T50 -> 28820 | S50: =VLOOKUP(O50,$A$1:$H$37,5,0) -> 6560 | T50: =VLOOKUP(O50,$A$1:$H$37,6,0) -> 22260 | U50: =VLOOKUP(O50,$A$1:$H$37,7,0) -> 1100
O51: =A34 -> 45079 | P51: =R51*0.3 -> 3633 | Q51: =R51-P51 -> 8477 | R51: =S51+T51 -> 12110 | S51: =VLOOKUP(O51,$A$1:$H$37,5,0) -> 5280 | T51: =VLOOKUP(O51,$A$1:$H$37,6,0) -> 6830 | U51: =VLOOKUP(O51,$A$1:$H$37,7,0) -> 1810
O52: =A35 -> 45080 | P52: =R52*0.3 -> 2181 | Q52: =R52-P52 -> 5089 | R52: =S52+T52 -> 7270 | S52: =VLOOKUP(O52,$A$1:$H$37,5,0) -> 4800 | T52: =VLOOKUP(O52,$A$1:$H$37,6,0) -> 2470 | U52: =VLOOKUP(O52,$A$1:$H$37,7,0) -> 50
O53: =A36 -> 45081 | P53: =R53*0.3 -> 7683 | Q53: =R53-P53 -> 17927 | R53: =S53+T53 -> 25610 | S53: =VLOOKUP(O53,$A$1:$H$37,5,0) -> 13790 | T53: =VLOOKUP(O53,$A$1:$H$37,6,0) -> 11820 | U53: =VLOOKUP(O53,$A$1:$H$37,7,0) -> 2950
O54: Total | P54: =SUM(P47:P53) -> 37699.5 | Q54: =SUM(Q47:Q53) -> 87965.5 | R54: =SUM(R47:R53) -> 125665 | S54: =SUM(S47:S53) -> 52500 | T54: =SUM(T47:T53) -> 73165 | U54: =SUM(U47:U53) -> 60000
O55: Mul Bhag | P55: =P54/3 -> 12566.5
O58: Date | P58: Profit | Q58: Actual | R58: Total | S58: Cash | T58: Account Transfer | U58: Expense
O59: =A6 -> 45051 | P59: =SUM(B7:B36) -> 207171.9 | Q59: =SUM(C7:C36) -> 324038.1 | R59: =SUM(D7:D36) -> 531210 | S59: =SUM(E7:E36) -> 259270 | T59: =SUM(F7:F36) -> 271940 | U59: =SUM(G7:G36) -> 147190
O60: Mul Bhag | P60: =P59/3 -> 69057.3

Sheet June 2023
A1: Date | B1: Profit | C1: Actual | D1: Total | E1: Cash | F1: Account Transfer | G1: Expense | H1: Percentage | I1: Cash In Hand | K1: Date | L1: Profit | M1: Actual | N1: Total | O1: Cash | P1: Account Transfer | Q1: Expense
A2: 45082 | B2: =D2*0.39 -> 6181.5 | C2: =D2-B2 -> 9668.5 | D2: =E2+F2 -> 15850 | E2: =4150+910 -> 5060 | F2: 10790 | G2: 3700 | H2: =IFERROR(B2/C2,0) -> 0.63934426 | I2: =SUM($D$2:D2)-SUM($G$2:G2) -> 12150 | K2: Export | Q2: 0
A3: 45083 | B3: =D3*0.39 -> 1343.55 | C3: =D3-B3 -> 2101.45 | D3: =E3+F3 -> 3445 | E3: 2430 | F3: 1015 | G3: 10990 | H3: =IFERROR(B3/C3,0) -> 0.63934426 | I3: =SUM($D$2:D3)-SUM($G$2:G3) -> 4605 | K3: =A2 -> 45082 | L3: =N3*0.3 -> 4755 | M3: =N3-L3 -> 11095 | N3: =O3+P3 -> 15850 | O3: =VLOOKUP(K3,$A$1:$H$30,5,0) -> 5060 | P3: =VLOOKUP(K3,$A$1:$H$30,6,0) -> 10790 | Q3: =VLOOKUP(K3,$A$1:$H$30,7,0) -> 3700
A4: 45084 | B4: =D4*0.39 -> 8962.2 | C4: =D4-B4 -> 14017.8 | D4: =E4+F4 -> 22980 | E4: 5580 | F4: 17400 | G4: 7400 | H4: =IFERROR(B4/C4,0) -> 0.63934426 | I4: =SUM($D$2:D4)-SUM($G$2:G4) -> 20185 | K4: =A3 -> 45083 | L4: =N4*0.3 -> 1033.5 | M4: =N4-L4 -> 2411.5 | N4: =O4+P4 -> 3445 | O4: =VLOOKUP(K4,$A$1:$H$30,5,0) -> 2430 | P4: =VLOOKUP(K4,$A$1:$H$30,6,0) -> 1015 | Q4: =VLOOKUP(K4,$A$1:$H$30,7,0) -> 10990
A5: 45085 | B5: =D5*0.39 -> 2581.8 | C5: =D5-B5 -> 4038.2 | D5: =E5+F5 -> 6620 | E5: 3200 | F5: 3420 | G5: 1080 | H5: =IFERROR(B5/C5,0) -> 0.63934426 | I5: =SUM($D$2:D5)-SUM($G$2:G5) -> 25725 | K5: =A4 -> 45084 | L5: =N5*0.3 -> 6894 | M5: =N5-L5 -> 16086 | N5: =O5+P5 -> 22980 | O5: =VLOOKUP(K5,$A$1:$H$30,5,0) -> 5580 | P5: =VLOOKUP(K5,$A$1:$H$30,6,0) -> 17400 | Q5: =VLOOKUP(K5,$A$1:$H$30,7,0) -> 7400
A6: 45086 | B6: =D6*0.39 -> 8190 | C6: =D6-B6 -> 12810 | D6: =E6+F6 -> 21000 | E6: 18400 | F6: 2600 | G6: 1250 | H6: =IFERROR(B6/C6,0) -> 0.63934426 | I6: =SUM($D$2:D6)-SUM($G$2:G6) -> 45475 | K6: =A5 -> 45085 | L6: =N6*0.3 -> 1986 | M6: =N6-L6 -> 4634 | N6: =O6+P6 -> 6620 | O6: =VLOOKUP(K6,$A$1:$H$30,5,0) -> 3200 | P6: =VLOOKUP(K6,$A$1:$H$30,6,0) -> 3420 | Q6: =VLOOKUP(K6,$A$1:$H$30,7,0) -> 1080
A7: 45087 | B7: =D7*0.39 -> 8884.2 | C7: =D7-B7 -> 13895.8 | D7: =E7+F7 -> 22780 | E7: 8800 | F7: 13980 | G7: 1860 | H7: =IFERROR(B7/C7,0) -> 0.63934426 | I7: =SUM($D$2:D7)-SUM($G$2:G7) -> 66395 | K7: =A6 -> 45086 | L7: =N7*0.3 -> 6300 | M7: =N7-L7 -> 14700 | N7: =O7+P7 -> 21000 | O7: =VLOOKUP(K7,$A$1:$H$30,5,0) -> 18400 | P7: =VLOOKUP(K7,$A$1:$H$30,6,0) -> 2600 | Q7: =VLOOKUP(K7,$A$1:$H$30,7,0) -> 1250
A8: 45088 | B8: =D8*0.39 -> 4173 | C8: =D8-B8 -> 6527 | D8: =E8+F8 -> 10700 | E8: 6800 | F8: 3900 | G8: 340 | H8: =IFERROR(B8/C8,0) -> 0.63934426 | I8: =SUM($D$2:D8)-SUM($G$2:G8) -> 76755 | K8: =A7 -> 45087 | L8: =N8*0.3 -> 6834 | M8: =N8-L8 -> 15946 | N8: =O8+P8 -> 22780 | O8: =VLOOKUP(K8,$A$1:$H$30,5,0) -> 8800 | P8: =VLOOKUP(K8,$A$1:$H$30,6,0) -> 13980 | Q8: =VLOOKUP(K8,$A$1:$H$30,7,0) -> 1860
A9: 45089 | B9: =D9*0.39 -> 5749.38 | C9: =D9-B9 -> 8992.62 | D9: =E9+F9 -> 14742 | E9: 12860 | F9: 1882 | G9: 250 | H9: =IFERROR(B9/C9,0) -> 0.63934426 | I9: =SUM($D$2:D9)-SUM($G$2:G9) -> 91247 | K9: =A8 -> 45088 | L9: =N9*0.3 -> 3210 | M9: =N9-L9 -> 7490 | N9: =O9+P9 -> 10700 | O9: =VLOOKUP(K9,$A$1:$H$30,5,0) -> 6800 | P9: =VLOOKUP(K9,$A$1:$H$30,6,0) -> 3900 | Q9: =VLOOKUP(K9,$A$1:$H$30,7,0) -> 340
A10: 45090 | B10: =D10*0.39 -> 1544.4 | C10: =D10-B10 -> 2415.6 | D10: =E10+F10 -> 3960 | E10: 1600 | F10: 2360 | G10: 100 | H10: =IFERROR(B10/C10,0) -> 0.63934426 | I10: =SUM($D$2:D10)-SUM($G$2:G10) -> 95107 | K10: Total | L10: =SUM(L3:L9) -> 31012.5 | M10: =SUM(M2:M9) -> 72362.5 | N10: =SUM(N2:N9) -> 103375 | O10: =SUM(O2:O9) -> 50270 | P10: =SUM(P2:P9) -> 53105 | Q10: =SUM(Q2:Q9) -> 26620
A11: 45091 | B11: =D11*0.39 -> 15849.6 | C11: =D11-B11 -> 24790.4 | D11: =E11+F11 -> 40640 | E11: 18390 | F11: 22250 | G11: 7100 | H11: =IFERROR(B11/C11,0) -> 0.63934426 | I11: =SUM($D$2:D11)-SUM($G$2:G11) -> 128647 | K11: Mul Bhag | L11: =L10/3 -> 10337.5
A12: 45092 | B12: =D12*0.39 -> 4769.7 | C12: =D12-B12 -> 7460.3 | D12: =E12+F12 -> 12230 | E12: 9710 | F12: 2520 | G12: 100 | H12: =IFERROR(B12/C12,0) -> 0.63934426 | I12: =SUM($D$2:D12)-SUM($G$2:G12) -> 140777
A13: 45093 | B13: =D13*0.39 -> 5315.7 | C13: =D13-B13 -> 8314.3 | D13: =E13+F13 -> 13630 | E13: 4140 | F13: 9490 | G13: 4000 | H13: =IFERROR(B13/C13,0) -> 0.63934426 | I13: =SUM($D$2:D13)-SUM($G$2:G13) -> 150407 | K13: Date | L13: Profit | M13: Actual | N13: Total | O13: Cash | P13: Account Transfer | Q13: Expense
A14: 45094 | B14: =D14*0.39 -> 6649.5 | C14: =D14-B14 -> 10400.5 | D14: =E14+F14 -> 17050 | E14: 8550 | F14: 8500 | G14: =10900+6500 -> 17400 | H14: =IFERROR(B14/C14,0) -> 0.63934426 | I14: =SUM($D$2:D14)-SUM($G$2:G14) -> 150057 | K14: =A9 -> 45089 | L14: =N14*0.3 -> 4422.6 | M14: =N14-L14 -> 10319.4 | N14: =O14+P14 -> 14742 | O14: =VLOOKUP(K14,$A$1:$H$30,5,0) -> 12860 | P14: =VLOOKUP(K14,$A$1:$H$30,6,0) -> 1882 | Q14: =VLOOKUP(K14,$A$1:$H$30,7,0) -> 250
A15: 45095 | B15: =D15*0.39 -> 5651.88 | C15: =D15-B15 -> 8840.12 | D15: =E15+F15 -> 14492 | E15: 3360 | F15: 11132 | G15: 100 | H15: =IFERROR(B15/C15,0) -> 0.63934426 | I15: =SUM($D$2:D15)-SUM($G$2:G15) -> 164449 | K15: =A10 -> 45090 | L15: =N15*0.3 -> 1188 | M15: =N15-L15 -> 2772 | N15: =O15+P15 -> 3960 | O15: =VLOOKUP(K15,$A$1:$H$30,5,0) -> 1600 | P15: =VLOOKUP(K15,$A$1:$H$30,6,0) -> 2360 | Q15: =VLOOKUP(K15,$A$1:$H$30,7,0) -> 100
A16: 45096 | B16: =D16*0.39 -> 17062.5 | C16: =D16-B16 -> 26687.5 | D16: =E16+F16 -> 43750 | E16: 7490 | F16: 36260 | G16: 2360 | H16: =IFERROR(B16/C16,0) -> 0.63934426 | I16: =SUM($D$2:D16)-SUM($G$2:G16) -> 205839 | K16: =A11 -> 45091 | L16: =N16*0.3 -> 12192 | M16: =N16-L16 -> 28448 | N16: =O16+P16 -> 40640 | O16: =VLOOKUP(K16,$A$1:$H$30,5,0) -> 18390 | P16: =VLOOKUP(K16,$A$1:$H$30,6,0) -> 22250 | Q16: =VLOOKUP(K16,$A$1:$H$30,7,0) -> 7100
A17: 45097 | B17: =D17*0.39 -> 3607.5 | C17: =D17-B17 -> 5642.5 | D17: =E17+F17 -> 9250 | E17: 7730 | F17: 1520 | G17: 100 | H17: =IFERROR(B17/C17,0) -> 0.63934426 | I17: =SUM($D$2:D17)-SUM($G$2:G17) -> 214989 | K17: =A12 -> 45092 | L17: =N17*0.3 -> 3669 | M17: =N17-L17 -> 8561 | N17: =O17+P17 -> 12230 | O17: =VLOOKUP(K17,$A$1:$H$30,5,0) -> 9710 | P17: =VLOOKUP(K17,$A$1:$H$30,6,0) -> 2520 | Q17: =VLOOKUP(K17,$A$1:$H$30,7,0) -> 100
A18: 45098 | B18: =D18*0.39 -> 2349.75 | C18: =D18-B18 -> 3675.25 | D18: =E18+F18 -> 6025 | E18: 1380 | F18: 4645 | G18: 100 | H18: =IFERROR(B18/C18,0) -> 0.63934426 | I18: =SUM($D$2:D18)-SUM($G$2:G18) -> 220914 | K18: =A13 -> 45093 | L18: =N18*0.3 -> 4089 | M18: =N18-L18 -> 9541 | N18: =O18+P18 -> 13630 | O18: =VLOOKUP(K18,$A$1:$H$30,5,0) -> 4140 | P18: =VLOOKUP(K18,$A$1:$H$30,6,0) -> 9490 | Q18: =VLOOKUP(K18,$A$1:$H$30,7,0) -> 4000
A19: 45099 | B19: =D19*0.39 -> 7546.5 | C19: =D19-B19 -> 11803.5 | D19: =E19+F19 -> 19350 | E19: 5780 | F19: 13570 | G19: 120 | H19: =IFERROR(B19/C19,0) -> 0.63934426 | I19: =SUM($D$2:D19)-SUM($G$2:G19) -> 240144 | K19: =A14 -> 45094 | L19: =N19*0.3 -> 5115 | M19: =N19-L19 -> 11935 | N19: =O19+P19 -> 17050 | O19: =VLOOKUP(K19,$A$1:$H$30,5,0) -> 8550 | P19: =VLOOKUP(K19,$A$1:$H$30,6,0) -> 8500 | Q19: =VLOOKUP(K19,$A$1:$H$30,7,0) -> 17400
A20: 45100 | B20: =D20*0.39 -> 4847.7 | C20: =D20-B20 -> 7582.3 | D20: =E20+F20 -> 12430 | E20: 9650 | F20: 2780 | G20: 2500 | H20: =IFERROR(B20/C20,0) -> 0.63934426 | I20: =SUM($D$2:D20)-SUM($G$2:G20) -> 250074 | K20: =A15 -> 45095 | L20: =N20*0.3 -> 4347.6 | M20: =N20-L20 -> 10144.4 | N20: =O20+P20 -> 14492 | O20: =VLOOKUP(K20,$A$1:$H$30,5,0) -> 3360 | P20: =VLOOKUP(K20,$A$1:$H$30,6,0) -> 11132 | Q20: =VLOOKUP(K20,$A$1:$H$30,7,0) -> 100
A21: 45101 | B21: =D21*0.39 -> 6906.9 | C21: =D21-B21 -> 10803.1 | D21: =E21+F21 -> 17710 | E21: 3710 | F21: 14000 | G21: 3420 | H21: =IFERROR(B21/C21,0) -> 0.63934426 | I21: =SUM($D$2:D21)-SUM($G$2:G21) -> 264364 | K21: Total | L21: =SUM(L14:L20) -> 35023.2 | M21: =SUM(M14:M20) -> 81720.8 | N21: =SUM(N14:N20) -> 116744 | O21: =SUM(O14:O20) -> 58610 | P21: =SUM(P14:P20) -> 58134 | Q21: =SUM(Q14:Q20) -> 29050
A22: 45102 | B22: =D22*0.39 -> 1304.94 | C22: =D22-B22 -> 2041.06 | D22: =E22+F22 -> 3346 | E22: 1330 | F22: 2016 | G22: 20 | H22: =IFERROR(B22/C22,0) -> 0.63934426 | I22: =SUM($D$2:D22)-SUM($G$2:G22) -> 267690 | K22: Mul Bhag | L22: =L21/3 -> 11674.4 | M22: 12750 | N22: =M22+L22 -> 24424.4
A23: 45103 | B23: =D23*0.39 -> 6555.9 | C23: =D23-B23 -> 10254.1 | D23: =E23+F23 -> 16810 | E23: 3980 | F23: 12830 | G23: 10000 | H23: =IFERROR(B23/C23,0) -> 0.63934426 | I23: =SUM($D$2:D23)-SUM($G$2:G23) -> 274500 | M23: ser
A24: 45104 | B24: =D24*0.39 -> 1957.8 | C24: =D24-B24 -> 3062.2 | D24: =E24+F24 -> 5020 | E24: 0 | F24: 5020 | G24: 3200 | H24: =IFERROR(B24/C24,0) -> 0.63934426 | I24: =SUM($D$2:D24)-SUM($G$2:G24) -> 276320 | K24: Date | L24: Profit | M24: Actual | N24: Total | O24: Cash | P24: Account Transfer | Q24: Expense
A25: 45105 | B25: =D25*0.39 -> 3386.37 | C25: =D25-B25 -> 5296.63 | D25: =E25+F25 -> 8683 | E25: 930 | F25: 7753 | G25: 3200 | H25: =IFERROR(B25/C25,0) -> 0.63934426 | I25: =SUM($D$2:D25)-SUM($G$2:G25) -> 281803 | K25: =A16 -> 45096 | L25: =N25*0.3 -> 10878 | M25: =N25-L25 -> 25382 | N25: =O25+P25 -> 36260 | O25: 0 | P25: =VLOOKUP(K25,$A$1:$H$30,6,0) -> 36260 | Q25: =VLOOKUP(K25,$A$1:$H$30,7,0) -> 2360
A26: 45106 | B26: =D26*0.39 -> 4633.2 | C26: =D26-B26 -> 7246.8 | D26: =E26+F26 -> 11880 | E26: 5000 | F26: 6880 | G26: 700 | H26: =IFERROR(B26/C26,0) -> 0.63934426 | I26: =SUM($D$2:D26)-SUM($G$2:G26) -> 292983 | K26: =A17 -> 45097 | L26: =N26*0.3 -> 2775 | M26: =N26-L26 -> 6475 | N26: =O26+P26 -> 9250 | O26: =VLOOKUP(K26,$A$1:$H$30,5,0) -> 7730 | P26: =VLOOKUP(K26,$A$1:$H$30,6,0) -> 1520 | Q26: =VLOOKUP(K26,$A$1:$H$30,7,0) -> 100
A27: 45107 | B27: =D27*0.39 -> 9687.6 | C27: =D27-B27 -> 15152.4 | D27: =E27+F27 -> 24840 | E27: 7570 | F27: 17270 | G27: 65285 | H27: =IFERROR(B27/C27,0) -> 0.63934426 | I27: =SUM($D$2:D27)-SUM($G$2:G27) -> 252538 | K27: =A18 -> 45098 | L27: =N27*0.3 -> 1807.5 | M27: =N27-L27 -> 4217.5 | N27: =O27+P27 -> 6025 | O27: =VLOOKUP(K27,$A$1:$H$30,5,0) -> 1380 | P27: =VLOOKUP(K27,$A$1:$H$30,6,0) -> 4645 | Q27: =VLOOKUP(K27,$A$1:$H$30,7,0) -> 100
A28: 45108 | B28: =D28*0.39 -> 613.08 | C28: =D28-B28 -> 958.92 | D28: =E28+F28 -> 1572 | E28: 600 | F28: 972 | G28: 100 | H28: =IFERROR(B28/C28,0) -> 0.63934426 | I28: =SUM($D$2:D28)-SUM($G$2:G28) -> 254010 | K28: =A19 -> 45099 | L28: =N28*0.3 -> 5805 | M28: =N28-L28 -> 13545 | N28: =O28+P28 -> 19350 | O28: =VLOOKUP(K28,$A$1:$H$30,5,0) -> 5780 | P28: =VLOOKUP(K28,$A$1:$H$30,6,0) -> 13570 | Q28: =VLOOKUP(K28,$A$1:$H$30,7,0) -> 120
A29: 45109 | B29: =D29*0.39 -> 1248 | C29: =D29-B29 -> 1952 | D29: =E29+F29 -> 3200 | E29: 1400 | F29: 1800 | G29: 90 | H29: =IFERROR(B29/C29,0) -> 0.63934426 | I29: =SUM($D$2:D29)-SUM($G$2:G29) -> 257120 | K29: =A20 -> 45100 | L29: =N29*0.3 -> 3729 | M29: =N29-L29 -> 8701 | N29: =O29+P29 -> 12430 | O29: =VLOOKUP(K29,$A$1:$H$30,5,0) -> 9650 | P29: =VLOOKUP(K29,$A$1:$H$30,6,0) -> 2780 | Q29: =VLOOKUP(K29,$A$1:$H$30,7,0) -> 2500
A30: Total | B30: =SUM(B3:B27) -> 149511.57 | C30: =SUM(C3:C29) -> 236762.35 | D30: =SUM(D3:D29) -> 388135 | E30: =SUM(E3:E29) -> 160370 | F30: =SUM(F3:F29) -> 227765 | G30: =SUM(G3:G29) -> 143165 | H30: =SUM(G2:G29) -> 146865 | I30: =B30/C30 -> 0.63148372 | K30: =A21 -> 45101 | L30: =N30*0.3 -> 5313 | M30: =N30-L30 -> 12397 | N30: =O30+P30 -> 17710 | O30: =VLOOKUP(K30,$A$1:$H$30,5,0) -> 3710 | P30: =VLOOKUP(K30,$A$1:$H$30,6,0) -> 14000 | Q30: =VLOOKUP(K30,$A$1:$H$30,7,0) -> 3420
B31: =B30/3 -> 49837.19 | E31: =D30*0.42 -> 163016.7 | K31: =A22 -> 45102 | L31: =N31*0.3 -> 1003.8 | M31: =N31-L31 -> 2342.2 | N31: =O31+P31 -> 3346 | O31: =VLOOKUP(K31,$A$1:$H$30,5,0) -> 1330 | P31: =VLOOKUP(K31,$A$1:$H$30,6,0) -> 2016 | Q31: =VLOOKUP(K31,$A$1:$H$30,7,0) -> 20
B32: =B31*100/D30 -> 12.840169 | E32: =E31/3 -> 54338.9 | K32: Total | L32: =SUM(L25:L31) -> 31311.3 | M32: =SUM(M25:M31) -> 73059.7 | N32: =SUM(N25:N31) -> 104371 | O32: =SUM(O25:O31) -> 29580 | P32: =SUM(P25:P31) -> 74791 | Q32: =SUM(Q25:Q31) -> 8620
A33: Date | B33: Profit | C33: Actual | D33: Total | E33: Cash | F33: Account Transfer | G33: Expense | H33: Mul Bhag | K33: Mul Bhag | L33: =L32/3 -> 10437.1
A34: =CONCATENATE(TEXT(K3,"DD-MMM-YYY")," to ",TEXT(K9,"DD-MMM-YYYY")) -> 05-Jun-2023 to 11-Jun-2023 | B34: =L10 -> 31012.5 | C34: =M10 -> 72362.5 | D34: =N10 -> 103375 | E34: =O10 -> 50270 | F34: =P10 -> 53105 | G34: =Q10 -> 26620 | H34: =B34/3 -> 10337.5
A35: =CONCATENATE(TEXT(K14,"DD-MMM-YYY")," to ",TEXT(K20,"DD-MMM-YYYY")) -> 12-Jun-2023 to 18-Jun-2023 | B35: =L21 -> 35023.2 | C35: =M21 -> 81720.8 | D35: =N21 -> 116744 | E35: =O21 -> 58610 | F35: =P21 -> 58134 | G35: =Q21 -> 29050 | H35: =B35/3 -> 11674.4 | K35: Date | L35: Profit | M35: Actual | N35: Total | O35: Cash | P35: Account Transfer | Q35: Expense
A36: =CONCATENATE(TEXT(K25,"DD-MMM-YYY")," to ",TEXT(K31,"DD-MMM-YYYY")) -> 19-Jun-2023 to 25-Jun-2023 | B36: =L32 -> 31311.3 | C36: =M32 -> 73059.7 | D36: =N32 -> 104371 | E36: =O32 -> 29580 | F36: =P32 -> 74791 | G36: =Q32 -> 8620 | H36: =B36/3 -> 10437.1 | K36: =A23 -> 45103 | L36: =N36*0.3 -> 5043 | M36: =N36-L36 -> 11767 | N36: =O36+P36 -> 16810 | O36: =VLOOKUP(K36,$A$1:$H$30,5,0) -> 3980 | P36: =VLOOKUP(K36,$A$1:$H$30,6,0) -> 12830 | Q36: =VLOOKUP(K36,$A$1:$H$30,7,0) -> 10000
A37: =CONCATENATE(TEXT(K36,"DD-MMM-YYY")," to ",TEXT(K42,"DD-MMM-YYYY")) -> 26-Jun-2023 to 02-Jul-2023 | B37: =L43 -> 21601.5 | C37: =M43 -> 50403.5 | D37: =N43 -> 72005 | E37: =O43 -> 19480 | F37: =P43 -> 52525 | G37: =Q43 -> 82575 | H37: =B37/3 -> 7200.5 | K37: =A24 -> 45104 | L37: =N37*0.3 -> 1506 | M37: =N37-L37 -> 3514 | N37: =O37+P37 -> 5020 | O37: =VLOOKUP(K37,$A$1:$H$30,5,0) -> 0 | P37: =VLOOKUP(K37,$A$1:$H$30,6,0) -> 5020 | Q37: =VLOOKUP(K37,$A$1:$H$30,7,0) -> 3200
A38: =CONCATENATE(TEXT(K59,"DD-MMM-YYY")," to ",TEXT(K58,"DD-MMM-YYYY")) -> 09-Jun-2023 to Date | B38: =SUM(B34:B37) -> 118948.5 | C38: =SUM(C34:C37) -> 277546.5 | D38: =SUM(D34:D37) -> 396495 | E38: =SUM(E34:E37) -> 157940 | F38: =SUM(F34:F37) -> 238555 | G38: =SUM(G34:G37) -> 146865 | H38: =SUM(H34:H37) -> 39649.5 | K38: =A25 -> 45105 | L38: =N38*0.3 -> 2604.9 | M38: =N38-L38 -> 6078.1 | N38: =O38+P38 -> 8683 | O38: =VLOOKUP(K38,$A$1:$H$30,5,0) -> 930 | P38: =VLOOKUP(K38,$A$1:$H$30,6,0) -> 7753 | Q38: =VLOOKUP(K38,$A$1:$H$30,7,0) -> 3200
B39: =B38/3 -> 39649.5 | C39: Total | K39: =A26 -> 45106 | L39: =N39*0.3 -> 3564 | M39: =N39-L39 -> 8316 | N39: =O39+P39 -> 11880 | O39: =VLOOKUP(K39,$A$1:$H$30,5,0) -> 5000 | P39: =VLOOKUP(K39,$A$1:$H$30,6,0) -> 6880 | Q39: =VLOOKUP(K39,$A$1:$H$30,7,0) -> 700
K40: =A27 -> 45107 | L40: =N40*0.3 -> 7452 | M40: =N40-L40 -> 17388 | N40: =O40+P40 -> 24840 | O40: =VLOOKUP(K40,$A$1:$H$30,5,0) -> 7570 | P40: =VLOOKUP(K40,$A$1:$H$30,6,0) -> 17270 | Q40: =VLOOKUP(K40,$A$1:$H$30,7,0) -> 65285
K41: =A28 -> 45108 | L41: =N41*0.3 -> 471.6 | M41: =N41-L41 -> 1100.4 | N41: =O41+P41 -> 1572 | O41: =VLOOKUP(K41,$A$1:$H$30,5,0) -> 600 | P41: =VLOOKUP(K41,$A$1:$H$30,6,0) -> 972 | Q41: =VLOOKUP(K41,$A$1:$H$30,7,0) -> 100
K42: =A29 -> 45109 | L42: =N42*0.3 -> 960 | M42: =N42-L42 -> 2240 | N42: =O42+P42 -> 3200 | O42: =VLOOKUP(K42,$A$1:$H$30,5,0) -> 1400 | P42: =VLOOKUP(K42,$A$1:$H$30,6,0) -> 1800 | Q42: =VLOOKUP(K42,$A$1:$H$30,7,0) -> 90
K43: Total | L43: =SUM(L36:L42) -> 21601.5 | M43: =SUM(M36:M42) -> 50403.5 | N43: =SUM(N36:N42) -> 72005 | O43: =SUM(O36:O42) -> 19480 | P43: =SUM(P36:P42) -> 52525 | Q43: =SUM(Q36:Q42) -> 82575
K44: Mul Bhag | L44: =L43/3 -> 7200.5
K46: Date | L46: Profit | M46: Actual | N46: Total | O46: Cash | P46: Account Transfer | Q46: Expense
K47: =#REF! -> #REF! | L47: =N47*0.3 -> #REF! | M47: =N47-L47 -> #REF! | N47: =O47+P47 -> #REF! | O47: =VLOOKUP(K47,$A$1:$H$30,5,0) -> #REF! | P47: =VLOOKUP(K47,$A$1:$H$30,6,0) -> #REF! | Q47: =VLOOKUP(K47,$A$1:$H$30,7,0) -> #REF!
K48: =#REF! -> #REF! | L48: =N48*0.3 -> #REF! | M48: =N48-L48 -> #REF! | N48: =O48+P48 -> #REF! | O48: =VLOOKUP(K48,$A$1:$H$30,5,0) -> #REF! | P48: =VLOOKUP(K48,$A$1:$H$30,6,0) -> #REF! | Q48: =VLOOKUP(K48,$A$1:$H$30,7,0) -> #REF!
K49: =#REF! -> #REF! | L49: =N49*0.3 -> #REF! | M49: =N49-L49 -> #REF! | N49: =O49+P49 -> #REF! | O49: =VLOOKUP(K49,$A$1:$H$30,5,0) -> #REF! | P49: =VLOOKUP(K49,$A$1:$H$30,6,0) -> #REF! | Q49: =VLOOKUP(K49,$A$1:$H$30,7,0) -> #REF!
K50: =#REF! -> #REF! | L50: =N50*0.3 -> #REF! | M50: =N50-L50 -> #REF! | N50: =O50+P50 -> #REF! | O50: =VLOOKUP(K50,$A$1:$H$30,5,0) -> #REF! | P50: =VLOOKUP(K50,$A$1:$H$30,6,0) -> #REF! | Q50: =VLOOKUP(K50,$A$1:$H$30,7,0) -> #REF!
K51: =#REF! -> #REF! | L51: =N51*0.3 -> #REF! | M51: =N51-L51 -> #REF! | N51: =O51+P51 -> #REF! | O51: =VLOOKUP(K51,$A$1:$H$30,5,0) -> #REF! | P51: =VLOOKUP(K51,$A$1:$H$30,6,0) -> #REF! | Q51: =VLOOKUP(K51,$A$1:$H$30,7,0) -> #REF!
K52: =#REF! -> #REF! | L52: =N52*0.3 -> #REF! | M52: =N52-L52 -> #REF! | N52: =O52+P52 -> #REF! | O52: =VLOOKUP(K52,$A$1:$H$30,5,0) -> #REF! | P52: =VLOOKUP(K52,$A$1:$H$30,6,0) -> #REF! | Q52: =VLOOKUP(K52,$A$1:$H$30,7,0) -> #REF!
K53: =#REF! -> #REF! | L53: =N53*0.3 -> #REF! | M53: =N53-L53 -> #REF! | N53: =O53+P53 -> #REF! | O53: =VLOOKUP(K53,$A$1:$H$30,5,0) -> #REF! | P53: =VLOOKUP(K53,$A$1:$H$30,6,0) -> #REF! | Q53: =VLOOKUP(K53,$A$1:$H$30,7,0) -> #REF!
K54: Total | L54: =SUM(L47:L53) -> #REF! | M54: =SUM(M47:M53) -> #REF! | N54: =SUM(N47:N53) -> #REF!
K55: Mul Bhag | L55: =L54/3 -> #REF!
K58: Date | L58: Profit | M58: Actual | N58: Total | O58: Cash | P58: Account Transfer | Q58: Expense
K59: =A6 -> 45086 | L59: =SUM(B7:B29) -> 130295.1 | M59: =SUM(C7:C29) -> 203794.9 | N59: =SUM(D7:D29) -> 334090 | O59: =SUM(E7:E29) -> 130760 | P59: =SUM(F7:F29) -> 203330 | Q59: =SUM(G7:G29) -> 122445
K60: Mul Bhag | L60: =L59/3 -> 43431.7

Sheet July 2023
A1: Date | B1: Profit | C1: Actual | D1: Total | E1: Cash | F1: Account Transfer | G1: Expense | H1: Percentage | I1: Cash In Hand | K1: Date | L1: Profit | M1: Actual | N1: Total | O1: Cash | P1: Account Transfer | Q1: Expense
A2: 45110 | B2: =D2*0.39 -> 1228.5 | C2: =D2-B2 -> 1921.5 | D2: =E2+F2 -> 3150 | E2: 1350 | F2: 1800 | G2: 80 | H2: =IFERROR(B2/C2,0) -> 0.63934426 | I2: =SUM($D$2:D2)-SUM($G$2:G2) -> 3070 | K2: Export | Q2: 0
A3: 45111 | B3: =D3*0.39 -> 3042 | C3: =D3-B3 -> 4758 | D3: =E3+F3 -> 7800 | E3: 1330 | F3: 6470 | G3: 80 | H3: =IFERROR(B3/C3,0) -> 0.63934426 | I3: =SUM($D$2:D3)-SUM($G$2:G3) -> 10790 | K3: =A2 -> 45110 | L3: =N3*0.3 -> 945 | M3: =N3-L3 -> 2205 | N3: =O3+P3 -> 3150 | O3: =VLOOKUP(K3,$A$1:$H$31,5,0) -> 1350 | P3: =VLOOKUP(K3,$A$1:$H$31,6,0) -> 1800 | Q3: =VLOOKUP(K3,$A$1:$H$31,7,0) -> 80
A4: 45112 | B4: =D4*0.39 -> 4968.6 | C4: =D4-B4 -> 7771.4 | D4: =E4+F4 -> 12740 | E4: 1270 | F4: 11470 | G4: 950 | H4: =IFERROR(B4/C4,0) -> 0.63934426 | I4: =SUM($D$2:D4)-SUM($G$2:G4) -> 22580 | K4: =A3 -> 45111 | L4: =N4*0.3 -> 2340 | M4: =N4-L4 -> 5460 | N4: =O4+P4 -> 7800 | O4: =VLOOKUP(K4,$A$1:$H$31,5,0) -> 1330 | P4: =VLOOKUP(K4,$A$1:$H$31,6,0) -> 6470 | Q4: =VLOOKUP(K4,$A$1:$H$31,7,0) -> 80
A5: 45113 | B5: =D5*0.39 -> 2094.3 | C5: =D5-B5 -> 3275.7 | D5: =E5+F5 -> 5370 | E5: 3290 | F5: 2080 | G5: 90 | H5: =IFERROR(B5/C5,0) -> 0.63934426 | I5: =SUM($D$2:D5)-SUM($G$2:G5) -> 27860 | K5: =A4 -> 45112 | L5: =N5*0.3 -> 3822 | M5: =N5-L5 -> 8918 | N5: =O5+P5 -> 12740 | O5: =VLOOKUP(K5,$A$1:$H$31,5,0) -> 1270 | P5: =VLOOKUP(K5,$A$1:$H$31,6,0) -> 11470 | Q5: =VLOOKUP(K5,$A$1:$H$31,7,0) -> 950
A6: 45114 | B6: =D6*0.39 -> 4933.5 | C6: =D6-B6 -> 7716.5 | D6: =E6+F6 -> 12650 | E6: 1675 | F6: 10975 | G6: 80 | H6: =IFERROR(B6/C6,0) -> 0.63934426 | I6: =SUM($D$2:D6)-SUM($G$2:G6) -> 40430 | K6: =A5 -> 45113 | L6: =N6*0.3 -> 1611 | M6: =N6-L6 -> 3759 | N6: =O6+P6 -> 5370 | O6: =VLOOKUP(K6,$A$1:$H$31,5,0) -> 3290 | P6: =VLOOKUP(K6,$A$1:$H$31,6,0) -> 2080 | Q6: =VLOOKUP(K6,$A$1:$H$31,7,0) -> 90
A7: 45115 | B7: =D7*0.39 -> 3993.6 | C7: =D7-B7 -> 6246.4 | D7: =E7+F7 -> 10240 | E7: 6970 | F7: 3270 | G7: 12000 | H7: =IFERROR(B7/C7,0) -> 0.63934426 | I7: =SUM($D$2:D7)-SUM($G$2:G7) -> 38670 | K7: =A6 -> 45114 | L7: =N7*0.3 -> 3795 | M7: =N7-L7 -> 8855 | N7: =O7+P7 -> 12650 | O7: =VLOOKUP(K7,$A$1:$H$31,5,0) -> 1675 | P7: =VLOOKUP(K7,$A$1:$H$31,6,0) -> 10975 | Q7: =VLOOKUP(K7,$A$1:$H$31,7,0) -> 80
A8: 45116 | B8: =D8*0.39 -> 1189.5 | C8: =D8-B8 -> 1860.5 | D8: =E8+F8 -> 3050 | E8: 2060 | F8: 990 | G8: 580 | H8: =IFERROR(B8/C8,0) -> 0.63934426 | I8: =SUM($D$2:D8)-SUM($G$2:G8) -> 41140 | K8: =A7 -> 45115 | L8: =N8*0.3 -> 3072 | M8: =N8-L8 -> 7168 | N8: =O8+P8 -> 10240 | O8: =VLOOKUP(K8,$A$1:$H$31,5,0) -> 6970 | P8: =VLOOKUP(K8,$A$1:$H$31,6,0) -> 3270 | Q8: =VLOOKUP(K8,$A$1:$H$31,7,0) -> 12000
A9: 45117 | B9: =D9*0.39 -> 7394.4 | C9: =D9-B9 -> 11565.6 | D9: =E9+F9 -> 18960 | E9: 11360 | F9: 7600 | G9: 10080 | H9: =IFERROR(B9/C9,0) -> 0.63934426 | I9: =SUM($D$2:D9)-SUM($G$2:G9) -> 50020 | K9: =A8 -> 45116 | L9: =N9*0.3 -> 915 | M9: =N9-L9 -> 2135 | N9: =O9+P9 -> 3050 | O9: =VLOOKUP(K9,$A$1:$H$31,5,0) -> 2060 | P9: =VLOOKUP(K9,$A$1:$H$31,6,0) -> 990 | Q9: =VLOOKUP(K9,$A$1:$H$31,7,0) -> 580
A10: 45118 | B10: =D10*0.39 -> 10806.9 | C10: =D10-B10 -> 16903.1 | D10: =E10+F10 -> 27710 | E10: 3860 | F10: 23850 | G10: 3080 | H10: =IFERROR(B10/C10,0) -> 0.63934426 | I10: =SUM($D$2:D10)-SUM($G$2:G10) -> 74650 | K10: Total | L10: =SUM(L3:L9) -> 16500 | M10: =SUM(M2:M9) -> 38500 | N10: =SUM(N2:N9) -> 55000 | O10: =SUM(O2:O9) -> 17945 | P10: =SUM(P2:P9) -> 37055 | Q10: =SUM(Q2:Q9) -> 13860
A11: 45119 | B11: =D11*0.39 -> 2418 | C11: =D11-B11 -> 3782 | D11: =E11+F11 -> 6200 | E11: 6200 | G11: 700 | H11: =IFERROR(B11/C11,0) -> 0.63934426 | I11: =SUM($D$2:D11)-SUM($G$2:G11) -> 80150 | K11: Mul Bhag | L11: =L10/3 -> 5500
A12: 45120 | B12: =D12*0.39 -> 3771.3 | C12: =D12-B12 -> 5898.7 | D12: =E12+F12 -> 9670 | E12: 8810 | F12: 860 | G12: 5485 | H12: =IFERROR(B12/C12,0) -> 0.63934426 | I12: =SUM($D$2:D12)-SUM($G$2:G12) -> 84335
A13: 45121 | B13: =D13*0.39 -> 5046.6 | C13: =D13-B13 -> 7893.4 | D13: =E13+F13 -> 12940 | E13: 1900 | F13: 11040 | G13: 550 | H13: =IFERROR(B13/C13,0) -> 0.63934426 | I13: =SUM($D$2:D13)-SUM($G$2:G13) -> 96725 | K13: Date | L13: Profit | M13: Actual | N13: Total | O13: Cash | P13: Account Transfer | Q13: Expense
A14: 45122 | B14: =D14*0.39 -> 7876.05 | C14: =D14-B14 -> 12318.95 | D14: =E14+F14 -> 20195 | E14: 6905 | F14: 13290 | G14: 1100 | H14: =IFERROR(B14/C14,0) -> 0.63934426 | I14: =SUM($D$2:D14)-SUM($G$2:G14) -> 115820 | K14: =A9 -> 45117 | L14: =N14*0.3 -> 5688 | M14: =N14-L14 -> 13272 | N14: =O14+P14 -> 18960 | O14: =VLOOKUP(K14,$A$1:$H$31,5,0) -> 11360 | P14: =VLOOKUP(K14,$A$1:$H$31,6,0) -> 7600 | Q14: =VLOOKUP(K14,$A$1:$H$31,7,0) -> 10080
A15: 45123 | B15: =D15*0.39 -> 3305.25 | C15: =D15-B15 -> 5169.75 | D15: =E15+F15 -> 8475 | E15: 4900 | F15: 3575 | G15: 2800 | H15: =IFERROR(B15/C15,0) -> 0.63934426 | I15: =SUM($D$2:D15)-SUM($G$2:G15) -> 121495 | K15: =A10 -> 45118 | L15: =N15*0.3 -> 8313 | M15: =N15-L15 -> 19397 | N15: =O15+P15 -> 27710 | O15: =VLOOKUP(K15,$A$1:$H$31,5,0) -> 3860 | P15: =VLOOKUP(K15,$A$1:$H$31,6,0) -> 23850 | Q15: =VLOOKUP(K15,$A$1:$H$31,7,0) -> 3080
A16: 45124 | B16: =D16*0.39 -> 9633 | C16: =D16-B16 -> 15067 | D16: =E16+F16 -> 24700 | E16: 6700 | F16: 18000 | G16: 2050 | H16: =IFERROR(B16/C16,0) -> 0.63934426 | I16: =SUM($D$2:D16)-SUM($G$2:G16) -> 144145 | K16: =A11 -> 45119 | L16: =N16*0.3 -> 1860 | M16: =N16-L16 -> 4340 | N16: =O16+P16 -> 6200 | O16: =VLOOKUP(K16,$A$1:$H$31,5,0) -> 6200 | P16: =VLOOKUP(K16,$A$1:$H$31,6,0) -> 0 | Q16: =VLOOKUP(K16,$A$1:$H$31,7,0) -> 700
A17: 45125 | B17: =D17*0.39 -> 1755 | C17: =D17-B17 -> 2745 | D17: =E17+F17 -> 4500 | E17: 3670 | F17: 830 | G17: 910 | H17: =IFERROR(B17/C17,0) -> 0.63934426 | I17: =SUM($D$2:D17)-SUM($G$2:G17) -> 147735 | K17: =A12 -> 45120 | L17: =N17*0.3 -> 2901 | M17: =N17-L17 -> 6769 | N17: =O17+P17 -> 9670 | O17: =VLOOKUP(K17,$A$1:$H$31,5,0) -> 8810 | P17: =VLOOKUP(K17,$A$1:$H$31,6,0) -> 860 | Q17: =VLOOKUP(K17,$A$1:$H$31,7,0) -> 5485
A18: 45126 | B18: =D18*0.39 -> 2835.3 | C18: =D18-B18 -> 4434.7 | D18: =E18+F18 -> 7270 | E18: 2570 | F18: 4700 | G18: 5100 | H18: =IFERROR(B18/C18,0) -> 0.63934426 | I18: =SUM($D$2:D18)-SUM($G$2:G18) -> 149905 | K18: =A13 -> 45121 | L18: =N18*0.3 -> 3882 | M18: =N18-L18 -> 9058 | N18: =O18+P18 -> 12940 | O18: =VLOOKUP(K18,$A$1:$H$31,5,0) -> 1900 | P18: =VLOOKUP(K18,$A$1:$H$31,6,0) -> 11040 | Q18: =VLOOKUP(K18,$A$1:$H$31,7,0) -> 550
A19: 45127 | B19: =D19*0.39 -> 1704.3 | C19: =D19-B19 -> 2665.7 | D19: =E19+F19 -> 4370 | E19: 4370 | F19: 0 | G19: 1600 | H19: =IFERROR(B19/C19,0) -> 0.63934426 | I19: =SUM($D$2:D19)-SUM($G$2:G19) -> 152675 | K19: =A14 -> 45122 | L19: =N19*0.3 -> 6058.5 | M19: =N19-L19 -> 14136.5 | N19: =O19+P19 -> 20195 | O19: =VLOOKUP(K19,$A$1:$H$31,5,0) -> 6905 | P19: =VLOOKUP(K19,$A$1:$H$31,6,0) -> 13290 | Q19: =VLOOKUP(K19,$A$1:$H$31,7,0) -> 1100
A20: 45128 | B20: =D20*0.39 -> 74.1 | C20: =D20-B20 -> 115.9 | D20: =E20+F20 -> 190 | E20: 190 | G20: 100 | H20: =IFERROR(B20/C20,0) -> 0.63934426 | I20: =SUM($D$2:D20)-SUM($G$2:G20) -> 152765 | K20: =A15 -> 45123 | L20: =N20*0.3 -> 2542.5 | M20: =N20-L20 -> 5932.5 | N20: =O20+P20 -> 8475 | O20: =VLOOKUP(K20,$A$1:$H$31,5,0) -> 4900 | P20: =VLOOKUP(K20,$A$1:$H$31,6,0) -> 3575 | Q20: =VLOOKUP(K20,$A$1:$H$31,7,0) -> 2800
A21: 45129 | B21: =D21*0.39 -> 8697 | C21: =D21-B21 -> 13603 | D21: =E21+F21 -> 22300 | E21: =4860+1800 -> 6660 | F21: 15640 | G21: 1350 | H21: =IFERROR(B21/C21,0) -> 0.63934426 | I21: =SUM($D$2:D21)-SUM($G$2:G21) -> 173715 | K21: Total | L21: =SUM(L14:L20) -> 31245 | M21: =SUM(M14:M20) -> 72905 | N21: =SUM(N14:N20) -> 104150 | O21: =SUM(O14:O20) -> 43935 | P21: =SUM(P14:P20) -> 60215 | Q21: =SUM(Q14:Q20) -> 23795
A22: 45130 | B22: =D22*0.39 -> 23088 | C22: =D22-B22 -> 36112 | D22: =E22+F22 -> 59200 | E22: 6680 | F22: 52520 | G22: 53430 | H22: =IFERROR(B22/C22,0) -> 0.63934426 | I22: =SUM($D$2:D22)-SUM($G$2:G22) -> 179485 | K22: Mul Bhag | L22: =L21/3 -> 10415 | M22: 12750 | N22: =M22+L22 -> 23165
A23: 45131 | B23: =D23*0.39 -> 1248 | C23: =D23-B23 -> 1952 | D23: =E23+F23 -> 3200 | E23: 850 | F23: 2350 | G23: 100 | H23: =IFERROR(B23/C23,0) -> 0.63934426 | I23: =SUM($D$2:D23)-SUM($G$2:G23) -> 182585 | M23: ser
A24: 45132 | B24: =D24*0.39 -> 4566.9 | C24: =D24-B24 -> 7143.1 | D24: =E24+F24 -> 11710 | E24: 3170 | F24: 8540 | G24: =10700+150 -> 10850 | H24: =IFERROR(B24/C24,0) -> 0.63934426 | I24: =SUM($D$2:D24)-SUM($G$2:G24) -> 183445 | K24: Date | L24: Profit | M24: Actual | N24: Total | O24: Cash | P24: Account Transfer | Q24: Expense
A25: 45133 | B25: =D25*0.39 -> 5888.22 | C25: =D25-B25 -> 9209.78 | D25: =E25+F25 -> 15098 | E25: 4000 | F25: 11098 | G25: 150 | H25: =IFERROR(B25/C25,0) -> 0.63934426 | I25: =SUM($D$2:D25)-SUM($G$2:G25) -> 198393 | K25: =A16 -> 45124 | L25: =N25*0.3 -> 5400 | M25: =N25-L25 -> 12600 | N25: =O25+P25 -> 18000 | O25: 0 | P25: =VLOOKUP(K25,$A$1:$H$31,6,0) -> 18000 | Q25: =VLOOKUP(K25,$A$1:$H$31,7,0) -> 2050
A26: 45134 | B26: =D26*0.39 -> 854.1 | C26: =D26-B26 -> 1335.9 | D26: =E26+F26 -> 2190 | E26: 1290 | F26: 900 | G26: 2680 | H26: =IFERROR(B26/C26,0) -> 0.63934426 | I26: =SUM($D$2:D26)-SUM($G$2:G26) -> 197903 | K26: =A17 -> 45125 | L26: =N26*0.3 -> 1350 | M26: =N26-L26 -> 3150 | N26: =O26+P26 -> 4500 | O26: =VLOOKUP(K26,$A$1:$H$31,5,0) -> 3670 | P26: =VLOOKUP(K26,$A$1:$H$31,6,0) -> 830 | Q26: =VLOOKUP(K26,$A$1:$H$31,7,0) -> 910
A27: 45135 | B27: =D27*0.39 -> 4149.6 | C27: =D27-B27 -> 6490.4 | D27: =E27+F27 -> 10640 | E27: 10520 | F27: 120 | G27: 100 | H27: =IFERROR(B27/C27,0) -> 0.63934426 | I27: =SUM($D$2:D27)-SUM($G$2:G27) -> 208443 | K27: =A18 -> 45126 | L27: =N27*0.3 -> 2181 | M27: =N27-L27 -> 5089 | N27: =O27+P27 -> 7270 | O27: =VLOOKUP(K27,$A$1:$H$31,5,0) -> 2570 | P27: =VLOOKUP(K27,$A$1:$H$31,6,0) -> 4700 | Q27: =VLOOKUP(K27,$A$1:$H$31,7,0) -> 5100
A28: 45136 | B28: =D28*0.39 -> 1493.7 | C28: =D28-B28 -> 2336.3 | D28: =E28+F28 -> 3830 | E28: 2750 | F28: 1080 | G28: 1300 | H28: =IFERROR(B28/C28,0) -> 0.63934426 | I28: =SUM($D$2:D28)-SUM($G$2:G28) -> 210973 | K28: =A19 -> 45127 | L28: =N28*0.3 -> 1311 | M28: =N28-L28 -> 3059 | N28: =O28+P28 -> 4370 | O28: =VLOOKUP(K28,$A$1:$H$31,5,0) -> 4370 | P28: =VLOOKUP(K28,$A$1:$H$31,6,0) -> 0 | Q28: =VLOOKUP(K28,$A$1:$H$31,7,0) -> 1600
A29: 45137 | B29: =D29*0.39 -> 4683.9 | C29: =D29-B29 -> 7326.1 | D29: =E29+F29 -> 12010 | E29: 5650 | F29: 6360 | G29: 3600 | H29: =IFERROR(B29/C29,0) -> 0.63934426 | I29: =SUM($D$2:D29)-SUM($G$2:G29) -> 219383 | K29: =A20 -> 45128 | L29: =N29*0.3 -> 57 | M29: =N29-L29 -> 133 | N29: =O29+P29 -> 190 | O29: =VLOOKUP(K29,$A$1:$H$31,5,0) -> 190 | P29: =VLOOKUP(K29,$A$1:$H$31,6,0) -> 0 | Q29: =VLOOKUP(K29,$A$1:$H$31,7,0) -> 100
A30: 45138 | B30: =D30*0.39 -> 5066.1 | C30: =D30-B30 -> 7923.9 | D30: =E30+F30 -> 12990 | E30: 4190 | F30: 8800 | G30: 600 | H30: =IFERROR(B30/C30,0) -> 0.63934426 | I30: =SUM($D$2:D30)-SUM($G$2:G30) -> 231773 | K30: =A21 -> 45129 | L30: =N30*0.3 -> 6690 | M30: =N30-L30 -> 15610 | N30: =O30+P30 -> 22300 | O30: =VLOOKUP(K30,$A$1:$H$31,5,0) -> 6660 | P30: =VLOOKUP(K30,$A$1:$H$31,6,0) -> 15640 | Q30: =VLOOKUP(K30,$A$1:$H$31,7,0) -> 1350
A31: Total | B31: =SUM(B3:B30) -> 136577.22 | C31: =SUM(C3:C30) -> 213620.78 | D31: =SUM(D3:D30) -> 350198 | E31: =SUM(E3:E30) -> 123790 | F31: =SUM(F3:F30) -> 226408 | G31: =SUM(G3:G30) -> 121495 | H31: =SUM(G2:G30) -> 121575 | I31: =B31/C31 -> 0.63934426 | K31: =A22 -> 45130 | L31: =N31*0.3 -> 17760 | M31: =N31-L31 -> 41440 | N31: =O31+P31 -> 59200 | O31: =VLOOKUP(K31,$A$1:$H$31,5,0) -> 6680 | P31: =VLOOKUP(K31,$A$1:$H$31,6,0) -> 52520 | Q31: =VLOOKUP(K31,$A$1:$H$31,7,0) -> 53430
B32: =B31/3 -> 45525.74 | E32: =D31*0.42 -> 147083.16 | K32: Total | L32: =SUM(L25:L31) -> 34749 | M32: =SUM(M25:M31) -> 81081 | N32: =SUM(N25:N31) -> 115830 | O32: =SUM(O25:O31) -> 24140 | P32: =SUM(P25:P31) -> 91690 | Q32: =SUM(Q25:Q31) -> 64540
B33: =B32*100/D31 -> 13 | E33: =E32/3 -> 49027.72 | K33: Mul Bhag | L33: =L32/3 -> 11583
A34: Date | B34: Profit | C34: Actual | D34: Total | E34: Cash | F34: Account Transfer | G34: Expense | H34: Mul Bhag
A35: =CONCATENATE(TEXT(K3,"DD-MMM-YYY")," to ",TEXT(K9,"DD-MMM-YYYY")) -> 03-Jul-2023 to 09-Jul-2023 | B35: =L10 -> 16500 | C35: =M10 -> 38500 | D35: =N10 -> 55000 | E35: =O10 -> 17945 | F35: =P10 -> 37055 | G35: =Q10 -> 13860 | H35: =B35/3 -> 5500 | K35: Date | L35: Profit | M35: Actual | N35: Total | O35: Cash | P35: Account Transfer | Q35: Expense
A36: =CONCATENATE(TEXT(K14,"DD-MMM-YYY")," to ",TEXT(K20,"DD-MMM-YYYY")) -> 10-Jul-2023 to 16-Jul-2023 | B36: =L21 -> 31245 | C36: =M21 -> 72905 | D36: =N21 -> 104150 | E36: =O21 -> 43935 | F36: =P21 -> 60215 | G36: =Q21 -> 23795 | H36: =B36/3 -> 10415 | K36: =A23 -> 45131 | L36: =N36*0.3 -> 960 | M36: =N36-L36 -> 2240 | N36: =O36+P36 -> 3200 | O36: =VLOOKUP(K36,$A$1:$H$31,5,0) -> 850 | P36: =VLOOKUP(K36,$A$1:$H$31,6,0) -> 2350 | Q36: =VLOOKUP(K36,$A$1:$H$31,7,0) -> 100
A37: =CONCATENATE(TEXT(K25,"DD-MMM-YYY")," to ",TEXT(K31,"DD-MMM-YYYY")) -> 17-Jul-2023 to 23-Jul-2023 | B37: =L32 -> 34749 | C37: =M32 -> 81081 | D37: =N32 -> 115830 | E37: =O32 -> 24140 | F37: =P32 -> 91690 | G37: =Q32 -> 64540 | H37: =B37/3 -> 11583 | K37: =A24 -> 45132 | L37: =N37*0.3 -> 3513 | M37: =N37-L37 -> 8197 | N37: =O37+P37 -> 11710 | O37: =VLOOKUP(K37,$A$1:$H$31,5,0) -> 3170 | P37: =VLOOKUP(K37,$A$1:$H$31,6,0) -> 8540 | Q37: =VLOOKUP(K37,$A$1:$H$31,7,0) -> 10850
A38: =CONCATENATE(TEXT(K36,"DD-MMM-YYY")," to ",TEXT(K42,"DD-MMM-YYYY")) -> 24-Jul-2023 to 30-Jul-2023 | B38: =L43 -> 17603.4 | C38: =M43 -> 41074.6 | D38: =N43 -> 58678 | E38: =O43 -> 28230 | F38: =P43 -> 30448 | G38: =Q43 -> 18780 | H38: =B38/3 -> 5867.8 | K38: =A25 -> 45133 | L38: =N38*0.3 -> 4529.4 | M38: =N38-L38 -> 10568.6 | N38: =O38+P38 -> 15098 | O38: =VLOOKUP(K38,$A$1:$H$31,5,0) -> 4000 | P38: =VLOOKUP(K38,$A$1:$H$31,6,0) -> 11098 | Q38: =VLOOKUP(K38,$A$1:$H$31,7,0) -> 150
A39: =CONCATENATE(TEXT(K59,"DD-MMM-YYY")," to ",TEXT(K58,"DD-MMM-YYYY")) -> 07-Jul-2023 to Date | B39: =SUM(B35:B38) -> 100097.4 | C39: =SUM(C35:C38) -> 233560.6 | D39: =SUM(D35:D38) -> 333658 | E39: =SUM(E35:E38) -> 114250 | F39: =SUM(F35:F38) -> 219408 | G39: =SUM(G35:G38) -> 120975 | H39: =SUM(H35:H38) -> 33365.8 | K39: =A26 -> 45134 | L39: =N39*0.3 -> 657 | M39: =N39-L39 -> 1533 | N39: =O39+P39 -> 2190 | O39: =VLOOKUP(K39,$A$1:$H$31,5,0) -> 1290 | P39: =VLOOKUP(K39,$A$1:$H$31,6,0) -> 900 | Q39: =VLOOKUP(K39,$A$1:$H$31,7,0) -> 2680
C40: Total | K40: =A27 -> 45135 | L40: =N40*0.3 -> 3192 | M40: =N40-L40 -> 7448 | N40: =O40+P40 -> 10640 | O40: =VLOOKUP(K40,$A$1:$H$31,5,0) -> 10520 | P40: =VLOOKUP(K40,$A$1:$H$31,6,0) -> 120 | Q40: =VLOOKUP(K40,$A$1:$H$31,7,0) -> 100
B41: =SUM('June 2023'!B28:B29) -> 1861.08 | C41: =SUM('June 2023'!C28:C29) -> 2910.92 | D41: =SUM('June 2023'!D28:D29) -> 4772 | E41: =SUM('June 2023'!E28:E29) -> 2000 | F41: =SUM('June 2023'!F28:F29) -> 2772 | G41: =SUM('June 2023'!G28:G29) -> 190 | H41: =SUM('June 2023'!H28:H29) -> 1.2786885 | I41: =SUM('June 2023'!I28:I29) -> 511130 | K41: =A28 -> 45136 | L41: =N41*0.3 -> 1149 | M41: =N41-L41 -> 2681 | N41: =O41+P41 -> 3830 | O41: =VLOOKUP(K41,$A$1:$H$31,5,0) -> 2750 | P41: =VLOOKUP(K41,$A$1:$H$31,6,0) -> 1080 | Q41: =VLOOKUP(K41,$A$1:$H$31,7,0) -> 1300
K42: =A29 -> 45137 | L42: =N42*0.3 -> 3603 | M42: =N42-L42 -> 8407 | N42: =O42+P42 -> 12010 | O42: =VLOOKUP(K42,$A$1:$H$31,5,0) -> 5650 | P42: =VLOOKUP(K42,$A$1:$H$31,6,0) -> 6360 | Q42: =VLOOKUP(K42,$A$1:$H$31,7,0) -> 3600
K43: Total | L43: =SUM(L36:L42) -> 17603.4 | M43: =SUM(M36:M42) -> 41074.6 | N43: =SUM(N36:N42) -> 58678 | O43: =SUM(O36:O42) -> 28230 | P43: =SUM(P36:P42) -> 30448 | Q43: =SUM(Q36:Q42) -> 18780
K44: Mul Bhag | L44: =L43/3 -> 5867.8
K46: Date | L46: Profit | M46: Actual | N46: Total | O46: Cash | P46: Account Transfer | Q46: Expense
K47: =A30 -> 45138 | L47: =N47*0.3 -> 3897 | M47: =N47-L47 -> 9093 | N47: =O47+P47 -> 12990 | O47: =VLOOKUP(K47,$A$1:$H$31,5,0) -> 4190 | P47: =VLOOKUP(K47,$A$1:$H$31,6,0) -> 8800 | Q47: =VLOOKUP(K47,$A$1:$H$31,7,0) -> 600
K48: =#REF! -> #REF! | L48: =N48*0.3 -> #REF! | M48: =N48-L48 -> #REF! | N48: =O48+P48 -> #REF! | O48: =VLOOKUP(K48,$A$1:$H$31,5,0) -> #REF! | P48: =VLOOKUP(K48,$A$1:$H$31,6,0) -> #REF! | Q48: =VLOOKUP(K48,$A$1:$H$31,7,0) -> #REF!
K49: =#REF! -> #REF! | L49: =N49*0.3 -> #REF! | M49: =N49-L49 -> #REF! | N49: =O49+P49 -> #REF! | O49: =VLOOKUP(K49,$A$1:$H$31,5,0) -> #REF! | P49: =VLOOKUP(K49,$A$1:$H$31,6,0) -> #REF! | Q49: =VLOOKUP(K49,$A$1:$H$31,7,0) -> #REF!
K50: =#REF! -> #REF! | L50: =N50*0.3 -> #REF! | M50: =N50-L50 -> #REF! | N50: =O50+P50 -> #REF! | O50: =VLOOKUP(K50,$A$1:$H$31,5,0) -> #REF! | P50: =VLOOKUP(K50,$A$1:$H$31,6,0) -> #REF! | Q50: =VLOOKUP(K50,$A$1:$H$31,7,0) -> #REF!
K51: =#REF! -> #REF! | L51: =N51*0.3 -> #REF! | M51: =N51-L51 -> #REF! | N51: =O51+P51 -> #REF! | O51: =VLOOKUP(K51,$A$1:$H$31,5,0) -> #REF! | P51: =VLOOKUP(K51,$A$1:$H$31,6,0) -> #REF! | Q51: =VLOOKUP(K51,$A$1:$H$31,7,0) -> #REF!
K52: =#REF! -> #REF! | L52: =N52*0.3 -> #REF! | M52: =N52-L52 -> #REF! | N52: =O52+P52 -> #REF! | O52: =VLOOKUP(K52,$A$1:$H$31,5,0) -> #REF! | P52: =VLOOKUP(K52,$A$1:$H$31,6,0) -> #REF! | Q52: =VLOOKUP(K52,$A$1:$H$31,7,0) -> #REF!
K53: =#REF! -> #REF! | L53: =N53*0.3 -> #REF! | M53: =N53-L53 -> #REF! | N53: =O53+P53 -> #REF! | O53: =VLOOKUP(K53,$A$1:$H$31,5,0) -> #REF! | P53: =VLOOKUP(K53,$A$1:$H$31,6,0) -> #REF! | Q53: =VLOOKUP(K53,$A$1:$H$31,7,0) -> #REF!
K54: Total | L54: =SUM(L47:L53) -> #REF! | M54: =SUM(M47:M53) -> #REF! | N54: =SUM(N47:N53) -> #REF!
K55: Mul Bhag | L55: =L54/3 -> #REF!
K58: Date | L58: Profit | M58: Actual | N58: Total | O58: Cash | P58: Account Transfer | Q58: Expense
K59: =A6 -> 45114 | L59: =SUM(B7:B30) -> 121538.82 | M59: =SUM(C7:C30) -> 190099.18 | N59: =SUM(D7:D30) -> 311638 | O59: =SUM(E7:E30) -> 116225 | P59: =SUM(F7:F30) -> 195413 | Q59: =SUM(G7:G30) -> 120295
K60: Mul Bhag | L60: =L59/3 -> 40512.94

Sheet August 2023
A1: Date | B1: Profit | C1: Actual | D1: Total | E1: Cash | F1: Account Transfer | G1: Expense | H1: Percentage | I1: Cash In Hand | K1: Date | L1: Profit | M1: Actual | N1: Total | O1: Cash | P1: Account Transfer | Q1: Expense
A2: 45138 | B2: =D2*0.3 -> 3897 | C2: =D2-B2 -> 9093 | D2: =E2+F2 -> 12990 | E2: 4190 | F2: 8800 | G2: 600 | H2: =IFERROR(B2/C2,0) -> 0.42857143 | I2: =SUM($D$2:D2)-SUM($G$2:G2) -> 12390 | K2: Export | Q2: 0
A3: 45139 | B3: =D3*0.3 -> 3516 | C3: =D3-B3 -> 8204 | D3: =E3+F3 -> 11720 | E3: 1000 | F3: 10720 | G3: 1000 | H3: =IFERROR(B3/C3,0) -> 0.42857143 | I3: =SUM($D$2:D3)-SUM($G$2:G3) -> 23110 | K3: =A2 -> 45138 | L3: =N3*0.3 -> 3897 | M3: =N3-L3 -> 9093 | N3: =O3+P3 -> 12990 | O3: =VLOOKUP(K3,$A$1:$H$37,5,0) -> 4190 | P3: =VLOOKUP(K3,$A$1:$H$37,6,0) -> 8800 | Q3: =VLOOKUP(K3,$A$1:$H$37,7,0) -> 600
A4: 45140 | B4: =D4*0.3 -> 3552 | C4: =D4-B4 -> 8288 | D4: =E4+F4 -> 11840 | E4: 1030 | F4: 10810 | G4: 1000 | H4: =IFERROR(B4/C4,0) -> 0.42857143 | I4: =SUM($D$2:D4)-SUM($G$2:G4) -> 33950 | K4: =A3 -> 45139 | L4: =N4*0.3 -> 3516 | M4: =N4-L4 -> 8204 | N4: =O4+P4 -> 11720 | O4: =VLOOKUP(K4,$A$1:$H$37,5,0) -> 1000 | P4: =VLOOKUP(K4,$A$1:$H$37,6,0) -> 10720 | Q4: =VLOOKUP(K4,$A$1:$H$37,7,0) -> 1000
A5: 45141 | B5: =D5*0.3 -> 2505 | C5: =D5-B5 -> 5845 | D5: =E5+F5 -> 8350 | E5: 1580 | F5: 6770 | G5: 100 | H5: =IFERROR(B5/C5,0) -> 0.42857143 | I5: =SUM($D$2:D5)-SUM($G$2:G5) -> 42200 | K5: =A4 -> 45140 | L5: =N5*0.3 -> 3552 | M5: =N5-L5 -> 8288 | N5: =O5+P5 -> 11840 | O5: =VLOOKUP(K5,$A$1:$H$37,5,0) -> 1030 | P5: =VLOOKUP(K5,$A$1:$H$37,6,0) -> 10810 | Q5: =VLOOKUP(K5,$A$1:$H$37,7,0) -> 1000
A6: 45142 | B6: =D6*0.3 -> 5710.5 | C6: =D6-B6 -> 13324.5 | D6: =E6+F6 -> 19035 | E6: 9030 | F6: 10005 | G6: 500 | H6: =IFERROR(B6/C6,0) -> 0.42857143 | I6: =SUM($D$2:D6)-SUM($G$2:G6) -> 60735 | K6: =A5 -> 45141 | L6: =N6*0.3 -> 2505 | M6: =N6-L6 -> 5845 | N6: =O6+P6 -> 8350 | O6: =VLOOKUP(K6,$A$1:$H$37,5,0) -> 1580 | P6: =VLOOKUP(K6,$A$1:$H$37,6,0) -> 6770 | Q6: =VLOOKUP(K6,$A$1:$H$37,7,0) -> 100
A7: 45143 | B7: =D7*0.3 -> 3675 | C7: =D7-B7 -> 8575 | D7: =E7+F7 -> 12250 | E7: 8150 | F7: 4100 | G7: 13120 | H7: =IFERROR(B7/C7,0) -> 0.42857143 | I7: =SUM($D$2:D7)-SUM($G$2:G7) -> 59865 | K7: =A6 -> 45142 | L7: =N7*0.3 -> 5710.5 | M7: =N7-L7 -> 13324.5 | N7: =O7+P7 -> 19035 | O7: =VLOOKUP(K7,$A$1:$H$37,5,0) -> 9030 | P7: =VLOOKUP(K7,$A$1:$H$37,6,0) -> 10005 | Q7: =VLOOKUP(K7,$A$1:$H$37,7,0) -> 500
A8: 45144 | B8: =D8*0.3 -> 6786.3 | C8: =D8-B8 -> 15834.7 | D8: =E8+F8 -> 22621 | E8: 13166 | F8: 9455 | G8: 4010 | H8: =IFERROR(B8/C8,0) -> 0.42857143 | I8: =SUM($D$2:D8)-SUM($G$2:G8) -> 78476 | K8: =A7 -> 45143 | L8: =N8*0.3 -> 3675 | M8: =N8-L8 -> 8575 | N8: =O8+P8 -> 12250 | O8: =VLOOKUP(K8,$A$1:$H$37,5,0) -> 8150 | P8: =VLOOKUP(K8,$A$1:$H$37,6,0) -> 4100 | Q8: =VLOOKUP(K8,$A$1:$H$37,7,0) -> 13120
A9: 45145 | B9: =D9*0.3 -> 2862 | C9: =D9-B9 -> 6678 | D9: =E9+F9 -> 9540 | E9: 6900 | F9: 2640 | G9: 2600 | H9: =IFERROR(B9/C9,0) -> 0.42857143 | I9: =SUM($D$2:D9)-SUM($G$2:G9) -> 85416 | K9: =A8 -> 45144 | L9: =N9*0.3 -> 6786.3 | M9: =N9-L9 -> 15834.7 | N9: =O9+P9 -> 22621 | O9: =VLOOKUP(K9,$A$1:$H$37,5,0) -> 13166 | P9: =VLOOKUP(K9,$A$1:$H$37,6,0) -> 9455 | Q9: =VLOOKUP(K9,$A$1:$H$37,7,0) -> 4010
A10: 45146 | B10: =D10*0.3 -> 6522 | C10: =D10-B10 -> 15218 | D10: =E10+F10 -> 21740 | E10: =8630+570 -> 9200 | F10: 12540 | G10: 2900 | H10: =IFERROR(B10/C10,0) -> 0.42857143 | I10: =SUM($D$2:D10)-SUM($G$2:G10) -> 104256 | K10: Total | L10: =SUM(L3:L9) -> 29641.8 | M10: =SUM(M2:M9) -> 69164.2 | N10: =SUM(N2:N9) -> 98806 | O10: =SUM(O2:O9) -> 38146 | P10: =SUM(P2:P9) -> 60660 | Q10: =SUM(Q2:Q9) -> 20330
A11: 45147 | B11: =D11*0.3 -> 4290 | C11: =D11-B11 -> 10010 | D11: =E11+F11 -> 14300 | E11: 8200 | F11: 6100 | G11: 600 | H11: =IFERROR(B11/C11,0) -> 0.42857143 | I11: =SUM($D$2:D11)-SUM($G$2:G11) -> 117956 | K11: Mul Bhag | L11: =L10/3 -> 9880.6
A12: 45148 | B12: =D12*0.3 -> 2394 | C12: =D12-B12 -> 5586 | D12: =E12+F12 -> 7980 | E12: 3380 | F12: 4600 | G12: 1560 | H12: =IFERROR(B12/C12,0) -> 0.42857143 | I12: =SUM($D$2:D12)-SUM($G$2:G12) -> 124376
A13: 45149 | B13: =D13*0.3 -> 1278 | C13: =D13-B13 -> 2982 | D13: =E13+F13 -> 4260 | E13: 3810 | F13: 450 | G13: 3000 | H13: =IFERROR(B13/C13,0) -> 0.42857143 | I13: =SUM($D$2:D13)-SUM($G$2:G13) -> 125636 | K13: Date | L13: Profit | M13: Actual | N13: Total | O13: Cash | P13: Account Transfer | Q13: Expense
A14: 45150 | B14: =D14*0.3 -> 5238 | C14: =D14-B14 -> 12222 | D14: =E14+F14 -> 17460 | E14: 7510 | F14: 9950 | G14: 2600 | H14: =IFERROR(B14/C14,0) -> 0.42857143 | I14: =SUM($D$2:D14)-SUM($G$2:G14) -> 140496 | K14: =A9 -> 45145 | L14: =N14*0.3 -> 2862 | M14: =N14-L14 -> 6678 | N14: =O14+P14 -> 9540 | O14: =VLOOKUP(K14,$A$1:$H$37,5,0) -> 6900 | P14: =VLOOKUP(K14,$A$1:$H$37,6,0) -> 2640 | Q14: =VLOOKUP(K14,$A$1:$H$37,7,0) -> 2600
A15: 45151 | B15: =D15*0.3 -> 5994 | C15: =D15-B15 -> 13986 | D15: =E15+F15 -> 19980 | E15: 11710 | F15: 8270 | G15: 20050 | H15: =IFERROR(B15/C15,0) -> 0.42857143 | I15: =SUM($D$2:D15)-SUM($G$2:G15) -> 140426 | K15: =A10 -> 45146 | L15: =N15*0.3 -> 6522 | M15: =N15-L15 -> 15218 | N15: =O15+P15 -> 21740 | O15: =VLOOKUP(K15,$A$1:$H$37,5,0) -> 9200 | P15: =VLOOKUP(K15,$A$1:$H$37,6,0) -> 12540 | Q15: =VLOOKUP(K15,$A$1:$H$37,7,0) -> 2900
A16: 45152 | B16: =D16*0.3 -> 8703 | C16: =D16-B16 -> 20307 | D16: =E16+F16 -> 29010 | E16: 6190 | F16: 22820 | G16: 1550 | H16: =IFERROR(B16/C16,0) -> 0.42857143 | I16: =SUM($D$2:D16)-SUM($G$2:G16) -> 167886 | K16: =A11 -> 45147 | L16: =N16*0.3 -> 4290 | M16: =N16-L16 -> 10010 | N16: =O16+P16 -> 14300 | O16: =VLOOKUP(K16,$A$1:$H$37,5,0) -> 8200 | P16: =VLOOKUP(K16,$A$1:$H$37,6,0) -> 6100 | Q16: =VLOOKUP(K16,$A$1:$H$37,7,0) -> 600
A17: 45153 | B17: =D17*0.3 -> 13143 | C17: =D17-B17 -> 30667 | D17: =E17+F17 -> 43810 | E17: =7120+17500 -> 24620 | F17: 19190 | G17: 1250 | H17: =IFERROR(B17/C17,0) -> 0.42857143 | I17: =SUM($D$2:D17)-SUM($G$2:G17) -> 210446 | K17: =A12 -> 45148 | L17: =N17*0.3 -> 2394 | M17: =N17-L17 -> 5586 | N17: =O17+P17 -> 7980 | O17: =VLOOKUP(K17,$A$1:$H$37,5,0) -> 3380 | P17: =VLOOKUP(K17,$A$1:$H$37,6,0) -> 4600 | Q17: =VLOOKUP(K17,$A$1:$H$37,7,0) -> 1560
A18: 45154 | B18: =D18*0.3 -> 18246 | C18: =D18-B18 -> 42574 | D18: =E18+F18 -> 60820 | E18: 20270 | F18: 40550 | G18: 4750 | H18: =IFERROR(B18/C18,0) -> 0.42857143 | I18: =SUM($D$2:D18)-SUM($G$2:G18) -> 266516 | K18: =A13 -> 45149 | L18: =N18*0.3 -> 1278 | M18: =N18-L18 -> 2982 | N18: =O18+P18 -> 4260 | O18: =VLOOKUP(K18,$A$1:$H$37,5,0) -> 3810 | P18: =VLOOKUP(K18,$A$1:$H$37,6,0) -> 450 | Q18: =VLOOKUP(K18,$A$1:$H$37,7,0) -> 3000
A19: 45155 | B19: =D19*0.3 -> 7326 | C19: =D19-B19 -> 17094 | D19: =E19+F19 -> 24420 | E19: =10530+820 -> 11350 | F19: 13070 | G19: 16600 | H19: =IFERROR(B19/C19,0) -> 0.42857143 | I19: =SUM($D$2:D19)-SUM($G$2:G19) -> 274336 | K19: =A14 -> 45150 | L19: =N19*0.3 -> 5238 | M19: =N19-L19 -> 12222 | N19: =O19+P19 -> 17460 | O19: =VLOOKUP(K19,$A$1:$H$37,5,0) -> 7510 | P19: =VLOOKUP(K19,$A$1:$H$37,6,0) -> 9950 | Q19: =VLOOKUP(K19,$A$1:$H$37,7,0) -> 2600
A20: 45156 | B20: =D20*0.3 -> 8320.5 | C20: =D20-B20 -> 19414.5 | D20: =E20+F20 -> 27735 | E20: 6015 | F20: 21720 | G20: 650 | H20: =IFERROR(B20/C20,0) -> 0.42857143 | I20: =SUM($D$2:D20)-SUM($G$2:G20) -> 301421 | K20: =A15 -> 45151 | L20: =N20*0.3 -> 5994 | M20: =N20-L20 -> 13986 | N20: =O20+P20 -> 19980 | O20: =VLOOKUP(K20,$A$1:$H$37,5,0) -> 11710 | P20: =VLOOKUP(K20,$A$1:$H$37,6,0) -> 8270 | Q20: =VLOOKUP(K20,$A$1:$H$37,7,0) -> 20050
A21: 45157 | B21: =D21*0.3 -> 7269 | C21: =D21-B21 -> 16961 | D21: =E21+F21 -> 24230 | E21: 1180 | F21: 23050 | G21: 640 | H21: =IFERROR(B21/C21,0) -> 0.42857143 | I21: =SUM($D$2:D21)-SUM($G$2:G21) -> 325011 | K21: Total | L21: =SUM(L14:L20) -> 28578 | M21: =SUM(M14:M20) -> 66682 | N21: =SUM(N14:N20) -> 95260 | O21: =SUM(O14:O20) -> 50710 | P21: =SUM(P14:P20) -> 44550 | Q21: =SUM(Q14:Q20) -> 33310
A22: 45158 | B22: =D22*0.3 -> 5436 | C22: =D22-B22 -> 12684 | D22: =E22+F22 -> 18120 | E22: 4200 | F22: 13920 | G22: 5485 | H22: =IFERROR(B22/C22,0) -> 0.42857143 | I22: =SUM($D$2:D22)-SUM($G$2:G22) -> 337646 | K22: Mul Bhag | L22: =L21/3 -> 9526 | M22: 12750 | N22: =M22+L22 -> 22276
A23: 45159 | B23: =D23*0.3 -> 6180 | C23: =D23-B23 -> 14420 | D23: =E23+F23 -> 20600 | E23: 3930 | F23: 16670 | G23: 1770 | H23: =IFERROR(B23/C23,0) -> 0.42857143 | I23: =SUM($D$2:D23)-SUM($G$2:G23) -> 356476 | M23: ser
A24: 45160 | B24: =D24*0.3 -> 7008 | C24: =D24-B24 -> 16352 | D24: =E24+F24 -> 23360 | E24: =5190+1470 -> 6660 | F24: 16700 | G24: 1460 | H24: =IFERROR(B24/C24,0) -> 0.42857143 | I24: =SUM($D$2:D24)-SUM($G$2:G24) -> 378376 | K24: Date | L24: Profit | M24: Actual | N24: Total | O24: Cash | P24: Account Transfer | Q24: Expense
A25: 45161 | B25: =D25*0.3 -> 4476.3 | C25: =D25-B25 -> 10444.7 | D25: =E25+F25 -> 14921 | E25: 4700 | F25: 10221 | G25: 3700 | H25: =IFERROR(B25/C25,0) -> 0.42857143 | I25: =SUM($D$2:D25)-SUM($G$2:G25) -> 389597 | K25: =A16 -> 45152 | L25: =N25*0.3 -> 6846 | M25: =N25-L25 -> 15974 | N25: =O25+P25 -> 22820 | O25: 0 | P25: =VLOOKUP(K25,$A$1:$H$37,6,0) -> 22820 | Q25: =VLOOKUP(K25,$A$1:$H$37,7,0) -> 1550
A26: 45162 | B26: =D26*0.3 -> 11223 | C26: =D26-B26 -> 26187 | D26: =E26+F26 -> 37410 | E26: 1700 | F26: 35710 | G26: =2240+230 -> 2470 | H26: =IFERROR(B26/C26,0) -> 0.42857143 | I26: =SUM($D$2:D26)-SUM($G$2:G26) -> 424537 | K26: =A17 -> 45153 | L26: =N26*0.3 -> 13143 | M26: =N26-L26 -> 30667 | N26: =O26+P26 -> 43810 | O26: =VLOOKUP(K26,$A$1:$H$37,5,0) -> 24620 | P26: =VLOOKUP(K26,$A$1:$H$37,6,0) -> 19190 | Q26: =VLOOKUP(K26,$A$1:$H$37,7,0) -> 1250
A27: 45163 | B27: =D27*0.3 -> 2997 | C27: =D27-B27 -> 6993 | D27: =E27+F27 -> 9990 | E27: 6300 | F27: 3690 | G27: 2650 | H27: =IFERROR(B27/C27,0) -> 0.42857143 | I27: =SUM($D$2:D27)-SUM($G$2:G27) -> 431877 | K27: =A18 -> 45154 | L27: =N27*0.3 -> 18246 | M27: =N27-L27 -> 42574 | N27: =O27+P27 -> 60820 | O27: =VLOOKUP(K27,$A$1:$H$37,5,0) -> 20270 | P27: =VLOOKUP(K27,$A$1:$H$37,6,0) -> 40550 | Q27: =VLOOKUP(K27,$A$1:$H$37,7,0) -> 4750
A28: 45164 | B28: =D28*0.3 -> 3235.5 | C28: =D28-B28 -> 7549.5 | D28: =E28+F28 -> 10785 | E28: =4900+350 -> 5250 | F28: 5535 | G28: 650 | H28: =IFERROR(B28/C28,0) -> 0.42857143 | I28: =SUM($D$2:D28)-SUM($G$2:G28) -> 442012 | K28: =A19 -> 45155 | L28: =N28*0.3 -> 7326 | M28: =N28-L28 -> 17094 | N28: =O28+P28 -> 24420 | O28: =VLOOKUP(K28,$A$1:$H$37,5,0) -> 11350 | P28: =VLOOKUP(K28,$A$1:$H$37,6,0) -> 13070 | Q28: =VLOOKUP(K28,$A$1:$H$37,7,0) -> 16600
A29: 45165 | B29: =D29*0.3 -> 3834 | C29: =D29-B29 -> 8946 | D29: =E29+F29 -> 12780 | E29: 10770 | F29: 2010 | G29: 750 | H29: =IFERROR(B29/C29,0) -> 0.42857143 | I29: =SUM($D$2:D29)-SUM($G$2:G29) -> 454042 | K29: =A20 -> 45156 | L29: =N29*0.3 -> 8320.5 | M29: =N29-L29 -> 19414.5 | N29: =O29+P29 -> 27735 | O29: =VLOOKUP(K29,$A$1:$H$37,5,0) -> 6015 | P29: =VLOOKUP(K29,$A$1:$H$37,6,0) -> 21720 | Q29: =VLOOKUP(K29,$A$1:$H$37,7,0) -> 650
A30: 45166 | B30: =D30*0.3 -> 2926.5 | C30: =D30-B30 -> 6828.5 | D30: =E30+F30 -> 9755 | E30: 3450 | F30: 6305 | G30: 4070 | H30: =IFERROR(B30/C30,0) -> 0.42857143 | I30: =SUM($D$2:D30)-SUM($G$2:G30) -> 459727 | K30: =A21 -> 45157 | L30: =N30*0.3 -> 7269 | M30: =N30-L30 -> 16961 | N30: =O30+P30 -> 24230 | O30: =VLOOKUP(K30,$A$1:$H$37,5,0) -> 1180 | P30: =VLOOKUP(K30,$A$1:$H$37,6,0) -> 23050 | Q30: =VLOOKUP(K30,$A$1:$H$37,7,0) -> 640
A31: 45167 | B31: =D31*0.3 -> 5478 | C31: =D31-B31 -> 12782 | D31: =E31+F31 -> 18260 | E31: 2490 | F31: 15770 | G31: 5090 | H31: =IFERROR(B31/C31,0) -> 0.42857143 | I31: =SUM($D$2:D31)-SUM($G$2:G31) -> 472897 | K31: =A22 -> 45158 | L31: =N31*0.3 -> 5436 | M31: =N31-L31 -> 12684 | N31: =O31+P31 -> 18120 | O31: =VLOOKUP(K31,$A$1:$H$37,5,0) -> 4200 | P31: =VLOOKUP(K31,$A$1:$H$37,6,0) -> 13920 | Q31: =VLOOKUP(K31,$A$1:$H$37,7,0) -> 5485
A32: 45168 | B32: =D32*0.3 -> 3474 | C32: =D32-B32 -> 8106 | D32: =E32+F32 -> 11580 | E32: 5000 | F32: 6580 | G32: 5550 | H32: =IFERROR(B32/C32,0) -> 0.42857143 | I32: =SUM($D$2:D32)-SUM($G$2:G32) -> 478927 | K32: Total | L32: =SUM(L25:L31) -> 66586.5 | M32: =SUM(M25:M31) -> 155368.5 | N32: =SUM(N25:N31) -> 221955 | O32: =SUM(O25:O31) -> 67635 | P32: =SUM(P25:P31) -> 154320 | Q32: =SUM(Q25:Q31) -> 30925
A33: 45169 | B33: =D33*0.3 -> 12163.5 | C33: =D33-B33 -> 28381.5 | D33: =E33+F33 -> 40545 | E33: 12100 | F33: 28445 | G33: 100 | H33: =IFERROR(B33/C33,0) -> 0.42857143 | I33: =SUM($D$2:D33)-SUM($G$2:G33) -> 519372 | K33: Mul Bhag | L33: =L32/3 -> 22195.5
A34: 45170 | B34: =D34*0.3 -> 3318 | C34: =D34-B34 -> 7742 | D34: =E34+F34 -> 11060 | E34: 4820 | F34: 6240 | G34: 750 | H34: =IFERROR(B34/C34,0) -> 0.42857143 | I34: =SUM($D$2:D34)-SUM($G$2:G34) -> 529682
A35: 45171 | B35: =D35*0.3 -> 7600.5 | C35: =D35-B35 -> 17734.5 | D35: =E35+F35 -> 25335 | E35: 13280 | F35: 12055 | G35: 8150 | H35: =IFERROR(B35/C35,0) -> 0.42857143 | I35: =SUM($D$2:D35)-SUM($G$2:G35) -> 546867 | K35: Date | L35: Profit | M35: Actual | N35: Total | O35: Cash | P35: Account Transfer | Q35: Expense
A36: 45172 | B36: =D36*0.3 -> 4686 | C36: =D36-B36 -> 10934 | D36: =E36+F36 -> 15620 | E36: 11020 | F36: 4600 | G36: 7950 | H36: =IFERROR(B36/C36,0) -> 0.42857143 | I36: =SUM($D$2:D36)-SUM($G$2:G36) -> 554537 | K36: =A23 -> 45159 | L36: =N36*0.3 -> 6180 | M36: =N36-L36 -> 14420 | N36: =O36+P36 -> 20600 | O36: =VLOOKUP(K36,$A$1:$H$37,5,0) -> 3930 | P36: =VLOOKUP(K36,$A$1:$H$37,6,0) -> 16670 | Q36: =VLOOKUP(K36,$A$1:$H$37,7,0) -> 1770
A37: Total | B37: =SUM(B3:B33) -> 185762.1 | C37: =SUM(C3:C33) -> 433444.9 | D37: =SUM(D3:D33) -> 619207 | E37: =SUM(E3:E33) -> 220841 | F37: =SUM(F3:F33) -> 398366 | G37: =SUM(G3:G33) -> 112225 | H37: =SUM(H3:H33) -> 13.285714 | I37: =SUM(I3:I33) -> 7828000 | K37: =A24 -> 45160 | L37: =N37*0.3 -> 7008 | M37: =N37-L37 -> 16352 | N37: =O37+P37 -> 23360 | O37: =VLOOKUP(K37,$A$1:$H$37,5,0) -> 6660 | P37: =VLOOKUP(K37,$A$1:$H$37,6,0) -> 16700 | Q37: =VLOOKUP(K37,$A$1:$H$37,7,0) -> 1460
B38: =B37/3 -> 61920.7 | E38: =D37*0.42 -> 260066.94 | K38: =A25 -> 45161 | L38: =N38*0.3 -> 4476.3 | M38: =N38-L38 -> 10444.7 | N38: =O38+P38 -> 14921 | O38: =VLOOKUP(K38,$A$1:$H$37,5,0) -> 4700 | P38: =VLOOKUP(K38,$A$1:$H$37,6,0) -> 10221 | Q38: =VLOOKUP(K38,$A$1:$H$37,7,0) -> 3700
B39: =B38*100/D37 -> 10 | E39: =E38/3 -> 86688.98 | K39: =A26 -> 45162 | L39: =N39*0.3 -> 11223 | M39: =N39-L39 -> 26187 | N39: =O39+P39 -> 37410 | O39: =VLOOKUP(K39,$A$1:$H$37,5,0) -> 1700 | P39: =VLOOKUP(K39,$A$1:$H$37,6,0) -> 35710 | Q39: =VLOOKUP(K39,$A$1:$H$37,7,0) -> 2470
A40: Date | B40: Profit | C40: Actual | D40: Total | E40: Cash | F40: Account Transfer | G40: Expense | H40: Mul Bhag | K40: =A27 -> 45163 | L40: =N40*0.3 -> 2997 | M40: =N40-L40 -> 6993 | N40: =O40+P40 -> 9990 | O40: =VLOOKUP(K40,$A$1:$H$37,5,0) -> 6300 | P40: =VLOOKUP(K40,$A$1:$H$37,6,0) -> 3690 | Q40: =VLOOKUP(K40,$A$1:$H$37,7,0) -> 2650
A41: =CONCATENATE(TEXT(K3,"DD-MMM-YYY")," to ",TEXT(K9,"DD-MMM-YYYY")) -> 31-Jul-2023 to 06-Aug-2023 | B41: =L10 -> 29641.8 | C41: =M10 -> 69164.2 | D41: =N10 -> 98806 | E41: =O10 -> 38146 | F41: =P10 -> 60660 | G41: =Q10 -> 20330 | H41: =B41/3 -> 9880.6 | K41: =A28 -> 45164 | L41: =N41*0.3 -> 3235.5 | M41: =N41-L41 -> 7549.5 | N41: =O41+P41 -> 10785 | O41: =VLOOKUP(K41,$A$1:$H$37,5,0) -> 5250 | P41: =VLOOKUP(K41,$A$1:$H$37,6,0) -> 5535 | Q41: =VLOOKUP(K41,$A$1:$H$37,7,0) -> 650
A42: =CONCATENATE(TEXT(K14,"DD-MMM-YYY")," to ",TEXT(K20,"DD-MMM-YYYY")) -> 07-Aug-2023 to 13-Aug-2023 | B42: =L21 -> 28578 | C42: =M21 -> 66682 | D42: =N21 -> 95260 | E42: =O21 -> 50710 | F42: =P21 -> 44550 | G42: =Q21 -> 33310 | H42: =B42/3 -> 9526 | K42: =A29 -> 45165 | L42: =N42*0.3 -> 3834 | M42: =N42-L42 -> 8946 | N42: =O42+P42 -> 12780 | O42: =VLOOKUP(K42,$A$1:$H$37,5,0) -> 10770 | P42: =VLOOKUP(K42,$A$1:$H$37,6,0) -> 2010 | Q42: =VLOOKUP(K42,$A$1:$H$37,7,0) -> 750
A43: =CONCATENATE(TEXT(K25,"DD-MMM-YYY")," to ",TEXT(K31,"DD-MMM-YYYY")) -> 14-Aug-2023 to 20-Aug-2023 | B43: =L32 -> 66586.5 | C43: =M32 -> 155368.5 | D43: =N32 -> 221955 | E43: =O32 -> 67635 | F43: =P32 -> 154320 | G43: =Q32 -> 30925 | H43: =B43/3 -> 22195.5 | K43: Total | L43: =SUM(L36:L42) -> 38953.8 | M43: =SUM(M36:M42) -> 90892.2 | N43: =SUM(N36:N42) -> 129846 | O43: =SUM(O36:O42) -> 39310 | P43: =SUM(P36:P42) -> 90536 | Q43: =SUM(Q36:Q42) -> 13450
A44: =CONCATENATE(TEXT(K36,"DD-MMM-YYY")," to ",TEXT(K42,"DD-MMM-YYYY")) -> 21-Aug-2023 to 27-Aug-2023 | B44: =L43 -> 38953.8 | C44: =M43 -> 90892.2 | D44: =N43 -> 129846 | E44: =O43 -> 39310 | F44: =P43 -> 90536 | G44: =Q43 -> 13450 | H44: =B44/3 -> 12984.6 | K44: Mul Bhag | L44: =L43/3 -> 12984.6
A45: =CONCATENATE(TEXT(K47,"DD-MMM-YYY")," to ",TEXT(K53,"DD-MMM-YYYY")) -> 28-Aug-2023 to 03-Sep-2023 | B45: =L54 -> 39646.5 | C45: =M54 -> 92508.5 | D45: =N54 -> 132155 | E45: =O54 -> 52160 | F45: =P54 -> 79995 | G45: =Q54 -> 31660 | H45: =B45/3 -> 13215.5
A46: =CONCATENATE(TEXT(K59,"DD-MMM-YYY")," to ",TEXT(K58,"DD-MMM-YYYY")) -> 04-Aug-2023 to Date | B46: =SUM(B41:B45) -> 203406.6 | C46: =SUM(C41:C45) -> 474615.4 | D46: =SUM(D41:D45) -> 678022 | E46: =SUM(E41:E45) -> 247961 | F46: =SUM(F41:F45) -> 430061 | G46: =SUM(G41:G45) -> 129675 | H46: =SUM(H41:H45) -> 67802.2 | K46: Date | L46: Profit | M46: Actual | N46: Total | O46: Cash | P46: Account Transfer | Q46: Expense
C47: Total | K47: =A30 -> 45166 | L47: =N47*0.3 -> 2926.5 | M47: =N47-L47 -> 6828.5 | N47: =O47+P47 -> 9755 | O47: =VLOOKUP(K47,$A$1:$H$37,5,0) -> 3450 | P47: =VLOOKUP(K47,$A$1:$H$37,6,0) -> 6305 | Q47: =VLOOKUP(K47,$A$1:$H$37,7,0) -> 4070
K48: =A31 -> 45167 | L48: =N48*0.3 -> 5478 | M48: =N48-L48 -> 12782 | N48: =O48+P48 -> 18260 | O48: =VLOOKUP(K48,$A$1:$H$37,5,0) -> 2490 | P48: =VLOOKUP(K48,$A$1:$H$37,6,0) -> 15770 | Q48: =VLOOKUP(K48,$A$1:$H$37,7,0) -> 5090
K49: =A32 -> 45168 | L49: =N49*0.3 -> 3474 | M49: =N49-L49 -> 8106 | N49: =O49+P49 -> 11580 | O49: =VLOOKUP(K49,$A$1:$H$37,5,0) -> 5000 | P49: =VLOOKUP(K49,$A$1:$H$37,6,0) -> 6580 | Q49: =VLOOKUP(K49,$A$1:$H$37,7,0) -> 5550
K50: =A33 -> 45169 | L50: =N50*0.3 -> 12163.5 | M50: =N50-L50 -> 28381.5 | N50: =O50+P50 -> 40545 | O50: =VLOOKUP(K50,$A$1:$H$37,5,0) -> 12100 | P50: =VLOOKUP(K50,$A$1:$H$37,6,0) -> 28445 | Q50: =VLOOKUP(K50,$A$1:$H$37,7,0) -> 100
K51: =A34 -> 45170 | L51: =N51*0.3 -> 3318 | M51: =N51-L51 -> 7742 | N51: =O51+P51 -> 11060 | O51: =VLOOKUP(K51,$A$1:$H$37,5,0) -> 4820 | P51: =VLOOKUP(K51,$A$1:$H$37,6,0) -> 6240 | Q51: =VLOOKUP(K51,$A$1:$H$37,7,0) -> 750
K52: =A35 -> 45171 | L52: =N52*0.3 -> 7600.5 | M52: =N52-L52 -> 17734.5 | N52: =O52+P52 -> 25335 | O52: =VLOOKUP(K52,$A$1:$H$37,5,0) -> 13280 | P52: =VLOOKUP(K52,$A$1:$H$37,6,0) -> 12055 | Q52: =VLOOKUP(K52,$A$1:$H$37,7,0) -> 8150
K53: =A36 -> 45172 | L53: =N53*0.3 -> 4686 | M53: =N53-L53 -> 10934 | N53: =O53+P53 -> 15620 | O53: =VLOOKUP(K53,$A$1:$H$37,5,0) -> 11020 | P53: =VLOOKUP(K53,$A$1:$H$37,6,0) -> 4600 | Q53: =VLOOKUP(K53,$A$1:$H$37,7,0) -> 7950
K54: Total | L54: =SUM(L47:L53) -> 39646.5 | M54: =SUM(M47:M53) -> 92508.5 | N54: =SUM(N47:N53) -> 132155 | O54: =SUM(O47:O53) -> 52160 | P54: =SUM(P47:P53) -> 79995 | Q54: =SUM(Q47:Q53) -> 31660
K55: Mul Bhag | L55: =L54/3 -> 13215.5
K58: Date | L58: Profit | M58: Actual | N58: Total | O58: Cash | P58: Account Transfer | Q58: Expense
K59: =A6 -> 45142 | L59: =SUM(B7:B36) -> 186083.1 | M59: =SUM(C7:C36) -> 434193.9 | N59: =SUM(D7:D36) -> 620277 | O59: =SUM(E7:E36) -> 237321 | P59: =SUM(F7:F36) -> 382956 | Q59: =SUM(G7:G36) -> 126475
K60: Mul Bhag | L60: =L59/3 -> 62027.7

Sheet September 2023
A1: Date | B1: Profit | C1: Actual | D1: Total | E1: Cash | F1: Account Transfer | G1: Expense | H1: Percentage | I1: Cash In Hand | K1: Date | L1: Profit | M1: Actual | N1: Total | O1: Cash | P1: Account Transfer | Q1: Expense
A2: 45166 | B2: =D2*0.39 -> 3804.45 | C2: =D2-B2 -> 5950.55 | D2: =E2+F2 -> 9755 | E2: 3450 | F2: 6305 | G2: 4070 | H2: =IFERROR(B2/C2,0) -> 0.63934426 | I2: =SUM($D$2:D2)-SUM($G$2:G2) -> 5685 | K2: Export | Q2: 0
A3: 45167 | B3: =D3*0.39 -> 7121.4 | C3: =D3-B3 -> 11138.6 | D3: =E3+F3 -> 18260 | E3: 2490 | F3: 15770 | G3: 5090 | H3: =IFERROR(B3/C3,0) -> 0.63934426 | I3: =SUM($D$2:D3)-SUM($G$2:G3) -> 18855 | K3: =A2 -> 45166 | L3: =N3*0.3 -> 2926.5 | M3: =N3-L3 -> 6828.5 | N3: =O3+P3 -> 9755 | O3: =VLOOKUP(K3,$A$1:$H$37,5,0) -> 3450 | P3: =VLOOKUP(K3,$A$1:$H$37,6,0) -> 6305 | Q3: =VLOOKUP(K3,$A$1:$H$37,7,0) -> 4070
A4: 45168 | B4: =D4*0.39 -> 4516.2 | C4: =D4-B4 -> 7063.8 | D4: =E4+F4 -> 11580 | E4: 5000 | F4: 6580 | G4: 5550 | H4: =IFERROR(B4/C4,0) -> 0.63934426 | I4: =SUM($D$2:D4)-SUM($G$2:G4) -> 24885 | K4: =A3 -> 45167 | L4: =N4*0.3 -> 5478 | M4: =N4-L4 -> 12782 | N4: =O4+P4 -> 18260 | O4: =VLOOKUP(K4,$A$1:$H$37,5,0) -> 2490 | P4: =VLOOKUP(K4,$A$1:$H$37,6,0) -> 15770 | Q4: =VLOOKUP(K4,$A$1:$H$37,7,0) -> 5090
A5: 45169 | B5: =D5*0.39 -> 15812.55 | C5: =D5-B5 -> 24732.45 | D5: =E5+F5 -> 40545 | E5: 12100 | F5: 28445 | G5: 100 | H5: =IFERROR(B5/C5,0) -> 0.63934426 | I5: =SUM($D$2:D5)-SUM($G$2:G5) -> 65330 | K5: =A4 -> 45168 | L5: =N5*0.3 -> 3474 | M5: =N5-L5 -> 8106 | N5: =O5+P5 -> 11580 | O5: =VLOOKUP(K5,$A$1:$H$37,5,0) -> 5000 | P5: =VLOOKUP(K5,$A$1:$H$37,6,0) -> 6580 | Q5: =VLOOKUP(K5,$A$1:$H$37,7,0) -> 5550
A6: 45170 | B6: =D6*0.39 -> 4313.4 | C6: =D6-B6 -> 6746.6 | D6: =E6+F6 -> 11060 | E6: 4820 | F6: 6240 | G6: 750 | H6: =IFERROR(B6/C6,0) -> 0.63934426 | I6: =SUM($D$2:D6)-SUM($G$2:G6) -> 75640 | K6: =A5 -> 45169 | L6: =N6*0.3 -> 12163.5 | M6: =N6-L6 -> 28381.5 | N6: =O6+P6 -> 40545 | O6: =VLOOKUP(K6,$A$1:$H$37,5,0) -> 12100 | P6: =VLOOKUP(K6,$A$1:$H$37,6,0) -> 28445 | Q6: =VLOOKUP(K6,$A$1:$H$37,7,0) -> 100
A7: 45171 | B7: =D7*0.39 -> 9880.65 | C7: =D7-B7 -> 15454.35 | D7: =E7+F7 -> 25335 | E7: 13280 | F7: 12055 | G7: 8150 | H7: =IFERROR(B7/C7,0) -> 0.63934426 | I7: =SUM($D$2:D7)-SUM($G$2:G7) -> 92825 | K7: =A6 -> 45170 | L7: =N7*0.3 -> 3318 | M7: =N7-L7 -> 7742 | N7: =O7+P7 -> 11060 | O7: =VLOOKUP(K7,$A$1:$H$37,5,0) -> 4820 | P7: =VLOOKUP(K7,$A$1:$H$37,6,0) -> 6240 | Q7: =VLOOKUP(K7,$A$1:$H$37,7,0) -> 750
A8: 45172 | B8: =D8*0.39 -> 6091.8 | C8: =D8-B8 -> 9528.2 | D8: =E8+F8 -> 15620 | E8: 11020 | F8: 4600 | G8: 7950 | H8: =IFERROR(B8/C8,0) -> 0.63934426 | I8: =SUM($D$2:D8)-SUM($G$2:G8) -> 100495 | K8: =A7 -> 45171 | L8: =N8*0.3 -> 7600.5 | M8: =N8-L8 -> 17734.5 | N8: =O8+P8 -> 25335 | O8: =VLOOKUP(K8,$A$1:$H$37,5,0) -> 13280 | P8: =VLOOKUP(K8,$A$1:$H$37,6,0) -> 12055 | Q8: =VLOOKUP(K8,$A$1:$H$37,7,0) -> 8150
A9: 45173 | B9: =D9*0.39 -> 10783.5 | C9: =D9-B9 -> 16866.5 | D9: =E9+F9 -> 27650 | E9: 3420 | F9: 24230 | G9: 36590 | H9: =IFERROR(B9/C9,0) -> 0.63934426 | I9: =SUM($D$2:D9)-SUM($G$2:G9) -> 91555 | K9: =A8 -> 45172 | L9: =N9*0.3 -> 4686 | M9: =N9-L9 -> 10934 | N9: =O9+P9 -> 15620 | O9: =VLOOKUP(K9,$A$1:$H$37,5,0) -> 11020 | P9: =VLOOKUP(K9,$A$1:$H$37,6,0) -> 4600 | Q9: =VLOOKUP(K9,$A$1:$H$37,7,0) -> 7950
A10: 45174 | B10: =D10*0.39 -> 13593.45 | C10: =D10-B10 -> 21261.55 | D10: =E10+F10 -> 34855 | E10: 15044 | F10: 19811 | G10: 71150 | H10: =IFERROR(B10/C10,0) -> 0.63934426 | I10: =SUM($D$2:D10)-SUM($G$2:G10) -> 55260 | K10: Total | L10: =SUM(L3:L9) -> 39646.5 | M10: =SUM(M2:M9) -> 92508.5 | N10: =SUM(N2:N9) -> 132155 | O10: =SUM(O2:O9) -> 52160 | P10: =SUM(P2:P9) -> 79995 | Q10: =SUM(Q2:Q9) -> 31660
A11: 45175 | B11: =D11*0.39 -> 5671.38 | C11: =D11-B11 -> 8870.62 | D11: =E11+F11 -> 14542 | E11: 9090 | F11: 5452 | G11: 3020 | H11: =IFERROR(B11/C11,0) -> 0.63934426 | I11: =SUM($D$2:D11)-SUM($G$2:G11) -> 66782 | K11: Mul Bhag | L11: =L10/3 -> 13215.5
A12: 45176 | B12: =D12*0.39 -> 7770.75 | C12: =D12-B12 -> 12154.25 | D12: =E12+F12 -> 19925 | E12: 1670 | F12: 18255 | G12: 10150 | H12: =IFERROR(B12/C12,0) -> 0.63934426 | I12: =SUM($D$2:D12)-SUM($G$2:G12) -> 76557
A13: 45177 | B13: =D13*0.39 -> 3174.6 | C13: =D13-B13 -> 4965.4 | D13: =E13+F13 -> 8140 | E13: 4030 | F13: 4110 | G13: 2150 | H13: =IFERROR(B13/C13,0) -> 0.63934426 | I13: =SUM($D$2:D13)-SUM($G$2:G13) -> 82547 | K13: Date | L13: Profit | M13: Actual | N13: Total | O13: Cash | P13: Account Transfer | Q13: Expense
A14: 45178 | B14: =D14*0.39 -> 4009.2 | C14: =D14-B14 -> 6270.8 | D14: =E14+F14 -> 10280 | E14: 2280 | F14: 8000 | G14: 2100 | H14: =IFERROR(B14/C14,0) -> 0.63934426 | I14: =SUM($D$2:D14)-SUM($G$2:G14) -> 90727 | K14: =A9 -> 45173 | L14: =N14*0.3 -> 8295 | M14: =N14-L14 -> 19355 | N14: =O14+P14 -> 27650 | O14: =VLOOKUP(K14,$A$1:$H$37,5,0) -> 3420 | P14: =VLOOKUP(K14,$A$1:$H$37,6,0) -> 24230 | Q14: =VLOOKUP(K14,$A$1:$H$37,7,0) -> 36590
A15: 45179 | B15: =D15*0.39 -> 3890.25 | C15: =D15-B15 -> 6084.75 | D15: =E15+F15 -> 9975 | E15: 4675 | F15: 5300 | G15: 14860 | H15: =IFERROR(B15/C15,0) -> 0.63934426 | I15: =SUM($D$2:D15)-SUM($G$2:G15) -> 85842 | K15: =A10 -> 45174 | L15: =N15*0.3 -> 10456.5 | M15: =N15-L15 -> 24398.5 | N15: =O15+P15 -> 34855 | O15: =VLOOKUP(K15,$A$1:$H$37,5,0) -> 15044 | P15: =VLOOKUP(K15,$A$1:$H$37,6,0) -> 19811 | Q15: =VLOOKUP(K15,$A$1:$H$37,7,0) -> 71150
A16: 45180 | B16: =D16*0.39 -> 4817.28 | C16: =D16-B16 -> 7534.72 | D16: =E16+F16 -> 12352 | E16: 7140 | F16: 5212 | G16: =21700+1445 -> 23145 | H16: =IFERROR(B16/C16,0) -> 0.63934426 | I16: =SUM($D$2:D16)-SUM($G$2:G16) -> 75049 | K16: =A11 -> 45175 | L16: =N16*0.3 -> 4362.6 | M16: =N16-L16 -> 10179.4 | N16: =O16+P16 -> 14542 | O16: =VLOOKUP(K16,$A$1:$H$37,5,0) -> 9090 | P16: =VLOOKUP(K16,$A$1:$H$37,6,0) -> 5452 | Q16: =VLOOKUP(K16,$A$1:$H$37,7,0) -> 3020
A17: 45181 | B17: =D17*0.39 -> 1778.4 | C17: =D17-B17 -> 2781.6 | D17: =E17+F17 -> 4560 | E17: 4150 | F17: 410 | G17: 1350 | H17: =IFERROR(B17/C17,0) -> 0.63934426 | I17: =SUM($D$2:D17)-SUM($G$2:G17) -> 78259 | K17: =A12 -> 45176 | L17: =N17*0.3 -> 5977.5 | M17: =N17-L17 -> 13947.5 | N17: =O17+P17 -> 19925 | O17: =VLOOKUP(K17,$A$1:$H$37,5,0) -> 1670 | P17: =VLOOKUP(K17,$A$1:$H$37,6,0) -> 18255 | Q17: =VLOOKUP(K17,$A$1:$H$37,7,0) -> 10150
A18: 45182 | B18: =D18*0.39 -> 15527.85 | C18: =D18-B18 -> 24287.15 | D18: =E18+F18 -> 39815 | E18: 8950 | F18: 30865 | G18: 2900 | H18: =IFERROR(B18/C18,0) -> 0.63934426 | I18: =SUM($D$2:D18)-SUM($G$2:G18) -> 115174 | K18: =A13 -> 45177 | L18: =N18*0.3 -> 2442 | M18: =N18-L18 -> 5698 | N18: =O18+P18 -> 8140 | O18: =VLOOKUP(K18,$A$1:$H$37,5,0) -> 4030 | P18: =VLOOKUP(K18,$A$1:$H$37,6,0) -> 4110 | Q18: =VLOOKUP(K18,$A$1:$H$37,7,0) -> 2150
A19: 45183 | B19: =D19*0.39 -> 20248.8 | C19: =D19-B19 -> 31671.2 | D19: =E19+F19 -> 51920 | E19: 11670 | F19: 40250 | G19: 820 | H19: =IFERROR(B19/C19,0) -> 0.63934426 | I19: =SUM($D$2:D19)-SUM($G$2:G19) -> 166274 | K19: =A14 -> 45178 | L19: =N19*0.3 -> 3084 | M19: =N19-L19 -> 7196 | N19: =O19+P19 -> 10280 | O19: =VLOOKUP(K19,$A$1:$H$37,5,0) -> 2280 | P19: =VLOOKUP(K19,$A$1:$H$37,6,0) -> 8000 | Q19: =VLOOKUP(K19,$A$1:$H$37,7,0) -> 2100
A20: 45184 | B20: =D20*0.39 -> 7187.7 | C20: =D20-B20 -> 11242.3 | D20: =E20+F20 -> 18430 | E20: 9100 | F20: 9330 | G20: 2550 | H20: =IFERROR(B20/C20,0) -> 0.63934426 | I20: =SUM($D$2:D20)-SUM($G$2:G20) -> 182154 | K20: =A15 -> 45179 | L20: =N20*0.3 -> 2992.5 | M20: =N20-L20 -> 6982.5 | N20: =O20+P20 -> 9975 | O20: =VLOOKUP(K20,$A$1:$H$37,5,0) -> 4675 | P20: =VLOOKUP(K20,$A$1:$H$37,6,0) -> 5300 | Q20: =VLOOKUP(K20,$A$1:$H$37,7,0) -> 14860
A21: 45185 | B21: =D21*0.39 -> 19449.3 | C21: =D21-B21 -> 30420.7 | D21: =E21+F21 -> 49870 | E21: 13670 | F21: =32700+3500 -> 36200 | G21: 250 | H21: =IFERROR(B21/C21,0) -> 0.63934426 | I21: =SUM($D$2:D21)-SUM($G$2:G21) -> 231774 | K21: Total | L21: =SUM(L14:L20) -> 37610.1 | M21: =SUM(M14:M20) -> 87756.9 | N21: =SUM(N14:N20) -> 125367 | O21: =SUM(O14:O20) -> 40209 | P21: =SUM(P14:P20) -> 85158 | Q21: =SUM(Q14:Q20) -> 140020
A22: 45186 | B22: =D22*0.39 -> 8347.17 | C22: =D22-B22 -> 13055.83 | D22: =E22+F22 -> 21403 | E22: =7260+6100 -> 13360 | F22: 8043 | G22: 7260 | H22: =IFERROR(B22/C22,0) -> 0.63934426 | I22: =SUM($D$2:D22)-SUM($G$2:G22) -> 245917 | K22: Mul Bhag | L22: =L21/3 -> 12536.7 | N22: =M22+L22 -> 12536.7
A23: 45187 | B23: =D23*0.39 -> 5551.65 | C23: =D23-B23 -> 8683.35 | D23: =E23+F23 -> 14235 | E23: 11550 | F23: 2685 | G23: 5310 | H23: =IFERROR(B23/C23,0) -> 0.63934426 | I23: =SUM($D$2:D23)-SUM($G$2:G23) -> 254842 | M23: ser
A24: 45188 | B24: =D24*0.39 -> 13642.59 | C24: =D24-B24 -> 21338.41 | D24: =E24+F24 -> 34981 | E24: 2230 | F24: 32751 | G24: 2250 | H24: =IFERROR(B24/C24,0) -> 0.63934426 | I24: =SUM($D$2:D24)-SUM($G$2:G24) -> 287573 | K24: Date | L24: Profit | M24: Actual | N24: Total | O24: Cash | P24: Account Transfer | Q24: Expense
A25: 45189 | B25: =D25*0.39 -> 5124.6 | C25: =D25-B25 -> 8015.4 | D25: =E25+F25 -> 13140 | E25: 2900 | F25: 10240 | G25: 2710 | H25: =IFERROR(B25/C25,0) -> 0.63934426 | I25: =SUM($D$2:D25)-SUM($G$2:G25) -> 298003 | K25: =A16 -> 45180 | L25: =N25*0.3 -> 1563.6 | M25: =N25-L25 -> 3648.4 | N25: =O25+P25 -> 5212 | O25: 0 | P25: =VLOOKUP(K25,$A$1:$H$37,6,0) -> 5212 | Q25: =VLOOKUP(K25,$A$1:$H$37,7,0) -> 23145
A26: 45190 | B26: =D26*0.39 -> 5928 | C26: =D26-B26 -> 9272 | D26: =E26+F26 -> 15200 | E26: 5890 | F26: 9310 | G26: 1250 | H26: =IFERROR(B26/C26,0) -> 0.63934426 | I26: =SUM($D$2:D26)-SUM($G$2:G26) -> 311953 | K26: =A17 -> 45181 | L26: =N26*0.3 -> 1368 | M26: =N26-L26 -> 3192 | N26: =O26+P26 -> 4560 | O26: =VLOOKUP(K26,$A$1:$H$37,5,0) -> 4150 | P26: =VLOOKUP(K26,$A$1:$H$37,6,0) -> 410 | Q26: =VLOOKUP(K26,$A$1:$H$37,7,0) -> 1350
A27: 45191 | B27: =D27*0.39 -> 2451.15 | C27: =D27-B27 -> 3833.85 | D27: =E27+F27 -> 6285 | E27: 2570 | F27: 3715 | G27: 2250 | H27: =IFERROR(B27/C27,0) -> 0.63934426 | I27: =SUM($D$2:D27)-SUM($G$2:G27) -> 315988 | K27: =A18 -> 45182 | L27: =N27*0.3 -> 11944.5 | M27: =N27-L27 -> 27870.5 | N27: =O27+P27 -> 39815 | O27: =VLOOKUP(K27,$A$1:$H$37,5,0) -> 8950 | P27: =VLOOKUP(K27,$A$1:$H$37,6,0) -> 30865 | Q27: =VLOOKUP(K27,$A$1:$H$37,7,0) -> 2900
A28: 45192 | B28: =D28*0.39 -> 3030.3 | C28: =D28-B28 -> 4739.7 | D28: =E28+F28 -> 7770 | E28: 4470 | F28: 3300 | G28: 2000 | H28: =IFERROR(B28/C28,0) -> 0.63934426 | I28: =SUM($D$2:D28)-SUM($G$2:G28) -> 321758 | K28: =A19 -> 45183 | L28: =N28*0.3 -> 15576 | M28: =N28-L28 -> 36344 | N28: =O28+P28 -> 51920 | O28: =VLOOKUP(K28,$A$1:$H$37,5,0) -> 11670 | P28: =VLOOKUP(K28,$A$1:$H$37,6,0) -> 40250 | Q28: =VLOOKUP(K28,$A$1:$H$37,7,0) -> 820
A29: 45193 | B29: =D29*0.39 -> 38537.85 | C29: =D29-B29 -> 60277.15 | D29: =E29+F29 -> 98815 | E29: 38130 | F29: 60685 | G29: 2900 | H29: =IFERROR(B29/C29,0) -> 0.63934426 | I29: =SUM($D$2:D29)-SUM($G$2:G29) -> 417673 | K29: =A20 -> 45184 | L29: =N29*0.3 -> 5529 | M29: =N29-L29 -> 12901 | N29: =O29+P29 -> 18430 | O29: =VLOOKUP(K29,$A$1:$H$37,5,0) -> 9100 | P29: =VLOOKUP(K29,$A$1:$H$37,6,0) -> 9330 | Q29: =VLOOKUP(K29,$A$1:$H$37,7,0) -> 2550
A30: 45194 | B30: =D30*0.39 -> 4137.9 | C30: =D30-B30 -> 6472.1 | D30: =E30+F30 -> 10610 | E30: 4900 | F30: 5710 | G30: 1000 | H30: =IFERROR(B30/C30,0) -> 0.63934426 | I30: =SUM($D$2:D30)-SUM($G$2:G30) -> 427283 | K30: =A21 -> 45185 | L30: =N30*0.3 -> 14961 | M30: =N30-L30 -> 34909 | N30: =O30+P30 -> 49870 | O30: =VLOOKUP(K30,$A$1:$H$37,5,0) -> 13670 | P30: =VLOOKUP(K30,$A$1:$H$37,6,0) -> 36200 | Q30: =VLOOKUP(K30,$A$1:$H$37,7,0) -> 250
A31: 45195 | B31: =D31*0.39 -> 4123.86 | C31: =D31-B31 -> 6450.14 | D31: =E31+F31 -> 10574 | E31: 4660 | F31: 5914 | G31: 2000 | H31: =IFERROR(B31/C31,0) -> 0.63934426 | I31: =SUM($D$2:D31)-SUM($G$2:G31) -> 435857 | K31: =A22 -> 45186 | L31: =N31*0.3 -> 6420.9 | M31: =N31-L31 -> 14982.1 | N31: =O31+P31 -> 21403 | O31: =VLOOKUP(K31,$A$1:$H$37,5,0) -> 13360 | P31: =VLOOKUP(K31,$A$1:$H$37,6,0) -> 8043 | Q31: =VLOOKUP(K31,$A$1:$H$37,7,0) -> 7260
A32: 45196 | B32: =D32*0.39 -> 8798.4 | C32: =D32-B32 -> 13761.6 | D32: =E32+F32 -> 22560 | E32: 6840 | F32: 15720 | G32: 250 | H32: =IFERROR(B32/C32,0) -> 0.63934426 | I32: =SUM($D$2:D32)-SUM($G$2:G32) -> 458167 | K32: Total | L32: =SUM(L25:L31) -> 57363 | M32: =SUM(M25:M31) -> 133847 | N32: =SUM(N25:N31) -> 191210 | O32: =SUM(O25:O31) -> 60900 | P32: =SUM(P25:P31) -> 130310 | Q32: =SUM(Q25:Q31) -> 38275
A33: 45197 | B33: =D33*0.39 -> 13464.75 | C33: =D33-B33 -> 21060.25 | D33: =E33+F33 -> 34525 | E33: 900 | F33: 33625 | G33: 200 | H33: =IFERROR(B33/C33,0) -> 0.63934426 | I33: =SUM($D$2:D33)-SUM($G$2:G33) -> 492492 | K33: Mul Bhag | L33: =L32/3 -> 19121
A34: 45198 | B34: =D34*0.39 -> 8022.3 | C34: =D34-B34 -> 12547.7 | D34: =E34+F34 -> 20570 | E34: 1570 | F34: 19000 | G34: 500 | H34: =IFERROR(B34/C34,0) -> 0.63934426 | I34: =SUM($D$2:D34)-SUM($G$2:G34) -> 512562
A35: 45199 | B35: =D35*0.39 -> 27116.7 | C35: =D35-B35 -> 42413.3 | D35: =E35+F35 -> 69530 | E35: 38210 | F35: 31320 | G35: 1940 | H35: =IFERROR(B35/C35,0) -> 0.63934426 | I35: =SUM($D$2:D35)-SUM($G$2:G35) -> 580152 | K35: Date | L35: Profit | M35: Actual | N35: Total | O35: Cash | P35: Account Transfer | Q35: Expense
A36: 45200 | B36: =D36*0.39 -> 6624.93 | C36: =D36-B36 -> 10362.07 | D36: =E36+F36 -> 16987 | E36: 7110 | F36: 9877 | G36: 3700 | H36: =IFERROR(B36/C36,0) -> 0.63934426 | I36: =SUM($D$2:D36)-SUM($G$2:G36) -> 593439 | K36: =A23 -> 45187 | L36: =N36*0.3 -> 4270.5 | M36: =N36-L36 -> 9964.5 | N36: =O36+P36 -> 14235 | O36: =VLOOKUP(K36,$A$1:$H$37,5,0) -> 11550 | P36: =VLOOKUP(K36,$A$1:$H$37,6,0) -> 2685 | Q36: =VLOOKUP(K36,$A$1:$H$37,7,0) -> 5310
A37: Total | B37: =SUM(B6:B35) -> 286465.53 | C37: =SUM(C6:C35) -> 448061.47 | D37: =SUM(D6:D35) -> 734527 | E37: =SUM(E6:E35) -> 262189 | F37: =SUM(F6:F35) -> 472338 | G37: =SUM(G6:G35) -> 219705 | H37: =SUM(H6:H35) -> 19.180328 | I37: =SUM(I6:I35) -> 7027134 | K37: =A24 -> 45188 | L37: =N37*0.3 -> 10494.3 | M37: =N37-L37 -> 24486.7 | N37: =O37+P37 -> 34981 | O37: =VLOOKUP(K37,$A$1:$H$37,5,0) -> 2230 | P37: =VLOOKUP(K37,$A$1:$H$37,6,0) -> 32751 | Q37: =VLOOKUP(K37,$A$1:$H$37,7,0) -> 2250
B38: =B37/3 -> 95488.51 | E38: =D37*0.42 -> 308501.34 | K38: =A25 -> 45189 | L38: =N38*0.3 -> 3942 | M38: =N38-L38 -> 9198 | N38: =O38+P38 -> 13140 | O38: =VLOOKUP(K38,$A$1:$H$37,5,0) -> 2900 | P38: =VLOOKUP(K38,$A$1:$H$37,6,0) -> 10240 | Q38: =VLOOKUP(K38,$A$1:$H$37,7,0) -> 2710
B39: =B38*100/D37 -> 13 | E39: =E38/3 -> 102833.78 | K39: =A26 -> 45190 | L39: =N39*0.3 -> 4560 | M39: =N39-L39 -> 10640 | N39: =O39+P39 -> 15200 | O39: =VLOOKUP(K39,$A$1:$H$37,5,0) -> 5890 | P39: =VLOOKUP(K39,$A$1:$H$37,6,0) -> 9310 | Q39: =VLOOKUP(K39,$A$1:$H$37,7,0) -> 1250
A40: Date | B40: Profit | C40: Actual | D40: Total | E40: Cash | F40: Account Transfer | G40: Expense | H40: Mul Bhag | K40: =A27 -> 45191 | L40: =N40*0.3 -> 1885.5 | M40: =N40-L40 -> 4399.5 | N40: =O40+P40 -> 6285 | O40: =VLOOKUP(K40,$A$1:$H$37,5,0) -> 2570 | P40: =VLOOKUP(K40,$A$1:$H$37,6,0) -> 3715 | Q40: =VLOOKUP(K40,$A$1:$H$37,7,0) -> 2250
A41: =CONCATENATE(TEXT(K3,"DD-MMM-YYY")," to ",TEXT(K9,"DD-MMM-YYYY")) -> 28-Aug-2023 to 03-Sep-2023 | B41: =L10 -> 39646.5 | C41: =M10 -> 92508.5 | D41: =N10 -> 132155 | E41: =O10 -> 52160 | F41: =P10 -> 79995 | G41: =Q10 -> 31660 | H41: =B41/3 -> 13215.5 | K41: =A28 -> 45192 | L41: =N41*0.3 -> 2331 | M41: =N41-L41 -> 5439 | N41: =O41+P41 -> 7770 | O41: =VLOOKUP(K41,$A$1:$H$37,5,0) -> 4470 | P41: =VLOOKUP(K41,$A$1:$H$37,6,0) -> 3300 | Q41: =VLOOKUP(K41,$A$1:$H$37,7,0) -> 2000
A42: =CONCATENATE(TEXT(K14,"DD-MMM-YYY")," to ",TEXT(K20,"DD-MMM-YYYY")) -> 04-Sep-2023 to 10-Sep-2023 | B42: =L21 -> 37610.1 | C42: =M21 -> 87756.9 | D42: =N21 -> 125367 | E42: =O21 -> 40209 | F42: =P21 -> 85158 | G42: =Q21 -> 140020 | H42: =B42/3 -> 12536.7 | K42: =A29 -> 45193 | L42: =N42*0.3 -> 29644.5 | M42: =N42-L42 -> 69170.5 | N42: =O42+P42 -> 98815 | O42: =VLOOKUP(K42,$A$1:$H$37,5,0) -> 38130 | P42: =VLOOKUP(K42,$A$1:$H$37,6,0) -> 60685 | Q42: =VLOOKUP(K42,$A$1:$H$37,7,0) -> 2900
A43: =CONCATENATE(TEXT(K25,"DD-MMM-YYY")," to ",TEXT(K31,"DD-MMM-YYYY")) -> 11-Sep-2023 to 17-Sep-2023 | B43: =L32 -> 57363 | C43: =M32 -> 133847 | D43: =N32 -> 191210 | E43: =O32 -> 60900 | F43: =P32 -> 130310 | G43: =Q32 -> 38275 | H43: =B43/3 -> 19121 | K43: Total | L43: =SUM(L36:L42) -> 57127.8 | M43: =SUM(M36:M42) -> 133298.2 | N43: =SUM(N36:N42) -> 190426 | O43: =SUM(O36:O42) -> 67740 | P43: =SUM(P36:P42) -> 122686 | Q43: =SUM(Q36:Q42) -> 18670
A44: =CONCATENATE(TEXT(K36,"DD-MMM-YYY")," to ",TEXT(K42,"DD-MMM-YYYY")) -> 18-Sep-2023 to 24-Sep-2023 | B44: =L43 -> 57127.8 | C44: =M43 -> 133298.2 | D44: =N43 -> 190426 | E44: =O43 -> 67740 | F44: =P43 -> 122686 | G44: =Q43 -> 18670 | H44: =B44/3 -> 19042.6 | K44: Mul Bhag | L44: =L43/3 -> 19042.6
A45: =CONCATENATE(TEXT(K47,"DD-MMM-YYY")," to ",TEXT(K53,"DD-MMM-YYYY")) -> 25-Sep-2023 to 01-Oct-2023 | B45: =L54 -> 55606.8 | C45: =M54 -> 129749.2 | D45: =N54 -> 185356 | E45: =O54 -> 64190 | F45: =P54 -> 121166 | G45: =Q54 -> 9590 | H45: =B45/3 -> 18535.6
A46: =CONCATENATE(TEXT(K59,"DD-MMM-YYY")," to ",TEXT(K58,"DD-MMM-YYYY")) -> 01-Sep-2023 to Date | B46: =SUM(B41:B45) -> 247354.2 | C46: =SUM(C41:C45) -> 577159.8 | D46: =SUM(D41:D45) -> 824514 | E46: =SUM(E41:E45) -> 285199 | F46: =SUM(F41:F45) -> 539315 | G46: =SUM(G41:G45) -> 238215 | H46: =SUM(H41:H45) -> 82451.4 | K46: Date | L46: Profit | M46: Actual | N46: Total | O46: Cash | P46: Account Transfer | Q46: Expense
C47: Total | K47: =A30 -> 45194 | L47: =N47*0.3 -> 3183 | M47: =N47-L47 -> 7427 | N47: =O47+P47 -> 10610 | O47: =VLOOKUP(K47,$A$1:$H$37,5,0) -> 4900 | P47: =VLOOKUP(K47,$A$1:$H$37,6,0) -> 5710 | Q47: =VLOOKUP(K47,$A$1:$H$37,7,0) -> 1000
K48: =A31 -> 45195 | L48: =N48*0.3 -> 3172.2 | M48: =N48-L48 -> 7401.8 | N48: =O48+P48 -> 10574 | O48: =VLOOKUP(K48,$A$1:$H$37,5,0) -> 4660 | P48: =VLOOKUP(K48,$A$1:$H$37,6,0) -> 5914 | Q48: =VLOOKUP(K48,$A$1:$H$37,7,0) -> 2000
K49: =A32 -> 45196 | L49: =N49*0.3 -> 6768 | M49: =N49-L49 -> 15792 | N49: =O49+P49 -> 22560 | O49: =VLOOKUP(K49,$A$1:$H$37,5,0) -> 6840 | P49: =VLOOKUP(K49,$A$1:$H$37,6,0) -> 15720 | Q49: =VLOOKUP(K49,$A$1:$H$37,7,0) -> 250
K50: =A33 -> 45197 | L50: =N50*0.3 -> 10357.5 | M50: =N50-L50 -> 24167.5 | N50: =O50+P50 -> 34525 | O50: =VLOOKUP(K50,$A$1:$H$37,5,0) -> 900 | P50: =VLOOKUP(K50,$A$1:$H$37,6,0) -> 33625 | Q50: =VLOOKUP(K50,$A$1:$H$37,7,0) -> 200
K51: =A34 -> 45198 | L51: =N51*0.3 -> 6171 | M51: =N51-L51 -> 14399 | N51: =O51+P51 -> 20570 | O51: =VLOOKUP(K51,$A$1:$H$37,5,0) -> 1570 | P51: =VLOOKUP(K51,$A$1:$H$37,6,0) -> 19000 | Q51: =VLOOKUP(K51,$A$1:$H$37,7,0) -> 500
K52: =A35 -> 45199 | L52: =N52*0.3 -> 20859 | M52: =N52-L52 -> 48671 | N52: =O52+P52 -> 69530 | O52: =VLOOKUP(K52,$A$1:$H$37,5,0) -> 38210 | P52: =VLOOKUP(K52,$A$1:$H$37,6,0) -> 31320 | Q52: =VLOOKUP(K52,$A$1:$H$37,7,0) -> 1940
K53: =A36 -> 45200 | L53: =N53*0.3 -> 5096.1 | M53: =N53-L53 -> 11890.9 | N53: =O53+P53 -> 16987 | O53: =VLOOKUP(K53,$A$1:$H$37,5,0) -> 7110 | P53: =VLOOKUP(K53,$A$1:$H$37,6,0) -> 9877 | Q53: =VLOOKUP(K53,$A$1:$H$37,7,0) -> 3700
K54: Total | L54: =SUM(L47:L53) -> 55606.8 | M54: =SUM(M47:M53) -> 129749.2 | N54: =SUM(N47:N53) -> 185356 | O54: =SUM(O47:O53) -> 64190 | P54: =SUM(P47:P53) -> 121166 | Q54: =SUM(Q47:Q53) -> 9590
K55: Mul Bhag | L55: =L54/3 -> 18535.6
K58: Date | L58: Profit | M58: Actual | N58: Total | O58: Cash | P58: Account Transfer | Q58: Expense
K59: =A6 -> 45170 | L59: =SUM(B7:B36) -> 288777.06 | M59: =SUM(C7:C36) -> 451676.94 | N59: =SUM(D7:D36) -> 740454 | O59: =SUM(E7:E36) -> 264479 | P59: =SUM(F7:F36) -> 475975 | Q59: =SUM(G7:G36) -> 222655
K60: Mul Bhag | L60: =L59/3 -> 96259.02

Sheet October 2023
A1: Date | B1: Profit | C1: Actual | D1: Total | E1: Cash | F1: Account Transfer | G1: Expense | H1: Percentage | I1: Cash In Hand | K1: Date | L1: Profit | M1: Actual | N1: Total | O1: Cash | P1: Account Transfer | Q1: Expense
A2: 45201 | B2: =D2*0.39 -> 12559.95 | C2: =D2-B2 -> 19645.05 | D2: =E2+F2+G2 -> 32205 | E2: 6620 | F2: 24015 | G2: 1570 | H2: =IFERROR(B2/C2,0) -> 0.63934426 | I2: =SUM($D$2:D2)-SUM($G$2:G2) -> 30635 | K2: Export | Q2: 0
A3: 45202 | B3: =D3*0.39 -> 19568.25 | C3: =D3-B3 -> 30606.75 | D3: =E3+F3+G3 -> 50175 | E3: =11810+940 -> 12750 | F3: 25825 | G3: =6500+5100 -> 11600 | H3: =IFERROR(B3/C3,0) -> 0.63934426 | I3: =SUM($D$2:D3)-SUM($G$2:G3) -> 69210 | K3: =A2 -> 45201 | L3: =N3*0.3 -> 9190.5 | M3: =N3-L3 -> 21444.5 | N3: =O3+P3 -> 30635 | O3: =VLOOKUP(K3,$A$1:$H$37,5,0) -> 6620 | P3: =VLOOKUP(K3,$A$1:$H$37,6,0) -> 24015 | Q3: =VLOOKUP(K3,$A$1:$H$37,7,0) -> 1570
A4: 45203 | B4: =D4*0.39 -> 37869 | C4: =D4-B4 -> 59231 | D4: =E4+F4+G4 -> 97100 | E4: 43700 | F4: 33690 | G4: 19710 | H4: =IFERROR(B4/C4,0) -> 0.63934426 | I4: =SUM($D$2:D4)-SUM($G$2:G4) -> 146600 | K4: =A3 -> 45202 | L4: =N4*0.3 -> 11572.5 | M4: =N4-L4 -> 27002.5 | N4: =O4+P4 -> 38575 | O4: =VLOOKUP(K4,$A$1:$H$37,5,0) -> 12750 | P4: =VLOOKUP(K4,$A$1:$H$37,6,0) -> 25825 | Q4: =VLOOKUP(K4,$A$1:$H$37,7,0) -> 11600
A5: 45204 | B5: =D5*0.39 -> 4329 | C5: =D5-B5 -> 6771 | D5: =E5+F5+G5 -> 11100 | E5: 10000 | G5: 1100 | H5: =IFERROR(B5/C5,0) -> 0.63934426 | I5: =SUM($D$2:D5)-SUM($G$2:G5) -> 156600 | K5: =A4 -> 45203 | L5: =N5*0.3 -> 23217 | M5: =N5-L5 -> 54173 | N5: =O5+P5 -> 77390 | O5: =VLOOKUP(K5,$A$1:$H$37,5,0) -> 43700 | P5: =VLOOKUP(K5,$A$1:$H$37,6,0) -> 33690 | Q5: =VLOOKUP(K5,$A$1:$H$37,7,0) -> 19710
A6: 45205 | B6: =D6*0.39 -> 8028.579 | C6: =D6-B6 -> 12557.521 | D6: =E6+F6+G6 -> 20586.1 | E6: 9000 | F6: 9586.1 | G6: 2000 | H6: =IFERROR(B6/C6,0) -> 0.63934426 | I6: =SUM($D$2:D6)-SUM($G$2:G6) -> 175186.1 | K6: =A5 -> 45204 | L6: =N6*0.3 -> 3000 | M6: =N6-L6 -> 7000 | N6: =O6+P6 -> 10000 | O6: =VLOOKUP(K6,$A$1:$H$37,5,0) -> 10000 | P6: =VLOOKUP(K6,$A$1:$H$37,6,0) -> 0 | Q6: =VLOOKUP(K6,$A$1:$H$37,7,0) -> 1100
A7: 45206 | B7: =D7*0.39 -> 19970.34 | C7: =D7-B7 -> 31235.66 | D7: =E7+F7+G7 -> 51206 | E7: 25500 | F7: 24456 | G7: 1250 | H7: =IFERROR(B7/C7,0) -> 0.63934426 | I7: =SUM($D$2:D7)-SUM($G$2:G7) -> 225142.1 | K7: =A6 -> 45205 | L7: =N7*0.3 -> 5575.83 | M7: =N7-L7 -> 13010.27 | N7: =O7+P7 -> 18586.1 | O7: =VLOOKUP(K7,$A$1:$H$37,5,0) -> 9000 | P7: =VLOOKUP(K7,$A$1:$H$37,6,0) -> 9586.1 | Q7: =VLOOKUP(K7,$A$1:$H$37,7,0) -> 2000
A8: 45207 | B8: =D8*0.39 -> 23602.8 | C8: =D8-B8 -> 36917.2 | D8: =E8+F8+G8 -> 60520 | E8: 55000 | F8: 3520 | G8: 2000 | H8: =IFERROR(B8/C8,0) -> 0.63934426 | I8: =SUM($D$2:D8)-SUM($G$2:G8) -> 283662.1 | K8: =A7 -> 45206 | L8: =N8*0.3 -> 14986.8 | M8: =N8-L8 -> 34969.2 | N8: =O8+P8 -> 49956 | O8: =VLOOKUP(K8,$A$1:$H$37,5,0) -> 25500 | P8: =VLOOKUP(K8,$A$1:$H$37,6,0) -> 24456 | Q8: =VLOOKUP(K8,$A$1:$H$37,7,0) -> 1250
A9: 45208 | B9: =D9*0.39 -> 34585.2 | C9: =D9-B9 -> 54094.8 | D9: =E9+F9+G9 -> 88680 | E9: 15600 | F9: 70080 | G9: 3000 | H9: =IFERROR(B9/C9,0) -> 0.63934426 | I9: =SUM($D$2:D9)-SUM($G$2:G9) -> 369342.1 | K9: =A8 -> 45207 | L9: =N9*0.3 -> 17556 | M9: =N9-L9 -> 40964 | N9: =O9+P9 -> 58520 | O9: =VLOOKUP(K9,$A$1:$H$37,5,0) -> 55000 | P9: =VLOOKUP(K9,$A$1:$H$37,6,0) -> 3520 | Q9: =VLOOKUP(K9,$A$1:$H$37,7,0) -> 2000
A10: 45209 | B10: =D10*0.39 -> 33404.28 | C10: =D10-B10 -> 52247.72 | D10: =E10+F10+G10 -> 85652 | E10: 26500 | F10: 53302 | G10: 5850 | H10: =IFERROR(B10/C10,0) -> 0.63934426 | I10: =SUM($D$2:D10)-SUM($G$2:G10) -> 449144.1 | K10: Total | L10: =SUM(L3:L9) -> 85098.63 | M10: =SUM(M2:M9) -> 198563.47 | N10: =SUM(N2:N9) -> 283662.1 | O10: =SUM(O2:O9) -> 162570 | P10: =SUM(P2:P9) -> 121092.1 | Q10: =SUM(Q2:Q9) -> 39230
A11: 45210 | B11: =D11*0.39 -> 50719.11 | C11: =D11-B11 -> 79329.89 | D11: =E11+F11+G11 -> 130049 | E11: =17000+2400+51600 -> 71000 | F11: 54249 | G11: 4800 | H11: =IFERROR(B11/C11,0) -> 0.63934426 | I11: =SUM($D$2:D11)-SUM($G$2:G11) -> 574393.1 | K11: Mul Bhag | L11: =L10/3 -> 28366.21
A12: 45211 | B12: =D12*0.39 -> 20009.73 | C12: =D12-B12 -> 31297.27 | D12: =E12+F12+G12 -> 51307 | E12: 7000 | F12: 42657 | G12: 1650 | H12: =IFERROR(B12/C12,0) -> 0.63934426 | I12: =SUM($D$2:D12)-SUM($G$2:G12) -> 624050.1
A13: 45212 | B13: =D13*0.39 -> 11864.97 | C13: =D13-B13 -> 18558.03 | D13: =E13+F13+G13 -> 30423 | E13: 10000 | F13: 15023 | G13: 5400 | H13: =IFERROR(B13/C13,0) -> 0.63934426 | I13: =SUM($D$2:D13)-SUM($G$2:G13) -> 649073.1 | K13: Date | L13: Profit | M13: Actual | N13: Total | O13: Cash | P13: Account Transfer | Q13: Expense
A14: 45213 | B14: =D14*0.39 -> 45277.83 | C14: =D14-B14 -> 70819.17 | D14: =E14+F14+G14 -> 116097 | E14: 54500 | F14: 57297 | G14: 4300 | H14: =IFERROR(B14/C14,0) -> 0.63934426 | I14: =SUM($D$2:D14)-SUM($G$2:G14) -> 760870.1 | K14: =A9 -> 45208 | L14: =N14*0.3 -> 25704 | M14: =N14-L14 -> 59976 | N14: =O14+P14 -> 85680 | O14: =VLOOKUP(K14,$A$1:$H$37,5,0) -> 15600 | P14: =VLOOKUP(K14,$A$1:$H$37,6,0) -> 70080 | Q14: =VLOOKUP(K14,$A$1:$H$37,7,0) -> 3000
A15: 45214 | B15: =D15*0.39 -> 57464.94 | C15: =D15-B15 -> 89881.06 | D15: =E15+F15+G15 -> 147346 | E15: 75000 | F15: 63346 | G15: 9000 | H15: =IFERROR(B15/C15,0) -> 0.63934426 | I15: =SUM($D$2:D15)-SUM($G$2:G15) -> 899216.1 | K15: =A10 -> 45209 | L15: =N15*0.3 -> 23940.6 | M15: =N15-L15 -> 55861.4 | N15: =O15+P15 -> 79802 | O15: =VLOOKUP(K15,$A$1:$H$37,5,0) -> 26500 | P15: =VLOOKUP(K15,$A$1:$H$37,6,0) -> 53302 | Q15: =VLOOKUP(K15,$A$1:$H$37,7,0) -> 5850
A16: 45215 | B16: =D16*0.39 -> 48851.4 | C16: =D16-B16 -> 76408.6 | D16: =E16+F16+G16 -> 125260 | E16: 46500 | F16: 73260 | G16: 5500 | H16: =IFERROR(B16/C16,0) -> 0.63934426 | I16: =SUM($D$2:D16)-SUM($G$2:G16) -> 1018976.1 | K16: =A11 -> 45210 | L16: =N16*0.3 -> 37574.7 | M16: =N16-L16 -> 87674.3 | N16: =O16+P16 -> 125249 | O16: =VLOOKUP(K16,$A$1:$H$37,5,0) -> 71000 | P16: =VLOOKUP(K16,$A$1:$H$37,6,0) -> 54249 | Q16: =VLOOKUP(K16,$A$1:$H$37,7,0) -> 4800
A17: 45216 | B17: =D17*0.39 -> 35948.25 | C17: =D17-B17 -> 56226.75 | D17: =E17+F17+G17 -> 92175 | E17: 63000 | F17: 21475 | G17: 7700 | H17: =IFERROR(B17/C17,0) -> 0.63934426 | I17: =SUM($D$2:D17)-SUM($G$2:G17) -> 1103451.1 | K17: =A12 -> 45211 | L17: =N17*0.3 -> 14897.1 | M17: =N17-L17 -> 34759.9 | N17: =O17+P17 -> 49657 | O17: =VLOOKUP(K17,$A$1:$H$37,5,0) -> 7000 | P17: =VLOOKUP(K17,$A$1:$H$37,6,0) -> 42657 | Q17: =VLOOKUP(K17,$A$1:$H$37,7,0) -> 1650
A18: 45217 | B18: =D18*0.39 -> 26715 | C18: =D18-B18 -> 41785 | D18: =E18+F18+G18 -> 68500 | E18: 46000 | F18: 15500 | G18: 7000 | H18: =IFERROR(B18/C18,0) -> 0.63934426 | I18: =SUM($D$2:D18)-SUM($G$2:G18) -> 1164951.1 | K18: =A13 -> 45212 | L18: =N18*0.3 -> 7506.9 | M18: =N18-L18 -> 17516.1 | N18: =O18+P18 -> 25023 | O18: =VLOOKUP(K18,$A$1:$H$37,5,0) -> 10000 | P18: =VLOOKUP(K18,$A$1:$H$37,6,0) -> 15023 | Q18: =VLOOKUP(K18,$A$1:$H$37,7,0) -> 5400
A19: 45218 | B19: =D19*0.39 -> 48405.63 | C19: =D19-B19 -> 75711.37 | D19: =E19+F19+G19 -> 124117 | E19: 65500 | F19: 51617 | G19: 7000 | H19: =IFERROR(B19/C19,0) -> 0.63934426 | I19: =SUM($D$2:D19)-SUM($G$2:G19) -> 1282068.1 | K19: =A14 -> 45213 | L19: =N19*0.3 -> 33539.1 | M19: =N19-L19 -> 78257.9 | N19: =O19+P19 -> 111797 | O19: =VLOOKUP(K19,$A$1:$H$37,5,0) -> 54500 | P19: =VLOOKUP(K19,$A$1:$H$37,6,0) -> 57297 | Q19: =VLOOKUP(K19,$A$1:$H$37,7,0) -> 4300
A20: 45219 | B20: =D20*0.39 -> 98188.74 | C20: =D20-B20 -> 153577.26 | D20: =E20+F20+G20 -> 251766 | E20: 114500 | F20: 78116 | G20: 59150 | H20: =IFERROR(B20/C20,0) -> 0.63934426 | I20: =SUM($D$2:D20)-SUM($G$2:G20) -> 1474684.1 | K20: =A15 -> 45214 | L20: =N20*0.3 -> 41503.8 | M20: =N20-L20 -> 96842.2 | N20: =O20+P20 -> 138346 | O20: =VLOOKUP(K20,$A$1:$H$37,5,0) -> 75000 | P20: =VLOOKUP(K20,$A$1:$H$37,6,0) -> 63346 | Q20: =VLOOKUP(K20,$A$1:$H$37,7,0) -> 9000
A21: 45220 | B21: =D21*0.39 -> 41712.45 | C21: =D21-B21 -> 65242.55 | D21: =E21+F21+G21 -> 106955 | E21: 31500 | F21: 65455 | G21: 10000 | H21: =IFERROR(B21/C21,0) -> 0.63934426 | I21: =SUM($D$2:D21)-SUM($G$2:G21) -> 1571639.1 | K21: Total | L21: =SUM(L14:L20) -> 184666.2 | M21: =SUM(M14:M20) -> 430887.8 | N21: =SUM(N14:N20) -> 615554 | O21: =SUM(O14:O20) -> 259600 | P21: =SUM(P14:P20) -> 355954 | Q21: =SUM(Q14:Q20) -> 34000
A22: 45221 | B22: =D22*0.39 -> 51129.39 | C22: =D22-B22 -> 79971.61 | D22: =E22+F22+G22 -> 131101 | E22: 114600 | F22: 12901 | G22: 3600 | H22: =IFERROR(B22/C22,0) -> 0.63934426 | I22: =SUM($D$2:D22)-SUM($G$2:G22) -> 1699140.1 | K22: Mul Bhag | L22: =L21/3 -> 61555.4 | N22: =M22+L22 -> 61555.4
A23: 45222 | B23: =D23*0.39 -> 10218 | C23: =D23-B23 -> 15982 | D23: =E23+F23+G23 -> 26200 | E23: 11800 | F23: 8710 | G23: 5690 | H23: =IFERROR(B23/C23,0) -> 0.63934426 | I23: =SUM($D$2:D23)-SUM($G$2:G23) -> 1719650.1 | M23: ser
A24: 45223 | B24: =D24*0.39 -> 34788 | C24: =D24-B24 -> 54412 | D24: =E24+F24+G24 -> 89200 | E24: 66700 | F24: 16800 | G24: 5700 | H24: =IFERROR(B24/C24,0) -> 0.63934426 | I24: =SUM($D$2:D24)-SUM($G$2:G24) -> 1803150.1 | K24: Date | L24: Profit | M24: Actual | N24: Total | O24: Cash | P24: Account Transfer | Q24: Expense
A25: 45224 | B25: =D25*0.39 -> 129336.09 | C25: =D25-B25 -> 202294.91 | D25: =E25+F25+G25 -> 331631 | E25: 167200 | F25: 21231 | G25: 143200 | H25: =IFERROR(B25/C25,0) -> 0.63934426 | I25: =SUM($D$2:D25)-SUM($G$2:G25) -> 1991581.1 | K25: =A16 -> 45215 | L25: =N25*0.3 -> 21978 | M25: =N25-L25 -> 51282 | N25: =O25+P25 -> 73260 | O25: 0 | P25: =VLOOKUP(K25,$A$1:$H$37,6,0) -> 73260 | Q25: =VLOOKUP(K25,$A$1:$H$37,7,0) -> 5500
A26: 45225 | B26: =D26*0.39 -> 101869.56 | C26: =D26-B26 -> 159334.44 | D26: =E26+F26+G26 -> 261204 | E26: 228600 | F26: 29604 | G26: 3000 | H26: =IFERROR(B26/C26,0) -> 0.63934426 | I26: =SUM($D$2:D26)-SUM($G$2:G26) -> 2249785.1 | K26: =A17 -> 45216 | L26: =N26*0.3 -> 25342.5 | M26: =N26-L26 -> 59132.5 | N26: =O26+P26 -> 84475 | O26: =VLOOKUP(K26,$A$1:$H$37,5,0) -> 63000 | P26: =VLOOKUP(K26,$A$1:$H$37,6,0) -> 21475 | Q26: =VLOOKUP(K26,$A$1:$H$37,7,0) -> 7700
A27: 45226 | B27: =D27*0.39 -> 178105.2 | C27: =D27-B27 -> 278574.8 | D27: =E27+F27+G27 -> 456680 | E27: 262800 | F27: 98240 | G27: 95640 | H27: =IFERROR(B27/C27,0) -> 0.63934426 | I27: =SUM($D$2:D27)-SUM($G$2:G27) -> 2610825.1 | K27: =A18 -> 45217 | L27: =N27*0.3 -> 18450 | M27: =N27-L27 -> 43050 | N27: =O27+P27 -> 61500 | O27: =VLOOKUP(K27,$A$1:$H$37,5,0) -> 46000 | P27: =VLOOKUP(K27,$A$1:$H$37,6,0) -> 15500 | Q27: =VLOOKUP(K27,$A$1:$H$37,7,0) -> 7000
A28: 45227 | B28: =D28*0.39 -> 133630.38 | C28: =D28-B28 -> 209011.62 | D28: =E28+F28+G28 -> 342642 | E28: 264500 | F28: 75142 | G28: 3000 | H28: =IFERROR(B28/C28,0) -> 0.63934426 | I28: =SUM($D$2:D28)-SUM($G$2:G28) -> 2950467.1 | K28: =A19 -> 45218 | L28: =N28*0.3 -> 35135.1 | M28: =N28-L28 -> 81981.9 | N28: =O28+P28 -> 117117 | O28: =VLOOKUP(K28,$A$1:$H$37,5,0) -> 65500 | P28: =VLOOKUP(K28,$A$1:$H$37,6,0) -> 51617 | Q28: =VLOOKUP(K28,$A$1:$H$37,7,0) -> 7000
A29: 45228 | B29: =D29*0.39 -> 129743.25 | C29: =D29-B29 -> 202931.75 | D29: =E29+F29+G29 -> 332675 | E29: 268800 | F29: 57075 | G29: 6800 | H29: =IFERROR(B29/C29,0) -> 0.63934426 | I29: =SUM($D$2:D29)-SUM($G$2:G29) -> 3276342.1 | K29: =A20 -> 45219 | L29: =N29*0.3 -> 57784.8 | M29: =N29-L29 -> 134831.2 | N29: =O29+P29 -> 192616 | O29: =VLOOKUP(K29,$A$1:$H$37,5,0) -> 114500 | P29: =VLOOKUP(K29,$A$1:$H$37,6,0) -> 78116 | Q29: =VLOOKUP(K29,$A$1:$H$37,7,0) -> 59150
A30: 45229 | B30: =D30*0.39 -> 109790.85 | C30: =D30-B30 -> 171724.15 | D30: =E30+F30+G30 -> 281515 | E30: 200000 | F30: 77515 | G30: 4000 | H30: =IFERROR(B30/C30,0) -> 0.63934426 | I30: =SUM($D$2:D30)-SUM($G$2:G30) -> 3553857.1 | K30: =A21 -> 45220 | L30: =N30*0.3 -> 29086.5 | M30: =N30-L30 -> 67868.5 | N30: =O30+P30 -> 96955 | O30: =VLOOKUP(K30,$A$1:$H$37,5,0) -> 31500 | P30: =VLOOKUP(K30,$A$1:$H$37,6,0) -> 65455 | Q30: =VLOOKUP(K30,$A$1:$H$37,7,0) -> 10000
A31: 45230 | B31: =D31*0.39 -> 99699.6 | C31: =D31-B31 -> 155940.4 | D31: =E31+F31+G31 -> 255640 | E31: 115000 | F31: 136640 | G31: 4000 | H31: =IFERROR(B31/C31,0) -> 0.63934426 | I31: =SUM($D$2:D31)-SUM($G$2:G31) -> 3805497.1 | K31: =A22 -> 45221 | L31: =N31*0.3 -> 38250.3 | M31: =N31-L31 -> 89250.7 | N31: =O31+P31 -> 127501 | O31: =VLOOKUP(K31,$A$1:$H$37,5,0) -> 114600 | P31: =VLOOKUP(K31,$A$1:$H$37,6,0) -> 12901 | Q31: =VLOOKUP(K31,$A$1:$H$37,7,0) -> 3600
A32: 45200 | B32: =D32*0.39 -> 8067.93 | C32: =D32-B32 -> 12619.07 | D32: =E32+F32+G32 -> 20687 | E32: 7110 | F32: 9877 | G32: 3700 | H32: =IFERROR(B32/C32,0) -> 0.63934426 | I32: =SUM($D$2:D32)-SUM($G$2:G32) -> 3822484.1 | K32: Total | L32: =SUM(L25:L31) -> 226027.2 | M32: =SUM(M25:M31) -> 527396.8 | N32: =SUM(N25:N31) -> 753424 | O32: =SUM(O25:O31) -> 435100 | P32: =SUM(P25:P31) -> 318324 | Q32: =SUM(Q25:Q31) -> 99950
A33: 45232 | B33: =D33*0.39 -> 0 | C33: =D33-B33 -> 0 | D33: =E33+F33+G33 -> 0 | H33: =IFERROR(B33/C33,0) -> 0 | I33: =SUM($D$2:D33)-SUM($G$2:G33) -> 3822484.1 | K33: Mul Bhag | L33: =L32/3 -> 75342.4
A34: 45233 | B34: =D34*0.39 -> 0 | C34: =D34-B34 -> 0 | D34: =E34+F34+G34 -> 0 | H34: =IFERROR(B34/C34,0) -> 0 | I34: =SUM($D$2:D34)-SUM($G$2:G34) -> 3822484.1
A35: 45234 | B35: =D35*0.39 -> 0 | C35: =D35-B35 -> 0 | D35: =E35+F35+G35 -> 0 | H35: =IFERROR(B35/C35,0) -> 0 | I35: =SUM($D$2:D35)-SUM($G$2:G35) -> 3822484.1 | K35: Date | L35: Profit | M35: Actual | N35: Total | O35: Cash | P35: Account Transfer | Q35: Expense
A36: 45235 | B36: =D36*0.39 -> 0 | C36: =D36-B36 -> 0 | D36: =E36+F36+G36 -> 0 | H36: =IFERROR(B36/C36,0) -> 0 | I36: =SUM($D$2:D36)-SUM($G$2:G36) -> 3822484.1 | K36: =A23 -> 45222 | L36: =N36*0.3 -> 6153 | M36: =N36-L36 -> 14357 | N36: =O36+P36 -> 20510 | O36: =VLOOKUP(K36,$A$1:$H$37,5,0) -> 11800 | P36: =VLOOKUP(K36,$A$1:$H$37,6,0) -> 8710 | Q36: =VLOOKUP(K36,$A$1:$H$37,7,0) -> 5690
A37: Total | B37: =SUM(B2:B36) -> 1665453.7 | C37: =SUM(C2:C36) -> 2604940.4 | D37: =SUM(D2:D36) -> 4270394.1 | E37: =SUM(E2:E36) -> 2496280 | F37: =SUM(F2:F36) -> 1326204.1 | G37: =SUM(G2:G36) -> 447910 | H37: =SUM(H2:H36) -> 19.819672 | I37: =SUM(I2:I36) -> 57801609 | K37: =A24 -> 45223 | L37: =N37*0.3 -> 25050 | M37: =N37-L37 -> 58450 | N37: =O37+P37 -> 83500 | O37: =VLOOKUP(K37,$A$1:$H$37,5,0) -> 66700 | P37: =VLOOKUP(K37,$A$1:$H$37,6,0) -> 16800 | Q37: =VLOOKUP(K37,$A$1:$H$37,7,0) -> 5700
B38: =B37/3 -> 555151.23 | E38: =D37*0.42 -> 1793565.5 | K38: =A25 -> 45224 | L38: =N38*0.3 -> 56529.3 | M38: =N38-L38 -> 131901.7 | N38: =O38+P38 -> 188431 | O38: =VLOOKUP(K38,$A$1:$H$37,5,0) -> 167200 | P38: =VLOOKUP(K38,$A$1:$H$37,6,0) -> 21231 | Q38: =VLOOKUP(K38,$A$1:$H$37,7,0) -> 143200
B39: =B38*100/D37 -> 13 | E39: =E38/3 -> 597855.17 | K39: =A26 -> 45225 | L39: =N39*0.3 -> 77461.2 | M39: =N39-L39 -> 180742.8 | N39: =O39+P39 -> 258204 | O39: =VLOOKUP(K39,$A$1:$H$37,5,0) -> 228600 | P39: =VLOOKUP(K39,$A$1:$H$37,6,0) -> 29604 | Q39: =VLOOKUP(K39,$A$1:$H$37,7,0) -> 3000
A40: Date | B40: Profit | C40: Actual | D40: Total | E40: Cash | F40: Account Transfer | G40: Expense | H40: Mul Bhag | K40: =A27 -> 45226 | L40: =N40*0.3 -> 108312 | M40: =N40-L40 -> 252728 | N40: =O40+P40 -> 361040 | O40: =VLOOKUP(K40,$A$1:$H$37,5,0) -> 262800 | P40: =VLOOKUP(K40,$A$1:$H$37,6,0) -> 98240 | Q40: =VLOOKUP(K40,$A$1:$H$37,7,0) -> 95640
A41: =CONCATENATE(TEXT(K3,"DD-MMM-YYY")," to ",TEXT(K9,"DD-MMM-YYYY")) -> 02-Oct-2023 to 08-Oct-2023 | B41: =L10 -> 85098.63 | C41: =M10 -> 198563.47 | D41: =N10 -> 283662.1 | E41: =O10 -> 162570 | F41: =P10 -> 121092.1 | G41: =Q10 -> 39230 | H41: =B41/3 -> 28366.21 | K41: =A28 -> 45227 | L41: =N41*0.3 -> 101892.6 | M41: =N41-L41 -> 237749.4 | N41: =O41+P41 -> 339642 | O41: =VLOOKUP(K41,$A$1:$H$37,5,0) -> 264500 | P41: =VLOOKUP(K41,$A$1:$H$37,6,0) -> 75142 | Q41: =VLOOKUP(K41,$A$1:$H$37,7,0) -> 3000
A42: =CONCATENATE(TEXT(K14,"DD-MMM-YYY")," to ",TEXT(K20,"DD-MMM-YYYY")) -> 09-Oct-2023 to 15-Oct-2023 | B42: =L21 -> 184666.2 | C42: =M21 -> 430887.8 | D42: =N21 -> 615554 | E42: =O21 -> 259600 | F42: =P21 -> 355954 | G42: =Q21 -> 34000 | H42: =B42/3 -> 61555.4 | K42: =A29 -> 45228 | L42: =N42*0.3 -> 97762.5 | M42: =N42-L42 -> 228112.5 | N42: =O42+P42 -> 325875 | O42: =VLOOKUP(K42,$A$1:$H$37,5,0) -> 268800 | P42: =VLOOKUP(K42,$A$1:$H$37,6,0) -> 57075 | Q42: =VLOOKUP(K42,$A$1:$H$37,7,0) -> 6800
A43: =CONCATENATE(TEXT(K25,"DD-MMM-YYY")," to ",TEXT(K31,"DD-MMM-YYYY")) -> 16-Oct-2023 to 22-Oct-2023 | B43: =L32 -> 226027.2 | C43: =M32 -> 527396.8 | D43: =N32 -> 753424 | E43: =O32 -> 435100 | F43: =P32 -> 318324 | G43: =Q32 -> 99950 | H43: =B43/3 -> 75342.4 | K43: Total | L43: =SUM(L36:L42) -> 473160.6 | M43: =SUM(M36:M42) -> 1104041.4 | N43: =SUM(N36:N42) -> 1577202 | O43: =SUM(O36:O42) -> 1270400 | P43: =SUM(P36:P42) -> 306802 | Q43: =SUM(Q36:Q42) -> 263030
A44: =CONCATENATE(TEXT(K36,"DD-MMM-YYY")," to ",TEXT(K42,"DD-MMM-YYYY")) -> 23-Oct-2023 to 29-Oct-2023 | B44: =L43 -> 473160.6 | C44: =M43 -> 1104041.4 | D44: =N43 -> 1577202 | E44: =O43 -> 1270400 | F44: =P43 -> 306802 | G44: =Q43 -> 263030 | H44: =B44/3 -> 157720.2 | K44: Mul Bhag | L44: =L43/3 -> 157720.2
A45: =CONCATENATE(TEXT(K47,"DD-MMM-YYY")," to ",TEXT(K53,"DD-MMM-YYYY")) -> 30-Oct-2023 to 05-Nov-2023 | B45: =L54 -> 163842.6 | C45: =M54 -> 382299.4 | D45: =N54 -> 546142 | E45: =O54 -> 322110 | F45: =P54 -> 224032 | G45: =Q54 -> 11700 | H45: =B45/3 -> 54614.2
A46: =CONCATENATE(TEXT(K59,"DD-MMM-YYY")," to ",TEXT(K58,"DD-MMM-YYYY")) -> 06-Oct-2023 to Date | B46: =SUM(B41:B45) -> 1132795.2 | C46: =SUM(C41:C45) -> 2643188.9 | D46: =SUM(D41:D45) -> 3775984.1 | E46: =SUM(E41:E45) -> 2449780 | F46: =SUM(F41:F45) -> 1326204.1 | G46: =SUM(G41:G45) -> 447910 | H46: =SUM(H41:H45) -> 377598.41 | K46: Date | L46: Profit | M46: Actual | N46: Total | O46: Cash | P46: Account Transfer | Q46: Expense
C47: Total | K47: =A30 -> 45229 | L47: =N47*0.3 -> 83254.5 | M47: =N47-L47 -> 194260.5 | N47: =O47+P47 -> 277515 | O47: =VLOOKUP(K47,$A$1:$H$37,5,0) -> 200000 | P47: =VLOOKUP(K47,$A$1:$H$37,6,0) -> 77515 | Q47: =VLOOKUP(K47,$A$1:$H$37,7,0) -> 4000
K48: =A31 -> 45230 | L48: =N48*0.3 -> 75492 | M48: =N48-L48 -> 176148 | N48: =O48+P48 -> 251640 | O48: =VLOOKUP(K48,$A$1:$H$37,5,0) -> 115000 | P48: =VLOOKUP(K48,$A$1:$H$37,6,0) -> 136640 | Q48: =VLOOKUP(K48,$A$1:$H$37,7,0) -> 4000
K49: =A32 -> 45200 | L49: =N49*0.3 -> 5096.1 | M49: =N49-L49 -> 11890.9 | N49: =O49+P49 -> 16987 | O49: =VLOOKUP(K49,$A$1:$H$37,5,0) -> 7110 | P49: =VLOOKUP(K49,$A$1:$H$37,6,0) -> 9877 | Q49: =VLOOKUP(K49,$A$1:$H$37,7,0) -> 3700
K50: =A33 -> 45232 | L50: =N50*0.3 -> 0 | M50: =N50-L50 -> 0 | N50: =O50+P50 -> 0 | O50: =VLOOKUP(K50,$A$1:$H$37,5,0) -> 0 | P50: =VLOOKUP(K50,$A$1:$H$37,6,0) -> 0 | Q50: =VLOOKUP(K50,$A$1:$H$37,7,0) -> 0
K51: =A34 -> 45233 | L51: =N51*0.3 -> 0 | M51: =N51-L51 -> 0 | N51: =O51+P51 -> 0 | O51: =VLOOKUP(K51,$A$1:$H$37,5,0) -> 0 | P51: =VLOOKUP(K51,$A$1:$H$37,6,0) -> 0 | Q51: =VLOOKUP(K51,$A$1:$H$37,7,0) -> 0
K52: =A35 -> 45234 | L52: =N52*0.3 -> 0 | M52: =N52-L52 -> 0 | N52: =O52+P52 -> 0 | O52: =VLOOKUP(K52,$A$1:$H$37,5,0) -> 0 | P52: =VLOOKUP(K52,$A$1:$H$37,6,0) -> 0 | Q52: =VLOOKUP(K52,$A$1:$H$37,7,0) -> 0
K53: =A36 -> 45235 | L53: =N53*0.3 -> 0 | M53: =N53-L53 -> 0 | N53: =O53+P53 -> 0 | O53: =VLOOKUP(K53,$A$1:$H$37,5,0) -> 0 | P53: =VLOOKUP(K53,$A$1:$H$37,6,0) -> 0 | Q53: =VLOOKUP(K53,$A$1:$H$37,7,0) -> 0
K54: Total | L54: =SUM(L47:L53) -> 163842.6 | M54: =SUM(M47:M53) -> 382299.4 | N54: =SUM(N47:N53) -> 546142 | O54: =SUM(O47:O53) -> 322110 | P54: =SUM(P47:P53) -> 224032 | Q54: =SUM(Q47:Q53) -> 11700
K55: Mul Bhag | L55: =L54/3 -> 54614.2
K58: Date | L58: Profit | M58: Actual | N58: Total | O58: Cash | P58: Account Transfer | Q58: Expense
