Workbook

Sheet Forecast
A2: Loan From BOB | B2: 1500000 | D2: Dharmesh Loan | H2: 80000
D3: Cred | E3: 320000 | H3: 70000
D4: Bajaj | E4: 125000 | H4: 60000
D5: Early Salary | E5: =17800*5 -> 89000
D6: Navi | E6: 280000 | H6: =SUM(H2:H5) -> 210000
D7: Axis | E7: 271000 | F7: Credit card
D8: Axis | E8: 271000 | F8: Credit card
D9: Hdfc | E9: 273000
D10: Citi | E10: 78000
D11: SBI | E11: 69000
D12: SBI | E12: 75000
D13: SBI | E13: 25000
D14: RBL | E14: 20000
E16: =SUM(E3:E15) -> 1896000

Sheet Diwali 2025
A1: Diwali 2025(01-Sept-2025 to 22-Oct-2025)
A2: Income
A3: 01-Sept-25 to 30-Sept-25 | B3: 956793
A4: Oct 2025 Sale | B4: 4652048
A5: Total Sale | B5: =SUM(B3:B4) -> 5608841
A10: Expense
A11: 01-Sept-25 to 30-Sept-25 | B11: 105202
A12: Oct 2025 Cash | B12: 170930
A13: Oct 2025 Online | B13: 365012.56
A14: Gold Loan Closure | B14: 1238266
A15: Gold Loan Closure | B15: 1253049
A16: Sept 2025 Rent | B16: 110000
A17: Oct 2025 Rent | B17: 110000
A18: Sept Mul Bhag | B18: =B3*0.1 -> 95679.3
A19: Oct Mul Bhag | B19: =B4*0.1 -> 465204.8

Sheet EMI
A1: EMI Chart Ocotober 2025 | I1: Income | O1: Daily Payment System
A2: Owner | B2: Type | C2: Bank | D2: EMI Date | E2: Amount | F2: Outstanding | G2: Status | I2: Month | J2: Mulbhag | K2: Profit | L2: Actual | M2: Total | O2: Date | P2: Home | Q2: Mulbhag | R2: Bank | S2: Salary | T2: Vendor
A3: Dharmesh | B3: CC | C3: HDFC CC | D3: 45956 | E3: =F3*0.022 -> 6006 | F3: 273000 | G3: PAID | H3: =SUMIFS(E3:E24,D3:D24,TODAY(),G3:G24,"") -> 0 | I3: 45597 | J3: 74746.2 | K3: 224238.6 | L3: 523223.4 | M3: 747462 | O3: Amount--> | P3: 2000 | Q3: 10000 | R3: 1000 | S3: 2000 | T3: 5000 | U3: =SUM(P3:T3) -> 20000
A4: Dharmesh | B4: CC | C4: Tata Card CC | D4: 45960 | E4: =F4*0.0215 -> 537.5 | F4: 25000 | G4: PAID | I4: 45627 | J4: 81472.1 | K4: 244416.3 | L4: 244416.3 | M4: 814721 | O4: 45942
A5: Vinod | B5: CC | C5: SBI CC | D5: 45962 | E5: =F5*0.025 -> 9375 | F5: 375000 | G5: PAID | I5: 45658 | J5: 65232.5 | K5: 195697.5 | L5: 195697.5 | M5: 652325 | O5: 45943
A6: Yagnesh | B6: CC | C6: RBL | D6: 45963 | E6: 9823 | F6: 200000 | G6: PAID | I6: 45689 | J6: 55399.5 | K6: 166198.5 | L6: 166198.5 | M6: 553995 | O6: 45944
A7: Chetan SIP | B7: CC | C7: IDFC | D7: 45965 | E7: 20000 | F7: 360000 | G7: paid | I7: 45809 | J7: 62522.8 | K7: 187568.4 | L7: 187568.4 | M7: 561037 | O7: 45945
A8: Dharmesh | B8: CC | C8: SBI CC | D8: 45965 | E8: =F8*0.025 -> 1725 | F8: 69000 | G8: PAID | I8: 45748 | J8: =K8/3 -> 54742.7 | K8: 164228.1 | L8: 164228.1 | M8: 547427 | O8: 45946
A9: Dharmesh | B9: CC | C9: Bajaj | D9: 45965 | E9: 18600 | F9: 450000 | G9: paid | M9: =SUM(M3:M8) -> 3876967 | O9: 45947
A10: Arun | B10: EMI | C10: ICICI ML | D10: 45966 | E10: 37000 | F10: 2368000 | G10: paid | O10: 45948
A11: Vinod | B11: CC | C11: HDFC Jumbo | D11: 45966 | E11: =6538+8530 -> 15068 | F11: 250000 | G11: paid | I11: Balance | L11: =TODAY() -> 45983 | O11: 45949
A12: Chetan HDFC | B12: EMI | C12: HDFC | D12: 45967 | E12: 12900 | F12: 750000 | G12: paid | H12: 12900 | I12: BOB | J12: 31170 | O12: 45950
A13: Dharmesh | B13: EMI | C13: HDFC PL | D13: 45967 | E13: 59663 | F13: 2800000 | G13: PAID | I13: Cash | J13: 5000 | O13: 45951
A14: Vinod | B14: CC | C14: HDFC CC | D14: 45967 | E14: =F14*0.0215 -> 14663 | F14: 682000 | G14: PAID | I14: BOB | O14: 45952
A15: Dharmesh | B15: CC | C15: Axis Priveldege | D15: 45968 | E15: =F15*0.025 -> 6143.275 | F15: 245731 | G15: PAID | I15: =L11 -> 45983 | J15: 0 | O15: 45953
A16: Dharmesh | B16: CC | C16: RBL CC | D16: 45968 | E16: 1100 | F16: 17000 | G16: PAID | I16: =$L$11+1 -> 45984 | J16: 20000 | O16: 45954
A17: Yagnesh | B17: CC | C17: HSBC CC | D17: 45968 | E17: 13185 | F17: 217000 | G17: PAID | I17: =$L$11+2 -> 45985 | J17: 20000 | O17: 45955
A18: Yagnesh | B18: CC | C18: HDFC CC | D18: 45970 | E18: 11532 | F18: 205000 | G18: PAID | I18: =$L$11+3 -> 45986 | J18: 20000 | O18: 45956
A19: Arun | B19: Credit card Repayment | C19: ALL CC | D19: 45971 | E19: 70000 | F19: 500000 | G19: PAID | I19: =$L$11+4 -> 45987 | P19: =COUNTA(P4:P18)*P3 -> 0 | Q19: =COUNTA(Q4:Q18)*Q3 -> 0 | R19: =COUNTA(R4:R18)*R3 -> 0 | S19: =COUNTA(S4:S18)*S3 -> 0 | T19: =COUNTA(T4:T18)*T3 -> 0 | U19: =COUNTA(U4:U18)*U3 -> 0
A20: Arun | B20: EMI | C20: ICICI | D20: 45971 | E20: 35000 | F20: 608000 | G20: Paid | I20: =$L$11+5 -> 45988
A21: Dharmesh | B21: CC | C21: SBI CC | D21: 45971 | E21: =F21*0.0218 -> 1635 | F21: 75000 | G21: Paid | I21: =$L$11+6 -> 45989
A22: Dharmesh | B22: CC | C22: Citi -Axis | D22: 45971 | E22: 3891 | F22: 31800 | G22: Paid | I22: =$L$11+7 -> 45990
A23: Dharmesh | B23: CC | C23: Axis MM | D23: 45971 | E23: =F23*0.025 -> 6825 | F23: 273000 | G23: Paid | I23: udhar | J23: =N28 -> 0
A24: Narottam | B24: EMI | C24: Bharat bank | D24: 45971 | E24: 35000 | F24: 3400000 | G24: Paid | I24: Total | J24: =SUM(J12:J23) -> 96170
A25: Yagnesh | B25: CC | C25: AXIS Citi | D25: 45971 | E25: 6500 | F25: 108000 | G25: Paid | I25: EMI | J25: =SUMIF(G3:G24,"",E3:E24) -> 0
A26: Total | E26: =SUM(E3:E25) -> 396171.78 | F26: =SUM(F3:F25) -> 14282531 | I26: Balance | J26: =J24-J25 -> 96170
E27: =SUMIF(G3:G25,"",E3:E25) -> 0 | F27: =400000-E27 -> 400000 | K27: =SUM(K14:K26) -> 0
E28: 133164 | J28: =N32-K27 -> 0
E29: =E27-E28 -> -133164

Sheet Forecast 2025
A1: Vendor Name | B1: Balance Amount | C1: Payment Amount | D1: Balance Amount | E1: Payment Date | F1: Actual Payment | G1: Remarks | H1: Expense | J1: Income | L1: As on 18-05-25 | M1: =TODAY() -> 45983
A2: Raju kaka | B2: 3040 | D2: =B2-C2 -> 3040 | J2: Balance | L2: 45838
A3: Hareshbhai Than | B3: 39900 | D3: =B3-C3 -> 39900 | H3: Vendor Payment | I3: 148000 | J3: Daily Sales(01Nov to 30Nov) | K3: =20000*9 -> 180000 | L3: =L2-M1 -> -145
A4: HP | B4: =3695+2400 -> 6095 | D4: =B4-C4 -> 6095 | H4: Pune | I4: 40000 | J4: Udhar | K4: =I26 -> 920480
A5: Virar | B5: 18060 | D5: =B5-C5 -> 18060 | H5: Sekaran Malaysia | I5: 305000 | J5: HDFC | K5: 14000
A6: BOB Interest | B6: 30000 | C6: 30000 | D6: =B6-C6 -> 0 | H6: Grey Shade | I6: 46480 | J6: Bob | K6: 59000
A7: Ambalal | B7: 27710 | D7: =B7-C7 -> 27710 | H7: Dinner set | I7: 216000 | J7: ICICI
A8: Matala bandhavana | B8: 8000 | C8: 8000 | D8: =B8-C8 -> 0 | H8: Dukan Udhari | I8: =15000+15000+3000 -> 33000 | J8: Cash | K8: 3000
A9: Sajid Bhai | B9: 17680 | D9: =B9-C9 -> 17680 | H9: Fitoor Plate | I9: 100000
A10: Vakeel Saab | B10: 392000 | D10: =B10-C10 -> 392000 | H10: Girish | I10: 32000
A11: Akash Potterywale | B11: =40000+14000 -> 54000 | D11: =B11-C11 -> 54000
A12: Hukumpal | B12: =24580+7510+55500 -> 87590 | C12: 29602 | D12: =B12-C12 -> 57988
A13: Parth | B13: 32496 | D13: =B13-C13 -> 32496
A14: Dasrath | B14: 6000 | D14: =B14-C14 -> 6000
A15: Atul | B15: 125000 | D15: =B15-C15 -> 125000
A16: Silver | B16: 275000 | D16: =B16-C16 -> 275000
A17: tax + fees | B17: 105221 | C17: 105221 | D17: =B17-C17 -> 0
A18: EMI - Nov25 | B18: =EMI!E27 -> 0 | D18: =B18-C18 -> 0
A19: Light Bill | B19: 12000 | C19: 12000 | D19: =B19-C19 -> 0 | K19: =SUM(K2:K13) -> 1176480
A20: Salary | B20: 56000 | C20: 56000 | D20: =B20-C20 -> 0
A21: Rent | B21: 110000 | C21: 110000 | D21: =B21-C21 -> 0
A22: Mul bhag | B22: 100000 | C22: 70000 | D22: =B22-C22 -> 30000
D23: =B23-C23 -> 0
A24: Total | B24: =SUM(B2:B23) -> 1505792 | C24: =SUM(C2:C23) -> 420823 | D24: =B24-C24 -> 1084969
H26: Total | I26: =SUM(I3:I25) -> 920480
H27: Balance | I27: =K19-D24 -> 91511

Sheet Loan 062025
A1: Owner | B1: Type | C1: Bank | D1: EMI Date | E1: Amount | F1: Outstanding | H1: After EMI | J1: Owner | K1: Type | L1: Bank | M1: EMI Date | N1: Amount | O1: Outstanding | P1: Paid | Q1: Remaining OS | S1: Income
A2: Dharmesh | B2: CC | C2: HDFC CC | D2: 45834 | E2: 9985 | F2: 257406 | G2: =F2 -> 257406 | H2: =IF(G2="",E2,0) -> 0 | I2: =IF(G2<>"",E2,0) -> 9985 | J2: Dharmesh | K2: EMI | L2: Early Salary | M2: 45810 | N2: 17247 | O2: 80436 | P2: 80436 | Q2: =O2-P2 -> 0 | S2: Owner | T2: Source | U2: Bank | V2: Amount | W2: Remarks
A3: Dharmesh | B3: CC | C3: Tata Card CC | D3: 45838 | E3: 2500 | F3: 25000 | G3: =F3 -> 25000 | H3: =IF(G3="",E3,0) -> 0 | I3: =IF(G3<>"",E3,0) -> 2500 | J3: Dharmesh | K3: EMI | L3: VIVIF | M3: 45808 | N3: 5700 | O3: 118000 | P3: 118000 | Q3: =O3-P3 -> 0 | S3: Arun | T3: Salary | U3: SBI | V3: 824543 | W3: Account
A4: Vinod | B4: CC | C4: SBI CC | D4: 45839 | E4: =F4*0.025 -> 3069.875 | F4: 122795 | G4: =F4 -> 122795 | H4: =IF(G4="",E4,0) -> 0 | I4: =IF(G4<>"",E4,0) -> 3069.875 | J4: Dharmesh | K4: EMI | L4: Navi | M4: 45811 | N4: 9999 | O4: 278749 | P4: 278749 | Q4: =O4-P4 -> 0 | S4: Arun | T4: Salary | U4: SBI NRO | V4: 69000 | W4: Account
A5: Yagnesh | B5: CC | C5: RBL | D5: 45840 | E5: 9823 | F5: =200000-38000 -> 162000 | G5: =F5 -> 162000 | H5: =IF(G5="",E5,0) -> 0 | I5: =IF(G5<>"",E5,0) -> 9823 | J5: Dharmesh | K5: EMI | L5: Cred | M5: 45810 | N5: 17544 | O5: 278894 | P5: 278894 | Q5: =O5-P5 -> 0 | S5: Dharmesh | T5: Salary | U5: HDFC | V5: 40000 | W5: Account
A6: Dharmesh | B6: EMI | C6: Bajaj | D6: 45840 | E6: 32392 | F6: =E6 -> 32392 | G6: 0 | H6: =IF(G6="",E6,0) -> 0 | I6: =IF(G6<>"",E6,0) -> 32392 | J6: Dharmesh | K6: EMI | L6: Kreditbee | M6: 45812 | N6: 3186 | O6: 24000 | P6: 8000 | Q6: =O6-P6 -> 16000 | S6: Total | V6: =SUM(V3:V5) -> 933543
A7: Dharmesh | B7: CC | C7: SBI CC | D7: 45842 | E7: =F7*0.025 -> 731.75 | F7: 29270 | G7: 69000 | H7: =IF(G7="",E7,0) -> 0 | I7: =IF(G7<>"",E7,0) -> 731.75 | J7: Dharmesh | K7: CC | L7: Tata Card CC | M7: 45807 | N7: 2500 | O7: 20000 | P7: 3000 | Q7: =O7-P7 -> 17000 | S7: LIC | T7: LIC | U7: IOB | V7: 282635 | W7: Addition
A8: Dharmesh | B8: EMI | C8: Kreditbee | D8: 45842 | E8: 3186 | F8: 15000 | G8: 15000 | H8: =IF(G8="",E8,0) -> 0 | I8: =IF(G8<>"",E8,0) -> 3186 | J8: Dharmesh | K8: CC | L8: RBL CC | M8: 45815 | N8: 1300 | O8: 20000 | P8: 3000 | Q8: =O8-P8 -> 17000 | S8: Total | V8: =V6+V7 -> 1216178
A9: Vinod | B9: CC | C9: HDFC CC | D9: 45844 | E9: =F9*0.05 -> 3468.15 | F9: 69363 | G9: 69363 | H9: =IF(G9="",E9,0) -> 0 | I9: =IF(G9<>"",E9,0) -> 3468.15 | J9: Dharmesh | K9: CC | L9: HDFC CC | M9: 45803 | N9: 9985 | O9: 273000 | P9: 253500 | Q9: =O9-P9 -> 19500
A10: Vinod | B10: CC | C10: HDFC Jumbo | D10: 45843 | E10: =6538+8530 -> 15068 | F10: 200000 | H10: =IF(G10="",E10,0) -> 15068 | I10: =IF(G10<>"",E10,0) -> 0 | J10: Dharmesh | K10: EMI | L10: Bajaj | M10: 45810 | N10: 32392 | O10: 32392 | P10: 0 | Q10: =O10-P10 -> 32392 | S10: Expense
A11: Arun | B11: EMI | C11: ICICI ML | D11: 45843 | E11: 37000 | F11: 860000 | H11: =IF(G11="",E11,0) -> 37000 | I11: =IF(G11<>"",E11,0) -> 0 | J11: Dharmesh | K11: CC | L11: Axis Priveldege | M11: 45815 | N11: 6320 | O11: 271000 | P11: 233566 | Q11: =O11-P11 -> 37434 | S11: Owner | U11: Bank | V11: Amount | W11: Remarks | X11: Actual
A12: Dharmesh | B12: EMI | C12: HDFC PL | D12: 45844 | E12: 59663 | F12: 3100000 | H12: =IF(G12="",E12,0) -> 59663 | I12: =IF(G12<>"",E12,0) -> 0 | J12: Dharmesh | K12: CC | L12: SBI CC | M12: 45818 | N12: 6320 | O12: 75000 | P12: 25000 | Q12: =O12-P12 -> 50000 | S12: Dharmesh | U12: HDFC | V12: 700000 | W12: Credit Card Payment | X12: 700000
A13: Rajubhai | B13: EMI | C13: Bharat bank | D13: 45844 | E13: 32500 | F13: 850000 | H13: =IF(G13="",E13,0) -> 32500 | I13: =IF(G13<>"",E13,0) -> 0 | J13: Dharmesh | K13: CC | L13: SBI CC | M13: 45812 | N13: 6320 | O13: 69000 | P13: 6320 | Q13: =O13-P13 -> 62680 | S13: Arun | U13: ICICI | V13: 25000 | W13: Arun Personal | X13: 25000
A14: Yagnesh | B14: CC | C14: HSBC CC | D14: 45847 | E14: 11482 | F14: =389000-166175 -> 222825 | G14: =389000-166175 -> 222825 | H14: =IF(G14="",E14,0) -> 0 | I14: =IF(G14<>"",E14,0) -> 11482 | J14: Dharmesh | K14: CC | L14: Axis Citi | M14: 45819 | N14: 3500 | O14: 78000 | P14: 6000 | Q14: =O14-P14 -> 72000 | S14: Virar Tax | U14: SBI | V14: 20000 | W14: Virar Tax
A15: Dharmesh | B15: CC | C15: Axis Priveldege | D15: 45845 | E15: =F15*0.025 -> 6043.275 | F15: 241731 | G15: 241731 | H15: =IF(G15="",E15,0) -> 0 | I15: =IF(G15<>"",E15,0) -> 6043.275 | J15: Dharmesh | K15: CC | L15: Axis MM | M15: 45822 | N15: 1200 | O15: 271000 | P15: 176336 | Q15: =O15-P15 -> 94664 | S15: Ved Trusha Fees | U15: SBI | V15: 120000 | W15: School Fees
A16: Dharmesh | B16: CC | C16: RBL CC | D16: 45845 | E16: 1100 | F16: 18000 | G16: 18000 | H16: =IF(G16="",E16,0) -> 0 | I16: =IF(G16<>"",E16,0) -> 1100 | J16: Dharmesh | K16: EMI | L16: HDFC PL | M16: 45814 | N16: 59663 | O16: 3100000 | P16: 200000 | Q16: =O16-P16 -> 2900000 | S16: Dharmesh | U16: HDFC | V16: 40000 | W16: SIP
A17: Yagnesh | B17: CC | C17: ICICI CC | D17: 45846 | E17: 12740 | F17: 90000 | G17: 67000 | H17: =IF(G17="",E17,0) -> 0 | I17: =IF(G17<>"",E17,0) -> 12740 | O17: =SUM(O2:O16) -> 4989471 | Q17: =SUM(Q2:Q16) -> 3318670 | S17: Arun | U17: SBI NRO | V17: 9000 | W17: Balance | X17: 59000
A18: Yagnesh | B18: CC | C18: HDFC CC | D18: 45847 | E18: 11532 | F18: 263000 | G18: 263000 | H18: =IF(G18="",E18,0) -> 0 | I18: =IF(G18<>"",E18,0) -> 11532 | S18: Arun | U18: SBI NRO | V18: 19543 | W18: Balance | X18: 19543
A19: Dharmesh | B19: CC | C19: SBI CC | D19: 45848 | E19: =F19*0.0218 -> 1958.294 | F19: 89830 | G19: 89830 | H19: =IF(G19="",E19,0) -> 0 | I19: =IF(G19<>"",E19,0) -> 1958.294 | S19: Total | V19: =SUM(V12:V18) -> 933543
A20: Yagnesh | B20: CC | C20: AXIS Citi | D20: 45848 | E20: 6500 | F20: 110000 | G20: 110000 | H20: =IF(G20="",E20,0) -> 0 | I20: =IF(G20<>"",E20,0) -> 6500 | S20: LIC | T20: LIC | U20: IOB | V20: 282635 | W20: LIC | X20: 200000
A21: Arun | B21: EMI | C21: ICICI | D21: 45848 | E21: 35000 | F21: 1200000 | H21: =IF(G21="",E21,0) -> 35000 | I21: =IF(G21<>"",E21,0) -> 0 | S21: Grand Total | V21: =V19+V20 -> 1216178 | X21: =SUM(X12:X20) -> 1003543 | Y21: =V21-X21 -> 212635
A22: Narottam | B22: EMI | C22: Bharat bank | D22: 45848 | E22: 35000 | F22: 3500000 | H22: =IF(G22="",E22,0) -> 35000 | I22: =IF(G22<>"",E22,0) -> 0
A23: Dharmesh | B23: CC | C23: SBI CC | D23: 45848 | E23: =F23*0.025 -> 795 | F23: 31800 | G23: 75000 | H23: =IF(G23="",E23,0) -> 0 | I23: =IF(G23<>"",E23,0) -> 795
A24: Dharmesh | B24: CC | C24: Citi -Axis | D24: 45848 | E24: 3891 | F24: 31800 | G24: 78000 | H24: =IF(G24="",E24,0) -> 0 | I24: =IF(G24<>"",E24,0) -> 3891
A25: Dharmesh | B25: CC | C25: Axis MM | D25: 45848 | E25: =F25*0.025 -> 6775 | F25: 271000 | G25: 271000 | H25: =IF(G25="",E25,0) -> 0 | I25: =IF(G25<>"",E25,0) -> 6775
A26: Dharmesh New Loan | B26: EMI | C26: HDFC_Axis | D26: 45848 | F26: 2000000
A27: Arun | B27: Credit card Repayment | C27: ALL CC | D27: 45848 | E27: =F27*0.1 -> 70000 | F27: 700000
A28: Total | E28: =SUM(E2:E25) -> 342203.34 | F28: =SUM(F2:F27) -> 14493212 | G28: =SUM(G2:G27) -> 2156950 | H28: =SUM(H2:H27) -> 214231
A29: Dharmesh Loab BT | B29: 1600000 | C29: Credit Card Payment | D29: 630000
A30: LIC Balance | C30: Karande | D30: 50000
A31: SBI Balance | C31: SIP | D31: 40000
C35: Yagnesh CC | D35: 590500
C36: Processing fees | D36: 46865
A38: Total | B38: =SUM(B29:B35) -> 1600000 | D38: =SUM(D29:D36) -> 1357365
A39: Balance | B39: =B38-D38 -> 242635

Sheet November 2024
A1: Date | B1: Actual Profit | C1: Mulbhag | D1: Profit | E1: Actual | F1: Total | G1: Cash | H1: Account Transfer | I1: Expense | J1: Expense Online | K1: Account Balance | L1: cash on hand | M1: Actual Balance | O1: Date | P1: Mul Bhag | Q1: Profit | R1: Actual | S1: Total | T1: Cash | U1: Account Transfer | V1: Expense
A2: Last month Balance | B2: =Table2345345687911121514161718192021222324252627283456789101134567891011126[[#This Row],[Profit]]-Table2345345687911121514161718192021222324252627283456789101134567891011126[[#This Row],[Mulbhag]] -> 0 | C2: =Table2345345687911121514161718192021222324252627283456789101134567891011126[[#This Row],[Profit]]/3 -> 0 | D2: =F2*0.3 -> 0 | E2: =F2-D2 -> 0 | F2: =G2+H2 -> 0 | K2: =Table2345345687911121514161718192021222324252627283456789101134567891011126[[#This Row],[Account Transfer]]-Table2345345687911121514161718192021222324252627283456789101134567891011126[[#This Row],[Expense Online]] -> 0 | L2: =Table2345345687911121514161718192021222324252627283456789101134567891011126[[#This Row],[Cash]]-Table2345345687911121514161718192021222324252627283456789101134567891011126[[#This Row],[Mulbhag]]-Table2345345687911121514161718192021222324252627283456789101134567891011126[[#This Row],[Actual Profit]]-Table2345345687911121514161718192021222324252627283456789101134567891011126[[#This Row],[Expense]] -> 0 | M2: =Table2345345687911121514161718192021222324252627283456789101134567891011126[[#This Row],[Cash]]-Table2345345687911121514161718192021222324252627283456789101134567891011126[[#This Row],[Expense]] -> 0 | O2: Export | V2: 0
A3: 45597 | B3: =Table2345345687911121514161718192021222324252627283456789101134567891011126[[#This Row],[Profit]]-Table2345345687911121514161718192021222324252627283456789101134567891011126[[#This Row],[Mulbhag]] -> 3611 | C3: =Table2345345687911121514161718192021222324252627283456789101134567891011126[[#This Row],[Profit]]/3 -> 1805.5 | D3: =F3*0.3 -> 5416.5 | E3: =F3-D3 -> 12638.5 | F3: =G3+H3 -> 18055 | G3: 7000 | H3: 11055 | I3: 500 | K3: =Table2345345687911121514161718192021222324252627283456789101134567891011126[[#This Row],[Account Transfer]]-Table2345345687911121514161718192021222324252627283456789101134567891011126[[#This Row],[Expense Online]] -> 11055 | L3: =Table2345345687911121514161718192021222324252627283456789101134567891011126[[#This Row],[Cash]]-Table2345345687911121514161718192021222324252627283456789101134567891011126[[#This Row],[Mulbhag]]-Table2345345687911121514161718192021222324252627283456789101134567891011126[[#This Row],[Actual Profit]]-Table2345345687911121514161718192021222324252627283456789101134567891011126[[#This Row],[Expense]] -> 1083.5 | M3: =Table2345345687911121514161718192021222324252627283456789101134567891011126[[#This Row],[Cash]]-Table2345345687911121514161718192021222324252627283456789101134567891011126[[#This Row],[Expense]] -> 6500 | O3: =A3 -> 45597 | P3: =Q3/3 -> 1805.5 | Q3: =S3*0.3 -> 5416.5 | R3: =S3-Q3 -> 12638.5 | S3: =T3+U3 -> 18055 | T3: =VLOOKUP(O3,$A$1:$J$34,7,0) -> 7000 | U3: =VLOOKUP(O3,$A$1:$J$34,8,0) -> 11055 | V3: =VLOOKUP(O3,$A$1:$J$34,9,0) -> 500
A4: 45598 | B4: =Table2345345687911121514161718192021222324252627283456789101134567891011126[[#This Row],[Profit]]-Table2345345687911121514161718192021222324252627283456789101134567891011126[[#This Row],[Mulbhag]] -> 1503.4 | C4: =Table2345345687911121514161718192021222324252627283456789101134567891011126[[#This Row],[Profit]]/3 -> 751.7 | D4: =F4*0.3 -> 2255.1 | E4: =F4-D4 -> 5261.9 | F4: =G4+H4 -> 7517 | G4: 236 | H4: 7281 | I4: 20 | K4: =Table2345345687911121514161718192021222324252627283456789101134567891011126[[#This Row],[Account Transfer]]-Table2345345687911121514161718192021222324252627283456789101134567891011126[[#This Row],[Expense Online]] -> 7281 | L4: =Table2345345687911121514161718192021222324252627283456789101134567891011126[[#This Row],[Cash]]-Table2345345687911121514161718192021222324252627283456789101134567891011126[[#This Row],[Mulbhag]]-Table2345345687911121514161718192021222324252627283456789101134567891011126[[#This Row],[Actual Profit]]-Table2345345687911121514161718192021222324252627283456789101134567891011126[[#This Row],[Expense]]+L3 -> -955.6 | M4: =Table2345345687911121514161718192021222324252627283456789101134567891011126[[#This Row],[Cash]]-Table2345345687911121514161718192021222324252627283456789101134567891011126[[#This Row],[Expense]] -> 216 | O4: =A4 -> 45598 | P4: =Q4/3 -> 751.7 | Q4: =S4*0.3 -> 2255.1 | R4: =S4-Q4 -> 5261.9 | S4: =T4+U4 -> 7517 | T4: =VLOOKUP(O4,$A$1:$J$34,7,0) -> 236 | U4: =VLOOKUP(O4,$A$1:$J$34,8,0) -> 7281 | V4: =VLOOKUP(O4,$A$1:$J$34,9,0) -> 20
A5: 45599 | B5: =Table2345345687911121514161718192021222324252627283456789101134567891011126[[#This Row],[Profit]]-Table2345345687911121514161718192021222324252627283456789101134567891011126[[#This Row],[Mulbhag]] -> 8690 | C5: =Table2345345687911121514161718192021222324252627283456789101134567891011126[[#This Row],[Profit]]/3 -> 4345 | D5: =F5*0.3 -> 13035 | E5: =F5-D5 -> 30415 | F5: =G5+H5 -> 43450 | G5: 30700 | H5: 12750 | I5: 260 | K5: =Table2345345687911121514161718192021222324252627283456789101134567891011126[[#This Row],[Account Transfer]]-Table2345345687911121514161718192021222324252627283456789101134567891011126[[#This Row],[Expense Online]] -> 12750 | L5: =Table2345345687911121514161718192021222324252627283456789101134567891011126[[#This Row],[Cash]]-Table2345345687911121514161718192021222324252627283456789101134567891011126[[#This Row],[Mulbhag]]-Table2345345687911121514161718192021222324252627283456789101134567891011126[[#This Row],[Actual Profit]]-Table2345345687911121514161718192021222324252627283456789101134567891011126[[#This Row],[Expense]] -> 17405 | M5: =Table2345345687911121514161718192021222324252627283456789101134567891011126[[#This Row],[Cash]]-Table2345345687911121514161718192021222324252627283456789101134567891011126[[#This Row],[Expense]] -> 30440 | O5: =A5 -> 45599 | P5: =Q5/3 -> 4345 | Q5: =S5*0.3 -> 13035 | R5: =S5-Q5 -> 30415 | S5: =T5+U5 -> 43450 | T5: =VLOOKUP(O5,$A$1:$J$34,7,0) -> 30700 | U5: =VLOOKUP(O5,$A$1:$J$34,8,0) -> 12750 | V5: =VLOOKUP(O5,$A$1:$J$34,9,0) -> 260
A6: 45600 | B6: =Table2345345687911121514161718192021222324252627283456789101134567891011126[[#This Row],[Profit]]-Table2345345687911121514161718192021222324252627283456789101134567891011126[[#This Row],[Mulbhag]] -> 1310 | C6: =Table2345345687911121514161718192021222324252627283456789101134567891011126[[#This Row],[Profit]]/3 -> 655 | D6: =F6*0.3 -> 1965 | E6: =F6-D6 -> 4585 | F6: =G6+H6 -> 6550 | G6: 4200 | H6: 2350 | I6: 120 | K6: =Table2345345687911121514161718192021222324252627283456789101134567891011126[[#This Row],[Account Transfer]]-Table2345345687911121514161718192021222324252627283456789101134567891011126[[#This Row],[Expense Online]] -> 2350 | L6: =Table2345345687911121514161718192021222324252627283456789101134567891011126[[#This Row],[Cash]]-Table2345345687911121514161718192021222324252627283456789101134567891011126[[#This Row],[Mulbhag]]-Table2345345687911121514161718192021222324252627283456789101134567891011126[[#This Row],[Actual Profit]]-Table2345345687911121514161718192021222324252627283456789101134567891011126[[#This Row],[Expense]] -> 2115 | M6: =Table2345345687911121514161718192021222324252627283456789101134567891011126[[#This Row],[Cash]]-Table2345345687911121514161718192021222324252627283456789101134567891011126[[#This Row],[Expense]] -> 4080 | O6: =A6 -> 45600 | P6: =Q6/3 -> 655 | Q6: =S6*0.3 -> 1965 | R6: =S6-Q6 -> 4585 | S6: =T6+U6 -> 6550 | T6: =VLOOKUP(O6,$A$1:$J$34,7,0) -> 4200 | U6: =VLOOKUP(O6,$A$1:$J$34,8,0) -> 2350 | V6: =VLOOKUP(O6,$A$1:$J$34,9,0) -> 120
A7: 45601 | B7: =Table2345345687911121514161718192021222324252627283456789101134567891011126[[#This Row],[Profit]]-Table2345345687911121514161718192021222324252627283456789101134567891011126[[#This Row],[Mulbhag]] -> 4920 | C7: =Table2345345687911121514161718192021222324252627283456789101134567891011126[[#This Row],[Profit]]/3 -> 2460 | D7: =F7*0.3 -> 7380 | E7: =F7-D7 -> 17220 | F7: =G7+H7 -> 24600 | G7: 10850 | H7: 13750 | I7: 550 | K7: =Table2345345687911121514161718192021222324252627283456789101134567891011126[[#This Row],[Account Transfer]]-Table2345345687911121514161718192021222324252627283456789101134567891011126[[#This Row],[Expense Online]] -> 13750 | L7: =Table2345345687911121514161718192021222324252627283456789101134567891011126[[#This Row],[Cash]]-Table2345345687911121514161718192021222324252627283456789101134567891011126[[#This Row],[Mulbhag]]-Table2345345687911121514161718192021222324252627283456789101134567891011126[[#This Row],[Actual Profit]]-Table2345345687911121514161718192021222324252627283456789101134567891011126[[#This Row],[Expense]] -> 2920 | M7: =Table2345345687911121514161718192021222324252627283456789101134567891011126[[#This Row],[Cash]]-Table2345345687911121514161718192021222324252627283456789101134567891011126[[#This Row],[Expense]] -> 10300 | O7: =A7 -> 45601 | P7: =Q7/3 -> 2460 | Q7: =S7*0.3 -> 7380 | R7: =S7-Q7 -> 17220 | S7: =T7+U7 -> 24600 | T7: =VLOOKUP(O7,$A$1:$J$34,7,0) -> 10850 | U7: =VLOOKUP(O7,$A$1:$J$34,8,0) -> 13750 | V7: =VLOOKUP(O7,$A$1:$J$34,9,0) -> 550
A8: 45602 | B8: =Table2345345687911121514161718192021222324252627283456789101134567891011126[[#This Row],[Profit]]-Table2345345687911121514161718192021222324252627283456789101134567891011126[[#This Row],[Mulbhag]] -> 2060 | C8: =Table2345345687911121514161718192021222324252627283456789101134567891011126[[#This Row],[Profit]]/3 -> 1030 | D8: =F8*0.3 -> 3090 | E8: =F8-D8 -> 7210 | F8: =G8+H8 -> 10300 | G8: 6820 | H8: 3480 | I8: 1640 | K8: =Table2345345687911121514161718192021222324252627283456789101134567891011126[[#This Row],[Account Transfer]]-Table2345345687911121514161718192021222324252627283456789101134567891011126[[#This Row],[Expense Online]] -> 3480 | L8: =Table2345345687911121514161718192021222324252627283456789101134567891011126[[#This Row],[Cash]]-Table2345345687911121514161718192021222324252627283456789101134567891011126[[#This Row],[Mulbhag]]-Table2345345687911121514161718192021222324252627283456789101134567891011126[[#This Row],[Actual Profit]]-Table2345345687911121514161718192021222324252627283456789101134567891011126[[#This Row],[Expense]] -> 2090 | M8: =Table2345345687911121514161718192021222324252627283456789101134567891011126[[#This Row],[Cash]]-Table2345345687911121514161718192021222324252627283456789101134567891011126[[#This Row],[Expense]] -> 5180 | O8: =A8 -> 45602 | P8: =Q8/3 -> 1030 | Q8: =S8*0.3 -> 3090 | R8: =S8-Q8 -> 7210 | S8: =T8+U8 -> 10300 | T8: =VLOOKUP(O8,$A$1:$J$34,7,0) -> 6820 | U8: =VLOOKUP(O8,$A$1:$J$34,8,0) -> 3480 | V8: =VLOOKUP(O8,$A$1:$J$34,9,0) -> 1640
A9: 45603 | B9: =Table2345345687911121514161718192021222324252627283456789101134567891011126[[#This Row],[Profit]]-Table2345345687911121514161718192021222324252627283456789101134567891011126[[#This Row],[Mulbhag]] -> 3828.6 | C9: =Table2345345687911121514161718192021222324252627283456789101134567891011126[[#This Row],[Profit]]/3 -> 1914.3 | D9: =F9*0.3 -> 5742.9 | E9: =F9-D9 -> 13400.1 | F9: =G9+H9 -> 19143 | G9: 15300 | H9: 3843 | I9: 1720 | K9: =Table2345345687911121514161718192021222324252627283456789101134567891011126[[#This Row],[Account Transfer]]-Table2345345687911121514161718192021222324252627283456789101134567891011126[[#This Row],[Expense Online]] -> 3843 | L9: =Table2345345687911121514161718192021222324252627283456789101134567891011126[[#This Row],[Cash]]-Table2345345687911121514161718192021222324252627283456789101134567891011126[[#This Row],[Mulbhag]]-Table2345345687911121514161718192021222324252627283456789101134567891011126[[#This Row],[Actual Profit]]-Table2345345687911121514161718192021222324252627283456789101134567891011126[[#This Row],[Expense]] -> 7837.1 | M9: =Table2345345687911121514161718192021222324252627283456789101134567891011126[[#This Row],[Cash]]-Table2345345687911121514161718192021222324252627283456789101134567891011126[[#This Row],[Expense]] -> 13580 | O9: =A9 -> 45603 | P9: =Q9/3 -> 1914.3 | Q9: =S9*0.3 -> 5742.9 | R9: =S9-Q9 -> 13400.1 | S9: =T9+U9 -> 19143 | T9: =VLOOKUP(O9,$A$1:$J$34,7,0) -> 15300 | U9: =VLOOKUP(O9,$A$1:$J$34,8,0) -> 3843 | V9: =VLOOKUP(O9,$A$1:$J$34,9,0) -> 1720
A10: 45604 | B10: =Table2345345687911121514161718192021222324252627283456789101134567891011126[[#This Row],[Profit]]-Table2345345687911121514161718192021222324252627283456789101134567891011126[[#This Row],[Mulbhag]] -> 1838 | C10: =Table2345345687911121514161718192021222324252627283456789101134567891011126[[#This Row],[Profit]]/3 -> 919 | D10: =F10*0.3 -> 2757 | E10: =F10-D10 -> 6433 | F10: =G10+H10 -> 9190 | G10: 4000 | H10: 5190 | I10: 120 | K10: =Table2345345687911121514161718192021222324252627283456789101134567891011126[[#This Row],[Account Transfer]]-Table2345345687911121514161718192021222324252627283456789101134567891011126[[#This Row],[Expense Online]] -> 5190 | L10: =Table2345345687911121514161718192021222324252627283456789101134567891011126[[#This Row],[Cash]]-Table2345345687911121514161718192021222324252627283456789101134567891011126[[#This Row],[Mulbhag]]-Table2345345687911121514161718192021222324252627283456789101134567891011126[[#This Row],[Actual Profit]]-Table2345345687911121514161718192021222324252627283456789101134567891011126[[#This Row],[Expense]] -> 1123 | M10: =Table2345345687911121514161718192021222324252627283456789101134567891011126[[#This Row],[Cash]]-Table2345345687911121514161718192021222324252627283456789101134567891011126[[#This Row],[Expense]] -> 3880 | O10: Total | P10: =SUM(P3:P9) -> 12961.5 | Q10: =SUM(Q3:Q9) -> 38884.5 | R10: =SUM(R2:R9) -> 90730.5 | S10: =SUM(S3:S9) -> 129615 | T10: =SUM(T2:T9) -> 75106 | U10: =SUM(U2:U9) -> 54509 | V10: =SUM(V2:V9) -> 4810
A11: 45605 | B11: =Table2345345687911121514161718192021222324252627283456789101134567891011126[[#This Row],[Profit]]-Table2345345687911121514161718192021222324252627283456789101134567891011126[[#This Row],[Mulbhag]] -> 10642 | C11: =Table2345345687911121514161718192021222324252627283456789101134567891011126[[#This Row],[Profit]]/3 -> 5321 | D11: =F11*0.3 -> 15963 | E11: =F11-D11 -> 37247 | F11: =G11+H11 -> 53210 | G11: 34175 | H11: =5110+13925 -> 19035 | I11: 1030 | K11: =Table2345345687911121514161718192021222324252627283456789101134567891011126[[#This Row],[Account Transfer]]-Table2345345687911121514161718192021222324252627283456789101134567891011126[[#This Row],[Expense Online]] -> 19035 | L11: =Table2345345687911121514161718192021222324252627283456789101134567891011126[[#This Row],[Cash]]-Table2345345687911121514161718192021222324252627283456789101134567891011126[[#This Row],[Mulbhag]]-Table2345345687911121514161718192021222324252627283456789101134567891011126[[#This Row],[Actual Profit]]-Table2345345687911121514161718192021222324252627283456789101134567891011126[[#This Row],[Expense]] -> 17182 | M11: =Table2345345687911121514161718192021222324252627283456789101134567891011126[[#This Row],[Cash]]-Table2345345687911121514161718192021222324252627283456789101134567891011126[[#This Row],[Expense]] -> 33145 | O11: Mul Bhag | Q11: =Q10/3 -> 12961.5
A12: 45606 | B12: =Table2345345687911121514161718192021222324252627283456789101134567891011126[[#This Row],[Profit]]-Table2345345687911121514161718192021222324252627283456789101134567891011126[[#This Row],[Mulbhag]] -> 10098.6 | C12: =Table2345345687911121514161718192021222324252627283456789101134567891011126[[#This Row],[Profit]]/3 -> 5049.3 | D12: =F12*0.3 -> 15147.9 | E12: =F12-D12 -> 35345.1 | F12: =G12+H12 -> 50493 | G12: 19050 | H12: 31443 | I12: 1400 | K12: =Table2345345687911121514161718192021222324252627283456789101134567891011126[[#This Row],[Account Transfer]]-Table2345345687911121514161718192021222324252627283456789101134567891011126[[#This Row],[Expense Online]] -> 31443 | L12: =Table2345345687911121514161718192021222324252627283456789101134567891011126[[#This Row],[Cash]]-Table2345345687911121514161718192021222324252627283456789101134567891011126[[#This Row],[Mulbhag]]-Table2345345687911121514161718192021222324252627283456789101134567891011126[[#This Row],[Actual Profit]]-Table2345345687911121514161718192021222324252627283456789101134567891011126[[#This Row],[Expense]] -> 2502.1 | M12: =Table2345345687911121514161718192021222324252627283456789101134567891011126[[#This Row],[Cash]]-Table2345345687911121514161718192021222324252627283456789101134567891011126[[#This Row],[Expense]] -> 17650
A13: 45607 | B13: =Table2345345687911121514161718192021222324252627283456789101134567891011126[[#This Row],[Profit]]-Table2345345687911121514161718192021222324252627283456789101134567891011126[[#This Row],[Mulbhag]] -> 3372 | C13: =Table2345345687911121514161718192021222324252627283456789101134567891011126[[#This Row],[Profit]]/3 -> 1686 | D13: =F13*0.3 -> 5058 | E13: =F13-D13 -> 11802 | F13: =G13+H13 -> 16860 | G13: 14150 | H13: 2710 | I13: 1200 | K13: =Table2345345687911121514161718192021222324252627283456789101134567891011126[[#This Row],[Account Transfer]]-Table2345345687911121514161718192021222324252627283456789101134567891011126[[#This Row],[Expense Online]] -> 2710 | L13: =Table2345345687911121514161718192021222324252627283456789101134567891011126[[#This Row],[Cash]]-Table2345345687911121514161718192021222324252627283456789101134567891011126[[#This Row],[Mulbhag]]-Table2345345687911121514161718192021222324252627283456789101134567891011126[[#This Row],[Actual Profit]]-Table2345345687911121514161718192021222324252627283456789101134567891011126[[#This Row],[Expense]] -> 7892 | M13: =Table2345345687911121514161718192021222324252627283456789101134567891011126[[#This Row],[Cash]]-Table2345345687911121514161718192021222324252627283456789101134567891011126[[#This Row],[Expense]] -> 12950 | O13: Date | Q13: Profit | R13: Actual | S13: Total | T13: Cash | U13: Account Transfer | V13: Expense
A14: 45608 | B14: =Table2345345687911121514161718192021222324252627283456789101134567891011126[[#This Row],[Profit]]-Table2345345687911121514161718192021222324252627283456789101134567891011126[[#This Row],[Mulbhag]] -> 7130.2 | C14: =Table2345345687911121514161718192021222324252627283456789101134567891011126[[#This Row],[Profit]]/3 -> 3565.1 | D14: =F14*0.3 -> 10695.3 | E14: =F14-D14 -> 24955.7 | F14: =G14+H14 -> 35651 | G14: 5710 | H14: 29941 | I14: 1700 | K14: =Table2345345687911121514161718192021222324252627283456789101134567891011126[[#This Row],[Account Transfer]]-Table2345345687911121514161718192021222324252627283456789101134567891011126[[#This Row],[Expense Online]] -> 29941 | L14: =Table2345345687911121514161718192021222324252627283456789101134567891011126[[#This Row],[Cash]]-Table2345345687911121514161718192021222324252627283456789101134567891011126[[#This Row],[Mulbhag]]-Table2345345687911121514161718192021222324252627283456789101134567891011126[[#This Row],[Actual Profit]]-Table2345345687911121514161718192021222324252627283456789101134567891011126[[#This Row],[Expense]] -> -6685.3 | M14: =Table2345345687911121514161718192021222324252627283456789101134567891011126[[#This Row],[Cash]]-Table2345345687911121514161718192021222324252627283456789101134567891011126[[#This Row],[Expense]] -> 4010 | O14: =A10 -> 45604 | P14: =Q14/3 -> 919 | Q14: =S14*0.3 -> 2757 | R14: =S14-Q14 -> 6433 | S14: =T14+U14 -> 9190 | T14: =VLOOKUP(O14,$A$1:$J$34,7,0) -> 4000 | U14: =VLOOKUP(O14,$A$1:$J$34,8,0) -> 5190 | V14: =VLOOKUP(O14,$A$1:$J$34,9,0) -> 120
A15: 45609 | B15: =Table2345345687911121514161718192021222324252627283456789101134567891011126[[#This Row],[Profit]]-Table2345345687911121514161718192021222324252627283456789101134567891011126[[#This Row],[Mulbhag]] -> 20120 | C15: =Table2345345687911121514161718192021222324252627283456789101134567891011126[[#This Row],[Profit]]/3 -> 10060 | D15: =F15*0.3 -> 30180 | E15: =F15-D15 -> 70420 | F15: =G15+H15 -> 100600 | G15: 7000 | H15: 93600 | I15: 1410 | J15: 610 | K15: =Table2345345687911121514161718192021222324252627283456789101134567891011126[[#This Row],[Account Transfer]]-Table2345345687911121514161718192021222324252627283456789101134567891011126[[#This Row],[Expense Online]] -> 92990 | L15: =Table2345345687911121514161718192021222324252627283456789101134567891011126[[#This Row],[Cash]]-Table2345345687911121514161718192021222324252627283456789101134567891011126[[#This Row],[Mulbhag]]-Table2345345687911121514161718192021222324252627283456789101134567891011126[[#This Row],[Actual Profit]]-Table2345345687911121514161718192021222324252627283456789101134567891011126[[#This Row],[Expense]] -> -24590 | M15: =Table2345345687911121514161718192021222324252627283456789101134567891011126[[#This Row],[Cash]]-Table2345345687911121514161718192021222324252627283456789101134567891011126[[#This Row],[Expense]] -> 5590 | O15: =A11 -> 45605 | P15: =Q15/3 -> 5321 | Q15: =S15*0.3 -> 15963 | R15: =S15-Q15 -> 37247 | S15: =T15+U15 -> 53210 | T15: =VLOOKUP(O15,$A$1:$J$34,7,0) -> 34175 | U15: =VLOOKUP(O15,$A$1:$J$34,8,0) -> 19035 | V15: =VLOOKUP(O15,$A$1:$J$34,9,0) -> 1030
A16: 45610 | B16: =Table2345345687911121514161718192021222324252627283456789101134567891011126[[#This Row],[Profit]]-Table2345345687911121514161718192021222324252627283456789101134567891011126[[#This Row],[Mulbhag]] -> 4529 | C16: =Table2345345687911121514161718192021222324252627283456789101134567891011126[[#This Row],[Profit]]/3 -> 2264.5 | D16: =F16*0.3 -> 6793.5 | E16: =F16-D16 -> 15851.5 | F16: =G16+H16 -> 22645 | G16: 7400 | H16: 15245 | I16: 2350 | J16: 520 | K16: =Table2345345687911121514161718192021222324252627283456789101134567891011126[[#This Row],[Account Transfer]]-Table2345345687911121514161718192021222324252627283456789101134567891011126[[#This Row],[Expense Online]] -> 14725 | L16: =Table2345345687911121514161718192021222324252627283456789101134567891011126[[#This Row],[Cash]]-Table2345345687911121514161718192021222324252627283456789101134567891011126[[#This Row],[Mulbhag]]-Table2345345687911121514161718192021222324252627283456789101134567891011126[[#This Row],[Actual Profit]]-Table2345345687911121514161718192021222324252627283456789101134567891011126[[#This Row],[Expense]] -> -1743.5 | M16: =Table2345345687911121514161718192021222324252627283456789101134567891011126[[#This Row],[Cash]]-Table2345345687911121514161718192021222324252627283456789101134567891011126[[#This Row],[Expense]] -> 5050 | O16: =A12 -> 45606 | P16: =Q16/3 -> 5049.3 | Q16: =S16*0.3 -> 15147.9 | R16: =S16-Q16 -> 35345.1 | S16: =T16+U16 -> 50493 | T16: =VLOOKUP(O16,$A$1:$J$34,7,0) -> 19050 | U16: =VLOOKUP(O16,$A$1:$J$34,8,0) -> 31443 | V16: =VLOOKUP(O16,$A$1:$J$34,9,0) -> 1400
A17: 45611 | B17: =Table2345345687911121514161718192021222324252627283456789101134567891011126[[#This Row],[Profit]]-Table2345345687911121514161718192021222324252627283456789101134567891011126[[#This Row],[Mulbhag]] -> 4430.6 | C17: =Table2345345687911121514161718192021222324252627283456789101134567891011126[[#This Row],[Profit]]/3 -> 2215.3 | D17: =F17*0.3 -> 6645.9 | E17: =F17-D17 -> 15507.1 | F17: =G17+H17 -> 22153 | G17: 18710 | H17: 3443 | I17: 3520 | K17: =Table2345345687911121514161718192021222324252627283456789101134567891011126[[#This Row],[Account Transfer]]-Table2345345687911121514161718192021222324252627283456789101134567891011126[[#This Row],[Expense Online]] -> 3443 | L17: =Table2345345687911121514161718192021222324252627283456789101134567891011126[[#This Row],[Cash]]-Table2345345687911121514161718192021222324252627283456789101134567891011126[[#This Row],[Mulbhag]]-Table2345345687911121514161718192021222324252627283456789101134567891011126[[#This Row],[Actual Profit]]-Table2345345687911121514161718192021222324252627283456789101134567891011126[[#This Row],[Expense]] -> 8544.1 | M17: =Table2345345687911121514161718192021222324252627283456789101134567891011126[[#This Row],[Cash]]-Table2345345687911121514161718192021222324252627283456789101134567891011126[[#This Row],[Expense]] -> 15190 | O17: =A13 -> 45607 | P17: =Q17/3 -> 1686 | Q17: =S17*0.3 -> 5058 | R17: =S17-Q17 -> 11802 | S17: =T17+U17 -> 16860 | T17: =VLOOKUP(O17,$A$1:$J$34,7,0) -> 14150 | U17: =VLOOKUP(O17,$A$1:$J$34,8,0) -> 2710 | V17: =VLOOKUP(O17,$A$1:$J$34,9,0) -> 1200
A18: 45612 | B18: =Table2345345687911121514161718192021222324252627283456789101134567891011126[[#This Row],[Profit]]-Table2345345687911121514161718192021222324252627283456789101134567891011126[[#This Row],[Mulbhag]] -> 6660 | C18: =Table2345345687911121514161718192021222324252627283456789101134567891011126[[#This Row],[Profit]]/3 -> 3330 | D18: =F18*0.3 -> 9990 | E18: =F18-D18 -> 23310 | F18: =G18+H18 -> 33300 | G18: 21000 | H18: 12300 | I18: 1190 | J18: 800 | K18: =Table2345345687911121514161718192021222324252627283456789101134567891011126[[#This Row],[Account Transfer]]-Table2345345687911121514161718192021222324252627283456789101134567891011126[[#This Row],[Expense Online]] -> 11500 | L18: =Table2345345687911121514161718192021222324252627283456789101134567891011126[[#This Row],[Cash]]-Table2345345687911121514161718192021222324252627283456789101134567891011126[[#This Row],[Mulbhag]]-Table2345345687911121514161718192021222324252627283456789101134567891011126[[#This Row],[Actual Profit]]-Table2345345687911121514161718192021222324252627283456789101134567891011126[[#This Row],[Expense]] -> 9820 | M18: =Table2345345687911121514161718192021222324252627283456789101134567891011126[[#This Row],[Cash]]-Table2345345687911121514161718192021222324252627283456789101134567891011126[[#This Row],[Expense]] -> 19810 | O18: =A14 -> 45608 | P18: =Q18/3 -> 3565.1 | Q18: =S18*0.3 -> 10695.3 | R18: =S18-Q18 -> 24955.7 | S18: =T18+U18 -> 35651 | T18: =VLOOKUP(O18,$A$1:$J$34,7,0) -> 5710 | U18: =VLOOKUP(O18,$A$1:$J$34,8,0) -> 29941 | V18: =VLOOKUP(O18,$A$1:$J$34,9,0) -> 1700
A19: 45613 | B19: =Table2345345687911121514161718192021222324252627283456789101134567891011126[[#This Row],[Profit]]-Table2345345687911121514161718192021222324252627283456789101134567891011126[[#This Row],[Mulbhag]] -> 6067 | C19: =Table2345345687911121514161718192021222324252627283456789101134567891011126[[#This Row],[Profit]]/3 -> 3033.5 | D19: =F19*0.3 -> 9100.5 | E19: =F19-D19 -> 21234.5 | F19: =G19+H19 -> 30335 | G19: 13675 | H19: 16660 | I19: 1350 | K19: =Table2345345687911121514161718192021222324252627283456789101134567891011126[[#This Row],[Account Transfer]]-Table2345345687911121514161718192021222324252627283456789101134567891011126[[#This Row],[Expense Online]] -> 16660 | L19: =Table2345345687911121514161718192021222324252627283456789101134567891011126[[#This Row],[Cash]]-Table2345345687911121514161718192021222324252627283456789101134567891011126[[#This Row],[Mulbhag]]-Table2345345687911121514161718192021222324252627283456789101134567891011126[[#This Row],[Actual Profit]]-Table2345345687911121514161718192021222324252627283456789101134567891011126[[#This Row],[Expense]] -> 3224.5 | M19: =Table2345345687911121514161718192021222324252627283456789101134567891011126[[#This Row],[Cash]]-Table2345345687911121514161718192021222324252627283456789101134567891011126[[#This Row],[Expense]] -> 12325 | O19: =A15 -> 45609 | P19: =Q19/3 -> 10060 | Q19: =S19*0.3 -> 30180 | R19: =S19-Q19 -> 70420 | S19: =T19+U19 -> 100600 | T19: =VLOOKUP(O19,$A$1:$J$34,7,0) -> 7000 | U19: =VLOOKUP(O19,$A$1:$J$34,8,0) -> 93600 | V19: =VLOOKUP(O19,$A$1:$J$34,9,0) -> 1410
A20: 45614 | B20: =Table2345345687911121514161718192021222324252627283456789101134567891011126[[#This Row],[Profit]]-Table2345345687911121514161718192021222324252627283456789101134567891011126[[#This Row],[Mulbhag]] -> 4058 | C20: =Table2345345687911121514161718192021222324252627283456789101134567891011126[[#This Row],[Profit]]/3 -> 2029 | D20: =F20*0.3 -> 6087 | E20: =F20-D20 -> 14203 | F20: =G20+H20 -> 20290 | G20: 4500 | H20: 15790 | I20: =1585+3540 -> 5125 | K20: =Table2345345687911121514161718192021222324252627283456789101134567891011126[[#This Row],[Account Transfer]]-Table2345345687911121514161718192021222324252627283456789101134567891011126[[#This Row],[Expense Online]] -> 15790 | L20: =Table2345345687911121514161718192021222324252627283456789101134567891011126[[#This Row],[Cash]]-Table2345345687911121514161718192021222324252627283456789101134567891011126[[#This Row],[Mulbhag]]-Table2345345687911121514161718192021222324252627283456789101134567891011126[[#This Row],[Actual Profit]]-Table2345345687911121514161718192021222324252627283456789101134567891011126[[#This Row],[Expense]] -> -6712 | M20: =Table2345345687911121514161718192021222324252627283456789101134567891011126[[#This Row],[Cash]]-Table2345345687911121514161718192021222324252627283456789101134567891011126[[#This Row],[Expense]] -> -625 | O20: =A16 -> 45610 | P20: =Q20/3 -> 2264.5 | Q20: =S20*0.3 -> 6793.5 | R20: =S20-Q20 -> 15851.5 | S20: =T20+U20 -> 22645 | T20: =VLOOKUP(O20,$A$1:$J$34,7,0) -> 7400 | U20: =VLOOKUP(O20,$A$1:$J$34,8,0) -> 15245 | V20: =VLOOKUP(O20,$A$1:$J$34,9,0) -> 2350
A21: 45615 | B21: =Table2345345687911121514161718192021222324252627283456789101134567891011126[[#This Row],[Profit]]-Table2345345687911121514161718192021222324252627283456789101134567891011126[[#This Row],[Mulbhag]] -> 1170 | C21: =Table2345345687911121514161718192021222324252627283456789101134567891011126[[#This Row],[Profit]]/3 -> 585 | D21: =F21*0.3 -> 1755 | E21: =F21-D21 -> 4095 | F21: =G21+H21 -> 5850 | G21: 1830 | H21: 4020 | I21: 1700 | K21: =Table2345345687911121514161718192021222324252627283456789101134567891011126[[#This Row],[Account Transfer]]-Table2345345687911121514161718192021222324252627283456789101134567891011126[[#This Row],[Expense Online]] -> 4020 | L21: =Table2345345687911121514161718192021222324252627283456789101134567891011126[[#This Row],[Cash]]-Table2345345687911121514161718192021222324252627283456789101134567891011126[[#This Row],[Mulbhag]]-Table2345345687911121514161718192021222324252627283456789101134567891011126[[#This Row],[Actual Profit]]-Table2345345687911121514161718192021222324252627283456789101134567891011126[[#This Row],[Expense]] -> -1625 | M21: =Table2345345687911121514161718192021222324252627283456789101134567891011126[[#This Row],[Cash]]-Table2345345687911121514161718192021222324252627283456789101134567891011126[[#This Row],[Expense]] -> 130 | O21: Total | P21: =SUM(P14:P20) -> 28864.9 | Q21: =SUM(Q14:Q20) -> 86594.7 | R21: =SUM(R14:R20) -> 202054.3 | S21: =SUM(S14:S20) -> 288649 | T21: =SUM(T14:T20) -> 91485 | U21: =SUM(U14:U20) -> 197164 | V21: =SUM(V14:V20) -> 9210
A22: 45616 | B22: =Table2345345687911121514161718192021222324252627283456789101134567891011126[[#This Row],[Profit]]-Table2345345687911121514161718192021222324252627283456789101134567891011126[[#This Row],[Mulbhag]] -> 1620 | C22: =Table2345345687911121514161718192021222324252627283456789101134567891011126[[#This Row],[Profit]]/3 -> 810 | D22: =F22*0.3 -> 2430 | E22: =F22-D22 -> 5670 | F22: =G22+H22 -> 8100 | G22: 2600 | H22: 5500 | I22: 1700 | J22: 120 | K22: =Table2345345687911121514161718192021222324252627283456789101134567891011126[[#This Row],[Account Transfer]]-Table2345345687911121514161718192021222324252627283456789101134567891011126[[#This Row],[Expense Online]] -> 5380 | L22: =Table2345345687911121514161718192021222324252627283456789101134567891011126[[#This Row],[Cash]]-Table2345345687911121514161718192021222324252627283456789101134567891011126[[#This Row],[Mulbhag]]-Table2345345687911121514161718192021222324252627283456789101134567891011126[[#This Row],[Actual Profit]]-Table2345345687911121514161718192021222324252627283456789101134567891011126[[#This Row],[Expense]] -> -1530 | M22: =Table2345345687911121514161718192021222324252627283456789101134567891011126[[#This Row],[Cash]]-Table2345345687911121514161718192021222324252627283456789101134567891011126[[#This Row],[Expense]] -> 900 | O22: Mul Bhag | Q22: =Q21/3 -> 28864.9 | S22: =R22+Q22 -> 28864.9
A23: 45617 | B23: =Table2345345687911121514161718192021222324252627283456789101134567891011126[[#This Row],[Profit]]-Table2345345687911121514161718192021222324252627283456789101134567891011126[[#This Row],[Mulbhag]] -> 4228 | C23: =Table2345345687911121514161718192021222324252627283456789101134567891011126[[#This Row],[Profit]]/3 -> 2114 | D23: =F23*0.3 -> 6342 | E23: =F23-D23 -> 14798 | F23: =G23+H23 -> 21140 | G23: 5320 | H23: 15820 | I23: =700+2500 -> 3200 | J23: 60 | K23: =Table2345345687911121514161718192021222324252627283456789101134567891011126[[#This Row],[Account Transfer]]-Table2345345687911121514161718192021222324252627283456789101134567891011126[[#This Row],[Expense Online]] -> 15760 | L23: =Table2345345687911121514161718192021222324252627283456789101134567891011126[[#This Row],[Cash]]-Table2345345687911121514161718192021222324252627283456789101134567891011126[[#This Row],[Mulbhag]]-Table2345345687911121514161718192021222324252627283456789101134567891011126[[#This Row],[Actual Profit]]-Table2345345687911121514161718192021222324252627283456789101134567891011126[[#This Row],[Expense]] -> -4222 | M23: =Table2345345687911121514161718192021222324252627283456789101134567891011126[[#This Row],[Cash]]-Table2345345687911121514161718192021222324252627283456789101134567891011126[[#This Row],[Expense]] -> 2120
A24: 45618 | B24: =Table2345345687911121514161718192021222324252627283456789101134567891011126[[#This Row],[Profit]]-Table2345345687911121514161718192021222324252627283456789101134567891011126[[#This Row],[Mulbhag]] -> 6993.8 | C24: =Table2345345687911121514161718192021222324252627283456789101134567891011126[[#This Row],[Profit]]/3 -> 3496.9 | D24: =F24*0.3 -> 10490.7 | E24: =F24-D24 -> 24478.3 | F24: =G24+H24 -> 34969 | G24: 32689 | H24: 2280 | I24: 4340 | K24: =Table2345345687911121514161718192021222324252627283456789101134567891011126[[#This Row],[Account Transfer]]-Table2345345687911121514161718192021222324252627283456789101134567891011126[[#This Row],[Expense Online]] -> 2280 | L24: =Table2345345687911121514161718192021222324252627283456789101134567891011126[[#This Row],[Cash]]-Table2345345687911121514161718192021222324252627283456789101134567891011126[[#This Row],[Mulbhag]]-Table2345345687911121514161718192021222324252627283456789101134567891011126[[#This Row],[Actual Profit]]-Table2345345687911121514161718192021222324252627283456789101134567891011126[[#This Row],[Expense]] -> 17858.3 | M24: =Table2345345687911121514161718192021222324252627283456789101134567891011126[[#This Row],[Cash]]-Table2345345687911121514161718192021222324252627283456789101134567891011126[[#This Row],[Expense]] -> 28349 | O24: Date | Q24: Profit | R24: Actual | S24: Total | T24: Cash | U24: Account Transfer | V24: Expense
A25: 45619 | B25: =Table2345345687911121514161718192021222324252627283456789101134567891011126[[#This Row],[Profit]]-Table2345345687911121514161718192021222324252627283456789101134567891011126[[#This Row],[Mulbhag]] -> 2672 | C25: =Table2345345687911121514161718192021222324252627283456789101134567891011126[[#This Row],[Profit]]/3 -> 1336 | D25: =F25*0.3 -> 4008 | E25: =F25-D25 -> 9352 | F25: =G25+H25 -> 13360 | G25: 4680 | H25: =7880+800 -> 8680 | I25: 1200 | K25: =Table2345345687911121514161718192021222324252627283456789101134567891011126[[#This Row],[Account Transfer]]-Table2345345687911121514161718192021222324252627283456789101134567891011126[[#This Row],[Expense Online]] -> 8680 | L25: =Table2345345687911121514161718192021222324252627283456789101134567891011126[[#This Row],[Cash]]-Table2345345687911121514161718192021222324252627283456789101134567891011126[[#This Row],[Mulbhag]]-Table2345345687911121514161718192021222324252627283456789101134567891011126[[#This Row],[Actual Profit]]-Table2345345687911121514161718192021222324252627283456789101134567891011126[[#This Row],[Expense]] -> -528 | M25: =Table2345345687911121514161718192021222324252627283456789101134567891011126[[#This Row],[Cash]]-Table2345345687911121514161718192021222324252627283456789101134567891011126[[#This Row],[Expense]] -> 3480 | O25: =A17 -> 45611 | P25: =Q25/3 -> 2215.3 | Q25: =S25*0.3 -> 6645.9 | R25: =S25-Q25 -> 15507.1 | S25: =T25+U25 -> 22153 | T25: =VLOOKUP(O25,$A$1:$J$34,7,0) -> 18710 | U25: =VLOOKUP(O25,$A$1:$J$34,8,0) -> 3443 | V25: =VLOOKUP(O25,$A$1:$J$34,9,0) -> 3520
A26: 45620 | B26: =Table2345345687911121514161718192021222324252627283456789101134567891011126[[#This Row],[Profit]]-Table2345345687911121514161718192021222324252627283456789101134567891011126[[#This Row],[Mulbhag]] -> 4193 | C26: =Table2345345687911121514161718192021222324252627283456789101134567891011126[[#This Row],[Profit]]/3 -> 2096.5 | D26: =F26*0.3 -> 6289.5 | E26: =F26-D26 -> 14675.5 | F26: =G26+H26 -> 20965 | G26: 6000 | H26: =11015+3950 -> 14965 | I26: 1250 | K26: =Table2345345687911121514161718192021222324252627283456789101134567891011126[[#This Row],[Account Transfer]]-Table2345345687911121514161718192021222324252627283456789101134567891011126[[#This Row],[Expense Online]] -> 14965 | L26: =Table2345345687911121514161718192021222324252627283456789101134567891011126[[#This Row],[Cash]]-Table2345345687911121514161718192021222324252627283456789101134567891011126[[#This Row],[Mulbhag]]-Table2345345687911121514161718192021222324252627283456789101134567891011126[[#This Row],[Actual Profit]]-Table2345345687911121514161718192021222324252627283456789101134567891011126[[#This Row],[Expense]] -> -1539.5 | M26: =Table2345345687911121514161718192021222324252627283456789101134567891011126[[#This Row],[Cash]]-Table2345345687911121514161718192021222324252627283456789101134567891011126[[#This Row],[Expense]] -> 4750 | O26: =A18 -> 45612 | P26: =Q26/3 -> 3330 | Q26: =S26*0.3 -> 9990 | R26: =S26-Q26 -> 23310 | S26: =T26+U26 -> 33300 | T26: =VLOOKUP(O26,$A$1:$J$34,7,0) -> 21000 | U26: =VLOOKUP(O26,$A$1:$J$34,8,0) -> 12300 | V26: =VLOOKUP(O26,$A$1:$J$34,9,0) -> 1190
A27: 45621 | B27: =Table2345345687911121514161718192021222324252627283456789101134567891011126[[#This Row],[Profit]]-Table2345345687911121514161718192021222324252627283456789101134567891011126[[#This Row],[Mulbhag]] -> 5650 | C27: =Table2345345687911121514161718192021222324252627283456789101134567891011126[[#This Row],[Profit]]/3 -> 2825 | D27: =F27*0.3 -> 8475 | E27: =F27-D27 -> 19775 | F27: =G27+H27 -> 28250 | G27: 9800 | H27: 18450 | I27: 3100 | K27: =Table2345345687911121514161718192021222324252627283456789101134567891011126[[#This Row],[Account Transfer]]-Table2345345687911121514161718192021222324252627283456789101134567891011126[[#This Row],[Expense Online]] -> 18450 | L27: =Table2345345687911121514161718192021222324252627283456789101134567891011126[[#This Row],[Cash]]-Table2345345687911121514161718192021222324252627283456789101134567891011126[[#This Row],[Mulbhag]]-Table2345345687911121514161718192021222324252627283456789101134567891011126[[#This Row],[Actual Profit]]-Table2345345687911121514161718192021222324252627283456789101134567891011126[[#This Row],[Expense]] -> -1775 | M27: =Table2345345687911121514161718192021222324252627283456789101134567891011126[[#This Row],[Cash]]-Table2345345687911121514161718192021222324252627283456789101134567891011126[[#This Row],[Expense]] -> 6700 | O27: =A19 -> 45613 | P27: =Q27/3 -> 3033.5 | Q27: =S27*0.3 -> 9100.5 | R27: =S27-Q27 -> 21234.5 | S27: =T27+U27 -> 30335 | T27: =VLOOKUP(O27,$A$1:$J$34,7,0) -> 13675 | U27: =VLOOKUP(O27,$A$1:$J$34,8,0) -> 16660 | V27: =VLOOKUP(O27,$A$1:$J$34,9,0) -> 1350
A28: 45622 | B28: =Table2345345687911121514161718192021222324252627283456789101134567891011126[[#This Row],[Profit]]-Table2345345687911121514161718192021222324252627283456789101134567891011126[[#This Row],[Mulbhag]] -> 2671 | C28: =Table2345345687911121514161718192021222324252627283456789101134567891011126[[#This Row],[Profit]]/3 -> 1335.5 | D28: =F28*0.3 -> 4006.5 | E28: =F28-D28 -> 9348.5 | F28: =G28+H28 -> 13355 | G28: 7655 | H28: 5700 | I28: 3655 | K28: =Table2345345687911121514161718192021222324252627283456789101134567891011126[[#This Row],[Account Transfer]]-Table2345345687911121514161718192021222324252627283456789101134567891011126[[#This Row],[Expense Online]] -> 5700 | L28: =Table2345345687911121514161718192021222324252627283456789101134567891011126[[#This Row],[Cash]]-Table2345345687911121514161718192021222324252627283456789101134567891011126[[#This Row],[Mulbhag]]-Table2345345687911121514161718192021222324252627283456789101134567891011126[[#This Row],[Actual Profit]]-Table2345345687911121514161718192021222324252627283456789101134567891011126[[#This Row],[Expense]] -> -6.5 | M28: =Table2345345687911121514161718192021222324252627283456789101134567891011126[[#This Row],[Cash]]-Table2345345687911121514161718192021222324252627283456789101134567891011126[[#This Row],[Expense]] -> 4000 | O28: =A20 -> 45614 | P28: =Q28/3 -> 2029 | Q28: =S28*0.3 -> 6087 | R28: =S28-Q28 -> 14203 | S28: =T28+U28 -> 20290 | T28: =VLOOKUP(O28,$A$1:$J$34,7,0) -> 4500 | U28: =VLOOKUP(O28,$A$1:$J$34,8,0) -> 15790 | V28: =VLOOKUP(O28,$A$1:$J$34,9,0) -> 5125
A29: 45623 | B29: =Table2345345687911121514161718192021222324252627283456789101134567891011126[[#This Row],[Profit]]-Table2345345687911121514161718192021222324252627283456789101134567891011126[[#This Row],[Mulbhag]] -> 8235.2 | C29: =Table2345345687911121514161718192021222324252627283456789101134567891011126[[#This Row],[Profit]]/3 -> 4117.6 | D29: =F29*0.3 -> 12352.8 | E29: =F29-D29 -> 28823.2 | F29: =G29+H29 -> 41176 | G29: 34785 | H29: 6391 | I29: 8540 | K29: =Table2345345687911121514161718192021222324252627283456789101134567891011126[[#This Row],[Account Transfer]]-Table2345345687911121514161718192021222324252627283456789101134567891011126[[#This Row],[Expense Online]] -> 6391 | L29: =Table2345345687911121514161718192021222324252627283456789101134567891011126[[#This Row],[Cash]]-Table2345345687911121514161718192021222324252627283456789101134567891011126[[#This Row],[Mulbhag]]-Table2345345687911121514161718192021222324252627283456789101134567891011126[[#This Row],[Actual Profit]]-Table2345345687911121514161718192021222324252627283456789101134567891011126[[#This Row],[Expense]] -> 13892.2 | M29: =Table2345345687911121514161718192021222324252627283456789101134567891011126[[#This Row],[Cash]]-Table2345345687911121514161718192021222324252627283456789101134567891011126[[#This Row],[Expense]] -> 26245 | O29: =A21 -> 45615 | P29: =Q29/3 -> 585 | Q29: =S29*0.3 -> 1755 | R29: =S29-Q29 -> 4095 | S29: =T29+U29 -> 5850 | T29: =VLOOKUP(O29,$A$1:$J$34,7,0) -> 1830 | U29: =VLOOKUP(O29,$A$1:$J$34,8,0) -> 4020 | V29: =VLOOKUP(O29,$A$1:$J$34,9,0) -> 1700
A30: 45624 | B30: =Table2345345687911121514161718192021222324252627283456789101134567891011126[[#This Row],[Profit]]-Table2345345687911121514161718192021222324252627283456789101134567891011126[[#This Row],[Mulbhag]] -> 1388 | C30: =Table2345345687911121514161718192021222324252627283456789101134567891011126[[#This Row],[Profit]]/3 -> 694 | D30: =F30*0.3 -> 2082 | E30: =F30-D30 -> 4858 | F30: =G30+H30 -> 6940 | G30: 4770 | H30: 2170 | I30: 1150 | K30: =Table2345345687911121514161718192021222324252627283456789101134567891011126[[#This Row],[Account Transfer]]-Table2345345687911121514161718192021222324252627283456789101134567891011126[[#This Row],[Expense Online]] -> 2170 | L30: =Table2345345687911121514161718192021222324252627283456789101134567891011126[[#This Row],[Cash]]-Table2345345687911121514161718192021222324252627283456789101134567891011126[[#This Row],[Mulbhag]]-Table2345345687911121514161718192021222324252627283456789101134567891011126[[#This Row],[Actual Profit]]-Table2345345687911121514161718192021222324252627283456789101134567891011126[[#This Row],[Expense]] -> 1538 | M30: =Table2345345687911121514161718192021222324252627283456789101134567891011126[[#This Row],[Cash]]-Table2345345687911121514161718192021222324252627283456789101134567891011126[[#This Row],[Expense]] -> 3620 | O30: =A22 -> 45616 | P30: =Q30/3 -> 810 | Q30: =S30*0.3 -> 2430 | R30: =S30-Q30 -> 5670 | S30: =T30+U30 -> 8100 | T30: =VLOOKUP(O30,$A$1:$J$34,7,0) -> 2600 | U30: =VLOOKUP(O30,$A$1:$J$34,8,0) -> 5500 | V30: =VLOOKUP(O30,$A$1:$J$34,9,0) -> 1700
A31: 45625 | B31: =Table2345345687911121514161718192021222324252627283456789101134567891011126[[#This Row],[Profit]]-Table2345345687911121514161718192021222324252627283456789101134567891011126[[#This Row],[Mulbhag]] -> 3921 | C31: =Table2345345687911121514161718192021222324252627283456789101134567891011126[[#This Row],[Profit]]/3 -> 1960.5 | D31: =F31*0.3 -> 5881.5 | E31: =F31-D31 -> 13723.5 | F31: =G31+H31 -> 19605 | G31: 6705 | H31: 12900 | I31: 1170 | K31: =Table2345345687911121514161718192021222324252627283456789101134567891011126[[#This Row],[Account Transfer]]-Table2345345687911121514161718192021222324252627283456789101134567891011126[[#This Row],[Expense Online]] -> 12900 | L31: =Table2345345687911121514161718192021222324252627283456789101134567891011126[[#This Row],[Cash]]-Table2345345687911121514161718192021222324252627283456789101134567891011126[[#This Row],[Mulbhag]]-Table2345345687911121514161718192021222324252627283456789101134567891011126[[#This Row],[Actual Profit]]-Table2345345687911121514161718192021222324252627283456789101134567891011126[[#This Row],[Expense]] -> -346.5 | M31: =Table2345345687911121514161718192021222324252627283456789101134567891011126[[#This Row],[Cash]]-Table2345345687911121514161718192021222324252627283456789101134567891011126[[#This Row],[Expense]] -> 5535 | O31: =A23 -> 45617 | P31: =Q31/3 -> 2114 | Q31: =S31*0.3 -> 6342 | R31: =S31-Q31 -> 14798 | S31: =T31+U31 -> 21140 | T31: =VLOOKUP(O31,$A$1:$J$34,7,0) -> 5320 | U31: =VLOOKUP(O31,$A$1:$J$34,8,0) -> 15820 | V31: =VLOOKUP(O31,$A$1:$J$34,9,0) -> 3200
A32: 45626 | B32: =Table2345345687911121514161718192021222324252627283456789101134567891011126[[#This Row],[Profit]]-Table2345345687911121514161718192021222324252627283456789101134567891011126[[#This Row],[Mulbhag]] -> 1882 | C32: =Table2345345687911121514161718192021222324252627283456789101134567891011126[[#This Row],[Profit]]/3 -> 941 | D32: =F32*0.3 -> 2823 | E32: =F32-D32 -> 6587 | F32: =G32+H32 -> 9410 | G32: 2425 | H32: 6985 | I32: 1160 | K32: =Table2345345687911121514161718192021222324252627283456789101134567891011126[[#This Row],[Account Transfer]]-Table2345345687911121514161718192021222324252627283456789101134567891011126[[#This Row],[Expense Online]] -> 6985 | L32: =Table2345345687911121514161718192021222324252627283456789101134567891011126[[#This Row],[Cash]]-Table2345345687911121514161718192021222324252627283456789101134567891011126[[#This Row],[Mulbhag]]-Table2345345687911121514161718192021222324252627283456789101134567891011126[[#This Row],[Actual Profit]]-Table2345345687911121514161718192021222324252627283456789101134567891011126[[#This Row],[Expense]] -> -1558 | M32: =Table2345345687911121514161718192021222324252627283456789101134567891011126[[#This Row],[Cash]]-Table2345345687911121514161718192021222324252627283456789101134567891011126[[#This Row],[Expense]] -> 1265 | O32: Total | P32: =SUM(P25:P31) -> 14116.8 | Q32: =SUM(Q25:Q31) -> 42350.4 | R32: =SUM(R25:R31) -> 98817.6 | S32: =SUM(S25:S31) -> 141168 | T32: =SUM(T25:T31) -> 67635 | U32: =SUM(U25:U31) -> 73533 | V32: =SUM(V25:V31) -> 17785
A33: 45627 | B33: =Table2345345687911121514161718192021222324252627283456789101134567891011126[[#This Row],[Profit]]-Table2345345687911121514161718192021222324252627283456789101134567891011126[[#This Row],[Mulbhag]] -> 0 | C33: =Table2345345687911121514161718192021222324252627283456789101134567891011126[[#This Row],[Profit]]/3 -> 0 | D33: =F33*0.3 -> 0 | E33: =F33-D33 -> 0 | F33: =G33+H33 -> 0 | K33: =Table2345345687911121514161718192021222324252627283456789101134567891011126[[#This Row],[Account Transfer]]-Table2345345687911121514161718192021222324252627283456789101134567891011126[[#This Row],[Expense Online]] -> 0 | L33: =Table2345345687911121514161718192021222324252627283456789101134567891011126[[#This Row],[Cash]]-Table2345345687911121514161718192021222324252627283456789101134567891011126[[#This Row],[Mulbhag]]-Table2345345687911121514161718192021222324252627283456789101134567891011126[[#This Row],[Actual Profit]]-Table2345345687911121514161718192021222324252627283456789101134567891011126[[#This Row],[Expense]] -> 0 | M33: =Table2345345687911121514161718192021222324252627283456789101134567891011126[[#This Row],[Cash]]-Table2345345687911121514161718192021222324252627283456789101134567891011126[[#This Row],[Expense]] -> 0 | O33: Mul Bhag | Q33: =Q32/3 -> 14116.8
A34: Total | B34: =SUBTOTAL(109,Table2345345687911121514161718192021222324252627283456789101134567891011126[Actual Profit]) -> 149492.4 | C34: =SUBTOTAL(109,Table2345345687911121514161718192021222324252627283456789101134567891011126[Mulbhag]) -> 74746.2 | D34: =SUBTOTAL(109,Table2345345687911121514161718192021222324252627283456789101134567891011126[Profit]) -> 224238.6 | E34: =SUBTOTAL(109,Table2345345687911121514161718192021222324252627283456789101134567891011126[Actual]) -> 523223.4 | F34: =SUBTOTAL(109,Table2345345687911121514161718192021222324252627283456789101134567891011126[Total]) -> 747462 | G34: =SUBTOTAL(109,Table2345345687911121514161718192021222324252627283456789101134567891011126[Profit]) -> 224238.6 | H34: =SUBTOTAL(109,Table2345345687911121514161718192021222324252627283456789101134567891011126[Profit]) -> 224238.6 | I34: =SUM(I5:I33) -> 56850 | J34: =SUBTOTAL(109,Table2345345687911121514161718192021222324252627283456789101134567891011126[Expense Online]) -> 2110 | K34: =SUBTOTAL(109,Table2345345687911121514161718192021222324252627283456789101134567891011126[Account Balance]) -> 401617 | L34: =SUM(L5:L33) -> 63082 | M34: =SUBTOTAL(109,Table2345345687911121514161718192021222324252627283456789101134567891011126[Actual Balance]) -> 286365
O35: Date | Q35: Profit | R35: Actual | S35: Total | T35: Cash | U35: Account Transfer | V35: Expense
O36: =A24 -> 45618 | P36: =Q36/3 -> 3496.9 | Q36: =S36*0.3 -> 10490.7 | R36: =S36-Q36 -> 24478.3 | S36: =T36+U36 -> 34969 | T36: =VLOOKUP(O36,$A$1:$J$34,7,0) -> 32689 | U36: =VLOOKUP(O36,$A$1:$J$34,8,0) -> 2280 | V36: =VLOOKUP(O36,$A$1:$J$34,9,0) -> 4340
A37: Date | B37: Actual Profit | C37: Mulbhag | D37: Profit | E37: Actual | F37: Total | G37: Cash | H37: Account Transfer | I37: Expense | O37: =A25 -> 45619 | P37: =Q37/3 -> 1336 | Q37: =S37*0.3 -> 4008 | R37: =S37-Q37 -> 9352 | S37: =T37+U37 -> 13360 | T37: =VLOOKUP(O37,$A$1:$J$34,7,0) -> 4680 | U37: =VLOOKUP(O37,$A$1:$J$34,8,0) -> 8680 | V37: =VLOOKUP(O37,$A$1:$J$34,9,0) -> 1200
A38: =CONCATENATE(TEXT(O3,"DD-MMM-YYY")," to ",TEXT(O9,"DD-MMM-YYYY")) -> 01-Nov-2024 to 07-Nov-2024 | B38: =D38-C38 -> 25923 | C38: =D38/3 -> 12961.5 | D38: =Q10 -> 38884.5 | E38: =R10 -> 90730.5 | F38: =S10 -> 129615 | G38: =T10 -> 75106 | H38: =U10 -> 54509 | I38: =V10 -> 4810 | O38: =A26 -> 45620 | P38: =Q38/3 -> 2096.5 | Q38: =S38*0.3 -> 6289.5 | R38: =S38-Q38 -> 14675.5 | S38: =T38+U38 -> 20965 | T38: =VLOOKUP(O38,$A$1:$J$34,7,0) -> 6000 | U38: =VLOOKUP(O38,$A$1:$J$34,8,0) -> 14965 | V38: =VLOOKUP(O38,$A$1:$J$34,9,0) -> 1250
A39: =CONCATENATE(TEXT(O14,"DD-MMM-YYY")," to ",TEXT(O20,"DD-MMM-YYYY")) -> 08-Nov-2024 to 14-Nov-2024 | B39: =D39-C39 -> 57729.8 | C39: =D39/3 -> 28864.9 | D39: =Q21 -> 86594.7 | E39: =R21 -> 202054.3 | F39: =S21 -> 288649 | G39: =T21 -> 91485 | H39: =U21 -> 197164 | I39: =V21 -> 9210 | O39: =A27 -> 45621 | P39: =Q39/3 -> 2825 | Q39: =S39*0.3 -> 8475 | R39: =S39-Q39 -> 19775 | S39: =T39+U39 -> 28250 | T39: =VLOOKUP(O39,$A$1:$J$34,7,0) -> 9800 | U39: =VLOOKUP(O39,$A$1:$J$34,8,0) -> 18450 | V39: =VLOOKUP(O39,$A$1:$J$34,9,0) -> 3100
A40: =CONCATENATE(TEXT(O25,"DD-MMM-YYY")," to ",TEXT(O31,"DD-MMM-YYYY")) -> 15-Nov-2024 to 21-Nov-2024 | B40: =D40-C40 -> 28233.6 | C40: =D40/3 -> 14116.8 | D40: =Q32 -> 42350.4 | E40: =R32 -> 98817.6 | F40: =S32 -> 141168 | G40: =T32 -> 67635 | H40: =U32 -> 73533 | I40: =V32 -> 17785 | O40: =A28 -> 45622 | P40: =Q40/3 -> 1335.5 | Q40: =S40*0.3 -> 4006.5 | R40: =S40-Q40 -> 9348.5 | S40: =T40+U40 -> 13355 | T40: =VLOOKUP(O40,$A$1:$J$34,7,0) -> 7655 | U40: =VLOOKUP(O40,$A$1:$J$34,8,0) -> 5700 | V40: =VLOOKUP(O40,$A$1:$J$34,9,0) -> 3655
A41: =CONCATENATE(TEXT(O36,"DD-MMM-YYY")," to ",TEXT(O41,"DD-MMM-YYYY")) -> 22-Nov-2024 to 01-Dec-2024 | B41: =D41-C41 -> 22179.8 | C41: =D41/3 -> 11089.9 | D41: =Q42 -> 33269.7 | E41: =R42 -> 77629.3 | F41: =S42 -> 110899 | G41: =T42 -> 60824 | H41: =U42 -> 50075 | I41: =V42 -> 13545 | O41: =A33 -> 45627 | P41: =Q41/3 -> 0 | Q41: =S41*0.3 -> 0 | R41: =S41-Q41 -> 0 | S41: =T41+U41 -> 0 | T41: =VLOOKUP(O41,$A$1:$J$34,7,0) -> 0 | U41: =VLOOKUP(O41,$A$1:$J$34,8,0) -> 0 | V41: =VLOOKUP(O41,$A$1:$J$34,9,0) -> 0
A42: =CONCATENATE(TEXT(O3,"DD-MMM-YYY")," to ",TEXT(O41,"DD-MMM-YYYY")) -> 01-Nov-2024 to 01-Dec-2024 | B42: =D42-C42 -> 134066.2 | C42: =D42/3 -> 67033.1 | D42: =SUM(D38:D41) -> 201099.3 | E42: =SUM(E38:E41) -> 469231.7 | F42: =SUM(F38:F41) -> 670331 | G42: =SUM(G38:G41) -> 295050 | H42: =SUM(H38:H41) -> 375281 | I42: =SUM(I38:I41) -> 45350 | O42: Total | P42: =SUM(P36:P41) -> 11089.9 | Q42: =SUM(Q36:Q41) -> 33269.7 | R42: =SUM(R36:R41) -> 77629.3 | S42: =SUM(S36:S41) -> 110899 | T42: =SUM(T36:T41) -> 60824 | U42: =SUM(U36:U41) -> 50075 | V42: =SUM(V36:V41) -> 13545
E43: Total | O43: Mul Bhag | Q43: =Q42/3 -> 11089.9
O46: Date | Q46: Profit | R46: Actual | S46: Total | T46: Cash | U46: Account Transfer | V46: Expense
O47: =A7 -> 45601 | Q47: =SUM(D8:D33) -> 194187 | R47: =SUM(E8:E33) -> 453103 | S47: =SUM(F8:F33) -> 647290 | T47: =SUM(G8:G33) -> 290749 | U47: =SUM(H8:H33) -> 356541 | V47: =SUM(I8:I33) -> 55920
O48: Mul Bhag | Q48: =Q47/3 -> 64729

Sheet December 2024
A1: Date | B1: Actual Profit | C1: Mulbhag | D1: Profit | E1: Actual | F1: Total | G1: Cash | H1: Account Transfer | I1: Expense | J1: Expense Online | K1: Account Balance | L1: cash on hand | M1: Actual Balance | O1: Date | P1: Mul Bhag | Q1: Profit | R1: Actual | S1: Total | T1: Cash | U1: Account Transfer | V1: Expense
A2: Last month Balance | B2: =Table23453456879111215141617181920212223242526272834567891011345678910111267[[#This Row],[Profit]]-Table23453456879111215141617181920212223242526272834567891011345678910111267[[#This Row],[Mulbhag]] -> 0 | C2: =Table23453456879111215141617181920212223242526272834567891011345678910111267[[#This Row],[Profit]]/3 -> 0 | D2: =F2*0.3 -> 0 | E2: =F2-D2 -> 0 | F2: =G2+H2 -> 0 | K2: =Table23453456879111215141617181920212223242526272834567891011345678910111267[[#This Row],[Account Transfer]]-Table23453456879111215141617181920212223242526272834567891011345678910111267[[#This Row],[Expense Online]] -> 0 | L2: =Table23453456879111215141617181920212223242526272834567891011345678910111267[[#This Row],[Cash]]-Table23453456879111215141617181920212223242526272834567891011345678910111267[[#This Row],[Mulbhag]]-Table23453456879111215141617181920212223242526272834567891011345678910111267[[#This Row],[Actual Profit]]-Table23453456879111215141617181920212223242526272834567891011345678910111267[[#This Row],[Expense]] -> 0 | M2: =Table23453456879111215141617181920212223242526272834567891011345678910111267[[#This Row],[Cash]]-Table23453456879111215141617181920212223242526272834567891011345678910111267[[#This Row],[Expense]] -> 0 | O2: Export | V2: 0
A3: 45627 | B3: =Table23453456879111215141617181920212223242526272834567891011345678910111267[[#This Row],[Profit]]-Table23453456879111215141617181920212223242526272834567891011345678910111267[[#This Row],[Mulbhag]] -> 1970 | C3: =Table23453456879111215141617181920212223242526272834567891011345678910111267[[#This Row],[Profit]]/3 -> 985 | D3: =F3*0.3 -> 2955 | E3: =F3-D3 -> 6895 | F3: =G3+H3 -> 9850 | G3: 6000 | H3: 3850 | I3: 170 | K3: =Table23453456879111215141617181920212223242526272834567891011345678910111267[[#This Row],[Account Transfer]]-Table23453456879111215141617181920212223242526272834567891011345678910111267[[#This Row],[Expense Online]] -> 3850 | L3: =Table23453456879111215141617181920212223242526272834567891011345678910111267[[#This Row],[Cash]]-Table23453456879111215141617181920212223242526272834567891011345678910111267[[#This Row],[Mulbhag]]-Table23453456879111215141617181920212223242526272834567891011345678910111267[[#This Row],[Actual Profit]]-Table23453456879111215141617181920212223242526272834567891011345678910111267[[#This Row],[Expense]] -> 2875 | M3: =Table23453456879111215141617181920212223242526272834567891011345678910111267[[#This Row],[Cash]]-Table23453456879111215141617181920212223242526272834567891011345678910111267[[#This Row],[Expense]] -> 5830 | O3: =A3 -> 45627 | P3: =Q3/3 -> 985 | Q3: =S3*0.3 -> 2955 | R3: =S3-Q3 -> 6895 | S3: =T3+U3 -> 9850 | T3: =VLOOKUP(O3,$A$1:$J$34,7,0) -> 6000 | U3: =VLOOKUP(O3,$A$1:$J$34,8,0) -> 3850 | V3: =VLOOKUP(O3,$A$1:$J$34,9,0) -> 170
A4: 45628 | B4: =Table23453456879111215141617181920212223242526272834567891011345678910111267[[#This Row],[Profit]]-Table23453456879111215141617181920212223242526272834567891011345678910111267[[#This Row],[Mulbhag]] -> 3734 | C4: =Table23453456879111215141617181920212223242526272834567891011345678910111267[[#This Row],[Profit]]/3 -> 1867 | D4: =F4*0.3 -> 5601 | E4: =F4-D4 -> 13069 | F4: =G4+H4 -> 18670 | G4: 11000 | H4: 7670 | I4: 1380 | K4: =Table23453456879111215141617181920212223242526272834567891011345678910111267[[#This Row],[Account Transfer]]-Table23453456879111215141617181920212223242526272834567891011345678910111267[[#This Row],[Expense Online]] -> 7670 | L4: =Table23453456879111215141617181920212223242526272834567891011345678910111267[[#This Row],[Cash]]-Table23453456879111215141617181920212223242526272834567891011345678910111267[[#This Row],[Mulbhag]]-Table23453456879111215141617181920212223242526272834567891011345678910111267[[#This Row],[Actual Profit]]-Table23453456879111215141617181920212223242526272834567891011345678910111267[[#This Row],[Expense]]+L3 -> 6894 | M4: =Table23453456879111215141617181920212223242526272834567891011345678910111267[[#This Row],[Cash]]-Table23453456879111215141617181920212223242526272834567891011345678910111267[[#This Row],[Expense]] -> 9620 | O4: =A4 -> 45628 | P4: =Q4/3 -> 1867 | Q4: =S4*0.3 -> 5601 | R4: =S4-Q4 -> 13069 | S4: =T4+U4 -> 18670 | T4: =VLOOKUP(O4,$A$1:$J$34,7,0) -> 11000 | U4: =VLOOKUP(O4,$A$1:$J$34,8,0) -> 7670 | V4: =VLOOKUP(O4,$A$1:$J$34,9,0) -> 1380
A5: 45629 | B5: =Table23453456879111215141617181920212223242526272834567891011345678910111267[[#This Row],[Profit]]-Table23453456879111215141617181920212223242526272834567891011345678910111267[[#This Row],[Mulbhag]] -> 1210 | C5: =Table23453456879111215141617181920212223242526272834567891011345678910111267[[#This Row],[Profit]]/3 -> 605 | D5: =F5*0.3 -> 1815 | E5: =F5-D5 -> 4235 | F5: =G5+H5 -> 6050 | G5: 3500 | H5: 2550 | I5: 180 | K5: =Table23453456879111215141617181920212223242526272834567891011345678910111267[[#This Row],[Account Transfer]]-Table23453456879111215141617181920212223242526272834567891011345678910111267[[#This Row],[Expense Online]] -> 2550 | L5: =Table23453456879111215141617181920212223242526272834567891011345678910111267[[#This Row],[Cash]]-Table23453456879111215141617181920212223242526272834567891011345678910111267[[#This Row],[Mulbhag]]-Table23453456879111215141617181920212223242526272834567891011345678910111267[[#This Row],[Actual Profit]]-Table23453456879111215141617181920212223242526272834567891011345678910111267[[#This Row],[Expense]] -> 1505 | M5: =Table23453456879111215141617181920212223242526272834567891011345678910111267[[#This Row],[Cash]]-Table23453456879111215141617181920212223242526272834567891011345678910111267[[#This Row],[Expense]] -> 3320 | O5: =A5 -> 45629 | P5: =Q5/3 -> 605 | Q5: =S5*0.3 -> 1815 | R5: =S5-Q5 -> 4235 | S5: =T5+U5 -> 6050 | T5: =VLOOKUP(O5,$A$1:$J$34,7,0) -> 3500 | U5: =VLOOKUP(O5,$A$1:$J$34,8,0) -> 2550 | V5: =VLOOKUP(O5,$A$1:$J$34,9,0) -> 180
A6: 45630 | B6: =Table23453456879111215141617181920212223242526272834567891011345678910111267[[#This Row],[Profit]]-Table23453456879111215141617181920212223242526272834567891011345678910111267[[#This Row],[Mulbhag]] -> 1826.4 | C6: =Table23453456879111215141617181920212223242526272834567891011345678910111267[[#This Row],[Profit]]/3 -> 913.2 | D6: =F6*0.3 -> 2739.6 | E6: =F6-D6 -> 6392.4 | F6: =G6+H6 -> 9132 | G6: 1991 | H6: 7141 | I6: 9560 | J6: 1780 | K6: =Table23453456879111215141617181920212223242526272834567891011345678910111267[[#This Row],[Account Transfer]]-Table23453456879111215141617181920212223242526272834567891011345678910111267[[#This Row],[Expense Online]] -> 5361 | L6: =Table23453456879111215141617181920212223242526272834567891011345678910111267[[#This Row],[Cash]]-Table23453456879111215141617181920212223242526272834567891011345678910111267[[#This Row],[Mulbhag]]-Table23453456879111215141617181920212223242526272834567891011345678910111267[[#This Row],[Actual Profit]]-Table23453456879111215141617181920212223242526272834567891011345678910111267[[#This Row],[Expense]] -> -10308.6 | M6: =Table23453456879111215141617181920212223242526272834567891011345678910111267[[#This Row],[Cash]]-Table23453456879111215141617181920212223242526272834567891011345678910111267[[#This Row],[Expense]] -> -7569 | O6: =A6 -> 45630 | P6: =Q6/3 -> 913.2 | Q6: =S6*0.3 -> 2739.6 | R6: =S6-Q6 -> 6392.4 | S6: =T6+U6 -> 9132 | T6: =VLOOKUP(O6,$A$1:$J$34,7,0) -> 1991 | U6: =VLOOKUP(O6,$A$1:$J$34,8,0) -> 7141 | V6: =VLOOKUP(O6,$A$1:$J$34,9,0) -> 9560
A7: 45631 | B7: =Table23453456879111215141617181920212223242526272834567891011345678910111267[[#This Row],[Profit]]-Table23453456879111215141617181920212223242526272834567891011345678910111267[[#This Row],[Mulbhag]] -> 727 | C7: =Table23453456879111215141617181920212223242526272834567891011345678910111267[[#This Row],[Profit]]/3 -> 363.5 | D7: =F7*0.3 -> 1090.5 | E7: =F7-D7 -> 2544.5 | F7: =G7+H7 -> 3635 | G7: 1485 | H7: 2150 | I7: 3065 | K7: =Table23453456879111215141617181920212223242526272834567891011345678910111267[[#This Row],[Account Transfer]]-Table23453456879111215141617181920212223242526272834567891011345678910111267[[#This Row],[Expense Online]] -> 2150 | L7: =Table23453456879111215141617181920212223242526272834567891011345678910111267[[#This Row],[Cash]]-Table23453456879111215141617181920212223242526272834567891011345678910111267[[#This Row],[Mulbhag]]-Table23453456879111215141617181920212223242526272834567891011345678910111267[[#This Row],[Actual Profit]]-Table23453456879111215141617181920212223242526272834567891011345678910111267[[#This Row],[Expense]] -> -2670.5 | M7: =Table23453456879111215141617181920212223242526272834567891011345678910111267[[#This Row],[Cash]]-Table23453456879111215141617181920212223242526272834567891011345678910111267[[#This Row],[Expense]] -> -1580 | O7: =A7 -> 45631 | P7: =Q7/3 -> 363.5 | Q7: =S7*0.3 -> 1090.5 | R7: =S7-Q7 -> 2544.5 | S7: =T7+U7 -> 3635 | T7: =VLOOKUP(O7,$A$1:$J$34,7,0) -> 1485 | U7: =VLOOKUP(O7,$A$1:$J$34,8,0) -> 2150 | V7: =VLOOKUP(O7,$A$1:$J$34,9,0) -> 3065
A8: 45632 | B8: =Table23453456879111215141617181920212223242526272834567891011345678910111267[[#This Row],[Profit]]-Table23453456879111215141617181920212223242526272834567891011345678910111267[[#This Row],[Mulbhag]] -> 2992 | C8: =Table23453456879111215141617181920212223242526272834567891011345678910111267[[#This Row],[Profit]]/3 -> 1496 | D8: =F8*0.3 -> 4488 | E8: =F8-D8 -> 10472 | F8: =G8+H8 -> 14960 | G8: 9800 | H8: 5160 | I8: 1160 | K8: =Table23453456879111215141617181920212223242526272834567891011345678910111267[[#This Row],[Account Transfer]]-Table23453456879111215141617181920212223242526272834567891011345678910111267[[#This Row],[Expense Online]] -> 5160 | L8: =Table23453456879111215141617181920212223242526272834567891011345678910111267[[#This Row],[Cash]]-Table23453456879111215141617181920212223242526272834567891011345678910111267[[#This Row],[Mulbhag]]-Table23453456879111215141617181920212223242526272834567891011345678910111267[[#This Row],[Actual Profit]]-Table23453456879111215141617181920212223242526272834567891011345678910111267[[#This Row],[Expense]] -> 4152 | M8: =Table23453456879111215141617181920212223242526272834567891011345678910111267[[#This Row],[Cash]]-Table23453456879111215141617181920212223242526272834567891011345678910111267[[#This Row],[Expense]] -> 8640 | O8: =A8 -> 45632 | P8: =Q8/3 -> 1496 | Q8: =S8*0.3 -> 4488 | R8: =S8-Q8 -> 10472 | S8: =T8+U8 -> 14960 | T8: =VLOOKUP(O8,$A$1:$J$34,7,0) -> 9800 | U8: =VLOOKUP(O8,$A$1:$J$34,8,0) -> 5160 | V8: =VLOOKUP(O8,$A$1:$J$34,9,0) -> 1160
A9: 45633 | B9: =Table23453456879111215141617181920212223242526272834567891011345678910111267[[#This Row],[Profit]]-Table23453456879111215141617181920212223242526272834567891011345678910111267[[#This Row],[Mulbhag]] -> 3047.6 | C9: =Table23453456879111215141617181920212223242526272834567891011345678910111267[[#This Row],[Profit]]/3 -> 1523.8 | D9: =F9*0.3 -> 4571.4 | E9: =F9-D9 -> 10666.6 | F9: =G9+H9 -> 15238 | G9: 7800 | H9: 7438 | I9: 1961 | K9: =Table23453456879111215141617181920212223242526272834567891011345678910111267[[#This Row],[Account Transfer]]-Table23453456879111215141617181920212223242526272834567891011345678910111267[[#This Row],[Expense Online]] -> 7438 | L9: =Table23453456879111215141617181920212223242526272834567891011345678910111267[[#This Row],[Cash]]-Table23453456879111215141617181920212223242526272834567891011345678910111267[[#This Row],[Mulbhag]]-Table23453456879111215141617181920212223242526272834567891011345678910111267[[#This Row],[Actual Profit]]-Table23453456879111215141617181920212223242526272834567891011345678910111267[[#This Row],[Expense]] -> 1267.6 | M9: =Table23453456879111215141617181920212223242526272834567891011345678910111267[[#This Row],[Cash]]-Table23453456879111215141617181920212223242526272834567891011345678910111267[[#This Row],[Expense]] -> 5839 | O9: =A9 -> 45633 | P9: =Q9/3 -> 1523.8 | Q9: =S9*0.3 -> 4571.4 | R9: =S9-Q9 -> 10666.6 | S9: =T9+U9 -> 15238 | T9: =VLOOKUP(O9,$A$1:$J$34,7,0) -> 7800 | U9: =VLOOKUP(O9,$A$1:$J$34,8,0) -> 7438 | V9: =VLOOKUP(O9,$A$1:$J$34,9,0) -> 1961
A10: 45634 | B10: =Table23453456879111215141617181920212223242526272834567891011345678910111267[[#This Row],[Profit]]-Table23453456879111215141617181920212223242526272834567891011345678910111267[[#This Row],[Mulbhag]] -> 6542 | C10: =Table23453456879111215141617181920212223242526272834567891011345678910111267[[#This Row],[Profit]]/3 -> 3271 | D10: =F10*0.3 -> 9813 | E10: =F10-D10 -> 22897 | F10: =G10+H10 -> 32710 | G10: 15000 | H10: 17710 | I10: 1000 | J10: 32570 | K10: =Table23453456879111215141617181920212223242526272834567891011345678910111267[[#This Row],[Account Transfer]]-Table23453456879111215141617181920212223242526272834567891011345678910111267[[#This Row],[Expense Online]] -> -14860 | L10: =Table23453456879111215141617181920212223242526272834567891011345678910111267[[#This Row],[Cash]]-Table23453456879111215141617181920212223242526272834567891011345678910111267[[#This Row],[Mulbhag]]-Table23453456879111215141617181920212223242526272834567891011345678910111267[[#This Row],[Actual Profit]]-Table23453456879111215141617181920212223242526272834567891011345678910111267[[#This Row],[Expense]] -> 4187 | M10: =Table23453456879111215141617181920212223242526272834567891011345678910111267[[#This Row],[Cash]]-Table23453456879111215141617181920212223242526272834567891011345678910111267[[#This Row],[Expense]] -> 14000 | O10: Total | P10: =SUM(P3:P9) -> 7753.5 | Q10: =SUM(Q3:Q9) -> 23260.5 | R10: =SUM(R2:R9) -> 54274.5 | S10: =SUM(S2:S9) -> 77535 | T10: =SUM(T2:T9) -> 41576 | U10: =SUM(U2:U9) -> 35959 | V10: =SUM(V2:V9) -> 17476
A11: 45635 | B11: =Table23453456879111215141617181920212223242526272834567891011345678910111267[[#This Row],[Profit]]-Table23453456879111215141617181920212223242526272834567891011345678910111267[[#This Row],[Mulbhag]] -> 3608 | C11: =Table23453456879111215141617181920212223242526272834567891011345678910111267[[#This Row],[Profit]]/3 -> 1804 | D11: =F11*0.3 -> 5412 | E11: =F11-D11 -> 12628 | F11: =G11+H11 -> 18040 | G11: 9400 | H11: 8640 | I11: 2450 | J11: 17068 | K11: =Table23453456879111215141617181920212223242526272834567891011345678910111267[[#This Row],[Account Transfer]]-Table23453456879111215141617181920212223242526272834567891011345678910111267[[#This Row],[Expense Online]] -> -8428 | L11: =Table23453456879111215141617181920212223242526272834567891011345678910111267[[#This Row],[Cash]]-Table23453456879111215141617181920212223242526272834567891011345678910111267[[#This Row],[Mulbhag]]-Table23453456879111215141617181920212223242526272834567891011345678910111267[[#This Row],[Actual Profit]]-Table23453456879111215141617181920212223242526272834567891011345678910111267[[#This Row],[Expense]] -> 1538 | M11: =Table23453456879111215141617181920212223242526272834567891011345678910111267[[#This Row],[Cash]]-Table23453456879111215141617181920212223242526272834567891011345678910111267[[#This Row],[Expense]] -> 6950 | O11: Mul Bhag | Q11: =Q10/3 -> 7753.5
A12: 45636 | B12: =Table23453456879111215141617181920212223242526272834567891011345678910111267[[#This Row],[Profit]]-Table23453456879111215141617181920212223242526272834567891011345678910111267[[#This Row],[Mulbhag]] -> 6373.8 | C12: =Table23453456879111215141617181920212223242526272834567891011345678910111267[[#This Row],[Profit]]/3 -> 3186.9 | D12: =F12*0.3 -> 9560.7 | E12: =F12-D12 -> 22308.3 | F12: =G12+H12 -> 31869 | G12: 4450 | H12: 27419 | I12: 3160 | J12: 79305 | K12: =Table23453456879111215141617181920212223242526272834567891011345678910111267[[#This Row],[Account Transfer]]-Table23453456879111215141617181920212223242526272834567891011345678910111267[[#This Row],[Expense Online]] -> -51886 | L12: =Table23453456879111215141617181920212223242526272834567891011345678910111267[[#This Row],[Cash]]-Table23453456879111215141617181920212223242526272834567891011345678910111267[[#This Row],[Mulbhag]]-Table23453456879111215141617181920212223242526272834567891011345678910111267[[#This Row],[Actual Profit]]-Table23453456879111215141617181920212223242526272834567891011345678910111267[[#This Row],[Expense]] -> -8270.7 | M12: =Table23453456879111215141617181920212223242526272834567891011345678910111267[[#This Row],[Cash]]-Table23453456879111215141617181920212223242526272834567891011345678910111267[[#This Row],[Expense]] -> 1290
A13: 45637 | B13: =Table23453456879111215141617181920212223242526272834567891011345678910111267[[#This Row],[Profit]]-Table23453456879111215141617181920212223242526272834567891011345678910111267[[#This Row],[Mulbhag]] -> 13470 | C13: =Table23453456879111215141617181920212223242526272834567891011345678910111267[[#This Row],[Profit]]/3 -> 6735 | D13: =F13*0.3 -> 20205 | E13: =F13-D13 -> 47145 | F13: =G13+H13 -> 67350 | G13: 52930 | H13: 14420 | I13: 11170 | J13: 43515 | K13: =Table23453456879111215141617181920212223242526272834567891011345678910111267[[#This Row],[Account Transfer]]-Table23453456879111215141617181920212223242526272834567891011345678910111267[[#This Row],[Expense Online]] -> -29095 | L13: =Table23453456879111215141617181920212223242526272834567891011345678910111267[[#This Row],[Cash]]-Table23453456879111215141617181920212223242526272834567891011345678910111267[[#This Row],[Mulbhag]]-Table23453456879111215141617181920212223242526272834567891011345678910111267[[#This Row],[Actual Profit]]-Table23453456879111215141617181920212223242526272834567891011345678910111267[[#This Row],[Expense]] -> 21555 | M13: =Table23453456879111215141617181920212223242526272834567891011345678910111267[[#This Row],[Cash]]-Table23453456879111215141617181920212223242526272834567891011345678910111267[[#This Row],[Expense]] -> 41760 | O13: Date | Q13: Profit | R13: Actual | S13: Total | T13: Cash | U13: Account Transfer | V13: Expense
A14: 45638 | B14: =Table23453456879111215141617181920212223242526272834567891011345678910111267[[#This Row],[Profit]]-Table23453456879111215141617181920212223242526272834567891011345678910111267[[#This Row],[Mulbhag]] -> 7543 | C14: =Table23453456879111215141617181920212223242526272834567891011345678910111267[[#This Row],[Profit]]/3 -> 3771.5 | D14: =F14*0.3 -> 11314.5 | E14: =F14-D14 -> 26400.5 | F14: =G14+H14 -> 37715 | G14: 2000 | H14: 35715 | I14: 23110 | J14: 3670 | K14: =Table23453456879111215141617181920212223242526272834567891011345678910111267[[#This Row],[Account Transfer]]-Table23453456879111215141617181920212223242526272834567891011345678910111267[[#This Row],[Expense Online]] -> 32045 | L14: =Table23453456879111215141617181920212223242526272834567891011345678910111267[[#This Row],[Cash]]-Table23453456879111215141617181920212223242526272834567891011345678910111267[[#This Row],[Mulbhag]]-Table23453456879111215141617181920212223242526272834567891011345678910111267[[#This Row],[Actual Profit]]-Table23453456879111215141617181920212223242526272834567891011345678910111267[[#This Row],[Expense]] -> -32424.5 | M14: =Table23453456879111215141617181920212223242526272834567891011345678910111267[[#This Row],[Cash]]-Table23453456879111215141617181920212223242526272834567891011345678910111267[[#This Row],[Expense]] -> -21110 | O14: =A10 -> 45634 | P14: =Q14/3 -> 3271 | Q14: =S14*0.3 -> 9813 | R14: =S14-Q14 -> 22897 | S14: =T14+U14 -> 32710 | T14: =VLOOKUP(O14,$A$1:$J$34,7,0) -> 15000 | U14: =VLOOKUP(O14,$A$1:$J$34,8,0) -> 17710 | V14: =VLOOKUP(O14,$A$1:$J$34,9,0) -> 1000
A15: 45639 | B15: =Table23453456879111215141617181920212223242526272834567891011345678910111267[[#This Row],[Profit]]-Table23453456879111215141617181920212223242526272834567891011345678910111267[[#This Row],[Mulbhag]] -> 5291.6 | C15: =Table23453456879111215141617181920212223242526272834567891011345678910111267[[#This Row],[Profit]]/3 -> 2645.8 | D15: =F15*0.3 -> 7937.4 | E15: =F15-D15 -> 18520.6 | F15: =G15+H15 -> 26458 | G15: 12595 | H15: 13863 | I15: 5265 | K15: =Table23453456879111215141617181920212223242526272834567891011345678910111267[[#This Row],[Account Transfer]]-Table23453456879111215141617181920212223242526272834567891011345678910111267[[#This Row],[Expense Online]] -> 13863 | L15: =Table23453456879111215141617181920212223242526272834567891011345678910111267[[#This Row],[Cash]]-Table23453456879111215141617181920212223242526272834567891011345678910111267[[#This Row],[Mulbhag]]-Table23453456879111215141617181920212223242526272834567891011345678910111267[[#This Row],[Actual Profit]]-Table23453456879111215141617181920212223242526272834567891011345678910111267[[#This Row],[Expense]] -> -607.4 | M15: =Table23453456879111215141617181920212223242526272834567891011345678910111267[[#This Row],[Cash]]-Table23453456879111215141617181920212223242526272834567891011345678910111267[[#This Row],[Expense]] -> 7330 | O15: =A11 -> 45635 | P15: =Q15/3 -> 1804 | Q15: =S15*0.3 -> 5412 | R15: =S15-Q15 -> 12628 | S15: =T15+U15 -> 18040 | T15: =VLOOKUP(O15,$A$1:$J$34,7,0) -> 9400 | U15: =VLOOKUP(O15,$A$1:$J$34,8,0) -> 8640 | V15: =VLOOKUP(O15,$A$1:$J$34,9,0) -> 2450
A16: 45640 | B16: =Table23453456879111215141617181920212223242526272834567891011345678910111267[[#This Row],[Profit]]-Table23453456879111215141617181920212223242526272834567891011345678910111267[[#This Row],[Mulbhag]] -> 5406.2 | C16: =Table23453456879111215141617181920212223242526272834567891011345678910111267[[#This Row],[Profit]]/3 -> 2703.1 | D16: =F16*0.3 -> 8109.3 | E16: =F16-D16 -> 18921.7 | F16: =G16+H16 -> 27031 | G16: 7290 | H16: 19741 | I16: 4645 | K16: =Table23453456879111215141617181920212223242526272834567891011345678910111267[[#This Row],[Account Transfer]]-Table23453456879111215141617181920212223242526272834567891011345678910111267[[#This Row],[Expense Online]] -> 19741 | L16: =Table23453456879111215141617181920212223242526272834567891011345678910111267[[#This Row],[Cash]]-Table23453456879111215141617181920212223242526272834567891011345678910111267[[#This Row],[Mulbhag]]-Table23453456879111215141617181920212223242526272834567891011345678910111267[[#This Row],[Actual Profit]]-Table23453456879111215141617181920212223242526272834567891011345678910111267[[#This Row],[Expense]] -> -5464.3 | M16: =Table23453456879111215141617181920212223242526272834567891011345678910111267[[#This Row],[Cash]]-Table23453456879111215141617181920212223242526272834567891011345678910111267[[#This Row],[Expense]] -> 2645 | O16: =A12 -> 45636 | P16: =Q16/3 -> 3186.9 | Q16: =S16*0.3 -> 9560.7 | R16: =S16-Q16 -> 22308.3 | S16: =T16+U16 -> 31869 | T16: =VLOOKUP(O16,$A$1:$J$34,7,0) -> 4450 | U16: =VLOOKUP(O16,$A$1:$J$34,8,0) -> 27419 | V16: =VLOOKUP(O16,$A$1:$J$34,9,0) -> 3160
A17: 45641 | B17: =Table23453456879111215141617181920212223242526272834567891011345678910111267[[#This Row],[Profit]]-Table23453456879111215141617181920212223242526272834567891011345678910111267[[#This Row],[Mulbhag]] -> 5260 | C17: =Table23453456879111215141617181920212223242526272834567891011345678910111267[[#This Row],[Profit]]/3 -> 2630 | D17: =F17*0.3 -> 7890 | E17: =F17-D17 -> 18410 | F17: =G17+H17 -> 26300 | G17: 18500 | H17: 7800 | I17: 4835 | K17: =Table23453456879111215141617181920212223242526272834567891011345678910111267[[#This Row],[Account Transfer]]-Table23453456879111215141617181920212223242526272834567891011345678910111267[[#This Row],[Expense Online]] -> 7800 | L17: =Table23453456879111215141617181920212223242526272834567891011345678910111267[[#This Row],[Cash]]-Table23453456879111215141617181920212223242526272834567891011345678910111267[[#This Row],[Mulbhag]]-Table23453456879111215141617181920212223242526272834567891011345678910111267[[#This Row],[Actual Profit]]-Table23453456879111215141617181920212223242526272834567891011345678910111267[[#This Row],[Expense]] -> 5775 | M17: =Table23453456879111215141617181920212223242526272834567891011345678910111267[[#This Row],[Cash]]-Table23453456879111215141617181920212223242526272834567891011345678910111267[[#This Row],[Expense]] -> 13665 | O17: =A13 -> 45637 | P17: =Q17/3 -> 6735 | Q17: =S17*0.3 -> 20205 | R17: =S17-Q17 -> 47145 | S17: =T17+U17 -> 67350 | T17: =VLOOKUP(O17,$A$1:$J$34,7,0) -> 52930 | U17: =VLOOKUP(O17,$A$1:$J$34,8,0) -> 14420 | V17: =VLOOKUP(O17,$A$1:$J$34,9,0) -> 11170
A18: 45642 | B18: =Table23453456879111215141617181920212223242526272834567891011345678910111267[[#This Row],[Profit]]-Table23453456879111215141617181920212223242526272834567891011345678910111267[[#This Row],[Mulbhag]] -> 7902 | C18: =Table23453456879111215141617181920212223242526272834567891011345678910111267[[#This Row],[Profit]]/3 -> 3951 | D18: =F18*0.3 -> 11853 | E18: =F18-D18 -> 27657 | F18: =G18+H18 -> 39510 | G18: 18330 | H18: 21180 | I18: 10000 | J18: 93472 | K18: =Table23453456879111215141617181920212223242526272834567891011345678910111267[[#This Row],[Account Transfer]]-Table23453456879111215141617181920212223242526272834567891011345678910111267[[#This Row],[Expense Online]] -> -72292 | L18: =Table23453456879111215141617181920212223242526272834567891011345678910111267[[#This Row],[Cash]]-Table23453456879111215141617181920212223242526272834567891011345678910111267[[#This Row],[Mulbhag]]-Table23453456879111215141617181920212223242526272834567891011345678910111267[[#This Row],[Actual Profit]]-Table23453456879111215141617181920212223242526272834567891011345678910111267[[#This Row],[Expense]] -> -3523 | M18: =Table23453456879111215141617181920212223242526272834567891011345678910111267[[#This Row],[Cash]]-Table23453456879111215141617181920212223242526272834567891011345678910111267[[#This Row],[Expense]] -> 8330 | O18: =A14 -> 45638 | P18: =Q18/3 -> 3771.5 | Q18: =S18*0.3 -> 11314.5 | R18: =S18-Q18 -> 26400.5 | S18: =T18+U18 -> 37715 | T18: =VLOOKUP(O18,$A$1:$J$34,7,0) -> 2000 | U18: =VLOOKUP(O18,$A$1:$J$34,8,0) -> 35715 | V18: =VLOOKUP(O18,$A$1:$J$34,9,0) -> 23110
A19: 45643 | B19: =Table23453456879111215141617181920212223242526272834567891011345678910111267[[#This Row],[Profit]]-Table23453456879111215141617181920212223242526272834567891011345678910111267[[#This Row],[Mulbhag]] -> 3968 | C19: =Table23453456879111215141617181920212223242526272834567891011345678910111267[[#This Row],[Profit]]/3 -> 1984 | D19: =F19*0.3 -> 5952 | E19: =F19-D19 -> 13888 | F19: =G19+H19 -> 19840 | G19: 1790 | H19: 18050 | I19: 1450 | J19: 3320 | K19: =Table23453456879111215141617181920212223242526272834567891011345678910111267[[#This Row],[Account Transfer]]-Table23453456879111215141617181920212223242526272834567891011345678910111267[[#This Row],[Expense Online]] -> 14730 | L19: =Table23453456879111215141617181920212223242526272834567891011345678910111267[[#This Row],[Cash]]-Table23453456879111215141617181920212223242526272834567891011345678910111267[[#This Row],[Mulbhag]]-Table23453456879111215141617181920212223242526272834567891011345678910111267[[#This Row],[Actual Profit]]-Table23453456879111215141617181920212223242526272834567891011345678910111267[[#This Row],[Expense]] -> -5612 | M19: =Table23453456879111215141617181920212223242526272834567891011345678910111267[[#This Row],[Cash]]-Table23453456879111215141617181920212223242526272834567891011345678910111267[[#This Row],[Expense]] -> 340 | O19: =A15 -> 45639 | P19: =Q19/3 -> 2645.8 | Q19: =S19*0.3 -> 7937.4 | R19: =S19-Q19 -> 18520.6 | S19: =T19+U19 -> 26458 | T19: =VLOOKUP(O19,$A$1:$J$34,7,0) -> 12595 | U19: =VLOOKUP(O19,$A$1:$J$34,8,0) -> 13863 | V19: =VLOOKUP(O19,$A$1:$J$34,9,0) -> 5265
A20: 45644 | B20: =Table23453456879111215141617181920212223242526272834567891011345678910111267[[#This Row],[Profit]]-Table23453456879111215141617181920212223242526272834567891011345678910111267[[#This Row],[Mulbhag]] -> 5996.8 | C20: =Table23453456879111215141617181920212223242526272834567891011345678910111267[[#This Row],[Profit]]/3 -> 2998.4 | D20: =F20*0.3 -> 8995.2 | E20: =F20-D20 -> 20988.8 | F20: =G20+H20 -> 29984 | G20: 5750 | H20: 24234 | I20: 9715 | K20: =Table23453456879111215141617181920212223242526272834567891011345678910111267[[#This Row],[Account Transfer]]-Table23453456879111215141617181920212223242526272834567891011345678910111267[[#This Row],[Expense Online]] -> 24234 | L20: =Table23453456879111215141617181920212223242526272834567891011345678910111267[[#This Row],[Cash]]-Table23453456879111215141617181920212223242526272834567891011345678910111267[[#This Row],[Mulbhag]]-Table23453456879111215141617181920212223242526272834567891011345678910111267[[#This Row],[Actual Profit]]-Table23453456879111215141617181920212223242526272834567891011345678910111267[[#This Row],[Expense]] -> -12960.2 | M20: =Table23453456879111215141617181920212223242526272834567891011345678910111267[[#This Row],[Cash]]-Table23453456879111215141617181920212223242526272834567891011345678910111267[[#This Row],[Expense]] -> -3965 | O20: =A16 -> 45640 | P20: =Q20/3 -> 2703.1 | Q20: =S20*0.3 -> 8109.3 | R20: =S20-Q20 -> 18921.7 | S20: =T20+U20 -> 27031 | T20: =VLOOKUP(O20,$A$1:$J$34,7,0) -> 7290 | U20: =VLOOKUP(O20,$A$1:$J$34,8,0) -> 19741 | V20: =VLOOKUP(O20,$A$1:$J$34,9,0) -> 4645
A21: 45645 | B21: =Table23453456879111215141617181920212223242526272834567891011345678910111267[[#This Row],[Profit]]-Table23453456879111215141617181920212223242526272834567891011345678910111267[[#This Row],[Mulbhag]] -> 15392.4 | C21: =Table23453456879111215141617181920212223242526272834567891011345678910111267[[#This Row],[Profit]]/3 -> 7696.2 | D21: =F21*0.3 -> 23088.6 | E21: =F21-D21 -> 53873.4 | F21: =G21+H21 -> 76962 | G21: 1340 | H21: 75622 | I21: 440 | J21: 82860 | K21: =Table23453456879111215141617181920212223242526272834567891011345678910111267[[#This Row],[Account Transfer]]-Table23453456879111215141617181920212223242526272834567891011345678910111267[[#This Row],[Expense Online]] -> -7238 | L21: =Table23453456879111215141617181920212223242526272834567891011345678910111267[[#This Row],[Cash]]-Table23453456879111215141617181920212223242526272834567891011345678910111267[[#This Row],[Mulbhag]]-Table23453456879111215141617181920212223242526272834567891011345678910111267[[#This Row],[Actual Profit]]-Table23453456879111215141617181920212223242526272834567891011345678910111267[[#This Row],[Expense]] -> -22188.6 | M21: =Table23453456879111215141617181920212223242526272834567891011345678910111267[[#This Row],[Cash]]-Table23453456879111215141617181920212223242526272834567891011345678910111267[[#This Row],[Expense]] -> 900 | O21: Total | P21: =SUM(P14:P20) -> 24117.3 | Q21: =SUM(Q14:Q20) -> 72351.9 | R21: =SUM(R14:R20) -> 168821.1 | S21: =SUM(S14:S20) -> 241173 | T21: =SUM(T14:T20) -> 103665 | U21: =SUM(U14:U20) -> 137508 | V21: =SUM(V14:V20) -> 50800
A22: 45646 | B22: =Table23453456879111215141617181920212223242526272834567891011345678910111267[[#This Row],[Profit]]-Table23453456879111215141617181920212223242526272834567891011345678910111267[[#This Row],[Mulbhag]] -> 4529.2 | C22: =Table23453456879111215141617181920212223242526272834567891011345678910111267[[#This Row],[Profit]]/3 -> 2264.6 | D22: =F22*0.3 -> 6793.8 | E22: =F22-D22 -> 15852.2 | F22: =G22+H22 -> 22646 | G22: 7380 | H22: 15266 | I22: 51140 | J22: 135975 | K22: =Table23453456879111215141617181920212223242526272834567891011345678910111267[[#This Row],[Account Transfer]]-Table23453456879111215141617181920212223242526272834567891011345678910111267[[#This Row],[Expense Online]] -> -120709 | L22: =Table23453456879111215141617181920212223242526272834567891011345678910111267[[#This Row],[Cash]]-Table23453456879111215141617181920212223242526272834567891011345678910111267[[#This Row],[Mulbhag]]-Table23453456879111215141617181920212223242526272834567891011345678910111267[[#This Row],[Actual Profit]]-Table23453456879111215141617181920212223242526272834567891011345678910111267[[#This Row],[Expense]] -> -50553.8 | M22: =Table23453456879111215141617181920212223242526272834567891011345678910111267[[#This Row],[Cash]]-Table23453456879111215141617181920212223242526272834567891011345678910111267[[#This Row],[Expense]] -> -43760 | O22: Mul Bhag | Q22: =Q21/3 -> 24117.3 | S22: =R22+Q22 -> 24117.3
A23: 45647 | B23: =Table23453456879111215141617181920212223242526272834567891011345678910111267[[#This Row],[Profit]]-Table23453456879111215141617181920212223242526272834567891011345678910111267[[#This Row],[Mulbhag]] -> 10724 | C23: =Table23453456879111215141617181920212223242526272834567891011345678910111267[[#This Row],[Profit]]/3 -> 5362 | D23: =F23*0.3 -> 16086 | E23: =F23-D23 -> 37534 | F23: =G23+H23 -> 53620 | G23: 10420 | H23: 43200 | I23: 1140 | K23: =Table23453456879111215141617181920212223242526272834567891011345678910111267[[#This Row],[Account Transfer]]-Table23453456879111215141617181920212223242526272834567891011345678910111267[[#This Row],[Expense Online]] -> 43200 | L23: =Table23453456879111215141617181920212223242526272834567891011345678910111267[[#This Row],[Cash]]-Table23453456879111215141617181920212223242526272834567891011345678910111267[[#This Row],[Mulbhag]]-Table23453456879111215141617181920212223242526272834567891011345678910111267[[#This Row],[Actual Profit]]-Table23453456879111215141617181920212223242526272834567891011345678910111267[[#This Row],[Expense]] -> -6806 | M23: =Table23453456879111215141617181920212223242526272834567891011345678910111267[[#This Row],[Cash]]-Table23453456879111215141617181920212223242526272834567891011345678910111267[[#This Row],[Expense]] -> 9280
A24: 45648 | B24: =Table23453456879111215141617181920212223242526272834567891011345678910111267[[#This Row],[Profit]]-Table23453456879111215141617181920212223242526272834567891011345678910111267[[#This Row],[Mulbhag]] -> 1440 | C24: =Table23453456879111215141617181920212223242526272834567891011345678910111267[[#This Row],[Profit]]/3 -> 720 | D24: =F24*0.3 -> 2160 | E24: =F24-D24 -> 5040 | F24: =G24+H24 -> 7200 | G24: 2150 | H24: 5050 | I24: 685 | K24: =Table23453456879111215141617181920212223242526272834567891011345678910111267[[#This Row],[Account Transfer]]-Table23453456879111215141617181920212223242526272834567891011345678910111267[[#This Row],[Expense Online]] -> 5050 | L24: =Table23453456879111215141617181920212223242526272834567891011345678910111267[[#This Row],[Cash]]-Table23453456879111215141617181920212223242526272834567891011345678910111267[[#This Row],[Mulbhag]]-Table23453456879111215141617181920212223242526272834567891011345678910111267[[#This Row],[Actual Profit]]-Table23453456879111215141617181920212223242526272834567891011345678910111267[[#This Row],[Expense]] -> -695 | M24: =Table23453456879111215141617181920212223242526272834567891011345678910111267[[#This Row],[Cash]]-Table23453456879111215141617181920212223242526272834567891011345678910111267[[#This Row],[Expense]] -> 1465 | O24: Date | Q24: Profit | R24: Actual | S24: Total | T24: Cash | U24: Account Transfer | V24: Expense
A25: 45649 | B25: =Table23453456879111215141617181920212223242526272834567891011345678910111267[[#This Row],[Profit]]-Table23453456879111215141617181920212223242526272834567891011345678910111267[[#This Row],[Mulbhag]] -> 1578 | C25: =Table23453456879111215141617181920212223242526272834567891011345678910111267[[#This Row],[Profit]]/3 -> 789 | D25: =F25*0.3 -> 2367 | E25: =F25-D25 -> 5523 | F25: =G25+H25 -> 7890 | G25: 2720 | H25: 5170 | I25: 3120 | J25: 1500 | K25: =Table23453456879111215141617181920212223242526272834567891011345678910111267[[#This Row],[Account Transfer]]-Table23453456879111215141617181920212223242526272834567891011345678910111267[[#This Row],[Expense Online]] -> 3670 | L25: =Table23453456879111215141617181920212223242526272834567891011345678910111267[[#This Row],[Cash]]-Table23453456879111215141617181920212223242526272834567891011345678910111267[[#This Row],[Mulbhag]]-Table23453456879111215141617181920212223242526272834567891011345678910111267[[#This Row],[Actual Profit]]-Table23453456879111215141617181920212223242526272834567891011345678910111267[[#This Row],[Expense]] -> -2767 | M25: =Table23453456879111215141617181920212223242526272834567891011345678910111267[[#This Row],[Cash]]-Table23453456879111215141617181920212223242526272834567891011345678910111267[[#This Row],[Expense]] -> -400 | O25: =A17 -> 45641 | P25: =Q25/3 -> 2630 | Q25: =S25*0.3 -> 7890 | R25: =S25-Q25 -> 18410 | S25: =T25+U25 -> 26300 | T25: =VLOOKUP(O25,$A$1:$J$34,7,0) -> 18500 | U25: =VLOOKUP(O25,$A$1:$J$34,8,0) -> 7800 | V25: =VLOOKUP(O25,$A$1:$J$34,9,0) -> 4835
A26: 45650 | B26: =Table23453456879111215141617181920212223242526272834567891011345678910111267[[#This Row],[Profit]]-Table23453456879111215141617181920212223242526272834567891011345678910111267[[#This Row],[Mulbhag]] -> 473 | C26: =Table23453456879111215141617181920212223242526272834567891011345678910111267[[#This Row],[Profit]]/3 -> 236.5 | D26: =F26*0.3 -> 709.5 | E26: =F26-D26 -> 1655.5 | F26: =G26+H26 -> 2365 | G26: 1440 | H26: 925 | I26: 1100 | K26: =Table23453456879111215141617181920212223242526272834567891011345678910111267[[#This Row],[Account Transfer]]-Table23453456879111215141617181920212223242526272834567891011345678910111267[[#This Row],[Expense Online]] -> 925 | L26: =Table23453456879111215141617181920212223242526272834567891011345678910111267[[#This Row],[Cash]]-Table23453456879111215141617181920212223242526272834567891011345678910111267[[#This Row],[Mulbhag]]-Table23453456879111215141617181920212223242526272834567891011345678910111267[[#This Row],[Actual Profit]]-Table23453456879111215141617181920212223242526272834567891011345678910111267[[#This Row],[Expense]] -> -369.5 | M26: =Table23453456879111215141617181920212223242526272834567891011345678910111267[[#This Row],[Cash]]-Table23453456879111215141617181920212223242526272834567891011345678910111267[[#This Row],[Expense]] -> 340 | O26: =A18 -> 45642 | P26: =Q26/3 -> 3951 | Q26: =S26*0.3 -> 11853 | R26: =S26-Q26 -> 27657 | S26: =T26+U26 -> 39510 | T26: =VLOOKUP(O26,$A$1:$J$34,7,0) -> 18330 | U26: =VLOOKUP(O26,$A$1:$J$34,8,0) -> 21180 | V26: =VLOOKUP(O26,$A$1:$J$34,9,0) -> 10000
A27: 45651 | B27: =Table23453456879111215141617181920212223242526272834567891011345678910111267[[#This Row],[Profit]]-Table23453456879111215141617181920212223242526272834567891011345678910111267[[#This Row],[Mulbhag]] -> 9329.2 | C27: =Table23453456879111215141617181920212223242526272834567891011345678910111267[[#This Row],[Profit]]/3 -> 4664.6 | D27: =F27*0.3 -> 13993.8 | E27: =F27-D27 -> 32652.2 | F27: =G27+H27 -> 46646 | G27: 8765 | H27: 37881 | I27: 1640 | J27: 2200 | K27: =Table23453456879111215141617181920212223242526272834567891011345678910111267[[#This Row],[Account Transfer]]-Table23453456879111215141617181920212223242526272834567891011345678910111267[[#This Row],[Expense Online]] -> 35681 | L27: =Table23453456879111215141617181920212223242526272834567891011345678910111267[[#This Row],[Cash]]-Table23453456879111215141617181920212223242526272834567891011345678910111267[[#This Row],[Mulbhag]]-Table23453456879111215141617181920212223242526272834567891011345678910111267[[#This Row],[Actual Profit]]-Table23453456879111215141617181920212223242526272834567891011345678910111267[[#This Row],[Expense]] -> -6868.8 | M27: =Table23453456879111215141617181920212223242526272834567891011345678910111267[[#This Row],[Cash]]-Table23453456879111215141617181920212223242526272834567891011345678910111267[[#This Row],[Expense]] -> 7125 | O27: =A19 -> 45643 | P27: =Q27/3 -> 1984 | Q27: =S27*0.3 -> 5952 | R27: =S27-Q27 -> 13888 | S27: =T27+U27 -> 19840 | T27: =VLOOKUP(O27,$A$1:$J$34,7,0) -> 1790 | U27: =VLOOKUP(O27,$A$1:$J$34,8,0) -> 18050 | V27: =VLOOKUP(O27,$A$1:$J$34,9,0) -> 1450
A28: 45652 | B28: =Table23453456879111215141617181920212223242526272834567891011345678910111267[[#This Row],[Profit]]-Table23453456879111215141617181920212223242526272834567891011345678910111267[[#This Row],[Mulbhag]] -> 12908 | C28: =Table23453456879111215141617181920212223242526272834567891011345678910111267[[#This Row],[Profit]]/3 -> 6454 | D28: =F28*0.3 -> 19362 | E28: =F28-D28 -> 45178 | F28: =G28+H28 -> 64540 | G28: 26400 | H28: 38140 | I28: 5815 | J28: 20000 | K28: =Table23453456879111215141617181920212223242526272834567891011345678910111267[[#This Row],[Account Transfer]]-Table23453456879111215141617181920212223242526272834567891011345678910111267[[#This Row],[Expense Online]] -> 18140 | L28: =Table23453456879111215141617181920212223242526272834567891011345678910111267[[#This Row],[Cash]]-Table23453456879111215141617181920212223242526272834567891011345678910111267[[#This Row],[Mulbhag]]-Table23453456879111215141617181920212223242526272834567891011345678910111267[[#This Row],[Actual Profit]]-Table23453456879111215141617181920212223242526272834567891011345678910111267[[#This Row],[Expense]] -> 1223 | M28: =Table23453456879111215141617181920212223242526272834567891011345678910111267[[#This Row],[Cash]]-Table23453456879111215141617181920212223242526272834567891011345678910111267[[#This Row],[Expense]] -> 20585 | O28: =A20 -> 45644 | P28: =Q28/3 -> 2998.4 | Q28: =S28*0.3 -> 8995.2 | R28: =S28-Q28 -> 20988.8 | S28: =T28+U28 -> 29984 | T28: =VLOOKUP(O28,$A$1:$J$34,7,0) -> 5750 | U28: =VLOOKUP(O28,$A$1:$J$34,8,0) -> 24234 | V28: =VLOOKUP(O28,$A$1:$J$34,9,0) -> 9715
A29: 45653 | B29: =Table23453456879111215141617181920212223242526272834567891011345678910111267[[#This Row],[Profit]]-Table23453456879111215141617181920212223242526272834567891011345678910111267[[#This Row],[Mulbhag]] -> 5922 | C29: =Table23453456879111215141617181920212223242526272834567891011345678910111267[[#This Row],[Profit]]/3 -> 2961 | D29: =F29*0.3 -> 8883 | E29: =F29-D29 -> 20727 | F29: =G29+H29 -> 29610 | G29: 10130 | H29: 19480 | I29: 3060 | J29: 1000 | K29: =Table23453456879111215141617181920212223242526272834567891011345678910111267[[#This Row],[Account Transfer]]-Table23453456879111215141617181920212223242526272834567891011345678910111267[[#This Row],[Expense Online]] -> 18480 | L29: =Table23453456879111215141617181920212223242526272834567891011345678910111267[[#This Row],[Cash]]-Table23453456879111215141617181920212223242526272834567891011345678910111267[[#This Row],[Mulbhag]]-Table23453456879111215141617181920212223242526272834567891011345678910111267[[#This Row],[Actual Profit]]-Table23453456879111215141617181920212223242526272834567891011345678910111267[[#This Row],[Expense]] -> -1813 | M29: =Table23453456879111215141617181920212223242526272834567891011345678910111267[[#This Row],[Cash]]-Table23453456879111215141617181920212223242526272834567891011345678910111267[[#This Row],[Expense]] -> 7070 | O29: =A21 -> 45645 | P29: =Q29/3 -> 7696.2 | Q29: =S29*0.3 -> 23088.6 | R29: =S29-Q29 -> 53873.4 | S29: =T29+U29 -> 76962 | T29: =VLOOKUP(O29,$A$1:$J$34,7,0) -> 1340 | U29: =VLOOKUP(O29,$A$1:$J$34,8,0) -> 75622 | V29: =VLOOKUP(O29,$A$1:$J$34,9,0) -> 440
A30: 45654 | B30: =Table23453456879111215141617181920212223242526272834567891011345678910111267[[#This Row],[Profit]]-Table23453456879111215141617181920212223242526272834567891011345678910111267[[#This Row],[Mulbhag]] -> 3176 | C30: =Table23453456879111215141617181920212223242526272834567891011345678910111267[[#This Row],[Profit]]/3 -> 1588 | D30: =F30*0.3 -> 4764 | E30: =F30-D30 -> 11116 | F30: =G30+H30 -> 15880 | G30: 9730 | H30: 6150 | I30: 1260 | K30: =Table23453456879111215141617181920212223242526272834567891011345678910111267[[#This Row],[Account Transfer]]-Table23453456879111215141617181920212223242526272834567891011345678910111267[[#This Row],[Expense Online]] -> 6150 | L30: =Table23453456879111215141617181920212223242526272834567891011345678910111267[[#This Row],[Cash]]-Table23453456879111215141617181920212223242526272834567891011345678910111267[[#This Row],[Mulbhag]]-Table23453456879111215141617181920212223242526272834567891011345678910111267[[#This Row],[Actual Profit]]-Table23453456879111215141617181920212223242526272834567891011345678910111267[[#This Row],[Expense]] -> 3706 | M30: =Table23453456879111215141617181920212223242526272834567891011345678910111267[[#This Row],[Cash]]-Table23453456879111215141617181920212223242526272834567891011345678910111267[[#This Row],[Expense]] -> 8470 | O30: =A22 -> 45646 | P30: =Q30/3 -> 2264.6 | Q30: =S30*0.3 -> 6793.8 | R30: =S30-Q30 -> 15852.2 | S30: =T30+U30 -> 22646 | T30: =VLOOKUP(O30,$A$1:$J$34,7,0) -> 7380 | U30: =VLOOKUP(O30,$A$1:$J$34,8,0) -> 15266 | V30: =VLOOKUP(O30,$A$1:$J$34,9,0) -> 51140
A31: 45655 | B31: =Table23453456879111215141617181920212223242526272834567891011345678910111267[[#This Row],[Profit]]-Table23453456879111215141617181920212223242526272834567891011345678910111267[[#This Row],[Mulbhag]] -> 2250 | C31: =Table23453456879111215141617181920212223242526272834567891011345678910111267[[#This Row],[Profit]]/3 -> 1125 | D31: =F31*0.3 -> 3375 | E31: =F31-D31 -> 7875 | F31: =G31+H31 -> 11250 | G31: 4100 | H31: 7150 | I31: 5450 | K31: =Table23453456879111215141617181920212223242526272834567891011345678910111267[[#This Row],[Account Transfer]]-Table23453456879111215141617181920212223242526272834567891011345678910111267[[#This Row],[Expense Online]] -> 7150 | L31: =Table23453456879111215141617181920212223242526272834567891011345678910111267[[#This Row],[Cash]]-Table23453456879111215141617181920212223242526272834567891011345678910111267[[#This Row],[Mulbhag]]-Table23453456879111215141617181920212223242526272834567891011345678910111267[[#This Row],[Actual Profit]]-Table23453456879111215141617181920212223242526272834567891011345678910111267[[#This Row],[Expense]] -> -4725 | M31: =Table23453456879111215141617181920212223242526272834567891011345678910111267[[#This Row],[Cash]]-Table23453456879111215141617181920212223242526272834567891011345678910111267[[#This Row],[Expense]] -> -1350 | O31: =A23 -> 45647 | P31: =Q31/3 -> 5362 | Q31: =S31*0.3 -> 16086 | R31: =S31-Q31 -> 37534 | S31: =T31+U31 -> 53620 | T31: =VLOOKUP(O31,$A$1:$J$34,7,0) -> 10420 | U31: =VLOOKUP(O31,$A$1:$J$34,8,0) -> 43200 | V31: =VLOOKUP(O31,$A$1:$J$34,9,0) -> 1140
A32: 45656 | B32: =Table23453456879111215141617181920212223242526272834567891011345678910111267[[#This Row],[Profit]]-Table23453456879111215141617181920212223242526272834567891011345678910111267[[#This Row],[Mulbhag]] -> 3188 | C32: =Table23453456879111215141617181920212223242526272834567891011345678910111267[[#This Row],[Profit]]/3 -> 1594 | D32: =F32*0.3 -> 4782 | E32: =F32-D32 -> 11158 | F32: =G32+H32 -> 15940 | G32: 6230 | H32: 9710 | I32: 1260 | K32: =Table23453456879111215141617181920212223242526272834567891011345678910111267[[#This Row],[Account Transfer]]-Table23453456879111215141617181920212223242526272834567891011345678910111267[[#This Row],[Expense Online]] -> 9710 | L32: =Table23453456879111215141617181920212223242526272834567891011345678910111267[[#This Row],[Cash]]-Table23453456879111215141617181920212223242526272834567891011345678910111267[[#This Row],[Mulbhag]]-Table23453456879111215141617181920212223242526272834567891011345678910111267[[#This Row],[Actual Profit]]-Table23453456879111215141617181920212223242526272834567891011345678910111267[[#This Row],[Expense]] -> 188 | M32: =Table23453456879111215141617181920212223242526272834567891011345678910111267[[#This Row],[Cash]]-Table23453456879111215141617181920212223242526272834567891011345678910111267[[#This Row],[Expense]] -> 4970 | O32: Total | P32: =SUM(P25:P31) -> 26886.2 | Q32: =SUM(Q25:Q31) -> 80658.6 | R32: =SUM(R25:R31) -> 188203.4 | S32: =SUM(S25:S31) -> 268862 | T32: =SUM(T25:T31) -> 63510 | U32: =SUM(U25:U31) -> 205352 | V32: =SUM(V25:V31) -> 78720
A33: 45657 | B33: =Table23453456879111215141617181920212223242526272834567891011345678910111267[[#This Row],[Profit]]-Table23453456879111215141617181920212223242526272834567891011345678910111267[[#This Row],[Mulbhag]] -> 5166 | C33: =Table23453456879111215141617181920212223242526272834567891011345678910111267[[#This Row],[Profit]]/3 -> 2583 | D33: =F33*0.3 -> 7749 | E33: =F33-D33 -> 18081 | F33: =G33+H33 -> 25830 | G33: 9030 | H33: 16800 | I33: 1720 | K33: =Table23453456879111215141617181920212223242526272834567891011345678910111267[[#This Row],[Account Transfer]]-Table23453456879111215141617181920212223242526272834567891011345678910111267[[#This Row],[Expense Online]] -> 16800 | L33: =Table23453456879111215141617181920212223242526272834567891011345678910111267[[#This Row],[Cash]]-Table23453456879111215141617181920212223242526272834567891011345678910111267[[#This Row],[Mulbhag]]-Table23453456879111215141617181920212223242526272834567891011345678910111267[[#This Row],[Actual Profit]]-Table23453456879111215141617181920212223242526272834567891011345678910111267[[#This Row],[Expense]] -> -439 | M33: =Table23453456879111215141617181920212223242526272834567891011345678910111267[[#This Row],[Cash]]-Table23453456879111215141617181920212223242526272834567891011345678910111267[[#This Row],[Expense]] -> 7310 | O33: Mul Bhag | Q33: =Q32/3 -> 26886.2
A34: Total | B34: =SUBTOTAL(109,Table23453456879111215141617181920212223242526272834567891011345678910111267[Actual Profit]) -> 162944.2 | C34: =SUBTOTAL(109,Table23453456879111215141617181920212223242526272834567891011345678910111267[Mulbhag]) -> 81472.1 | D34: =SUBTOTAL(109,Table23453456879111215141617181920212223242526272834567891011345678910111267[Profit]) -> 244416.3 | E34: =SUBTOTAL(109,Table23453456879111215141617181920212223242526272834567891011345678910111267[Profit]) -> 244416.3 | F34: =SUM(F3:F33) -> 814721 | G34: =SUBTOTAL(109,Table23453456879111215141617181920212223242526272834567891011345678910111267[Profit]) -> 244416.3 | H34: =SUBTOTAL(109,Table23453456879111215141617181920212223242526272834567891011345678910111267[Profit]) -> 244416.3 | I34: =SUM(I5:I33) -> 170556 | J34: =SUBTOTAL(109,Table23453456879111215141617181920212223242526272834567891011345678910111267[Expense Online]) -> 518235 | K34: =SUBTOTAL(109,Table23453456879111215141617181920212223242526272834567891011345678910111267[Account Balance]) -> 7040 | L34: =SUM(L5:L33) -> -133970.3 | M34: =SUBTOTAL(109,Table23453456879111215141617181920212223242526272834567891011345678910111267[Actual Balance]) -> 117340
O35: Date | Q35: Profit | R35: Actual | S35: Total | T35: Cash | U35: Account Transfer | V35: Expense
O36: =A24 -> 45648 | P36: =Q36/3 -> 720 | Q36: =S36*0.3 -> 2160 | R36: =S36-Q36 -> 5040 | S36: =T36+U36 -> 7200 | T36: =VLOOKUP(O36,$A$1:$J$34,7,0) -> 2150 | U36: =VLOOKUP(O36,$A$1:$J$34,8,0) -> 5050 | V36: =VLOOKUP(O36,$A$1:$J$34,9,0) -> 685
A37: Date | B37: Actual Profit | C37: Mulbhag | D37: Profit | E37: Actual | F37: Total | G37: Cash | H37: Account Transfer | I37: Expense | O37: =A25 -> 45649 | P37: =Q37/3 -> 789 | Q37: =S37*0.3 -> 2367 | R37: =S37-Q37 -> 5523 | S37: =T37+U37 -> 7890 | T37: =VLOOKUP(O37,$A$1:$J$34,7,0) -> 2720 | U37: =VLOOKUP(O37,$A$1:$J$34,8,0) -> 5170 | V37: =VLOOKUP(O37,$A$1:$J$34,9,0) -> 3120
A38: =CONCATENATE(TEXT(O3,"DD-MMM-YYY")," to ",TEXT(O9,"DD-MMM-YYYY")) -> 01-Dec-2024 to 07-Dec-2024 | B38: =D38-C38 -> 15507 | C38: =D38/3 -> 7753.5 | D38: =Q10 -> 23260.5 | E38: =R10 -> 54274.5 | F38: =S10 -> 77535 | G38: =T10 -> 41576 | H38: =U10 -> 35959 | I38: =V10 -> 17476 | O38: =A26 -> 45650 | P38: =Q38/3 -> 236.5 | Q38: =S38*0.3 -> 709.5 | R38: =S38-Q38 -> 1655.5 | S38: =T38+U38 -> 2365 | T38: =VLOOKUP(O38,$A$1:$J$34,7,0) -> 1440 | U38: =VLOOKUP(O38,$A$1:$J$34,8,0) -> 925 | V38: =VLOOKUP(O38,$A$1:$J$34,9,0) -> 1100
A39: =CONCATENATE(TEXT(O14,"DD-MMM-YYY")," to ",TEXT(O20,"DD-MMM-YYYY")) -> 08-Dec-2024 to 14-Dec-2024 | B39: =D39-C39 -> 48234.6 | C39: =D39/3 -> 24117.3 | D39: =Q21 -> 72351.9 | E39: =R21 -> 168821.1 | F39: =S21 -> 241173 | G39: =T21 -> 103665 | H39: =U21 -> 137508 | I39: =V21 -> 50800 | O39: =A27 -> 45651 | P39: =Q39/3 -> 4664.6 | Q39: =S39*0.3 -> 13993.8 | R39: =S39-Q39 -> 32652.2 | S39: =T39+U39 -> 46646 | T39: =VLOOKUP(O39,$A$1:$J$34,7,0) -> 8765 | U39: =VLOOKUP(O39,$A$1:$J$34,8,0) -> 37881 | V39: =VLOOKUP(O39,$A$1:$J$34,9,0) -> 1640
A40: =CONCATENATE(TEXT(O25,"DD-MMM-YYY")," to ",TEXT(O31,"DD-MMM-YYYY")) -> 15-Dec-2024 to 21-Dec-2024 | B40: =D40-C40 -> 53772.4 | C40: =D40/3 -> 26886.2 | D40: =Q32 -> 80658.6 | E40: =R32 -> 188203.4 | F40: =S32 -> 268862 | G40: =T32 -> 63510 | H40: =U32 -> 205352 | I40: =V32 -> 78720 | O40: =A28 -> 45652 | P40: =Q40/3 -> 6454 | Q40: =S40*0.3 -> 19362 | R40: =S40-Q40 -> 45178 | S40: =T40+U40 -> 64540 | T40: =VLOOKUP(O40,$A$1:$J$34,7,0) -> 26400 | U40: =VLOOKUP(O40,$A$1:$J$34,8,0) -> 38140 | V40: =VLOOKUP(O40,$A$1:$J$34,9,0) -> 5815
A41: =CONCATENATE(TEXT(O36,"DD-MMM-YYY")," to ",TEXT(O41,"DD-MMM-YYYY")) -> 22-Dec-2024 to 31-Dec-2024 | B41: =D41-C41 -> 30894.2 | C41: =D41/3 -> 15447.1 | D41: =Q42 -> 46341.3 | E41: =R42 -> 108129.7 | F41: =S42 -> 154471 | G41: =T42 -> 50505 | H41: =U42 -> 103966 | I41: =V42 -> 14080 | O41: =A33 -> 45657 | P41: =Q41/3 -> 2583 | Q41: =S41*0.3 -> 7749 | R41: =S41-Q41 -> 18081 | S41: =T41+U41 -> 25830 | T41: =VLOOKUP(O41,$A$1:$J$34,7,0) -> 9030 | U41: =VLOOKUP(O41,$A$1:$J$34,8,0) -> 16800 | V41: =VLOOKUP(O41,$A$1:$J$34,9,0) -> 1720
A42: =CONCATENATE(TEXT(O3,"DD-MMM-YYY")," to ",TEXT(O41,"DD-MMM-YYYY")) -> 01-Dec-2024 to 31-Dec-2024 | B42: =D42-C42 -> 148408.2 | C42: =D42/3 -> 74204.1 | D42: =SUM(D38:D41) -> 222612.3 | E42: =SUM(E38:E41) -> 519428.7 | F42: =SUM(F38:F41) -> 742041 | G42: =SUM(G38:G41) -> 259256 | H42: =SUM(H38:H41) -> 482785 | I42: =SUM(I38:I41) -> 161076 | O42: Total | P42: =SUM(P36:P41) -> 15447.1 | Q42: =SUM(Q36:Q41) -> 46341.3 | R42: =SUM(R36:R41) -> 108129.7 | S42: =SUM(S36:S41) -> 154471 | T42: =SUM(T36:T41) -> 50505 | U42: =SUM(U36:U41) -> 103966 | V42: =SUM(V36:V41) -> 14080
E43: Total | O43: Mul Bhag | Q43: =Q42/3 -> 15447.1
O46: Date | Q46: Profit | R46: Actual | S46: Total | T46: Cash | U46: Account Transfer | V46: Expense
O47: =A7 -> 45631 | Q47: =SUM(D8:D33) -> 230215.2 | R47: =SUM(E8:E33) -> 537168.8 | S47: =SUM(F8:F33) -> 767384 | T47: =SUM(G8:G33) -> 265470 | U47: =SUM(H8:H33) -> 501914 | V47: =SUM(I8:I33) -> 157751
O48: Mul Bhag | Q48: =Q47/3 -> 76738.4

Sheet January 2025
A1: Date | B1: Actual Profit | C1: Mulbhag | D1: Profit | E1: Actual | F1: Total | G1: Cash | H1: Account Transfer | I1: Expense | J1: Expense Online | K1: Account Balance | L1: cash on hand | M1: Actual Balance | O1: Date | P1: Mul Bhag | Q1: Profit | R1: Actual | S1: Total | T1: Cash | U1: Account Transfer | V1: Expense
A2: Last month Balance | B2: =Table234534568791112151416171819202122232425262728345678910113456789101112678[[#This Row],[Profit]]-Table234534568791112151416171819202122232425262728345678910113456789101112678[[#This Row],[Mulbhag]] -> 0 | C2: =Table234534568791112151416171819202122232425262728345678910113456789101112678[[#This Row],[Profit]]/3 -> 0 | D2: =F2*0.3 -> 0 | E2: =F2-D2 -> 0 | F2: =G2+H2 -> 0 | K2: =Table234534568791112151416171819202122232425262728345678910113456789101112678[[#This Row],[Account Transfer]]-Table234534568791112151416171819202122232425262728345678910113456789101112678[[#This Row],[Expense Online]] -> 0 | L2: =Table234534568791112151416171819202122232425262728345678910113456789101112678[[#This Row],[Cash]]-Table234534568791112151416171819202122232425262728345678910113456789101112678[[#This Row],[Mulbhag]]-Table234534568791112151416171819202122232425262728345678910113456789101112678[[#This Row],[Actual Profit]]-Table234534568791112151416171819202122232425262728345678910113456789101112678[[#This Row],[Expense]] -> 0 | M2: =Table234534568791112151416171819202122232425262728345678910113456789101112678[[#This Row],[Cash]]-Table234534568791112151416171819202122232425262728345678910113456789101112678[[#This Row],[Expense]] -> 0 | O2: Export | V2: 0
A3: 45658 | B3: =Table234534568791112151416171819202122232425262728345678910113456789101112678[[#This Row],[Profit]]-Table234534568791112151416171819202122232425262728345678910113456789101112678[[#This Row],[Mulbhag]] -> 3030 | C3: =Table234534568791112151416171819202122232425262728345678910113456789101112678[[#This Row],[Profit]]/3 -> 1515 | D3: =F3*0.3 -> 4545 | E3: =F3-D3 -> 10605 | F3: =G3+H3 -> 15150 | G3: 6220 | H3: 8930 | I3: 840 | J3: 500 | K3: =Table234534568791112151416171819202122232425262728345678910113456789101112678[[#This Row],[Account Transfer]]-Table234534568791112151416171819202122232425262728345678910113456789101112678[[#This Row],[Expense Online]] -> 8430 | L3: =Table234534568791112151416171819202122232425262728345678910113456789101112678[[#This Row],[Cash]]-Table234534568791112151416171819202122232425262728345678910113456789101112678[[#This Row],[Mulbhag]]-Table234534568791112151416171819202122232425262728345678910113456789101112678[[#This Row],[Actual Profit]]-Table234534568791112151416171819202122232425262728345678910113456789101112678[[#This Row],[Expense]] -> 835 | M3: =Table234534568791112151416171819202122232425262728345678910113456789101112678[[#This Row],[Cash]]-Table234534568791112151416171819202122232425262728345678910113456789101112678[[#This Row],[Expense]] -> 5380 | O3: =A3 -> 45658 | P3: =Q3/3 -> 1515 | Q3: =S3*0.3 -> 4545 | R3: =S3-Q3 -> 10605 | S3: =T3+U3 -> 15150 | T3: =VLOOKUP(O3,$A$1:$J$34,7,0) -> 6220 | U3: =VLOOKUP(O3,$A$1:$J$34,8,0) -> 8930 | V3: =VLOOKUP(O3,$A$1:$J$34,9,0) -> 840
A4: 45659 | B4: =Table234534568791112151416171819202122232425262728345678910113456789101112678[[#This Row],[Profit]]-Table234534568791112151416171819202122232425262728345678910113456789101112678[[#This Row],[Mulbhag]] -> 5388.8 | C4: =Table234534568791112151416171819202122232425262728345678910113456789101112678[[#This Row],[Profit]]/3 -> 2694.4 | D4: =F4*0.3 -> 8083.2 | E4: =F4-D4 -> 18860.8 | F4: =G4+H4 -> 26944 | G4: 8124 | H4: 18820 | I4: 1500 | K4: =Table234534568791112151416171819202122232425262728345678910113456789101112678[[#This Row],[Account Transfer]]-Table234534568791112151416171819202122232425262728345678910113456789101112678[[#This Row],[Expense Online]] -> 18820 | L4: =Table234534568791112151416171819202122232425262728345678910113456789101112678[[#This Row],[Cash]]-Table234534568791112151416171819202122232425262728345678910113456789101112678[[#This Row],[Mulbhag]]-Table234534568791112151416171819202122232425262728345678910113456789101112678[[#This Row],[Actual Profit]]-Table234534568791112151416171819202122232425262728345678910113456789101112678[[#This Row],[Expense]]+L3 -> -624.2 | M4: =Table234534568791112151416171819202122232425262728345678910113456789101112678[[#This Row],[Cash]]-Table234534568791112151416171819202122232425262728345678910113456789101112678[[#This Row],[Expense]] -> 6624 | O4: =A4 -> 45659 | P4: =Q4/3 -> 2694.4 | Q4: =S4*0.3 -> 8083.2 | R4: =S4-Q4 -> 18860.8 | S4: =T4+U4 -> 26944 | T4: =VLOOKUP(O4,$A$1:$J$34,7,0) -> 8124 | U4: =VLOOKUP(O4,$A$1:$J$34,8,0) -> 18820 | V4: =VLOOKUP(O4,$A$1:$J$34,9,0) -> 1500
A5: 45660 | B5: =Table234534568791112151416171819202122232425262728345678910113456789101112678[[#This Row],[Profit]]-Table234534568791112151416171819202122232425262728345678910113456789101112678[[#This Row],[Mulbhag]] -> 1104 | C5: =Table234534568791112151416171819202122232425262728345678910113456789101112678[[#This Row],[Profit]]/3 -> 552 | D5: =F5*0.3 -> 1656 | E5: =F5-D5 -> 3864 | F5: =G5+H5 -> 5520 | G5: 3810 | H5: 1710 | I5: 2070 | K5: =Table234534568791112151416171819202122232425262728345678910113456789101112678[[#This Row],[Account Transfer]]-Table234534568791112151416171819202122232425262728345678910113456789101112678[[#This Row],[Expense Online]] -> 1710 | L5: =Table234534568791112151416171819202122232425262728345678910113456789101112678[[#This Row],[Cash]]-Table234534568791112151416171819202122232425262728345678910113456789101112678[[#This Row],[Mulbhag]]-Table234534568791112151416171819202122232425262728345678910113456789101112678[[#This Row],[Actual Profit]]-Table234534568791112151416171819202122232425262728345678910113456789101112678[[#This Row],[Expense]] -> 84 | M5: =Table234534568791112151416171819202122232425262728345678910113456789101112678[[#This Row],[Cash]]-Table234534568791112151416171819202122232425262728345678910113456789101112678[[#This Row],[Expense]] -> 1740 | O5: =A5 -> 45660 | P5: =Q5/3 -> 552 | Q5: =S5*0.3 -> 1656 | R5: =S5-Q5 -> 3864 | S5: =T5+U5 -> 5520 | T5: =VLOOKUP(O5,$A$1:$J$34,7,0) -> 3810 | U5: =VLOOKUP(O5,$A$1:$J$34,8,0) -> 1710 | V5: =VLOOKUP(O5,$A$1:$J$34,9,0) -> 2070
A6: 45661 | B6: =Table234534568791112151416171819202122232425262728345678910113456789101112678[[#This Row],[Profit]]-Table234534568791112151416171819202122232425262728345678910113456789101112678[[#This Row],[Mulbhag]] -> 4949 | C6: =Table234534568791112151416171819202122232425262728345678910113456789101112678[[#This Row],[Profit]]/3 -> 2474.5 | D6: =F6*0.3 -> 7423.5 | E6: =F6-D6 -> 17321.5 | F6: =G6+H6 -> 24745 | G6: 22490 | H6: 2255 | I6: 340 | K6: =Table234534568791112151416171819202122232425262728345678910113456789101112678[[#This Row],[Account Transfer]]-Table234534568791112151416171819202122232425262728345678910113456789101112678[[#This Row],[Expense Online]] -> 2255 | L6: =Table234534568791112151416171819202122232425262728345678910113456789101112678[[#This Row],[Cash]]-Table234534568791112151416171819202122232425262728345678910113456789101112678[[#This Row],[Mulbhag]]-Table234534568791112151416171819202122232425262728345678910113456789101112678[[#This Row],[Actual Profit]]-Table234534568791112151416171819202122232425262728345678910113456789101112678[[#This Row],[Expense]] -> 14726.5 | M6: =Table234534568791112151416171819202122232425262728345678910113456789101112678[[#This Row],[Cash]]-Table234534568791112151416171819202122232425262728345678910113456789101112678[[#This Row],[Expense]] -> 22150 | O6: =A6 -> 45661 | P6: =Q6/3 -> 2474.5 | Q6: =S6*0.3 -> 7423.5 | R6: =S6-Q6 -> 17321.5 | S6: =T6+U6 -> 24745 | T6: =VLOOKUP(O6,$A$1:$J$34,7,0) -> 22490 | U6: =VLOOKUP(O6,$A$1:$J$34,8,0) -> 2255 | V6: =VLOOKUP(O6,$A$1:$J$34,9,0) -> 340
A7: 45662 | B7: =Table234534568791112151416171819202122232425262728345678910113456789101112678[[#This Row],[Profit]]-Table234534568791112151416171819202122232425262728345678910113456789101112678[[#This Row],[Mulbhag]] -> 4691 | C7: =Table234534568791112151416171819202122232425262728345678910113456789101112678[[#This Row],[Profit]]/3 -> 2345.5 | D7: =F7*0.3 -> 7036.5 | E7: =F7-D7 -> 16418.5 | F7: =G7+H7 -> 23455 | G7: 5530 | H7: 17925 | I7: 6190 | K7: =Table234534568791112151416171819202122232425262728345678910113456789101112678[[#This Row],[Account Transfer]]-Table234534568791112151416171819202122232425262728345678910113456789101112678[[#This Row],[Expense Online]] -> 17925 | L7: =Table234534568791112151416171819202122232425262728345678910113456789101112678[[#This Row],[Cash]]-Table234534568791112151416171819202122232425262728345678910113456789101112678[[#This Row],[Mulbhag]]-Table234534568791112151416171819202122232425262728345678910113456789101112678[[#This Row],[Actual Profit]]-Table234534568791112151416171819202122232425262728345678910113456789101112678[[#This Row],[Expense]] -> -7696.5 | M7: =Table234534568791112151416171819202122232425262728345678910113456789101112678[[#This Row],[Cash]]-Table234534568791112151416171819202122232425262728345678910113456789101112678[[#This Row],[Expense]] -> -660 | O7: =A7 -> 45662 | P7: =Q7/3 -> 2345.5 | Q7: =S7*0.3 -> 7036.5 | R7: =S7-Q7 -> 16418.5 | S7: =T7+U7 -> 23455 | T7: =VLOOKUP(O7,$A$1:$J$34,7,0) -> 5530 | U7: =VLOOKUP(O7,$A$1:$J$34,8,0) -> 17925 | V7: =VLOOKUP(O7,$A$1:$J$34,9,0) -> 6190
A8: 45663 | B8: =Table234534568791112151416171819202122232425262728345678910113456789101112678[[#This Row],[Profit]]-Table234534568791112151416171819202122232425262728345678910113456789101112678[[#This Row],[Mulbhag]] -> 5556.4 | C8: =Table234534568791112151416171819202122232425262728345678910113456789101112678[[#This Row],[Profit]]/3 -> 2778.2 | D8: =F8*0.3 -> 8334.6 | E8: =F8-D8 -> 19447.4 | F8: =G8+H8 -> 27782 | G8: 6440 | H8: 21342 | I8: 17432 | K8: =Table234534568791112151416171819202122232425262728345678910113456789101112678[[#This Row],[Account Transfer]]-Table234534568791112151416171819202122232425262728345678910113456789101112678[[#This Row],[Expense Online]] -> 21342 | L8: =Table234534568791112151416171819202122232425262728345678910113456789101112678[[#This Row],[Cash]]-Table234534568791112151416171819202122232425262728345678910113456789101112678[[#This Row],[Mulbhag]]-Table234534568791112151416171819202122232425262728345678910113456789101112678[[#This Row],[Actual Profit]]-Table234534568791112151416171819202122232425262728345678910113456789101112678[[#This Row],[Expense]] -> -19326.6 | M8: =Table234534568791112151416171819202122232425262728345678910113456789101112678[[#This Row],[Cash]]-Table234534568791112151416171819202122232425262728345678910113456789101112678[[#This Row],[Expense]] -> -10992 | O8: =A8 -> 45663 | P8: =Q8/3 -> 2778.2 | Q8: =S8*0.3 -> 8334.6 | R8: =S8-Q8 -> 19447.4 | S8: =T8+U8 -> 27782 | T8: =VLOOKUP(O8,$A$1:$J$34,7,0) -> 6440 | U8: =VLOOKUP(O8,$A$1:$J$34,8,0) -> 21342 | V8: =VLOOKUP(O8,$A$1:$J$34,9,0) -> 17432
A9: 45664 | B9: =Table234534568791112151416171819202122232425262728345678910113456789101112678[[#This Row],[Profit]]-Table234534568791112151416171819202122232425262728345678910113456789101112678[[#This Row],[Mulbhag]] -> 2818 | C9: =Table234534568791112151416171819202122232425262728345678910113456789101112678[[#This Row],[Profit]]/3 -> 1409 | D9: =F9*0.3 -> 4227 | E9: =F9-D9 -> 9863 | F9: =G9+H9 -> 14090 | G9: 12490 | H9: 1600 | I9: 37405 | K9: =Table234534568791112151416171819202122232425262728345678910113456789101112678[[#This Row],[Account Transfer]]-Table234534568791112151416171819202122232425262728345678910113456789101112678[[#This Row],[Expense Online]] -> 1600 | L9: =Table234534568791112151416171819202122232425262728345678910113456789101112678[[#This Row],[Cash]]-Table234534568791112151416171819202122232425262728345678910113456789101112678[[#This Row],[Mulbhag]]-Table234534568791112151416171819202122232425262728345678910113456789101112678[[#This Row],[Actual Profit]]-Table234534568791112151416171819202122232425262728345678910113456789101112678[[#This Row],[Expense]] -> -29142 | M9: =Table234534568791112151416171819202122232425262728345678910113456789101112678[[#This Row],[Cash]]-Table234534568791112151416171819202122232425262728345678910113456789101112678[[#This Row],[Expense]] -> -24915 | O9: =A9 -> 45664 | P9: =Q9/3 -> 1409 | Q9: =S9*0.3 -> 4227 | R9: =S9-Q9 -> 9863 | S9: =T9+U9 -> 14090 | T9: =VLOOKUP(O9,$A$1:$J$34,7,0) -> 12490 | U9: =VLOOKUP(O9,$A$1:$J$34,8,0) -> 1600 | V9: =VLOOKUP(O9,$A$1:$J$34,9,0) -> 37405
A10: 45665 | B10: =Table234534568791112151416171819202122232425262728345678910113456789101112678[[#This Row],[Profit]]-Table234534568791112151416171819202122232425262728345678910113456789101112678[[#This Row],[Mulbhag]] -> 4748 | C10: =Table234534568791112151416171819202122232425262728345678910113456789101112678[[#This Row],[Profit]]/3 -> 2374 | D10: =F10*0.3 -> 7122 | E10: =F10-D10 -> 16618 | F10: =G10+H10 -> 23740 | G10: 13870 | H10: 9870 | I10: 1800 | K10: =Table234534568791112151416171819202122232425262728345678910113456789101112678[[#This Row],[Account Transfer]]-Table234534568791112151416171819202122232425262728345678910113456789101112678[[#This Row],[Expense Online]] -> 9870 | L10: =Table234534568791112151416171819202122232425262728345678910113456789101112678[[#This Row],[Cash]]-Table234534568791112151416171819202122232425262728345678910113456789101112678[[#This Row],[Mulbhag]]-Table234534568791112151416171819202122232425262728345678910113456789101112678[[#This Row],[Actual Profit]]-Table234534568791112151416171819202122232425262728345678910113456789101112678[[#This Row],[Expense]] -> 4948 | M10: =Table234534568791112151416171819202122232425262728345678910113456789101112678[[#This Row],[Cash]]-Table234534568791112151416171819202122232425262728345678910113456789101112678[[#This Row],[Expense]] -> 12070 | O10: Total | P10: =SUM(P3:P9) -> 13768.6 | Q10: =SUM(Q3:Q9) -> 41305.8 | R10: =SUM(R2:R9) -> 96380.2 | S10: =SUM(S2:S9) -> 137686 | T10: =SUM(T2:T9) -> 65104 | U10: =SUM(U2:U9) -> 72582 | V10: =SUM(V2:V9) -> 65777
A11: 45666 | B11: =Table234534568791112151416171819202122232425262728345678910113456789101112678[[#This Row],[Profit]]-Table234534568791112151416171819202122232425262728345678910113456789101112678[[#This Row],[Mulbhag]] -> 6359.2 | C11: =Table234534568791112151416171819202122232425262728345678910113456789101112678[[#This Row],[Profit]]/3 -> 3179.6 | D11: =F11*0.3 -> 9538.8 | E11: =F11-D11 -> 22257.2 | F11: =G11+H11 -> 31796 | G11: 3214 | H11: 28582 | I11: 10230 | K11: =Table234534568791112151416171819202122232425262728345678910113456789101112678[[#This Row],[Account Transfer]]-Table234534568791112151416171819202122232425262728345678910113456789101112678[[#This Row],[Expense Online]] -> 28582 | L11: =Table234534568791112151416171819202122232425262728345678910113456789101112678[[#This Row],[Cash]]-Table234534568791112151416171819202122232425262728345678910113456789101112678[[#This Row],[Mulbhag]]-Table234534568791112151416171819202122232425262728345678910113456789101112678[[#This Row],[Actual Profit]]-Table234534568791112151416171819202122232425262728345678910113456789101112678[[#This Row],[Expense]] -> -16554.8 | M11: =Table234534568791112151416171819202122232425262728345678910113456789101112678[[#This Row],[Cash]]-Table234534568791112151416171819202122232425262728345678910113456789101112678[[#This Row],[Expense]] -> -7016 | O11: Mul Bhag | Q11: =Q10/3 -> 13768.6
A12: 45667 | B12: =Table234534568791112151416171819202122232425262728345678910113456789101112678[[#This Row],[Profit]]-Table234534568791112151416171819202122232425262728345678910113456789101112678[[#This Row],[Mulbhag]] -> 3293.2 | C12: =Table234534568791112151416171819202122232425262728345678910113456789101112678[[#This Row],[Profit]]/3 -> 1646.6 | D12: =F12*0.3 -> 4939.8 | E12: =F12-D12 -> 11526.2 | F12: =G12+H12 -> 16466 | G12: 5880 | H12: 10586 | I12: 2540 | K12: =Table234534568791112151416171819202122232425262728345678910113456789101112678[[#This Row],[Account Transfer]]-Table234534568791112151416171819202122232425262728345678910113456789101112678[[#This Row],[Expense Online]] -> 10586 | L12: =Table234534568791112151416171819202122232425262728345678910113456789101112678[[#This Row],[Cash]]-Table234534568791112151416171819202122232425262728345678910113456789101112678[[#This Row],[Mulbhag]]-Table234534568791112151416171819202122232425262728345678910113456789101112678[[#This Row],[Actual Profit]]-Table234534568791112151416171819202122232425262728345678910113456789101112678[[#This Row],[Expense]] -> -1599.8 | M12: =Table234534568791112151416171819202122232425262728345678910113456789101112678[[#This Row],[Cash]]-Table234534568791112151416171819202122232425262728345678910113456789101112678[[#This Row],[Expense]] -> 3340
A13: 45668 | B13: =Table234534568791112151416171819202122232425262728345678910113456789101112678[[#This Row],[Profit]]-Table234534568791112151416171819202122232425262728345678910113456789101112678[[#This Row],[Mulbhag]] -> 7081 | C13: =Table234534568791112151416171819202122232425262728345678910113456789101112678[[#This Row],[Profit]]/3 -> 3540.5 | D13: =F13*0.3 -> 10621.5 | E13: =F13-D13 -> 24783.5 | F13: =G13+H13 -> 35405 | G13: 11165 | H13: 24240 | I13: 3115 | K13: =Table234534568791112151416171819202122232425262728345678910113456789101112678[[#This Row],[Account Transfer]]-Table234534568791112151416171819202122232425262728345678910113456789101112678[[#This Row],[Expense Online]] -> 24240 | L13: =Table234534568791112151416171819202122232425262728345678910113456789101112678[[#This Row],[Cash]]-Table234534568791112151416171819202122232425262728345678910113456789101112678[[#This Row],[Mulbhag]]-Table234534568791112151416171819202122232425262728345678910113456789101112678[[#This Row],[Actual Profit]]-Table234534568791112151416171819202122232425262728345678910113456789101112678[[#This Row],[Expense]] -> -2571.5 | M13: =Table234534568791112151416171819202122232425262728345678910113456789101112678[[#This Row],[Cash]]-Table234534568791112151416171819202122232425262728345678910113456789101112678[[#This Row],[Expense]] -> 8050 | O13: Date | Q13: Profit | R13: Actual | S13: Total | T13: Cash | U13: Account Transfer | V13: Expense
A14: 45669 | B14: =Table234534568791112151416171819202122232425262728345678910113456789101112678[[#This Row],[Profit]]-Table234534568791112151416171819202122232425262728345678910113456789101112678[[#This Row],[Mulbhag]] -> 6267.2 | C14: =Table234534568791112151416171819202122232425262728345678910113456789101112678[[#This Row],[Profit]]/3 -> 3133.6 | D14: =F14*0.3 -> 9400.8 | E14: =F14-D14 -> 21935.2 | F14: =G14+H14 -> 31336 | G14: 14145 | H14: 17191 | I14: 950 | K14: =Table234534568791112151416171819202122232425262728345678910113456789101112678[[#This Row],[Account Transfer]]-Table234534568791112151416171819202122232425262728345678910113456789101112678[[#This Row],[Expense Online]] -> 17191 | L14: =Table234534568791112151416171819202122232425262728345678910113456789101112678[[#This Row],[Cash]]-Table234534568791112151416171819202122232425262728345678910113456789101112678[[#This Row],[Mulbhag]]-Table234534568791112151416171819202122232425262728345678910113456789101112678[[#This Row],[Actual Profit]]-Table234534568791112151416171819202122232425262728345678910113456789101112678[[#This Row],[Expense]] -> 3794.2 | M14: =Table234534568791112151416171819202122232425262728345678910113456789101112678[[#This Row],[Cash]]-Table234534568791112151416171819202122232425262728345678910113456789101112678[[#This Row],[Expense]] -> 13195 | O14: =A10 -> 45665 | P14: =Q14/3 -> 2374 | Q14: =S14*0.3 -> 7122 | R14: =S14-Q14 -> 16618 | S14: =T14+U14 -> 23740 | T14: =VLOOKUP(O14,$A$1:$J$34,7,0) -> 13870 | U14: =VLOOKUP(O14,$A$1:$J$34,8,0) -> 9870 | V14: =VLOOKUP(O14,$A$1:$J$34,9,0) -> 1800
A15: 45670 | B15: =Table234534568791112151416171819202122232425262728345678910113456789101112678[[#This Row],[Profit]]-Table234534568791112151416171819202122232425262728345678910113456789101112678[[#This Row],[Mulbhag]] -> 4210 | C15: =Table234534568791112151416171819202122232425262728345678910113456789101112678[[#This Row],[Profit]]/3 -> 2105 | D15: =F15*0.3 -> 6315 | E15: =F15-D15 -> 14735 | F15: =G15+H15 -> 21050 | G15: 8680 | H15: 12370 | I15: 5080 | K15: =Table234534568791112151416171819202122232425262728345678910113456789101112678[[#This Row],[Account Transfer]]-Table234534568791112151416171819202122232425262728345678910113456789101112678[[#This Row],[Expense Online]] -> 12370 | L15: =Table234534568791112151416171819202122232425262728345678910113456789101112678[[#This Row],[Cash]]-Table234534568791112151416171819202122232425262728345678910113456789101112678[[#This Row],[Mulbhag]]-Table234534568791112151416171819202122232425262728345678910113456789101112678[[#This Row],[Actual Profit]]-Table234534568791112151416171819202122232425262728345678910113456789101112678[[#This Row],[Expense]] -> -2715 | M15: =Table234534568791112151416171819202122232425262728345678910113456789101112678[[#This Row],[Cash]]-Table234534568791112151416171819202122232425262728345678910113456789101112678[[#This Row],[Expense]] -> 3600 | O15: =A11 -> 45666 | P15: =Q15/3 -> 3179.6 | Q15: =S15*0.3 -> 9538.8 | R15: =S15-Q15 -> 22257.2 | S15: =T15+U15 -> 31796 | T15: =VLOOKUP(O15,$A$1:$J$34,7,0) -> 3214 | U15: =VLOOKUP(O15,$A$1:$J$34,8,0) -> 28582 | V15: =VLOOKUP(O15,$A$1:$J$34,9,0) -> 10230
A16: 45671 | B16: =Table234534568791112151416171819202122232425262728345678910113456789101112678[[#This Row],[Profit]]-Table234534568791112151416171819202122232425262728345678910113456789101112678[[#This Row],[Mulbhag]] -> 3849.2 | C16: =Table234534568791112151416171819202122232425262728345678910113456789101112678[[#This Row],[Profit]]/3 -> 1924.6 | D16: =F16*0.3 -> 5773.8 | E16: =F16-D16 -> 13472.2 | F16: =G16+H16 -> 19246 | G16: 6080 | H16: 13166 | I16: 6160 | K16: =Table234534568791112151416171819202122232425262728345678910113456789101112678[[#This Row],[Account Transfer]]-Table234534568791112151416171819202122232425262728345678910113456789101112678[[#This Row],[Expense Online]] -> 13166 | L16: =Table234534568791112151416171819202122232425262728345678910113456789101112678[[#This Row],[Cash]]-Table234534568791112151416171819202122232425262728345678910113456789101112678[[#This Row],[Mulbhag]]-Table234534568791112151416171819202122232425262728345678910113456789101112678[[#This Row],[Actual Profit]]-Table234534568791112151416171819202122232425262728345678910113456789101112678[[#This Row],[Expense]] -> -5853.8 | M16: =Table234534568791112151416171819202122232425262728345678910113456789101112678[[#This Row],[Cash]]-Table234534568791112151416171819202122232425262728345678910113456789101112678[[#This Row],[Expense]] -> -80 | O16: =A12 -> 45667 | P16: =Q16/3 -> 1646.6 | Q16: =S16*0.3 -> 4939.8 | R16: =S16-Q16 -> 11526.2 | S16: =T16+U16 -> 16466 | T16: =VLOOKUP(O16,$A$1:$J$34,7,0) -> 5880 | U16: =VLOOKUP(O16,$A$1:$J$34,8,0) -> 10586 | V16: =VLOOKUP(O16,$A$1:$J$34,9,0) -> 2540
A17: 45672 | B17: =Table234534568791112151416171819202122232425262728345678910113456789101112678[[#This Row],[Profit]]-Table234534568791112151416171819202122232425262728345678910113456789101112678[[#This Row],[Mulbhag]] -> 3169.6 | C17: =Table234534568791112151416171819202122232425262728345678910113456789101112678[[#This Row],[Profit]]/3 -> 1584.8 | D17: =F17*0.3 -> 4754.4 | E17: =F17-D17 -> 11093.6 | F17: =G17+H17 -> 15848 | G17: 8868 | H17: 6980 | I17: 1500 | K17: =Table234534568791112151416171819202122232425262728345678910113456789101112678[[#This Row],[Account Transfer]]-Table234534568791112151416171819202122232425262728345678910113456789101112678[[#This Row],[Expense Online]] -> 6980 | L17: =Table234534568791112151416171819202122232425262728345678910113456789101112678[[#This Row],[Cash]]-Table234534568791112151416171819202122232425262728345678910113456789101112678[[#This Row],[Mulbhag]]-Table234534568791112151416171819202122232425262728345678910113456789101112678[[#This Row],[Actual Profit]]-Table234534568791112151416171819202122232425262728345678910113456789101112678[[#This Row],[Expense]] -> 2613.6 | M17: =Table234534568791112151416171819202122232425262728345678910113456789101112678[[#This Row],[Cash]]-Table234534568791112151416171819202122232425262728345678910113456789101112678[[#This Row],[Expense]] -> 7368 | O17: =A13 -> 45668 | P17: =Q17/3 -> 3540.5 | Q17: =S17*0.3 -> 10621.5 | R17: =S17-Q17 -> 24783.5 | S17: =T17+U17 -> 35405 | T17: =VLOOKUP(O17,$A$1:$J$34,7,0) -> 11165 | U17: =VLOOKUP(O17,$A$1:$J$34,8,0) -> 24240 | V17: =VLOOKUP(O17,$A$1:$J$34,9,0) -> 3115
A18: 45673 | B18: =Table234534568791112151416171819202122232425262728345678910113456789101112678[[#This Row],[Profit]]-Table234534568791112151416171819202122232425262728345678910113456789101112678[[#This Row],[Mulbhag]] -> 6724 | C18: =Table234534568791112151416171819202122232425262728345678910113456789101112678[[#This Row],[Profit]]/3 -> 3362 | D18: =F18*0.3 -> 10086 | E18: =F18-D18 -> 23534 | F18: =G18+H18 -> 33620 | G18: 9360 | H18: 24260 | I18: 7100 | K18: =Table234534568791112151416171819202122232425262728345678910113456789101112678[[#This Row],[Account Transfer]]-Table234534568791112151416171819202122232425262728345678910113456789101112678[[#This Row],[Expense Online]] -> 24260 | L18: =Table234534568791112151416171819202122232425262728345678910113456789101112678[[#This Row],[Cash]]-Table234534568791112151416171819202122232425262728345678910113456789101112678[[#This Row],[Mulbhag]]-Table234534568791112151416171819202122232425262728345678910113456789101112678[[#This Row],[Actual Profit]]-Table234534568791112151416171819202122232425262728345678910113456789101112678[[#This Row],[Expense]] -> -7826 | M18: =Table234534568791112151416171819202122232425262728345678910113456789101112678[[#This Row],[Cash]]-Table234534568791112151416171819202122232425262728345678910113456789101112678[[#This Row],[Expense]] -> 2260 | O18: =A14 -> 45669 | P18: =Q18/3 -> 3133.6 | Q18: =S18*0.3 -> 9400.8 | R18: =S18-Q18 -> 21935.2 | S18: =T18+U18 -> 31336 | T18: =VLOOKUP(O18,$A$1:$J$34,7,0) -> 14145 | U18: =VLOOKUP(O18,$A$1:$J$34,8,0) -> 17191 | V18: =VLOOKUP(O18,$A$1:$J$34,9,0) -> 950
A19: 45674 | B19: =Table234534568791112151416171819202122232425262728345678910113456789101112678[[#This Row],[Profit]]-Table234534568791112151416171819202122232425262728345678910113456789101112678[[#This Row],[Mulbhag]] -> 3818 | C19: =Table234534568791112151416171819202122232425262728345678910113456789101112678[[#This Row],[Profit]]/3 -> 1909 | D19: =F19*0.3 -> 5727 | E19: =F19-D19 -> 13363 | F19: =G19+H19 -> 19090 | G19: 14050 | H19: 5040 | I19: 4330 | K19: =Table234534568791112151416171819202122232425262728345678910113456789101112678[[#This Row],[Account Transfer]]-Table234534568791112151416171819202122232425262728345678910113456789101112678[[#This Row],[Expense Online]] -> 5040 | L19: =Table234534568791112151416171819202122232425262728345678910113456789101112678[[#This Row],[Cash]]-Table234534568791112151416171819202122232425262728345678910113456789101112678[[#This Row],[Mulbhag]]-Table234534568791112151416171819202122232425262728345678910113456789101112678[[#This Row],[Actual Profit]]-Table234534568791112151416171819202122232425262728345678910113456789101112678[[#This Row],[Expense]] -> 3993 | M19: =Table234534568791112151416171819202122232425262728345678910113456789101112678[[#This Row],[Cash]]-Table234534568791112151416171819202122232425262728345678910113456789101112678[[#This Row],[Expense]] -> 9720 | O19: =A15 -> 45670 | P19: =Q19/3 -> 2105 | Q19: =S19*0.3 -> 6315 | R19: =S19-Q19 -> 14735 | S19: =T19+U19 -> 21050 | T19: =VLOOKUP(O19,$A$1:$J$34,7,0) -> 8680 | U19: =VLOOKUP(O19,$A$1:$J$34,8,0) -> 12370 | V19: =VLOOKUP(O19,$A$1:$J$34,9,0) -> 5080
A20: 45675 | B20: =Table234534568791112151416171819202122232425262728345678910113456789101112678[[#This Row],[Profit]]-Table234534568791112151416171819202122232425262728345678910113456789101112678[[#This Row],[Mulbhag]] -> 2326.6 | C20: =Table234534568791112151416171819202122232425262728345678910113456789101112678[[#This Row],[Profit]]/3 -> 1163.3 | D20: =F20*0.3 -> 3489.9 | E20: =F20-D20 -> 8143.1 | F20: =G20+H20 -> 11633 | G20: 5783 | H20: 5850 | I20: 130 | K20: =Table234534568791112151416171819202122232425262728345678910113456789101112678[[#This Row],[Account Transfer]]-Table234534568791112151416171819202122232425262728345678910113456789101112678[[#This Row],[Expense Online]] -> 5850 | L20: =Table234534568791112151416171819202122232425262728345678910113456789101112678[[#This Row],[Cash]]-Table234534568791112151416171819202122232425262728345678910113456789101112678[[#This Row],[Mulbhag]]-Table234534568791112151416171819202122232425262728345678910113456789101112678[[#This Row],[Actual Profit]]-Table234534568791112151416171819202122232425262728345678910113456789101112678[[#This Row],[Expense]] -> 2163.1 | M20: =Table234534568791112151416171819202122232425262728345678910113456789101112678[[#This Row],[Cash]]-Table234534568791112151416171819202122232425262728345678910113456789101112678[[#This Row],[Expense]] -> 5653 | O20: =A16 -> 45671 | P20: =Q20/3 -> 1924.6 | Q20: =S20*0.3 -> 5773.8 | R20: =S20-Q20 -> 13472.2 | S20: =T20+U20 -> 19246 | T20: =VLOOKUP(O20,$A$1:$J$34,7,0) -> 6080 | U20: =VLOOKUP(O20,$A$1:$J$34,8,0) -> 13166 | V20: =VLOOKUP(O20,$A$1:$J$34,9,0) -> 6160
A21: 45676 | B21: =Table234534568791112151416171819202122232425262728345678910113456789101112678[[#This Row],[Profit]]-Table234534568791112151416171819202122232425262728345678910113456789101112678[[#This Row],[Mulbhag]] -> 540 | C21: =Table234534568791112151416171819202122232425262728345678910113456789101112678[[#This Row],[Profit]]/3 -> 270 | D21: =F21*0.3 -> 810 | E21: =F21-D21 -> 1890 | F21: =G21+H21 -> 2700 | G21: 2200 | H21: 500 | I21: 600 | K21: =Table234534568791112151416171819202122232425262728345678910113456789101112678[[#This Row],[Account Transfer]]-Table234534568791112151416171819202122232425262728345678910113456789101112678[[#This Row],[Expense Online]] -> 500 | L21: =Table234534568791112151416171819202122232425262728345678910113456789101112678[[#This Row],[Cash]]-Table234534568791112151416171819202122232425262728345678910113456789101112678[[#This Row],[Mulbhag]]-Table234534568791112151416171819202122232425262728345678910113456789101112678[[#This Row],[Actual Profit]]-Table234534568791112151416171819202122232425262728345678910113456789101112678[[#This Row],[Expense]] -> 790 | M21: =Table234534568791112151416171819202122232425262728345678910113456789101112678[[#This Row],[Cash]]-Table234534568791112151416171819202122232425262728345678910113456789101112678[[#This Row],[Expense]] -> 1600 | O21: Total | P21: =SUM(P14:P20) -> 17903.9 | Q21: =SUM(Q14:Q20) -> 53711.7 | R21: =SUM(R14:R20) -> 125327.3 | S21: =SUM(S14:S20) -> 179039 | T21: =SUM(T14:T20) -> 63034 | U21: =SUM(U14:U20) -> 116005 | V21: =SUM(V14:V20) -> 29875
A22: 45677 | B22: =Table234534568791112151416171819202122232425262728345678910113456789101112678[[#This Row],[Profit]]-Table234534568791112151416171819202122232425262728345678910113456789101112678[[#This Row],[Mulbhag]] -> 4475.2 | C22: =Table234534568791112151416171819202122232425262728345678910113456789101112678[[#This Row],[Profit]]/3 -> 2237.6 | D22: =F22*0.3 -> 6712.8 | E22: =F22-D22 -> 15663.2 | F22: =G22+H22 -> 22376 | G22: 200 | H22: 22176 | I22: 300 | K22: =Table234534568791112151416171819202122232425262728345678910113456789101112678[[#This Row],[Account Transfer]]-Table234534568791112151416171819202122232425262728345678910113456789101112678[[#This Row],[Expense Online]] -> 22176 | L22: =Table234534568791112151416171819202122232425262728345678910113456789101112678[[#This Row],[Cash]]-Table234534568791112151416171819202122232425262728345678910113456789101112678[[#This Row],[Mulbhag]]-Table234534568791112151416171819202122232425262728345678910113456789101112678[[#This Row],[Actual Profit]]-Table234534568791112151416171819202122232425262728345678910113456789101112678[[#This Row],[Expense]] -> -6812.8 | M22: =Table234534568791112151416171819202122232425262728345678910113456789101112678[[#This Row],[Cash]]-Table234534568791112151416171819202122232425262728345678910113456789101112678[[#This Row],[Expense]] -> -100 | O22: Mul Bhag | Q22: =Q21/3 -> 17903.9 | S22: =R22+Q22 -> 17903.9
A23: 45678 | B23: =Table234534568791112151416171819202122232425262728345678910113456789101112678[[#This Row],[Profit]]-Table234534568791112151416171819202122232425262728345678910113456789101112678[[#This Row],[Mulbhag]] -> 2066.2 | C23: =Table234534568791112151416171819202122232425262728345678910113456789101112678[[#This Row],[Profit]]/3 -> 1033.1 | D23: =F23*0.3 -> 3099.3 | E23: =F23-D23 -> 7231.7 | F23: =G23+H23 -> 10331 | G23: 3630 | H23: 6701 | I23: 1390 | K23: =Table234534568791112151416171819202122232425262728345678910113456789101112678[[#This Row],[Account Transfer]]-Table234534568791112151416171819202122232425262728345678910113456789101112678[[#This Row],[Expense Online]] -> 6701 | L23: =Table234534568791112151416171819202122232425262728345678910113456789101112678[[#This Row],[Cash]]-Table234534568791112151416171819202122232425262728345678910113456789101112678[[#This Row],[Mulbhag]]-Table234534568791112151416171819202122232425262728345678910113456789101112678[[#This Row],[Actual Profit]]-Table234534568791112151416171819202122232425262728345678910113456789101112678[[#This Row],[Expense]] -> -859.3 | M23: =Table234534568791112151416171819202122232425262728345678910113456789101112678[[#This Row],[Cash]]-Table234534568791112151416171819202122232425262728345678910113456789101112678[[#This Row],[Expense]] -> 2240
A24: 45679 | B24: =Table234534568791112151416171819202122232425262728345678910113456789101112678[[#This Row],[Profit]]-Table234534568791112151416171819202122232425262728345678910113456789101112678[[#This Row],[Mulbhag]] -> 5079.6 | C24: =Table234534568791112151416171819202122232425262728345678910113456789101112678[[#This Row],[Profit]]/3 -> 2539.8 | D24: =F24*0.3 -> 7619.4 | E24: =F24-D24 -> 17778.6 | F24: =G24+H24 -> 25398 | G24: 9780 | H24: 15618 | I24: 3330 | K24: =Table234534568791112151416171819202122232425262728345678910113456789101112678[[#This Row],[Account Transfer]]-Table234534568791112151416171819202122232425262728345678910113456789101112678[[#This Row],[Expense Online]] -> 15618 | L24: =Table234534568791112151416171819202122232425262728345678910113456789101112678[[#This Row],[Cash]]-Table234534568791112151416171819202122232425262728345678910113456789101112678[[#This Row],[Mulbhag]]-Table234534568791112151416171819202122232425262728345678910113456789101112678[[#This Row],[Actual Profit]]-Table234534568791112151416171819202122232425262728345678910113456789101112678[[#This Row],[Expense]] -> -1169.4 | M24: =Table234534568791112151416171819202122232425262728345678910113456789101112678[[#This Row],[Cash]]-Table234534568791112151416171819202122232425262728345678910113456789101112678[[#This Row],[Expense]] -> 6450 | O24: Date | Q24: Profit | R24: Actual | S24: Total | T24: Cash | U24: Account Transfer | V24: Expense
A25: 45680 | B25: =Table234534568791112151416171819202122232425262728345678910113456789101112678[[#This Row],[Profit]]-Table234534568791112151416171819202122232425262728345678910113456789101112678[[#This Row],[Mulbhag]] -> 5350 | C25: =Table234534568791112151416171819202122232425262728345678910113456789101112678[[#This Row],[Profit]]/3 -> 2675 | D25: =F25*0.3 -> 8025 | E25: =F25-D25 -> 18725 | F25: =G25+H25 -> 26750 | G25: 12900 | H25: 13850 | I25: 7080 | K25: =Table234534568791112151416171819202122232425262728345678910113456789101112678[[#This Row],[Account Transfer]]-Table234534568791112151416171819202122232425262728345678910113456789101112678[[#This Row],[Expense Online]] -> 13850 | L25: =Table234534568791112151416171819202122232425262728345678910113456789101112678[[#This Row],[Cash]]-Table234534568791112151416171819202122232425262728345678910113456789101112678[[#This Row],[Mulbhag]]-Table234534568791112151416171819202122232425262728345678910113456789101112678[[#This Row],[Actual Profit]]-Table234534568791112151416171819202122232425262728345678910113456789101112678[[#This Row],[Expense]] -> -2205 | M25: =Table234534568791112151416171819202122232425262728345678910113456789101112678[[#This Row],[Cash]]-Table234534568791112151416171819202122232425262728345678910113456789101112678[[#This Row],[Expense]] -> 5820 | O25: =A17 -> 45672 | P25: =Q25/3 -> 1584.8 | Q25: =S25*0.3 -> 4754.4 | R25: =S25-Q25 -> 11093.6 | S25: =T25+U25 -> 15848 | T25: =VLOOKUP(O25,$A$1:$J$34,7,0) -> 8868 | U25: =VLOOKUP(O25,$A$1:$J$34,8,0) -> 6980 | V25: =VLOOKUP(O25,$A$1:$J$34,9,0) -> 1500
A26: 45681 | B26: =Table234534568791112151416171819202122232425262728345678910113456789101112678[[#This Row],[Profit]]-Table234534568791112151416171819202122232425262728345678910113456789101112678[[#This Row],[Mulbhag]] -> 1556 | C26: =Table234534568791112151416171819202122232425262728345678910113456789101112678[[#This Row],[Profit]]/3 -> 778 | D26: =F26*0.3 -> 2334 | E26: =F26-D26 -> 5446 | F26: =G26+H26 -> 7780 | G26: 3580 | H26: 4200 | I26: 1800 | K26: =Table234534568791112151416171819202122232425262728345678910113456789101112678[[#This Row],[Account Transfer]]-Table234534568791112151416171819202122232425262728345678910113456789101112678[[#This Row],[Expense Online]] -> 4200 | L26: =Table234534568791112151416171819202122232425262728345678910113456789101112678[[#This Row],[Cash]]-Table234534568791112151416171819202122232425262728345678910113456789101112678[[#This Row],[Mulbhag]]-Table234534568791112151416171819202122232425262728345678910113456789101112678[[#This Row],[Actual Profit]]-Table234534568791112151416171819202122232425262728345678910113456789101112678[[#This Row],[Expense]] -> -554 | M26: =Table234534568791112151416171819202122232425262728345678910113456789101112678[[#This Row],[Cash]]-Table234534568791112151416171819202122232425262728345678910113456789101112678[[#This Row],[Expense]] -> 1780 | O26: =A18 -> 45673 | P26: =Q26/3 -> 3362 | Q26: =S26*0.3 -> 10086 | R26: =S26-Q26 -> 23534 | S26: =T26+U26 -> 33620 | T26: =VLOOKUP(O26,$A$1:$J$34,7,0) -> 9360 | U26: =VLOOKUP(O26,$A$1:$J$34,8,0) -> 24260 | V26: =VLOOKUP(O26,$A$1:$J$34,9,0) -> 7100
A27: 45682 | B27: =Table234534568791112151416171819202122232425262728345678910113456789101112678[[#This Row],[Profit]]-Table234534568791112151416171819202122232425262728345678910113456789101112678[[#This Row],[Mulbhag]] -> 3051 | C27: =Table234534568791112151416171819202122232425262728345678910113456789101112678[[#This Row],[Profit]]/3 -> 1525.5 | D27: =F27*0.3 -> 4576.5 | E27: =F27-D27 -> 10678.5 | F27: =G27+H27 -> 15255 | G27: 4845 | H27: 10410 | I27: 25550 | K27: =Table234534568791112151416171819202122232425262728345678910113456789101112678[[#This Row],[Account Transfer]]-Table234534568791112151416171819202122232425262728345678910113456789101112678[[#This Row],[Expense Online]] -> 10410 | L27: =Table234534568791112151416171819202122232425262728345678910113456789101112678[[#This Row],[Cash]]-Table234534568791112151416171819202122232425262728345678910113456789101112678[[#This Row],[Mulbhag]]-Table234534568791112151416171819202122232425262728345678910113456789101112678[[#This Row],[Actual Profit]]-Table234534568791112151416171819202122232425262728345678910113456789101112678[[#This Row],[Expense]] -> -25281.5 | M27: =Table234534568791112151416171819202122232425262728345678910113456789101112678[[#This Row],[Cash]]-Table234534568791112151416171819202122232425262728345678910113456789101112678[[#This Row],[Expense]] -> -20705 | O27: =A19 -> 45674 | P27: =Q27/3 -> 1909 | Q27: =S27*0.3 -> 5727 | R27: =S27-Q27 -> 13363 | S27: =T27+U27 -> 19090 | T27: =VLOOKUP(O27,$A$1:$J$34,7,0) -> 14050 | U27: =VLOOKUP(O27,$A$1:$J$34,8,0) -> 5040 | V27: =VLOOKUP(O27,$A$1:$J$34,9,0) -> 4330
A28: 45683 | B28: =Table234534568791112151416171819202122232425262728345678910113456789101112678[[#This Row],[Profit]]-Table234534568791112151416171819202122232425262728345678910113456789101112678[[#This Row],[Mulbhag]] -> 5738 | C28: =Table234534568791112151416171819202122232425262728345678910113456789101112678[[#This Row],[Profit]]/3 -> 2869 | D28: =F28*0.3 -> 8607 | E28: =F28-D28 -> 20083 | F28: =G28+H28 -> 28690 | G28: 3400 | H28: 25290 | I28: 2420 | K28: =Table234534568791112151416171819202122232425262728345678910113456789101112678[[#This Row],[Account Transfer]]-Table234534568791112151416171819202122232425262728345678910113456789101112678[[#This Row],[Expense Online]] -> 25290 | L28: =Table234534568791112151416171819202122232425262728345678910113456789101112678[[#This Row],[Cash]]-Table234534568791112151416171819202122232425262728345678910113456789101112678[[#This Row],[Mulbhag]]-Table234534568791112151416171819202122232425262728345678910113456789101112678[[#This Row],[Actual Profit]]-Table234534568791112151416171819202122232425262728345678910113456789101112678[[#This Row],[Expense]] -> -7627 | M28: =Table234534568791112151416171819202122232425262728345678910113456789101112678[[#This Row],[Cash]]-Table234534568791112151416171819202122232425262728345678910113456789101112678[[#This Row],[Expense]] -> 980 | O28: =A20 -> 45675 | P28: =Q28/3 -> 1163.3 | Q28: =S28*0.3 -> 3489.9 | R28: =S28-Q28 -> 8143.1 | S28: =T28+U28 -> 11633 | T28: =VLOOKUP(O28,$A$1:$J$34,7,0) -> 5783 | U28: =VLOOKUP(O28,$A$1:$J$34,8,0) -> 5850 | V28: =VLOOKUP(O28,$A$1:$J$34,9,0) -> 130
A29: 45684 | B29: =Table234534568791112151416171819202122232425262728345678910113456789101112678[[#This Row],[Profit]]-Table234534568791112151416171819202122232425262728345678910113456789101112678[[#This Row],[Mulbhag]] -> 4120 | C29: =Table234534568791112151416171819202122232425262728345678910113456789101112678[[#This Row],[Profit]]/3 -> 2060 | D29: =F29*0.3 -> 6180 | E29: =F29-D29 -> 14420 | F29: =G29+H29 -> 20600 | G29: 3980 | H29: 16620 | I29: 1690 | K29: =Table234534568791112151416171819202122232425262728345678910113456789101112678[[#This Row],[Account Transfer]]-Table234534568791112151416171819202122232425262728345678910113456789101112678[[#This Row],[Expense Online]] -> 16620 | L29: =Table234534568791112151416171819202122232425262728345678910113456789101112678[[#This Row],[Cash]]-Table234534568791112151416171819202122232425262728345678910113456789101112678[[#This Row],[Mulbhag]]-Table234534568791112151416171819202122232425262728345678910113456789101112678[[#This Row],[Actual Profit]]-Table234534568791112151416171819202122232425262728345678910113456789101112678[[#This Row],[Expense]] -> -3890 | M29: =Table234534568791112151416171819202122232425262728345678910113456789101112678[[#This Row],[Cash]]-Table234534568791112151416171819202122232425262728345678910113456789101112678[[#This Row],[Expense]] -> 2290 | O29: =A21 -> 45676 | P29: =Q29/3 -> 270 | Q29: =S29*0.3 -> 810 | R29: =S29-Q29 -> 1890 | S29: =T29+U29 -> 2700 | T29: =VLOOKUP(O29,$A$1:$J$34,7,0) -> 2200 | U29: =VLOOKUP(O29,$A$1:$J$34,8,0) -> 500 | V29: =VLOOKUP(O29,$A$1:$J$34,9,0) -> 600
A30: 45685 | B30: =Table234534568791112151416171819202122232425262728345678910113456789101112678[[#This Row],[Profit]]-Table234534568791112151416171819202122232425262728345678910113456789101112678[[#This Row],[Mulbhag]] -> 9683.4 | C30: =Table234534568791112151416171819202122232425262728345678910113456789101112678[[#This Row],[Profit]]/3 -> 4841.7 | D30: =F30*0.3 -> 14525.1 | E30: =F30-D30 -> 33891.9 | F30: =G30+H30 -> 48417 | G30: 37110 | H30: 11307 | I30: 1110 | K30: =Table234534568791112151416171819202122232425262728345678910113456789101112678[[#This Row],[Account Transfer]]-Table234534568791112151416171819202122232425262728345678910113456789101112678[[#This Row],[Expense Online]] -> 11307 | L30: =Table234534568791112151416171819202122232425262728345678910113456789101112678[[#This Row],[Cash]]-Table234534568791112151416171819202122232425262728345678910113456789101112678[[#This Row],[Mulbhag]]-Table234534568791112151416171819202122232425262728345678910113456789101112678[[#This Row],[Actual Profit]]-Table234534568791112151416171819202122232425262728345678910113456789101112678[[#This Row],[Expense]] -> 21474.9 | M30: =Table234534568791112151416171819202122232425262728345678910113456789101112678[[#This Row],[Cash]]-Table234534568791112151416171819202122232425262728345678910113456789101112678[[#This Row],[Expense]] -> 36000 | O30: =A22 -> 45677 | P30: =Q30/3 -> 2237.6 | Q30: =S30*0.3 -> 6712.8 | R30: =S30-Q30 -> 15663.2 | S30: =T30+U30 -> 22376 | T30: =VLOOKUP(O30,$A$1:$J$34,7,0) -> 200 | U30: =VLOOKUP(O30,$A$1:$J$34,8,0) -> 22176 | V30: =VLOOKUP(O30,$A$1:$J$34,9,0) -> 300
A31: 45686 | B31: =Table234534568791112151416171819202122232425262728345678910113456789101112678[[#This Row],[Profit]]-Table234534568791112151416171819202122232425262728345678910113456789101112678[[#This Row],[Mulbhag]] -> 3326 | C31: =Table234534568791112151416171819202122232425262728345678910113456789101112678[[#This Row],[Profit]]/3 -> 1663 | D31: =F31*0.3 -> 4989 | E31: =F31-D31 -> 11641 | F31: =G31+H31 -> 16630 | G31: 12900 | H31: 3730 | I31: 3333 | K31: =Table234534568791112151416171819202122232425262728345678910113456789101112678[[#This Row],[Account Transfer]]-Table234534568791112151416171819202122232425262728345678910113456789101112678[[#This Row],[Expense Online]] -> 3730 | L31: =Table234534568791112151416171819202122232425262728345678910113456789101112678[[#This Row],[Cash]]-Table234534568791112151416171819202122232425262728345678910113456789101112678[[#This Row],[Mulbhag]]-Table234534568791112151416171819202122232425262728345678910113456789101112678[[#This Row],[Actual Profit]]-Table234534568791112151416171819202122232425262728345678910113456789101112678[[#This Row],[Expense]] -> 4578 | M31: =Table234534568791112151416171819202122232425262728345678910113456789101112678[[#This Row],[Cash]]-Table234534568791112151416171819202122232425262728345678910113456789101112678[[#This Row],[Expense]] -> 9567 | O31: =A23 -> 45678 | P31: =Q31/3 -> 1033.1 | Q31: =S31*0.3 -> 3099.3 | R31: =S31-Q31 -> 7231.7 | S31: =T31+U31 -> 10331 | T31: =VLOOKUP(O31,$A$1:$J$34,7,0) -> 3630 | U31: =VLOOKUP(O31,$A$1:$J$34,8,0) -> 6701 | V31: =VLOOKUP(O31,$A$1:$J$34,9,0) -> 1390
A32: 45687 | B32: =Table234534568791112151416171819202122232425262728345678910113456789101112678[[#This Row],[Profit]]-Table234534568791112151416171819202122232425262728345678910113456789101112678[[#This Row],[Mulbhag]] -> 3198.4 | C32: =Table234534568791112151416171819202122232425262728345678910113456789101112678[[#This Row],[Profit]]/3 -> 1599.2 | D32: =F32*0.3 -> 4797.6 | E32: =F32-D32 -> 11194.4 | F32: =G32+H32 -> 15992 | G32: 8610 | H32: 7382 | I32: 1120 | K32: =Table234534568791112151416171819202122232425262728345678910113456789101112678[[#This Row],[Account Transfer]]-Table234534568791112151416171819202122232425262728345678910113456789101112678[[#This Row],[Expense Online]] -> 7382 | L32: =Table234534568791112151416171819202122232425262728345678910113456789101112678[[#This Row],[Cash]]-Table234534568791112151416171819202122232425262728345678910113456789101112678[[#This Row],[Mulbhag]]-Table234534568791112151416171819202122232425262728345678910113456789101112678[[#This Row],[Actual Profit]]-Table234534568791112151416171819202122232425262728345678910113456789101112678[[#This Row],[Expense]] -> 2692.4 | M32: =Table234534568791112151416171819202122232425262728345678910113456789101112678[[#This Row],[Cash]]-Table234534568791112151416171819202122232425262728345678910113456789101112678[[#This Row],[Expense]] -> 7490 | O32: Total | P32: =SUM(P25:P31) -> 11559.8 | Q32: =SUM(Q25:Q31) -> 34679.4 | R32: =SUM(R25:R31) -> 80918.6 | S32: =SUM(S25:S31) -> 115598 | T32: =SUM(T25:T31) -> 44091 | U32: =SUM(U25:U31) -> 71507 | V32: =SUM(V25:V31) -> 15350
A33: 45688 | B33: =Table234534568791112151416171819202122232425262728345678910113456789101112678[[#This Row],[Profit]]-Table234534568791112151416171819202122232425262728345678910113456789101112678[[#This Row],[Mulbhag]] -> 2898 | C33: =Table234534568791112151416171819202122232425262728345678910113456789101112678[[#This Row],[Profit]]/3 -> 1449 | D33: =F33*0.3 -> 4347 | E33: =F33-D33 -> 10143 | F33: =G33+H33 -> 14490 | G33: 12800 | H33: 1690 | I33: 3180 | K33: =Table234534568791112151416171819202122232425262728345678910113456789101112678[[#This Row],[Account Transfer]]-Table234534568791112151416171819202122232425262728345678910113456789101112678[[#This Row],[Expense Online]] -> 1690 | L33: =Table234534568791112151416171819202122232425262728345678910113456789101112678[[#This Row],[Cash]]-Table234534568791112151416171819202122232425262728345678910113456789101112678[[#This Row],[Mulbhag]]-Table234534568791112151416171819202122232425262728345678910113456789101112678[[#This Row],[Actual Profit]]-Table234534568791112151416171819202122232425262728345678910113456789101112678[[#This Row],[Expense]] -> 5273 | M33: =Table234534568791112151416171819202122232425262728345678910113456789101112678[[#This Row],[Cash]]-Table234534568791112151416171819202122232425262728345678910113456789101112678[[#This Row],[Expense]] -> 9620 | O33: Mul Bhag | Q33: =Q32/3 -> 11559.8
A34: Total | B34: =SUBTOTAL(109,Table234534568791112151416171819202122232425262728345678910113456789101112678[Actual Profit]) -> 130465 | C34: =SUBTOTAL(109,Table234534568791112151416171819202122232425262728345678910113456789101112678[Mulbhag]) -> 65232.5 | D34: =SUBTOTAL(109,Table234534568791112151416171819202122232425262728345678910113456789101112678[Profit]) -> 195697.5 | E34: =SUBTOTAL(109,Table234534568791112151416171819202122232425262728345678910113456789101112678[Profit]) -> 195697.5 | F34: =SUM(F3:F33) -> 652325 | G34: =SUBTOTAL(109,Table234534568791112151416171819202122232425262728345678910113456789101112678[Profit]) -> 195697.5 | H34: =SUBTOTAL(109,Table234534568791112151416171819202122232425262728345678910113456789101112678[Profit]) -> 195697.5 | I34: =SUM(I5:I33) -> 159275 | J34: =SUBTOTAL(109,Table234534568791112151416171819202122232425262728345678910113456789101112678[Expense Online]) -> 500 | K34: =SUBTOTAL(109,Table234534568791112151416171819202122232425262728345678910113456789101112678[Account Balance]) -> 369691 | L34: =SUM(L5:L33) -> -74554.3 | M34: =SUBTOTAL(109,Table234534568791112151416171819202122232425262728345678910113456789101112678[Actual Balance]) -> 120519
O35: Date | Q35: Profit | R35: Actual | S35: Total | T35: Cash | U35: Account Transfer | V35: Expense
O36: =A24 -> 45679 | P36: =Q36/3 -> 2539.8 | Q36: =S36*0.3 -> 7619.4 | R36: =S36-Q36 -> 17778.6 | S36: =T36+U36 -> 25398 | T36: =VLOOKUP(O36,$A$1:$J$34,7,0) -> 9780 | U36: =VLOOKUP(O36,$A$1:$J$34,8,0) -> 15618 | V36: =VLOOKUP(O36,$A$1:$J$34,9,0) -> 3330
A37: Date | B37: Actual Profit | C37: Mulbhag | D37: Profit | E37: Actual | F37: Total | G37: Cash | H37: Account Transfer | I37: Expense | O37: =A25 -> 45680 | P37: =Q37/3 -> 2675 | Q37: =S37*0.3 -> 8025 | R37: =S37-Q37 -> 18725 | S37: =T37+U37 -> 26750 | T37: =VLOOKUP(O37,$A$1:$J$34,7,0) -> 12900 | U37: =VLOOKUP(O37,$A$1:$J$34,8,0) -> 13850 | V37: =VLOOKUP(O37,$A$1:$J$34,9,0) -> 7080
A38: =CONCATENATE(TEXT(O3,"DD-MMM-YYY")," to ",TEXT(O9,"DD-MMM-YYYY")) -> 01-Jan-2025 to 07-Jan-2025 | B38: =D38-C38 -> 27537.2 | C38: =D38/3 -> 13768.6 | D38: =Q10 -> 41305.8 | E38: =R10 -> 96380.2 | F38: =S10 -> 137686 | G38: =T10 -> 65104 | H38: =U10 -> 72582 | I38: =V10 -> 65777 | O38: =A26 -> 45681 | P38: =Q38/3 -> 778 | Q38: =S38*0.3 -> 2334 | R38: =S38-Q38 -> 5446 | S38: =T38+U38 -> 7780 | T38: =VLOOKUP(O38,$A$1:$J$34,7,0) -> 3580 | U38: =VLOOKUP(O38,$A$1:$J$34,8,0) -> 4200 | V38: =VLOOKUP(O38,$A$1:$J$34,9,0) -> 1800
A39: =CONCATENATE(TEXT(O14,"DD-MMM-YYY")," to ",TEXT(O20,"DD-MMM-YYYY")) -> 08-Jan-2025 to 14-Jan-2025 | B39: =D39-C39 -> 35807.8 | C39: =D39/3 -> 17903.9 | D39: =Q21 -> 53711.7 | E39: =R21 -> 125327.3 | F39: =S21 -> 179039 | G39: =T21 -> 63034 | H39: =U21 -> 116005 | I39: =V21 -> 29875 | O39: =A27 -> 45682 | P39: =Q39/3 -> 1525.5 | Q39: =S39*0.3 -> 4576.5 | R39: =S39-Q39 -> 10678.5 | S39: =T39+U39 -> 15255 | T39: =VLOOKUP(O39,$A$1:$J$34,7,0) -> 4845 | U39: =VLOOKUP(O39,$A$1:$J$34,8,0) -> 10410 | V39: =VLOOKUP(O39,$A$1:$J$34,9,0) -> 25550
A40: =CONCATENATE(TEXT(O25,"DD-MMM-YYY")," to ",TEXT(O31,"DD-MMM-YYYY")) -> 15-Jan-2025 to 21-Jan-2025 | B40: =D40-C40 -> 23119.6 | C40: =D40/3 -> 11559.8 | D40: =Q32 -> 34679.4 | E40: =R32 -> 80918.6 | F40: =S32 -> 115598 | G40: =T32 -> 44091 | H40: =U32 -> 71507 | I40: =V32 -> 15350 | O40: =A28 -> 45683 | P40: =Q40/3 -> 2869 | Q40: =S40*0.3 -> 8607 | R40: =S40-Q40 -> 20083 | S40: =T40+U40 -> 28690 | T40: =VLOOKUP(O40,$A$1:$J$34,7,0) -> 3400 | U40: =VLOOKUP(O40,$A$1:$J$34,8,0) -> 25290 | V40: =VLOOKUP(O40,$A$1:$J$34,9,0) -> 2420
A41: =CONCATENATE(TEXT(O36,"DD-MMM-YYY")," to ",TEXT(O41,"DD-MMM-YYYY")) -> 22-Jan-2025 to 31-Jan-2025 | B41: =D41-C41 -> 23672.6 | C41: =D41/3 -> 11836.3 | D41: =Q42 -> 35508.9 | E41: =R42 -> 82854.1 | F41: =S42 -> 118363 | G41: =T42 -> 47305 | H41: =U42 -> 71058 | I41: =V42 -> 43360 | O41: =A33 -> 45688 | P41: =Q41/3 -> 1449 | Q41: =S41*0.3 -> 4347 | R41: =S41-Q41 -> 10143 | S41: =T41+U41 -> 14490 | T41: =VLOOKUP(O41,$A$1:$J$34,7,0) -> 12800 | U41: =VLOOKUP(O41,$A$1:$J$34,8,0) -> 1690 | V41: =VLOOKUP(O41,$A$1:$J$34,9,0) -> 3180
A42: =CONCATENATE(TEXT(O3,"DD-MMM-YYY")," to ",TEXT(O41,"DD-MMM-YYYY")) -> 01-Jan-2025 to 31-Jan-2025 | B42: =D42-C42 -> 110137.2 | C42: =D42/3 -> 55068.6 | D42: =SUM(D38:D41) -> 165205.8 | E42: =SUM(E38:E41) -> 385480.2 | F42: =SUM(F38:F41) -> 550686 | G42: =SUM(G38:G41) -> 219534 | H42: =SUM(H38:H41) -> 331152 | I42: =SUM(I38:I41) -> 154362 | O42: Total | P42: =SUM(P36:P41) -> 11836.3 | Q42: =SUM(Q36:Q41) -> 35508.9 | R42: =SUM(R36:R41) -> 82854.1 | S42: =SUM(S36:S41) -> 118363 | T42: =SUM(T36:T41) -> 47305 | U42: =SUM(U36:U41) -> 71058 | V42: =SUM(V36:V41) -> 43360
E43: Total | O43: Mul Bhag | Q43: =Q42/3 -> 11836.3
O46: Date | Q46: Profit | R46: Actual | S46: Total | T46: Cash | U46: Account Transfer | V46: Expense
O47: =A7 -> 45662 | Q47: =SUM(D8:D33) -> 166953.3 | R47: =SUM(E8:E33) -> 389557.7 | S47: =SUM(F8:F33) -> 556511 | T47: =SUM(G8:G33) -> 235960 | U47: =SUM(H8:H33) -> 320551 | V47: =SUM(I8:I33) -> 150675
O48: Mul Bhag | Q48: =Q47/3 -> 55651.1

Sheet Febuary 2025
A1: Date | B1: Actual Profit | C1: Mulbhag | D1: Profit | E1: Actual | F1: Total | G1: Cash | H1: Account Transfer | I1: Expense | J1: Expense Online | K1: Account Balance | L1: cash on hand | M1: Actual Balance | O1: Date | P1: Mul Bhag | Q1: Profit | R1: Actual | S1: Total | T1: Cash | U1: Account Transfer | V1: Expense
A2: Last month Balance | B2: =Table2345345687911121514161718192021222324252627283456789101134567891011126789[[#This Row],[Profit]]-Table2345345687911121514161718192021222324252627283456789101134567891011126789[[#This Row],[Mulbhag]] -> 0 | C2: =Table2345345687911121514161718192021222324252627283456789101134567891011126789[[#This Row],[Profit]]/3 -> 0 | D2: =F2*0.3 -> 0 | E2: =F2-D2 -> 0 | F2: =G2+H2 -> 0 | K2: =Table2345345687911121514161718192021222324252627283456789101134567891011126789[[#This Row],[Account Transfer]]-Table2345345687911121514161718192021222324252627283456789101134567891011126789[[#This Row],[Expense Online]] -> 0 | L2: =Table2345345687911121514161718192021222324252627283456789101134567891011126789[[#This Row],[Cash]]-Table2345345687911121514161718192021222324252627283456789101134567891011126789[[#This Row],[Mulbhag]]-Table2345345687911121514161718192021222324252627283456789101134567891011126789[[#This Row],[Actual Profit]]-Table2345345687911121514161718192021222324252627283456789101134567891011126789[[#This Row],[Expense]] -> 0 | M2: =Table2345345687911121514161718192021222324252627283456789101134567891011126789[[#This Row],[Cash]]-Table2345345687911121514161718192021222324252627283456789101134567891011126789[[#This Row],[Expense]] -> 0 | O2: Export | V2: 0
A3: 45689 | B3: =Table2345345687911121514161718192021222324252627283456789101134567891011126789[[#This Row],[Profit]]-Table2345345687911121514161718192021222324252627283456789101134567891011126789[[#This Row],[Mulbhag]] -> 834 | C3: =Table2345345687911121514161718192021222324252627283456789101134567891011126789[[#This Row],[Profit]]/3 -> 417 | D3: =F3*0.3 -> 1251 | E3: =F3-D3 -> 2919 | F3: =G3+H3 -> 4170 | G3: 1970 | H3: 2200 | I3: 1060 | K3: =Table2345345687911121514161718192021222324252627283456789101134567891011126789[[#This Row],[Account Transfer]]-Table2345345687911121514161718192021222324252627283456789101134567891011126789[[#This Row],[Expense Online]] -> 2200 | L3: =Table2345345687911121514161718192021222324252627283456789101134567891011126789[[#This Row],[Cash]]-Table2345345687911121514161718192021222324252627283456789101134567891011126789[[#This Row],[Mulbhag]]-Table2345345687911121514161718192021222324252627283456789101134567891011126789[[#This Row],[Actual Profit]]-Table2345345687911121514161718192021222324252627283456789101134567891011126789[[#This Row],[Expense]] -> -341 | M3: =Table2345345687911121514161718192021222324252627283456789101134567891011126789[[#This Row],[Cash]]-Table2345345687911121514161718192021222324252627283456789101134567891011126789[[#This Row],[Expense]] -> 910 | O3: =A3 -> 45689 | P3: =Q3/3 -> 417 | Q3: =S3*0.3 -> 1251 | R3: =S3-Q3 -> 2919 | S3: =T3+U3 -> 4170 | T3: =VLOOKUP(O3,$A$1:$J$34,7,0) -> 1970 | U3: =VLOOKUP(O3,$A$1:$J$34,8,0) -> 2200 | V3: =VLOOKUP(O3,$A$1:$J$34,9,0) -> 1060
A4: 45690 | B4: =Table2345345687911121514161718192021222324252627283456789101134567891011126789[[#This Row],[Profit]]-Table2345345687911121514161718192021222324252627283456789101134567891011126789[[#This Row],[Mulbhag]] -> 3533 | C4: =Table2345345687911121514161718192021222324252627283456789101134567891011126789[[#This Row],[Profit]]/3 -> 1766.5 | D4: =F4*0.3 -> 5299.5 | E4: =F4-D4 -> 12365.5 | F4: =G4+H4 -> 17665 | G4: 5595 | H4: 12070 | I4: 2154 | K4: =Table2345345687911121514161718192021222324252627283456789101134567891011126789[[#This Row],[Account Transfer]]-Table2345345687911121514161718192021222324252627283456789101134567891011126789[[#This Row],[Expense Online]] -> 12070 | L4: =Table2345345687911121514161718192021222324252627283456789101134567891011126789[[#This Row],[Cash]]-Table2345345687911121514161718192021222324252627283456789101134567891011126789[[#This Row],[Mulbhag]]-Table2345345687911121514161718192021222324252627283456789101134567891011126789[[#This Row],[Actual Profit]]-Table2345345687911121514161718192021222324252627283456789101134567891011126789[[#This Row],[Expense]]+L3 -> -2199.5 | M4: =Table2345345687911121514161718192021222324252627283456789101134567891011126789[[#This Row],[Cash]]-Table2345345687911121514161718192021222324252627283456789101134567891011126789[[#This Row],[Expense]] -> 3441 | O4: =A4 -> 45690 | P4: =Q4/3 -> 1766.5 | Q4: =S4*0.3 -> 5299.5 | R4: =S4-Q4 -> 12365.5 | S4: =T4+U4 -> 17665 | T4: =VLOOKUP(O4,$A$1:$J$34,7,0) -> 5595 | U4: =VLOOKUP(O4,$A$1:$J$34,8,0) -> 12070 | V4: =VLOOKUP(O4,$A$1:$J$34,9,0) -> 2154
A5: 45691 | B5: =Table2345345687911121514161718192021222324252627283456789101134567891011126789[[#This Row],[Profit]]-Table2345345687911121514161718192021222324252627283456789101134567891011126789[[#This Row],[Mulbhag]] -> 971 | C5: =Table2345345687911121514161718192021222324252627283456789101134567891011126789[[#This Row],[Profit]]/3 -> 485.5 | D5: =F5*0.3 -> 1456.5 | E5: =F5-D5 -> 3398.5 | F5: =G5+H5 -> 4855 | G5: 2465 | H5: =1250+1040+100 -> 2390 | I5: 180 | K5: =Table2345345687911121514161718192021222324252627283456789101134567891011126789[[#This Row],[Account Transfer]]-Table2345345687911121514161718192021222324252627283456789101134567891011126789[[#This Row],[Expense Online]] -> 2390 | L5: =Table2345345687911121514161718192021222324252627283456789101134567891011126789[[#This Row],[Cash]]-Table2345345687911121514161718192021222324252627283456789101134567891011126789[[#This Row],[Mulbhag]]-Table2345345687911121514161718192021222324252627283456789101134567891011126789[[#This Row],[Actual Profit]]-Table2345345687911121514161718192021222324252627283456789101134567891011126789[[#This Row],[Expense]] -> 828.5 | M5: =Table2345345687911121514161718192021222324252627283456789101134567891011126789[[#This Row],[Cash]]-Table2345345687911121514161718192021222324252627283456789101134567891011126789[[#This Row],[Expense]] -> 2285 | O5: =A5 -> 45691 | P5: =Q5/3 -> 485.5 | Q5: =S5*0.3 -> 1456.5 | R5: =S5-Q5 -> 3398.5 | S5: =T5+U5 -> 4855 | T5: =VLOOKUP(O5,$A$1:$J$34,7,0) -> 2465 | U5: =VLOOKUP(O5,$A$1:$J$34,8,0) -> 2390 | V5: =VLOOKUP(O5,$A$1:$J$34,9,0) -> 180
A6: 45692 | B6: =Table2345345687911121514161718192021222324252627283456789101134567891011126789[[#This Row],[Profit]]-Table2345345687911121514161718192021222324252627283456789101134567891011126789[[#This Row],[Mulbhag]] -> 2205 | C6: =Table2345345687911121514161718192021222324252627283456789101134567891011126789[[#This Row],[Profit]]/3 -> 1102.5 | D6: =F6*0.3 -> 3307.5 | E6: =F6-D6 -> 7717.5 | F6: =G6+H6 -> 11025 | G6: 3800 | H6: 7225 | I6: 3000 | K6: =Table2345345687911121514161718192021222324252627283456789101134567891011126789[[#This Row],[Account Transfer]]-Table2345345687911121514161718192021222324252627283456789101134567891011126789[[#This Row],[Expense Online]] -> 7225 | L6: =Table2345345687911121514161718192021222324252627283456789101134567891011126789[[#This Row],[Cash]]-Table2345345687911121514161718192021222324252627283456789101134567891011126789[[#This Row],[Mulbhag]]-Table2345345687911121514161718192021222324252627283456789101134567891011126789[[#This Row],[Actual Profit]]-Table2345345687911121514161718192021222324252627283456789101134567891011126789[[#This Row],[Expense]] -> -2507.5 | M6: =Table2345345687911121514161718192021222324252627283456789101134567891011126789[[#This Row],[Cash]]-Table2345345687911121514161718192021222324252627283456789101134567891011126789[[#This Row],[Expense]] -> 800 | O6: =A6 -> 45692 | P6: =Q6/3 -> 1102.5 | Q6: =S6*0.3 -> 3307.5 | R6: =S6-Q6 -> 7717.5 | S6: =T6+U6 -> 11025 | T6: =VLOOKUP(O6,$A$1:$J$34,7,0) -> 3800 | U6: =VLOOKUP(O6,$A$1:$J$34,8,0) -> 7225 | V6: =VLOOKUP(O6,$A$1:$J$34,9,0) -> 3000
A7: 45693 | B7: =Table2345345687911121514161718192021222324252627283456789101134567891011126789[[#This Row],[Profit]]-Table2345345687911121514161718192021222324252627283456789101134567891011126789[[#This Row],[Mulbhag]] -> 6939.4 | C7: =Table2345345687911121514161718192021222324252627283456789101134567891011126789[[#This Row],[Profit]]/3 -> 3469.7 | D7: =F7*0.3 -> 10409.1 | E7: =F7-D7 -> 24287.9 | F7: =G7+H7 -> 34697 | G7: 12356 | H7: 22341 | I7: 3530 | K7: =Table2345345687911121514161718192021222324252627283456789101134567891011126789[[#This Row],[Account Transfer]]-Table2345345687911121514161718192021222324252627283456789101134567891011126789[[#This Row],[Expense Online]] -> 22341 | L7: =Table2345345687911121514161718192021222324252627283456789101134567891011126789[[#This Row],[Cash]]-Table2345345687911121514161718192021222324252627283456789101134567891011126789[[#This Row],[Mulbhag]]-Table2345345687911121514161718192021222324252627283456789101134567891011126789[[#This Row],[Actual Profit]]-Table2345345687911121514161718192021222324252627283456789101134567891011126789[[#This Row],[Expense]] -> -1583.1 | M7: =Table2345345687911121514161718192021222324252627283456789101134567891011126789[[#This Row],[Cash]]-Table2345345687911121514161718192021222324252627283456789101134567891011126789[[#This Row],[Expense]] -> 8826 | O7: =A7 -> 45693 | P7: =Q7/3 -> 3469.7 | Q7: =S7*0.3 -> 10409.1 | R7: =S7-Q7 -> 24287.9 | S7: =T7+U7 -> 34697 | T7: =VLOOKUP(O7,$A$1:$J$34,7,0) -> 12356 | U7: =VLOOKUP(O7,$A$1:$J$34,8,0) -> 22341 | V7: =VLOOKUP(O7,$A$1:$J$34,9,0) -> 3530
A8: 45694 | B8: =Table2345345687911121514161718192021222324252627283456789101134567891011126789[[#This Row],[Profit]]-Table2345345687911121514161718192021222324252627283456789101134567891011126789[[#This Row],[Mulbhag]] -> 2704.6 | C8: =Table2345345687911121514161718192021222324252627283456789101134567891011126789[[#This Row],[Profit]]/3 -> 1352.3 | D8: =F8*0.3 -> 4056.9 | E8: =F8-D8 -> 9466.1 | F8: =G8+H8 -> 13523 | G8: 5020 | H8: 8503 | I8: 1090 | K8: =Table2345345687911121514161718192021222324252627283456789101134567891011126789[[#This Row],[Account Transfer]]-Table2345345687911121514161718192021222324252627283456789101134567891011126789[[#This Row],[Expense Online]] -> 8503 | L8: =Table2345345687911121514161718192021222324252627283456789101134567891011126789[[#This Row],[Cash]]-Table2345345687911121514161718192021222324252627283456789101134567891011126789[[#This Row],[Mulbhag]]-Table2345345687911121514161718192021222324252627283456789101134567891011126789[[#This Row],[Actual Profit]]-Table2345345687911121514161718192021222324252627283456789101134567891011126789[[#This Row],[Expense]] -> -126.9 | M8: =Table2345345687911121514161718192021222324252627283456789101134567891011126789[[#This Row],[Cash]]-Table2345345687911121514161718192021222324252627283456789101134567891011126789[[#This Row],[Expense]] -> 3930 | O8: =A8 -> 45694 | P8: =Q8/3 -> 1352.3 | Q8: =S8*0.3 -> 4056.9 | R8: =S8-Q8 -> 9466.1 | S8: =T8+U8 -> 13523 | T8: =VLOOKUP(O8,$A$1:$J$34,7,0) -> 5020 | U8: =VLOOKUP(O8,$A$1:$J$34,8,0) -> 8503 | V8: =VLOOKUP(O8,$A$1:$J$34,9,0) -> 1090
A9: 45695 | B9: =Table2345345687911121514161718192021222324252627283456789101134567891011126789[[#This Row],[Profit]]-Table2345345687911121514161718192021222324252627283456789101134567891011126789[[#This Row],[Mulbhag]] -> 4260.8 | C9: =Table2345345687911121514161718192021222324252627283456789101134567891011126789[[#This Row],[Profit]]/3 -> 2130.4 | D9: =F9*0.3 -> 6391.2 | E9: =F9-D9 -> 14912.8 | F9: =G9+H9 -> 21304 | G9: 4290 | H9: 17014 | I9: 150 | K9: =Table2345345687911121514161718192021222324252627283456789101134567891011126789[[#This Row],[Account Transfer]]-Table2345345687911121514161718192021222324252627283456789101134567891011126789[[#This Row],[Expense Online]] -> 17014 | L9: =Table2345345687911121514161718192021222324252627283456789101134567891011126789[[#This Row],[Cash]]-Table2345345687911121514161718192021222324252627283456789101134567891011126789[[#This Row],[Mulbhag]]-Table2345345687911121514161718192021222324252627283456789101134567891011126789[[#This Row],[Actual Profit]]-Table2345345687911121514161718192021222324252627283456789101134567891011126789[[#This Row],[Expense]] -> -2251.2 | M9: =Table2345345687911121514161718192021222324252627283456789101134567891011126789[[#This Row],[Cash]]-Table2345345687911121514161718192021222324252627283456789101134567891011126789[[#This Row],[Expense]] -> 4140 | O9: =A9 -> 45695 | P9: =Q9/3 -> 2130.4 | Q9: =S9*0.3 -> 6391.2 | R9: =S9-Q9 -> 14912.8 | S9: =T9+U9 -> 21304 | T9: =VLOOKUP(O9,$A$1:$J$34,7,0) -> 4290 | U9: =VLOOKUP(O9,$A$1:$J$34,8,0) -> 17014 | V9: =VLOOKUP(O9,$A$1:$J$34,9,0) -> 150
A10: 45696 | B10: =Table2345345687911121514161718192021222324252627283456789101134567891011126789[[#This Row],[Profit]]-Table2345345687911121514161718192021222324252627283456789101134567891011126789[[#This Row],[Mulbhag]] -> 2614 | C10: =Table2345345687911121514161718192021222324252627283456789101134567891011126789[[#This Row],[Profit]]/3 -> 1307 | D10: =F10*0.3 -> 3921 | E10: =F10-D10 -> 9149 | F10: =G10+H10 -> 13070 | G10: 8290 | H10: 4780 | I10: 590 | K10: =Table2345345687911121514161718192021222324252627283456789101134567891011126789[[#This Row],[Account Transfer]]-Table2345345687911121514161718192021222324252627283456789101134567891011126789[[#This Row],[Expense Online]] -> 4780 | L10: =Table2345345687911121514161718192021222324252627283456789101134567891011126789[[#This Row],[Cash]]-Table2345345687911121514161718192021222324252627283456789101134567891011126789[[#This Row],[Mulbhag]]-Table2345345687911121514161718192021222324252627283456789101134567891011126789[[#This Row],[Actual Profit]]-Table2345345687911121514161718192021222324252627283456789101134567891011126789[[#This Row],[Expense]] -> 3779 | M10: =Table2345345687911121514161718192021222324252627283456789101134567891011126789[[#This Row],[Cash]]-Table2345345687911121514161718192021222324252627283456789101134567891011126789[[#This Row],[Expense]] -> 7700 | O10: Total | P10: =SUM(P3:P9) -> 10723.9 | Q10: =SUM(Q3:Q9) -> 32171.7 | R10: =SUM(R2:R9) -> 75067.3 | S10: =SUM(S2:S9) -> 107239 | T10: =SUM(T2:T9) -> 35496 | U10: =SUM(U2:U9) -> 71743 | V10: =SUM(V2:V9) -> 11164
A11: 45697 | B11: =Table2345345687911121514161718192021222324252627283456789101134567891011126789[[#This Row],[Profit]]-Table2345345687911121514161718192021222324252627283456789101134567891011126789[[#This Row],[Mulbhag]] -> 4944 | C11: =Table2345345687911121514161718192021222324252627283456789101134567891011126789[[#This Row],[Profit]]/3 -> 2472 | D11: =F11*0.3 -> 7416 | E11: =F11-D11 -> 17304 | F11: =G11+H11 -> 24720 | G11: 14520 | H11: 10200 | I11: 6580 | K11: =Table2345345687911121514161718192021222324252627283456789101134567891011126789[[#This Row],[Account Transfer]]-Table2345345687911121514161718192021222324252627283456789101134567891011126789[[#This Row],[Expense Online]] -> 10200 | L11: =Table2345345687911121514161718192021222324252627283456789101134567891011126789[[#This Row],[Cash]]-Table2345345687911121514161718192021222324252627283456789101134567891011126789[[#This Row],[Mulbhag]]-Table2345345687911121514161718192021222324252627283456789101134567891011126789[[#This Row],[Actual Profit]]-Table2345345687911121514161718192021222324252627283456789101134567891011126789[[#This Row],[Expense]] -> 524 | M11: =Table2345345687911121514161718192021222324252627283456789101134567891011126789[[#This Row],[Cash]]-Table2345345687911121514161718192021222324252627283456789101134567891011126789[[#This Row],[Expense]] -> 7940 | O11: Mul Bhag | Q11: =Q10/3 -> 10723.9
A12: 45698 | B12: =Table2345345687911121514161718192021222324252627283456789101134567891011126789[[#This Row],[Profit]]-Table2345345687911121514161718192021222324252627283456789101134567891011126789[[#This Row],[Mulbhag]] -> 1982 | C12: =Table2345345687911121514161718192021222324252627283456789101134567891011126789[[#This Row],[Profit]]/3 -> 991 | D12: =F12*0.3 -> 2973 | E12: =F12-D12 -> 6937 | F12: =G12+H12 -> 9910 | G12: 6280 | H12: 3630 | I12: 4000 | K12: =Table2345345687911121514161718192021222324252627283456789101134567891011126789[[#This Row],[Account Transfer]]-Table2345345687911121514161718192021222324252627283456789101134567891011126789[[#This Row],[Expense Online]] -> 3630 | L12: =Table2345345687911121514161718192021222324252627283456789101134567891011126789[[#This Row],[Cash]]-Table2345345687911121514161718192021222324252627283456789101134567891011126789[[#This Row],[Mulbhag]]-Table2345345687911121514161718192021222324252627283456789101134567891011126789[[#This Row],[Actual Profit]]-Table2345345687911121514161718192021222324252627283456789101134567891011126789[[#This Row],[Expense]] -> -693 | M12: =Table2345345687911121514161718192021222324252627283456789101134567891011126789[[#This Row],[Cash]]-Table2345345687911121514161718192021222324252627283456789101134567891011126789[[#This Row],[Expense]] -> 2280
A13: 45699 | B13: =Table2345345687911121514161718192021222324252627283456789101134567891011126789[[#This Row],[Profit]]-Table2345345687911121514161718192021222324252627283456789101134567891011126789[[#This Row],[Mulbhag]] -> 13197 | C13: =Table2345345687911121514161718192021222324252627283456789101134567891011126789[[#This Row],[Profit]]/3 -> 6598.5 | D13: =F13*0.3 -> 19795.5 | E13: =F13-D13 -> 46189.5 | F13: =G13+H13 -> 65985 | G13: 54685 | H13: 11300 | K13: =Table2345345687911121514161718192021222324252627283456789101134567891011126789[[#This Row],[Account Transfer]]-Table2345345687911121514161718192021222324252627283456789101134567891011126789[[#This Row],[Expense Online]] -> 11300 | L13: =Table2345345687911121514161718192021222324252627283456789101134567891011126789[[#This Row],[Cash]]-Table2345345687911121514161718192021222324252627283456789101134567891011126789[[#This Row],[Mulbhag]]-Table2345345687911121514161718192021222324252627283456789101134567891011126789[[#This Row],[Actual Profit]]-Table2345345687911121514161718192021222324252627283456789101134567891011126789[[#This Row],[Expense]] -> 34889.5 | M13: =Table2345345687911121514161718192021222324252627283456789101134567891011126789[[#This Row],[Cash]]-Table2345345687911121514161718192021222324252627283456789101134567891011126789[[#This Row],[Expense]] -> 54685 | O13: Date | Q13: Profit | R13: Actual | S13: Total | T13: Cash | U13: Account Transfer | V13: Expense
A14: 45700 | B14: =Table2345345687911121514161718192021222324252627283456789101134567891011126789[[#This Row],[Profit]]-Table2345345687911121514161718192021222324252627283456789101134567891011126789[[#This Row],[Mulbhag]] -> 1813 | C14: =Table2345345687911121514161718192021222324252627283456789101134567891011126789[[#This Row],[Profit]]/3 -> 906.5 | D14: =F14*0.3 -> 2719.5 | E14: =F14-D14 -> 6345.5 | F14: =G14+H14 -> 9065 | G14: 585 | H14: 8480 | K14: =Table2345345687911121514161718192021222324252627283456789101134567891011126789[[#This Row],[Account Transfer]]-Table2345345687911121514161718192021222324252627283456789101134567891011126789[[#This Row],[Expense Online]] -> 8480 | L14: =Table2345345687911121514161718192021222324252627283456789101134567891011126789[[#This Row],[Cash]]-Table2345345687911121514161718192021222324252627283456789101134567891011126789[[#This Row],[Mulbhag]]-Table2345345687911121514161718192021222324252627283456789101134567891011126789[[#This Row],[Actual Profit]]-Table2345345687911121514161718192021222324252627283456789101134567891011126789[[#This Row],[Expense]] -> -2134.5 | M14: =Table2345345687911121514161718192021222324252627283456789101134567891011126789[[#This Row],[Cash]]-Table2345345687911121514161718192021222324252627283456789101134567891011126789[[#This Row],[Expense]] -> 585 | O14: =A10 -> 45696 | P14: =Q14/3 -> 1307 | Q14: =S14*0.3 -> 3921 | R14: =S14-Q14 -> 9149 | S14: =T14+U14 -> 13070 | T14: =VLOOKUP(O14,$A$1:$J$34,7,0) -> 8290 | U14: =VLOOKUP(O14,$A$1:$J$34,8,0) -> 4780 | V14: =VLOOKUP(O14,$A$1:$J$34,9,0) -> 590
A15: 45701 | B15: =Table2345345687911121514161718192021222324252627283456789101134567891011126789[[#This Row],[Profit]]-Table2345345687911121514161718192021222324252627283456789101134567891011126789[[#This Row],[Mulbhag]] -> 5626 | C15: =Table2345345687911121514161718192021222324252627283456789101134567891011126789[[#This Row],[Profit]]/3 -> 2813 | D15: =F15*0.3 -> 8439 | E15: =F15-D15 -> 19691 | F15: =G15+H15 -> 28130 | G15: 900 | H15: 27230 | K15: =Table2345345687911121514161718192021222324252627283456789101134567891011126789[[#This Row],[Account Transfer]]-Table2345345687911121514161718192021222324252627283456789101134567891011126789[[#This Row],[Expense Online]] -> 27230 | L15: =Table2345345687911121514161718192021222324252627283456789101134567891011126789[[#This Row],[Cash]]-Table2345345687911121514161718192021222324252627283456789101134567891011126789[[#This Row],[Mulbhag]]-Table2345345687911121514161718192021222324252627283456789101134567891011126789[[#This Row],[Actual Profit]]-Table2345345687911121514161718192021222324252627283456789101134567891011126789[[#This Row],[Expense]] -> -7539 | M15: =Table2345345687911121514161718192021222324252627283456789101134567891011126789[[#This Row],[Cash]]-Table2345345687911121514161718192021222324252627283456789101134567891011126789[[#This Row],[Expense]] -> 900 | O15: =A11 -> 45697 | P15: =Q15/3 -> 2472 | Q15: =S15*0.3 -> 7416 | R15: =S15-Q15 -> 17304 | S15: =T15+U15 -> 24720 | T15: =VLOOKUP(O15,$A$1:$J$34,7,0) -> 14520 | U15: =VLOOKUP(O15,$A$1:$J$34,8,0) -> 10200 | V15: =VLOOKUP(O15,$A$1:$J$34,9,0) -> 6580
A16: 45702 | B16: =Table2345345687911121514161718192021222324252627283456789101134567891011126789[[#This Row],[Profit]]-Table2345345687911121514161718192021222324252627283456789101134567891011126789[[#This Row],[Mulbhag]] -> 3827.4 | C16: =Table2345345687911121514161718192021222324252627283456789101134567891011126789[[#This Row],[Profit]]/3 -> 1913.7 | D16: =F16*0.3 -> 5741.1 | E16: =F16-D16 -> 13395.9 | F16: =G16+H16 -> 19137 | G16: 6360 | H16: 12777 | K16: =Table2345345687911121514161718192021222324252627283456789101134567891011126789[[#This Row],[Account Transfer]]-Table2345345687911121514161718192021222324252627283456789101134567891011126789[[#This Row],[Expense Online]] -> 12777 | L16: =Table2345345687911121514161718192021222324252627283456789101134567891011126789[[#This Row],[Cash]]-Table2345345687911121514161718192021222324252627283456789101134567891011126789[[#This Row],[Mulbhag]]-Table2345345687911121514161718192021222324252627283456789101134567891011126789[[#This Row],[Actual Profit]]-Table2345345687911121514161718192021222324252627283456789101134567891011126789[[#This Row],[Expense]] -> 618.9 | M16: =Table2345345687911121514161718192021222324252627283456789101134567891011126789[[#This Row],[Cash]]-Table2345345687911121514161718192021222324252627283456789101134567891011126789[[#This Row],[Expense]] -> 6360 | O16: =A12 -> 45698 | P16: =Q16/3 -> 991 | Q16: =S16*0.3 -> 2973 | R16: =S16-Q16 -> 6937 | S16: =T16+U16 -> 9910 | T16: =VLOOKUP(O16,$A$1:$J$34,7,0) -> 6280 | U16: =VLOOKUP(O16,$A$1:$J$34,8,0) -> 3630 | V16: =VLOOKUP(O16,$A$1:$J$34,9,0) -> 4000
